Workbook

Sheet Dashboard
A1: JSW STEEL TMT - MARKETING BUDGET MODEL FY 2026-27
A2: Executive Summary Dashboard | Total Budget: Rs. 5 Crore | Period: Apr 2026 - Mar 2027
B4: Total Budget | D4: Helix Budget | F4: JSW ONE Budget | H4: Blended Cost/MT | J4: Total Volume (MT)
B5: ='Master Inputs'!$C$5 -> 50000000 | D5: ='Master Inputs'!$C$13 -> 28500000 | F5: ='Master Inputs'!$C$14 -> 19000000 | H5: ='Vol Projections'!F6 -> 268000 | J5: ='Vol Projections'!F7 -> 389000
A7: BUDGET ALLOCATION SUMMARY
B8: Objective | C8: Budget (Rs.) | D8: % of Total | E8: ATL Spend | F8: BTL Spend | H8: Metric | I8: Helix | J8: JSW ONE | K8: Combined
A9: 1 | B9: Obj 1: Helix Launch | C9: ='Master Inputs'!$C$13 -> 28500000 | D9: ='Master Inputs'!$C$6 -> 0.6 | H9: A/S Ratio (Helix) | I9: ='Vol Projections'!B19 -> 0.030538061
A10: 2 | B10: Obj 2A: JSW ONE East | C10: ='Master Inputs'!$C$15 -> 11400000 | D10: ='Master Inputs'!$C$7*'Master Inputs'!$C$8 -> 0.24 | H10: A/S Ratio (JSW ONE) | I10: ='Vol Projections'!C19 -> 0.024905383
A11: 3 | B11: Obj 2B: JSW ONE UP+HR | C11: ='Master Inputs'!$C$16 -> 7600000 | D11: ='Master Inputs'!$C$7*'Master Inputs'!$C$9 -> 0.16 | H11: Helix Volume (MT) | I11: ='Vol Projections'!F5 -> 121000
A12: 4 | B12: Contingency Reserve | C12: ='Master Inputs'!$C$17 -> 2500000 | D12: ='Master Inputs'!$C$10 -> 0.05 | H12: JSW ONE Volume (MT) | I12: ='Vol Projections'!F6 -> 268000
B14: TOTAL | C14: ='Master Inputs'!$C$5 -> 50000000 | D14: 100.0%
A16: QUARTERLY SPEND TRAJECTORY
B17: Quarter | C17: Helix | D17: JSW ONE East | E17: JSW ONE UP+HR | F17: Total
B18: Q1 | C18: =Consolidated!B15 -> 45143103 | D18: =Consolidated!C15 -> 17730357 | E18: =Consolidated!D15 -> 65702677 | F18: =Consolidated!F15 -> 1.2857614e+08
B19: Q2 | C19: =Consolidated!B16 -> 27085862 | D19: =Consolidated!C16 -> 10638214 | E19: =Consolidated!D16 -> 39421606 | F19: =Consolidated!F16 -> 77145682
B20: Q3 | C20: =Consolidated!B17 -> 63200344 | D20: =Consolidated!C17 -> 24822500 | E20: =Consolidated!D17 -> 91983748 | F20: =Consolidated!F17 -> 1.8000659e+08
B21: Q4 | C21: =Consolidated!B18 -> 45143103 | D21: =Consolidated!C18 -> 17730357 | E21: =Consolidated!D18 -> 65702677 | F21: =Consolidated!F18 -> 1.2857614e+08
A39: HOW TO USE THIS MODEL
B40: 1. Go to 'Master Inputs' tab to change budget allocation, quarterly splits, and volume targets.
B41: 2. Yellow cells are editable - all other cells contain formulas that auto-update.
B42: 3. Change Helix vs JSW ONE split in Budget Allocation Controls section.
B43: 4. Adjust ATL/BTL mix in the Helix ATL vs BTL Split section.
B44: 5. Modify quarterly distribution in the Quarterly Allocation section.
B45: 6. Update unit costs in 'Activity Costs' tab to reflect market rates.
B46: 7. Track actuals in 'Quarterly Review' tab after each quarter.
B47: 8. Color Legend: YELLOW = Input | GREEN = Calculated | GRAY = Totals | RED = Alerts

Sheet Master Inputs
A1: MASTER INPUTS - ALL VARIABLE PARAMETERS
A2: Yellow cells are editable inputs. Green cells are auto-calculated. Change inputs here to update ALL tabs.
A4: BUDGET ALLOCATION CONTROLS
A5: 1 | B5: Total Marketing Budget | C5: 50000000 | D5: Rs. | F5: 5 Crores
A6: 2 | B6: Objective 1 - Helix Share % | C6: 0.6 | F6: 60% for national launch
A7: 3 | B7: Objective 2 - JSW ONE Share % | C7: =1-C6 -> 0.4 | F7: Auto = 1 - Helix%
A8: 4 | B8: Sub-2A East Share (of Obj2) % | C8: 0.6 | F8: 60% for broader East
A9: 5 | B9: Sub-2B UP+HR Share (of Obj2) % | C9: =1-C8 -> 0.4 | F9: Auto = 1 - East%
A10: 6 | B10: Contingency Reserve % | C10: 0.05 | F10: 5% held back
A12: DERIVED BUDGET AMOUNTS (Auto-Calculated)
B13: Helix Budget (Rs.) | C13: =C5*C6*(1-C10) -> 28500000
B14: JSW ONE Total Budget (Rs.) | C14: =C5*C7*(1-C10) -> 19000000
B15: Sub-2A East Budget (Rs.) | C15: =C14*C8 -> 11400000
B16: Sub-2B UP+HR Budget (Rs.) | C16: =C14*C9 -> 7600000
B17: Contingency Reserve (Rs.) | C17: =C5*C10 -> 2500000
B18: Total Allocated (Rs.) | C18: =C13+C14+C17 -> 50000000
A20: VERIFICATION CHECKS
B21: Budget Allocation = 100%? | C21: =IF(ABS(C6+C7-1)<0.001,"YES","NO") -> YES
B22: Sub-Obj sum = Obj2? | C22: =IF(ABS(C15+C16-C14)<1,"YES","NO") -> YES
B23: Total = Budget? | C23: =IF(ABS(C18-C5)<1,"YES","NO") -> YES
A25: HELIX ATL vs BTL SPLIT
B26: ATL Share % (Helix) | C26: 0.4 | F26: 40% ATL, 60% BTL
B27: BTL Share % (Helix) | C27: =1-C26 -> 0.6
A29: QUARTERLY ALLOCATION (Must sum to 100%)
B30: Q1 Allocation % | C30: 0.25 | F30: Apr-Jun: Launch push
B31: Q2 Allocation % | C31: 0.15 | F31: Jul-Sep: Monsoon dip
B32: Q3 Allocation % | C32: 0.35 | F32: Oct-Dec: Peak construction
B33: Q4 Allocation % | C33: 0.25 | F33: Jan-Mar: Year-end push
B34: Quarterly Sum Check | C34: =SUM(C30:C33) -> 1
B35: Quarterly Check | C35: =IF(ABS(C34-1)<0.001,"YES","NO") -> YES
A37: MONTHLY WEIGHTS WITHIN QUARTERS
B38: Q1 Month Weights (Apr/May/Jun) | C38: 0.3 | D38: 0.4 | E38: 0.3
B39: Q2 Month Weights (Jul/Aug/Sep) | C39: 0.3 | D39: 0.35 | E39: 0.35
B40: Q3 Month Weights (Oct/Nov/Dec) | C40: 0.35 | D40: 0.3 | E40: 0.35
B41: Q4 Month Weights (Jan/Feb/Mar) | C41: 0.4 | D41: 0.3 | E41: 0.3
A43: VOLUME TARGETS & ASSUMPTIONS
B44: Helix - Distributors | C44: 42 | D44: Nos
B45: Helix - Annual Volume Target | C45: 121000 | D45: MT
B46: Helix - Volume Mar 27 Exit Rate | C46: 27000 | D46: MT/month
B47: Helix - Avg Vol/Retailer/Month | C47: 20 | D47: MT
B48: Helix - Active Retailers (Mar 27) | C48: 2015 | D48: Nos
B49: Helix - Transacting Retailers | C49: 1310 | D49: Nos
B50: Helix - Priority Districts | C50: 250 | D50: Nos
B51: Helix - Selling Price/MT | C51: 48868 | D51: Rs/MT
B52: JSW ONE - Distributors | C52: 56 | D52: Nos
B53: JSW ONE - Annual Volume Target | C53: 268000 | D53: MT
B54: JSW ONE - Volume Mar 27 Exit Rate | C54: 31000 | D54: MT/month
B55: JSW ONE - Avg Vol/Retailer/Month | C55: 30 | D55: MT
... B61: JSW ONE - Selling Price/MT | C61: 50000 | D61: Rs/MT
B62: JSW ONE - East Volume Share % | C62: 0.6
B63: JSW ONE - UP+HR Volume Share % | C63: 0.4
B64: Target Growth Multiplier (Sub-2B) | C64: 2 | D64: x
A66: EAST REGION STATES (Sub-2A Coverage)
B67: State | C67: Budget Share % | D67: Dealers
B68: Bihar | C68: 0.3 | D68: 70
B69: West Bengal | C69: 0.3 | D69: 159
B70: Jharkhand | C70: 0.2 | D70: 61
B71: Odisha | C71: 0.2 | D71: 48
B72: East State Share Check | C72: =SUM(C68:C71) -> 1
A74: UP & HARYANA SPLIT (Sub-2B)
B75: Uttar Pradesh Budget Share % | C75: 0.6
B76: Haryana Budget Share % | C76: =1-C75 -> 0.4
B77: UP Dealers (Current) | C77: 152
B78: Haryana Dealers (Current) | C78: 81

Sheet Obj1 Helix
A1: OBJECTIVE 1: ONE HELIX INDIA LAUNCH - ATL + BTL PLAN (FY 2026-27)
A2: Allocated Budget: | B2: ='Master Inputs'!$C$13 -> 28500000 | D2: ATL Budget: | E2: ='Master Inputs'!$C$13*'Master Inputs'!$C$26 -> 11400000 | G2: BTL Budget: | H2: ='Master Inputs'!$C$13*'Master Inputs'!$C$27 -> 17100000
A4: Activity | B4: Remarks | C4: Year Total | D4: % of Total | E4: Apr | F4: May | G4: Jun | H4: Q1 Total | I4: Jul | J4: Aug | K4: Sep | L4: Q2 Total | M4: Oct | N4: Nov | O4: Dec | P4: Q3 Total | Q4: Jan | R4: Feb | S4: Mar | T4: Q4 Total
A5: ATL ACTIVITIES
A6: Impact Wall Painting | B6: 20K sqft x districts | C6: ='Activity Costs'!C5*'Master Inputs'!$C$50*20000 -> 75000000 | D6: =IF(C$31=0,0,C6/C$31) -> 0.41534584 | E6: =$C$6*'Master Inputs'!$C$30*'Master Inputs'!$C$38 -> 5625000 | F6: =$C$6*'Master Inputs'!$C$30*'Master Inputs'!$D$38 -> 7500000 | G6: =$C$6*'Master Inputs'!$C$30*'Master Inputs'!$E$38 -> 5625000 | H6: =SUM(E6:G6) -> 18750000 | I6: =$C$6*'Master Inputs'!$C$31*'Master Inputs'!$C$39 -> 3375000 | J6: =$C$6*'Master Inputs'!$C$31*'Master Inputs'!$D$39 -> 3937500 | K6: =$C$6*'Master Inputs'!$C$31*'Master Inputs'!$E$39 -> 3937500 | L6: =SUM(I6:K6) -> 11250000 | M6: =$C$6*'Master Inputs'!$C$32*'Master Inputs'!$C$40 -> 9187500 | N6: =$C$6*'Master Inputs'!$C$32*'Master Inputs'!$D$40 -> 7875000 | O6: =$C$6*'Master Inputs'!$C$32*'Master Inputs'!$E$40 -> 9187500 | P6: =SUM(M6:O6) -> 26250000 | Q6: =$C$6*'Master Inputs'!$C$33*'Master Inputs'!$C$41 -> 7500000 | R6: =$C$6*'Master Inputs'!$C$33*'Master Inputs'!$D$41 -> 5625000 | S6: =$C$6*'Master Inputs'!$C$33*'Master Inputs'!$E$41 -> 5625000 | T6: =SUM(Q6:S6) -> 18750000
A7: FM Radio Campaign | B7: 5% districts x 4 qtrs | C7: ='Activity Costs'!C6*'Master Inputs'!$C$50*0.05*4 -> 12500000 | D7: =IF(C$31=0,0,C7/C$31) -> 0.069224306 | E7: =$C$7*'Master Inputs'!$C$30*'Master Inputs'!$C$38 -> 937500 | F7: =$C$7*'Master Inputs'!$C$30*'Master Inputs'!$D$38 -> 1250000 | G7: =$C$7*'Master Inputs'!$C$30*'Master Inputs'!$E$38 -> 937500 | H7: =SUM(E7:G7) -> 3125000 | I7: =$C$7*'Master Inputs'!$C$31*'Master Inputs'!$C$39 -> 562500 | J7: =$C$7*'Master Inputs'!$C$31*'Master Inputs'!$D$39 -> 656250 | K7: =$C$7*'Master Inputs'!$C$31*'Master Inputs'!$E$39 -> 656250 | L7: =SUM(I7:K7) -> 1875000 | M7: =$C$7*'Master Inputs'!$C$32*'Master Inputs'!$C$40 -> 1531250 | N7: =$C$7*'Master Inputs'!$C$32*'Master Inputs'!$D$40 -> 1312500 | O7: =$C$7*'Master Inputs'!$C$32*'Master Inputs'!$E$40 -> 1531250 | P7: =SUM(M7:O7) -> 4375000 | Q7: =$C$7*'Master Inputs'!$C$33*'Master Inputs'!$C$41 -> 1250000 | R7: =$C$7*'Master Inputs'!$C$33*'Master Inputs'!$D$41 -> 937500 | S7: =$C$7*'Master Inputs'!$C$33*'Master Inputs'!$E$41 -> 937500 | T7: =SUM(Q7:S7) -> 3125000
A8: Hoardings (Flex/Billboard) | B8: 2 per district | C8: ='Activity Costs'!C7*'Master Inputs'!$C$50*2 -> 25000000 | D8: =IF(C$31=0,0,C8/C$31) -> 0.13844861 | E8: =$C$8*'Master Inputs'!$C$30*'Master Inputs'!$C$38 -> 1875000 | F8: =$C$8*'Master Inputs'!$C$30*'Master Inputs'!$D$38 -> 2500000 | G8: =$C$8*'Master Inputs'!$C$30*'Master Inputs'!$E$38 -> 1875000 | H8: =SUM(E8:G8) -> 6250000 | I8: =$C$8*'Master Inputs'!$C$31*'Master Inputs'!$C$39 -> 1125000 | J8: =$C$8*'Master Inputs'!$C$31*'Master Inputs'!$D$39 -> 1312500 | K8: =$C$8*'Master Inputs'!$C$31*'Master Inputs'!$E$39 -> 1312500 | L8: =SUM(I8:K8) -> 3750000 | M8: =$C$8*'Master Inputs'!$C$32*'Master Inputs'!$C$40 -> 3062500 | N8: =$C$8*'Master Inputs'!$C$32*'Master Inputs'!$D$40 -> 2625000 | O8: =$C$8*'Master Inputs'!$C$32*'Master Inputs'!$E$40 -> 3062500 | P8: =SUM(M8:O8) -> 8750000 | Q8: =$C$8*'Master Inputs'!$C$33*'Master Inputs'!$C$41 -> 2500000 | R8: =$C$8*'Master Inputs'!$C$33*'Master Inputs'!$D$41 -> 1875000 | S8: =$C$8*'Master Inputs'!$C$33*'Master Inputs'!$E$41 -> 1875000 | T8: =SUM(Q8:S8) -> 6250000
A9: Digital Marketing Campaign | B9: 4 campaigns/year | C9: ='Activity Costs'!C8*4 -> 2000000 | D9: =IF(C$31=0,0,C9/C$31) -> 0.011075889 | E9: =$C$9*'Master Inputs'!$C$30*'Master Inputs'!$C$38 -> 150000 | F9: =$C$9*'Master Inputs'!$C$30*'Master Inputs'!$D$38 -> 200000 | G9: =$C$9*'Master Inputs'!$C$30*'Master Inputs'!$E$38 -> 150000 | H9: =SUM(E9:G9) -> 500000 | I9: =$C$9*'Master Inputs'!$C$31*'Master Inputs'!$C$39 -> 90000 | J9: =$C$9*'Master Inputs'!$C$31*'Master Inputs'!$D$39 -> 105000 | K9: =$C$9*'Master Inputs'!$C$31*'Master Inputs'!$E$39 -> 105000 | L9: =SUM(I9:K9) -> 300000 | M9: =$C$9*'Master Inputs'!$C$32*'Master Inputs'!$C$40 -> 245000 | N9: =$C$9*'Master Inputs'!$C$32*'Master Inputs'!$D$40 -> 210000 | O9: =$C$9*'Master Inputs'!$C$32*'Master Inputs'!$E$40 -> 245000 | P9: =SUM(M9:O9) -> 700000 | Q9: =$C$9*'Master Inputs'!$C$33*'Master Inputs'!$C$41 -> 200000 | R9: =$C$9*'Master Inputs'!$C$33*'Master Inputs'!$D$41 -> 150000 | S9: =$C$9*'Master Inputs'!$C$33*'Master Inputs'!$E$41 -> 150000 | T9: =SUM(Q9:S9) -> 500000
A10: Local Events / Trade Fairs | B10: 8 zonal events | C10: ='Activity Costs'!C9*8 -> 4000000 | D10: =IF(C$31=0,0,C10/C$31) -> 0.022151778 | E10: =$C$10*'Master Inputs'!$C$30*'Master Inputs'!$C$38 -> 300000 | F10: =$C$10*'Master Inputs'!$C$30*'Master Inputs'!$D$38 -> 400000 | G10: =$C$10*'Master Inputs'!$C$30*'Master Inputs'!$E$38 -> 300000 | H10: =SUM(E10:G10) -> 1000000 | I10: =$C$10*'Master Inputs'!$C$31*'Master Inputs'!$C$39 -> 180000 | J10: =$C$10*'Master Inputs'!$C$31*'Master Inputs'!$D$39 -> 210000 | K10: =$C$10*'Master Inputs'!$C$31*'Master Inputs'!$E$39 -> 210000 | L10: =SUM(I10:K10) -> 600000 | M10: =$C$10*'Master Inputs'!$C$32*'Master Inputs'!$C$40 -> 490000 | N10: =$C$10*'Master Inputs'!$C$32*'Master Inputs'!$D$40 -> 420000 | O10: =$C$10*'Master Inputs'!$C$32*'Master Inputs'!$E$40 -> 490000 | P10: =SUM(M10:O10) -> 1400000 | Q10: =$C$10*'Master Inputs'!$C$33*'Master Inputs'!$C$41 -> 400000 | R10: =$C$10*'Master Inputs'!$C$33*'Master Inputs'!$D$41 -> 300000 | S10: =$C$10*'Master Inputs'!$C$33*'Master Inputs'!$E$41 -> 300000 | T10: =SUM(Q10:S10) -> 1000000
A11: Van Campaign (Mobile) | B11: 10 vans x 60 days | C11: ='Activity Costs'!C10*10*60 -> 4200000 | D11: =IF(C$31=0,0,C11/C$31) -> 0.023259367 | E11: =$C$11*'Master Inputs'!$C$30*'Master Inputs'!$C$38 -> 315000 | F11: =$C$11*'Master Inputs'!$C$30*'Master Inputs'!$D$38 -> 420000 | G11: =$C$11*'Master Inputs'!$C$30*'Master Inputs'!$E$38 -> 315000 | H11: =SUM(E11:G11) -> 1050000 | I11: =$C$11*'Master Inputs'!$C$31*'Master Inputs'!$C$39 -> 189000 | J11: =$C$11*'Master Inputs'!$C$31*'Master Inputs'!$D$39 -> 220500 | K11: =$C$11*'Master Inputs'!$C$31*'Master Inputs'!$E$39 -> 220500 | L11: =SUM(I11:K11) -> 630000 | M11: =$C$11*'Master Inputs'!$C$32*'Master Inputs'!$C$40 -> 514500 | N11: =$C$11*'Master Inputs'!$C$32*'Master Inputs'!$D$40 -> 441000 | O11: =$C$11*'Master Inputs'!$C$32*'Master Inputs'!$E$40 -> 514500 | P11: =SUM(M11:O11) -> 1470000 | Q11: =$C$11*'Master Inputs'!$C$33*'Master Inputs'!$C$41 -> 420000 | R11: =$C$11*'Master Inputs'!$C$33*'Master Inputs'!$D$41 -> 315000 | S11: =$C$11*'Master Inputs'!$C$33*'Master Inputs'!$E$41 -> 315000 | T11: =SUM(Q11:S11) -> 1050000
A12: Syndicate Launch Events | B12: 15 state launches | C12: ='Activity Costs'!C11*15 -> 7500000 | D12: =IF(C$31=0,0,C12/C$31) -> 0.041534584 | E12: =$C$12*'Master Inputs'!$C$30*'Master Inputs'!$C$38 -> 562500 | F12: =$C$12*'Master Inputs'!$C$30*'Master Inputs'!$D$38 -> 750000 | G12: =$C$12*'Master Inputs'!$C$30*'Master Inputs'!$E$38 -> 562500 | H12: =SUM(E12:G12) -> 1875000 | I12: =$C$12*'Master Inputs'!$C$31*'Master Inputs'!$C$39 -> 337500 | J12: =$C$12*'Master Inputs'!$C$31*'Master Inputs'!$D$39 -> 393750 | K12: =$C$12*'Master Inputs'!$C$31*'Master Inputs'!$E$39 -> 393750 | L12: =SUM(I12:K12) -> 1125000 | M12: =$C$12*'Master Inputs'!$C$32*'Master Inputs'!$C$40 -> 918750 | N12: =$C$12*'Master Inputs'!$C$32*'Master Inputs'!$D$40 -> 787500 | O12: =$C$12*'Master Inputs'!$C$32*'Master Inputs'!$E$40 -> 918750 | P12: =SUM(M12:O12) -> 2625000 | Q12: =$C$12*'Master Inputs'!$C$33*'Master Inputs'!$C$41 -> 750000 | R12: =$C$12*'Master Inputs'!$C$33*'Master Inputs'!$D$41 -> 562500 | S12: =$C$12*'Master Inputs'!$C$33*'Master Inputs'!$E$41 -> 562500 | T12: =SUM(Q12:S12) -> 1875000
A13: Transit Auto Branding | B13: 500 autos nationally | C13: ='Activity Costs'!C12*500 -> 350000 | D13: =IF(C$31=0,0,C13/C$31) -> 0.0019382806 | E13: =$C$13*'Master Inputs'!$C$30*'Master Inputs'!$C$38 -> 26250 | F13: =$C$13*'Master Inputs'!$C$30*'Master Inputs'!$D$38 -> 35000 | G13: =$C$13*'Master Inputs'!$C$30*'Master Inputs'!$E$38 -> 26250 | H13: =SUM(E13:G13) -> 87500 | I13: =$C$13*'Master Inputs'!$C$31*'Master Inputs'!$C$39 -> 15750 | J13: =$C$13*'Master Inputs'!$C$31*'Master Inputs'!$D$39 -> 18375 | K13: =$C$13*'Master Inputs'!$C$31*'Master Inputs'!$E$39 -> 18375 | L13: =SUM(I13:K13) -> 52500 | M13: =$C$13*'Master Inputs'!$C$32*'Master Inputs'!$C$40 -> 42875 | N13: =$C$13*'Master Inputs'!$C$32*'Master Inputs'!$D$40 -> 36750 | O13: =$C$13*'Master Inputs'!$C$32*'Master Inputs'!$E$40 -> 42875 | P13: =SUM(M13:O13) -> 122500 | Q13: =$C$13*'Master Inputs'!$C$33*'Master Inputs'!$C$41 -> 35000 | R13: =$C$13*'Master Inputs'!$C$33*'Master Inputs'!$D$41 -> 26250 | S13: =$C$13*'Master Inputs'!$C$33*'Master Inputs'!$E$41 -> 26250 | T13: =SUM(Q13:S13) -> 87500
A14: Tea Stall Branding | B14: 10% districts x 25 stalls | C14: ='Activity Costs'!C13*'Master Inputs'!$C$50*0.1*25 -> 2500000 | D14: =IF(C$31=0,0,C14/C$31) -> 0.013844861 | E14: =$C$14*'Master Inputs'!$C$30*'Master Inputs'!$C$38 -> 187500 | F14: =$C$14*'Master Inputs'!$C$30*'Master Inputs'!$D$38 -> 250000 | G14: =$C$14*'Master Inputs'!$C$30*'Master Inputs'!$E$38 -> 187500 | H14: =SUM(E14:G14) -> 625000 | I14: =$C$14*'Master Inputs'!$C$31*'Master Inputs'!$C$39 -> 112500 | J14: =$C$14*'Master Inputs'!$C$31*'Master Inputs'!$D$39 -> 131250 | K14: =$C$14*'Master Inputs'!$C$31*'Master Inputs'!$E$39 -> 131250 | L14: =SUM(I14:K14) -> 375000 | M14: =$C$14*'Master Inputs'!$C$32*'Master Inputs'!$C$40 -> 306250 | N14: =$C$14*'Master Inputs'!$C$32*'Master Inputs'!$D$40 -> 262500 | O14: =$C$14*'Master Inputs'!$C$32*'Master Inputs'!$E$40 -> 306250 | P14: =SUM(M14:O14) -> 875000 | Q14: =$C$14*'Master Inputs'!$C$33*'Master Inputs'!$C$41 -> 250000 | R14: =$C$14*'Master Inputs'!$C$33*'Master Inputs'!$D$41 -> 187500 | S14: =$C$14*'Master Inputs'!$C$33*'Master Inputs'!$E$41 -> 187500 | T14: =SUM(Q14:S14) -> 625000
A15: Paper Advertisement | B15: 12 insertions/year | C15: ='Activity Costs'!C14*12 -> 1200000 | D15: =IF(C$31=0,0,C15/C$31) -> 0.0066455334 | E15: =$C$15*'Master Inputs'!$C$30*'Master Inputs'!$C$38 -> 90000 | F15: =$C$15*'Master Inputs'!$C$30*'Master Inputs'!$D$38 -> 120000 | G15: =$C$15*'Master Inputs'!$C$30*'Master Inputs'!$E$38 -> 90000 | H15: =SUM(E15:G15) -> 300000 | I15: =$C$15*'Master Inputs'!$C$31*'Master Inputs'!$C$39 -> 54000 | J15: =$C$15*'Master Inputs'!$C$31*'Master Inputs'!$D$39 -> 63000 | K15: =$C$15*'Master Inputs'!$C$31*'Master Inputs'!$E$39 -> 63000 | L15: =SUM(I15:K15) -> 180000 | M15: =$C$15*'Master Inputs'!$C$32*'Master Inputs'!$C$40 -> 147000 | N15: =$C$15*'Master Inputs'!$C$32*'Master Inputs'!$D$40 -> 126000 | O15: =$C$15*'Master Inputs'!$C$32*'Master Inputs'!$E$40 -> 147000 | P15: =SUM(M15:O15) -> 420000 | Q15: =$C$15*'Master Inputs'!$C$33*'Master Inputs'!$C$41 -> 120000 | R15: =$C$15*'Master Inputs'!$C$33*'Master Inputs'!$D$41 -> 90000 | S15: =$C$15*'Master Inputs'!$C$33*'Master Inputs'!$E$41 -> 90000 | T15: =SUM(Q15:S15) -> 300000
A16: ATL ACTIVITIES TOTAL | C16: =SUM(C6:C15) -> 134250000 | D16: =IF(C$31=0,0,C16/C$31) -> 0.74346905 | E16: =SUM(E6:E15) -> 10068750 | F16: =SUM(F6:F15) -> 13425000 | G16: =SUM(G6:G15) -> 10068750 | H16: =SUM(H6:H15) -> 33562500 | I16: =SUM(I6:I15) -> 6041250 | J16: =SUM(J6:J15) -> 7048125 | K16: =SUM(K6:K15) -> 7048125 | L16: =SUM(L6:L15) -> 20137500 | ... T16: =SUM(T6:T15) -> 33562500
A18: BTL ACTIVITIES
A19: NLB (Name/Lit Board) | B19: 50% active retailers | C19: ='Activity Costs'!C16*'Master Inputs'!$C$48*0.5 -> 1209000 | D19: =IF(C$31=0,0,C19/C$31) -> 0.0066953749 | E19: =$C$19*'Master Inputs'!$C$30*'Master Inputs'!$C$38 -> 90675 | F19: =$C$19*'Master Inputs'!$C$30*'Master Inputs'!$D$38 -> 120900 | G19: =$C$19*'Master Inputs'!$C$30*'Master Inputs'!$E$38 -> 90675 | H19: =SUM(E19:G19) -> 302250 | I19: =$C$19*'Master Inputs'!$C$31*'Master Inputs'!$C$39 -> 54405 | J19: =$C$19*'Master Inputs'!$C$31*'Master Inputs'!$D$39 -> 63472.5 | K19: =$C$19*'Master Inputs'!$C$31*'Master Inputs'!$E$39 -> 63472.5 | L19: =SUM(I19:K19) -> 181350 | M19: =$C$19*'Master Inputs'!$C$32*'Master Inputs'!$C$40 -> 148102.5 | N19: =$C$19*'Master Inputs'!$C$32*'Master Inputs'!$D$40 -> 126945 | O19: =$C$19*'Master Inputs'!$C$32*'Master Inputs'!$E$40 -> 148102.5 | P19: =SUM(M19:O19) -> 423150 | Q19: =$C$19*'Master Inputs'!$C$33*'Master Inputs'!$C$41 -> 120900 | R19: =$C$19*'Master Inputs'!$C$33*'Master Inputs'!$D$41 -> 90675 | S19: =$C$19*'Master Inputs'!$C$33*'Master Inputs'!$E$41 -> 90675 | T19: =SUM(Q19:S19) -> 302250
A20: GSB (Glow Sign Board) | B20: 25% active retailers | C20: ='Activity Costs'!C17*'Master Inputs'!$C$48*0.25 -> 3279412.5 | D20: =IF(C$31=0,0,C20/C$31) -> 0.018161204 | E20: =$C$20*'Master Inputs'!$C$30*'Master Inputs'!$C$38 -> 245955.94 | F20: =$C$20*'Master Inputs'!$C$30*'Master Inputs'!$D$38 -> 327941.25 | G20: =$C$20*'Master Inputs'!$C$30*'Master Inputs'!$E$38 -> 245955.94 | H20: =SUM(E20:G20) -> 819853.12 | I20: =$C$20*'Master Inputs'!$C$31*'Master Inputs'!$C$39 -> 147573.56 | J20: =$C$20*'Master Inputs'!$C$31*'Master Inputs'!$D$39 -> 172169.16 | K20: =$C$20*'Master Inputs'!$C$31*'Master Inputs'!$E$39 -> 172169.16 | L20: =SUM(I20:K20) -> 491911.88 | M20: =$C$20*'Master Inputs'!$C$32*'Master Inputs'!$C$40 -> 401728.03 | N20: =$C$20*'Master Inputs'!$C$32*'Master Inputs'!$D$40 -> 344338.31 | O20: =$C$20*'Master Inputs'!$C$32*'Master Inputs'!$E$40 -> 401728.03 | P20: =SUM(M20:O20) -> 1147794.4 | Q20: =$C$20*'Master Inputs'!$C$33*'Master Inputs'!$C$41 -> 327941.25 | R20: =$C$20*'Master Inputs'!$C$33*'Master Inputs'!$D$41 -> 245955.94 | S20: =$C$20*'Master Inputs'!$C$33*'Master Inputs'!$E$41 -> 245955.94 | T20: =SUM(Q20:S20) -> 819853.12
A21: Counter Wall Painting | B21: 20% active retailers | C21: ='Activity Costs'!C18*'Master Inputs'!$C$48*0.2 -> 4030000 | D21: =IF(C$31=0,0,C21/C$31) -> 0.022317916 | E21: =$C$21*'Master Inputs'!$C$30*'Master Inputs'!$C$38 -> 302250 | F21: =$C$21*'Master Inputs'!$C$30*'Master Inputs'!$D$38 -> 403000 | G21: =$C$21*'Master Inputs'!$C$30*'Master Inputs'!$E$38 -> 302250 | H21: =SUM(E21:G21) -> 1007500 | I21: =$C$21*'Master Inputs'!$C$31*'Master Inputs'!$C$39 -> 181350 | J21: =$C$21*'Master Inputs'!$C$31*'Master Inputs'!$D$39 -> 211575 | K21: =$C$21*'Master Inputs'!$C$31*'Master Inputs'!$E$39 -> 211575 | L21: =SUM(I21:K21) -> 604500 | M21: =$C$21*'Master Inputs'!$C$32*'Master Inputs'!$C$40 -> 493675 | N21: =$C$21*'Master Inputs'!$C$32*'Master Inputs'!$D$40 -> 423150 | O21: =$C$21*'Master Inputs'!$C$32*'Master Inputs'!$E$40 -> 493675 | P21: =SUM(M21:O21) -> 1410500 | Q21: =$C$21*'Master Inputs'!$C$33*'Master Inputs'!$C$41 -> 403000 | R21: =$C$21*'Master Inputs'!$C$33*'Master Inputs'!$D$41 -> 302250 | S21: =$C$21*'Master Inputs'!$C$33*'Master Inputs'!$E$41 -> 302250 | T21: =SUM(Q21:S21) -> 1007500
A22: Inshop Branding | B22: 10% active retailers | C22: ='Activity Costs'!C19*'Master Inputs'!$C$48*0.1 -> 8060000 | D22: =IF(C$31=0,0,C22/C$31) -> 0.044635833 | E22: =$C$22*'Master Inputs'!$C$30*'Master Inputs'!$C$38 -> 604500 | F22: =$C$22*'Master Inputs'!$C$30*'Master Inputs'!$D$38 -> 806000 | G22: =$C$22*'Master Inputs'!$C$30*'Master Inputs'!$E$38 -> 604500 | H22: =SUM(E22:G22) -> 2015000 | I22: =$C$22*'Master Inputs'!$C$31*'Master Inputs'!$C$39 -> 362700 | J22: =$C$22*'Master Inputs'!$C$31*'Master Inputs'!$D$39 -> 423150 | K22: =$C$22*'Master Inputs'!$C$31*'Master Inputs'!$E$39 -> 423150 | L22: =SUM(I22:K22) -> 1209000 | M22: =$C$22*'Master Inputs'!$C$32*'Master Inputs'!$C$40 -> 987350 | N22: =$C$22*'Master Inputs'!$C$32*'Master Inputs'!$D$40 -> 846300 | O22: =$C$22*'Master Inputs'!$C$32*'Master Inputs'!$E$40 -> 987350 | P22: =SUM(M22:O22) -> 2821000 | Q22: =$C$22*'Master Inputs'!$C$33*'Master Inputs'!$C$41 -> 806000 | R22: =$C$22*'Master Inputs'!$C$33*'Master Inputs'!$D$41 -> 604500 | S22: =$C$22*'Master Inputs'!$C$33*'Master Inputs'!$E$41 -> 604500 | T22: =SUM(Q22:S22) -> 2015000
A23: Architect/Engineer Meets | B23: 50 pax x 50% dist x 4 qtrs | C23: ='Activity Costs'!C20*50*'Master Inputs'!$C$44*0.5*4 -> 14700000 | D23: =IF(C$31=0,0,C23/C$31) -> 0.081407784 | E23: =$C$23*'Master Inputs'!$C$30*'Master Inputs'!$C$38 -> 1102500 | F23: =$C$23*'Master Inputs'!$C$30*'Master Inputs'!$D$38 -> 1470000 | G23: =$C$23*'Master Inputs'!$C$30*'Master Inputs'!$E$38 -> 1102500 | H23: =SUM(E23:G23) -> 3675000 | I23: =$C$23*'Master Inputs'!$C$31*'Master Inputs'!$C$39 -> 661500 | J23: =$C$23*'Master Inputs'!$C$31*'Master Inputs'!$D$39 -> 771750 | K23: =$C$23*'Master Inputs'!$C$31*'Master Inputs'!$E$39 -> 771750 | L23: =SUM(I23:K23) -> 2205000 | M23: =$C$23*'Master Inputs'!$C$32*'Master Inputs'!$C$40 -> 1800750 | N23: =$C$23*'Master Inputs'!$C$32*'Master Inputs'!$D$40 -> 1543500 | O23: =$C$23*'Master Inputs'!$C$32*'Master Inputs'!$E$40 -> 1800750 | P23: =SUM(M23:O23) -> 5145000 | Q23: =$C$23*'Master Inputs'!$C$33*'Master Inputs'!$C$41 -> 1470000 | R23: =$C$23*'Master Inputs'!$C$33*'Master Inputs'!$D$41 -> 1102500 | S23: =$C$23*'Master Inputs'!$C$33*'Master Inputs'!$E$41 -> 1102500 | T23: =SUM(Q23:S23) -> 3675000
A24: Contractor Meets | B24: 50 pax x all dist x 4 qtrs | C24: ='Activity Costs'!C21*50*'Master Inputs'!$C$44*4 -> 8400000 | D24: =IF(C$31=0,0,C24/C$31) -> 0.046518734 | E24: =$C$24*'Master Inputs'!$C$30*'Master Inputs'!$C$38 -> 630000 | F24: =$C$24*'Master Inputs'!$C$30*'Master Inputs'!$D$38 -> 840000 | G24: =$C$24*'Master Inputs'!$C$30*'Master Inputs'!$E$38 -> 630000 | H24: =SUM(E24:G24) -> 2100000 | I24: =$C$24*'Master Inputs'!$C$31*'Master Inputs'!$C$39 -> 378000 | J24: =$C$24*'Master Inputs'!$C$31*'Master Inputs'!$D$39 -> 441000 | K24: =$C$24*'Master Inputs'!$C$31*'Master Inputs'!$E$39 -> 441000 | L24: =SUM(I24:K24) -> 1260000 | M24: =$C$24*'Master Inputs'!$C$32*'Master Inputs'!$C$40 -> 1029000 | N24: =$C$24*'Master Inputs'!$C$32*'Master Inputs'!$D$40 -> 882000 | O24: =$C$24*'Master Inputs'!$C$32*'Master Inputs'!$E$40 -> 1029000 | P24: =SUM(M24:O24) -> 2940000 | Q24: =$C$24*'Master Inputs'!$C$33*'Master Inputs'!$C$41 -> 840000 | R24: =$C$24*'Master Inputs'!$C$33*'Master Inputs'!$D$41 -> 630000 | S24: =$C$24*'Master Inputs'!$C$33*'Master Inputs'!$E$41 -> 630000 | T24: =SUM(Q24:S24) -> 2100000
A25: Mason Meets | B25: 30 pax x all dist x 4 qtrs | C25: ='Activity Costs'!C22*30*'Master Inputs'!$C$44*4 -> 1512000 | D25: =IF(C$31=0,0,C25/C$31) -> 0.0083733721 | E25: =$C$25*'Master Inputs'!$C$30*'Master Inputs'!$C$38 -> 113400 | F25: =$C$25*'Master Inputs'!$C$30*'Master Inputs'!$D$38 -> 151200 | G25: =$C$25*'Master Inputs'!$C$30*'Master Inputs'!$E$38 -> 113400 | H25: =SUM(E25:G25) -> 378000 | I25: =$C$25*'Master Inputs'!$C$31*'Master Inputs'!$C$39 -> 68040 | J25: =$C$25*'Master Inputs'!$C$31*'Master Inputs'!$D$39 -> 79380 | K25: =$C$25*'Master Inputs'!$C$31*'Master Inputs'!$E$39 -> 79380 | L25: =SUM(I25:K25) -> 226800 | M25: =$C$25*'Master Inputs'!$C$32*'Master Inputs'!$C$40 -> 185220 | N25: =$C$25*'Master Inputs'!$C$32*'Master Inputs'!$D$40 -> 158760 | O25: =$C$25*'Master Inputs'!$C$32*'Master Inputs'!$E$40 -> 185220 | P25: =SUM(M25:O25) -> 529200 | Q25: =$C$25*'Master Inputs'!$C$33*'Master Inputs'!$C$41 -> 151200 | R25: =$C$25*'Master Inputs'!$C$33*'Master Inputs'!$D$41 -> 113400 | S25: =$C$25*'Master Inputs'!$C$33*'Master Inputs'!$E$41 -> 113400 | T25: =SUM(Q25:S25) -> 378000
A26: Dealer Certificates | B26: All active retailers | C26: ='Activity Costs'!C23*'Master Inputs'!$C$48 -> 806000 | D26: =IF(C$31=0,0,C26/C$31) -> 0.0044635833 | E26: =$C$26*'Master Inputs'!$C$30*'Master Inputs'!$C$38 -> 60450 | F26: =$C$26*'Master Inputs'!$C$30*'Master Inputs'!$D$38 -> 80600 | G26: =$C$26*'Master Inputs'!$C$30*'Master Inputs'!$E$38 -> 60450 | H26: =SUM(E26:G26) -> 201500 | I26: =$C$26*'Master Inputs'!$C$31*'Master Inputs'!$C$39 -> 36270 | J26: =$C$26*'Master Inputs'!$C$31*'Master Inputs'!$D$39 -> 42315 | K26: =$C$26*'Master Inputs'!$C$31*'Master Inputs'!$E$39 -> 42315 | L26: =SUM(I26:K26) -> 120900 | M26: =$C$26*'Master Inputs'!$C$32*'Master Inputs'!$C$40 -> 98735 | N26: =$C$26*'Master Inputs'!$C$32*'Master Inputs'!$D$40 -> 84630 | O26: =$C$26*'Master Inputs'!$C$32*'Master Inputs'!$E$40 -> 98735 | P26: =SUM(M26:O26) -> 282100 | Q26: =$C$26*'Master Inputs'!$C$33*'Master Inputs'!$C$41 -> 80600 | R26: =$C$26*'Master Inputs'!$C$33*'Master Inputs'!$D$41 -> 60450 | S26: =$C$26*'Master Inputs'!$C$33*'Master Inputs'!$E$41 -> 60450 | T26: =SUM(Q26:S26) -> 201500
A27: POP Materials Kit | B27: All distributors | C27: ='Activity Costs'!C25*'Master Inputs'!$C$44 -> 126000 | D27: =IF(C$31=0,0,C27/C$31) -> 0.00069778101 | E27: =$C$27*'Master Inputs'!$C$30*'Master Inputs'!$C$38 -> 9450 | F27: =$C$27*'Master Inputs'!$C$30*'Master Inputs'!$D$38 -> 12600 | G27: =$C$27*'Master Inputs'!$C$30*'Master Inputs'!$E$38 -> 9450 | H27: =SUM(E27:G27) -> 31500 | I27: =$C$27*'Master Inputs'!$C$31*'Master Inputs'!$C$39 -> 5670 | J27: =$C$27*'Master Inputs'!$C$31*'Master Inputs'!$D$39 -> 6615 | K27: =$C$27*'Master Inputs'!$C$31*'Master Inputs'!$E$39 -> 6615 | L27: =SUM(I27:K27) -> 18900 | M27: =$C$27*'Master Inputs'!$C$32*'Master Inputs'!$C$40 -> 15435 | N27: =$C$27*'Master Inputs'!$C$32*'Master Inputs'!$D$40 -> 13230 | O27: =$C$27*'Master Inputs'!$C$32*'Master Inputs'!$E$40 -> 15435 | P27: =SUM(M27:O27) -> 44100 | Q27: =$C$27*'Master Inputs'!$C$33*'Master Inputs'!$C$41 -> 12600 | R27: =$C$27*'Master Inputs'!$C$33*'Master Inputs'!$D$41 -> 9450 | S27: =$C$27*'Master Inputs'!$C$33*'Master Inputs'!$E$41 -> 9450 | T27: =SUM(Q27:S27) -> 31500
A28: Distributor Meet (Grand) | B28: Annual convention | C28: ='Activity Costs'!C27*'Master Inputs'!$C$44 -> 4200000 | D28: =IF(C$31=0,0,C28/C$31) -> 0.023259367 | E28: =$C$28*'Master Inputs'!$C$30*'Master Inputs'!$C$38 -> 315000 | F28: =$C$28*'Master Inputs'!$C$30*'Master Inputs'!$D$38 -> 420000 | G28: =$C$28*'Master Inputs'!$C$30*'Master Inputs'!$E$38 -> 315000 | H28: =SUM(E28:G28) -> 1050000 | I28: =$C$28*'Master Inputs'!$C$31*'Master Inputs'!$C$39 -> 189000 | J28: =$C$28*'Master Inputs'!$C$31*'Master Inputs'!$D$39 -> 220500 | K28: =$C$28*'Master Inputs'!$C$31*'Master Inputs'!$E$39 -> 220500 | L28: =SUM(I28:K28) -> 630000 | M28: =$C$28*'Master Inputs'!$C$32*'Master Inputs'!$C$40 -> 514500 | N28: =$C$28*'Master Inputs'!$C$32*'Master Inputs'!$D$40 -> 441000 | O28: =$C$28*'Master Inputs'!$C$32*'Master Inputs'!$E$40 -> 514500 | P28: =SUM(M28:O28) -> 1470000 | Q28: =$C$28*'Master Inputs'!$C$33*'Master Inputs'!$C$41 -> 420000 | R28: =$C$28*'Master Inputs'!$C$33*'Master Inputs'!$D$41 -> 315000 | S28: =$C$28*'Master Inputs'!$C$33*'Master Inputs'!$E$41 -> 315000 | T28: =SUM(Q28:S28) -> 1050000
A29: BTL ACTIVITIES TOTAL | C29: =SUM(C19:C28) -> 46322412 | D29: =IF(C$31=0,0,C29/C$31) -> 0.25653095 | E29: =SUM(E19:E28) -> 3474180.9 | F29: =SUM(F19:F28) -> 4632241.2 | G29: =SUM(G19:G28) -> 3474180.9 | H29: =SUM(H19:H28) -> 11580603 | I29: =SUM(I19:I28) -> 2084508.6 | J29: =SUM(J19:J28) -> 2431926.7 | K29: =SUM(K19:K28) -> 2431926.7 | L29: =SUM(L19:L28) -> 6948361.9 | ... T29: =SUM(T19:T28) -> 11580603
A31: GRAND TOTAL | C31: =C16+C29 -> 1.8057241e+08 | D31: 100.0% | E31: =E16+E29 -> 13542931 | F31: =F16+F29 -> 18057241 | G31: =G16+G29 -> 13542931 | H31: =H16+H29 -> 45143103 | I31: =I16+I29 -> 8125758.6 | J31: =J16+J29 -> 9480051.7 | K31: =K16+K29 -> 9480051.7 | L31: =L16+L29 -> 27085862 | ... T31: =T16+T29 -> 45143103
A32: Allocated Budget | C32: ='Master Inputs'!$C$13 -> 28500000
A33: Variance (Budget - Spend) | C33: =C32-C31 -> -1.5207241e+08
A34: Utilization % | C34: =IF(C32=0,0,C31/C32) -> 6.3358741

Sheet Obj2A East
A1: OBJECTIVE 2A: JSW ONE TMT - EAST INDIA GROWTH (BTL-Focused)
A2: Allocated Budget: | B2: ='Master Inputs'!$C$15 -> 11400000
A4: Activity | B4: Remarks | C4: Year Total | D4: % of Total | E4: Apr | F4: May | G4: Jun | H4: Q1 Total | I4: Jul | J4: Aug | K4: Sep | L4: Q2 Total | M4: Oct | N4: Nov | O4: Dec | P4: Q3 Total | Q4: Jan | R4: Feb | S4: Mar | T4: Q4 Total
A5: ATL ACTIVITIES
A6: Impact Wall Painting | B6: 15K sqft x East districts | C6: ='Activity Costs'!C5*'Master Inputs'!$C$59*15000 -> 27000000 | D6: =IF(C$24=0,0,C6/C$24) -> 0.38070299 | E6: =$C$6*'Master Inputs'!$C$30*'Master Inputs'!$C$38 -> 2025000 | F6: =$C$6*'Master Inputs'!$C$30*'Master Inputs'!$D$38 -> 2700000 | G6: =$C$6*'Master Inputs'!$C$30*'Master Inputs'!$E$38 -> 2025000 | H6: =SUM(E6:G6) -> 6750000 | I6: =$C$6*'Master Inputs'!$C$31*'Master Inputs'!$C$39 -> 1215000 | J6: =$C$6*'Master Inputs'!$C$31*'Master Inputs'!$D$39 -> 1417500 | K6: =$C$6*'Master Inputs'!$C$31*'Master Inputs'!$E$39 -> 1417500 | L6: =SUM(I6:K6) -> 4050000 | M6: =$C$6*'Master Inputs'!$C$32*'Master Inputs'!$C$40 -> 3307500 | N6: =$C$6*'Master Inputs'!$C$32*'Master Inputs'!$D$40 -> 2835000 | O6: =$C$6*'Master Inputs'!$C$32*'Master Inputs'!$E$40 -> 3307500 | P6: =SUM(M6:O6) -> 9450000 | Q6: =$C$6*'Master Inputs'!$C$33*'Master Inputs'!$C$41 -> 2700000 | R6: =$C$6*'Master Inputs'!$C$33*'Master Inputs'!$D$41 -> 2025000 | S6: =$C$6*'Master Inputs'!$C$33*'Master Inputs'!$E$41 -> 2025000 | T6: =SUM(Q6:S6) -> 6750000
A7: Digital Marketing (Regional) | B7: 2 East-focused campaigns | C7: ='Activity Costs'!C8*2 -> 1000000 | D7: =IF(C$24=0,0,C7/C$24) -> 0.014100111 | E7: =$C$7*'Master Inputs'!$C$30*'Master Inputs'!$C$38 -> 75000 | F7: =$C$7*'Master Inputs'!$C$30*'Master Inputs'!$D$38 -> 100000 | G7: =$C$7*'Master Inputs'!$C$30*'Master Inputs'!$E$38 -> 75000 | H7: =SUM(E7:G7) -> 250000 | I7: =$C$7*'Master Inputs'!$C$31*'Master Inputs'!$C$39 -> 45000 | J7: =$C$7*'Master Inputs'!$C$31*'Master Inputs'!$D$39 -> 52500 | K7: =$C$7*'Master Inputs'!$C$31*'Master Inputs'!$E$39 -> 52500 | L7: =SUM(I7:K7) -> 150000 | M7: =$C$7*'Master Inputs'!$C$32*'Master Inputs'!$C$40 -> 122500 | N7: =$C$7*'Master Inputs'!$C$32*'Master Inputs'!$D$40 -> 105000 | O7: =$C$7*'Master Inputs'!$C$32*'Master Inputs'!$E$40 -> 122500 | P7: =SUM(M7:O7) -> 350000 | Q7: =$C$7*'Master Inputs'!$C$33*'Master Inputs'!$C$41 -> 100000 | R7: =$C$7*'Master Inputs'!$C$33*'Master Inputs'!$D$41 -> 75000 | S7: =$C$7*'Master Inputs'!$C$33*'Master Inputs'!$E$41 -> 75000 | T7: =SUM(Q7:S7) -> 250000
A8: Local Market Events | B8: 4 events across East | C8: ='Activity Costs'!C9*4 -> 2000000 | D8: =IF(C$24=0,0,C8/C$24) -> 0.028200222 | E8: =$C$8*'Master Inputs'!$C$30*'Master Inputs'!$C$38 -> 150000 | F8: =$C$8*'Master Inputs'!$C$30*'Master Inputs'!$D$38 -> 200000 | G8: =$C$8*'Master Inputs'!$C$30*'Master Inputs'!$E$38 -> 150000 | H8: =SUM(E8:G8) -> 500000 | I8: =$C$8*'Master Inputs'!$C$31*'Master Inputs'!$C$39 -> 90000 | J8: =$C$8*'Master Inputs'!$C$31*'Master Inputs'!$D$39 -> 105000 | K8: =$C$8*'Master Inputs'!$C$31*'Master Inputs'!$E$39 -> 105000 | L8: =SUM(I8:K8) -> 300000 | M8: =$C$8*'Master Inputs'!$C$32*'Master Inputs'!$C$40 -> 245000 | N8: =$C$8*'Master Inputs'!$C$32*'Master Inputs'!$D$40 -> 210000 | O8: =$C$8*'Master Inputs'!$C$32*'Master Inputs'!$E$40 -> 245000 | P8: =SUM(M8:O8) -> 700000 | Q8: =$C$8*'Master Inputs'!$C$33*'Master Inputs'!$C$41 -> 200000 | R8: =$C$8*'Master Inputs'!$C$33*'Master Inputs'!$D$41 -> 150000 | S8: =$C$8*'Master Inputs'!$C$33*'Master Inputs'!$E$41 -> 150000 | T8: =SUM(Q8:S8) -> 500000
A9: ATL ACTIVITIES TOTAL | C9: =SUM(C6:C8) -> 30000000 | D9: =IF(C$24=0,0,C9/C$24) -> 0.42300333 | E9: =SUM(E6:E8) -> 2250000 | F9: =SUM(F6:F8) -> 3000000 | G9: =SUM(G6:G8) -> 2250000 | H9: =SUM(H6:H8) -> 7500000 | I9: =SUM(I6:I8) -> 1350000 | J9: =SUM(J6:J8) -> 1575000 | K9: =SUM(K6:K8) -> 1575000 | L9: =SUM(L6:L8) -> 4500000 | ... T9: =SUM(T6:T8) -> 7500000
A11: BTL ACTIVITIES
A12: NLB (Name/Lit Board) | B12: 40% of East retailers | C12: ='Activity Costs'!C16*'Master Inputs'!$C$56*'Master Inputs'!$C$62*0.4 -> 457920 | D12: =IF(C$24=0,0,C12/C$24) -> 0.0064567228 | E12: =$C$12*'Master Inputs'!$C$30*'Master Inputs'!$C$38 -> 34344 | F12: =$C$12*'Master Inputs'!$C$30*'Master Inputs'!$D$38 -> 45792 | G12: =$C$12*'Master Inputs'!$C$30*'Master Inputs'!$E$38 -> 34344 | H12: =SUM(E12:G12) -> 114480 | I12: =$C$12*'Master Inputs'!$C$31*'Master Inputs'!$C$39 -> 20606.4 | J12: =$C$12*'Master Inputs'!$C$31*'Master Inputs'!$D$39 -> 24040.8 | K12: =$C$12*'Master Inputs'!$C$31*'Master Inputs'!$E$39 -> 24040.8 | L12: =SUM(I12:K12) -> 68688 | M12: =$C$12*'Master Inputs'!$C$32*'Master Inputs'!$C$40 -> 56095.2 | N12: =$C$12*'Master Inputs'!$C$32*'Master Inputs'!$D$40 -> 48081.6 | O12: =$C$12*'Master Inputs'!$C$32*'Master Inputs'!$E$40 -> 56095.2 | P12: =SUM(M12:O12) -> 160272 | Q12: =$C$12*'Master Inputs'!$C$33*'Master Inputs'!$C$41 -> 45792 | R12: =$C$12*'Master Inputs'!$C$33*'Master Inputs'!$D$41 -> 34344 | S12: =$C$12*'Master Inputs'!$C$33*'Master Inputs'!$E$41 -> 34344 | T12: =SUM(Q12:S12) -> 114480
A13: GSB (Glow Sign Board) | B13: 20% of East retailers | C13: ='Activity Costs'!C17*'Master Inputs'!$C$56*'Master Inputs'!$C$62*0.2 -> 1242108 | D13: =IF(C$24=0,0,C13/C$24) -> 0.017513861 | E13: =$C$13*'Master Inputs'!$C$30*'Master Inputs'!$C$38 -> 93158.1 | F13: =$C$13*'Master Inputs'!$C$30*'Master Inputs'!$D$38 -> 124210.8 | G13: =$C$13*'Master Inputs'!$C$30*'Master Inputs'!$E$38 -> 93158.1 | H13: =SUM(E13:G13) -> 310527 | I13: =$C$13*'Master Inputs'!$C$31*'Master Inputs'!$C$39 -> 55894.86 | J13: =$C$13*'Master Inputs'!$C$31*'Master Inputs'!$D$39 -> 65210.67 | K13: =$C$13*'Master Inputs'!$C$31*'Master Inputs'!$E$39 -> 65210.67 | L13: =SUM(I13:K13) -> 186316.2 | M13: =$C$13*'Master Inputs'!$C$32*'Master Inputs'!$C$40 -> 152158.23 | N13: =$C$13*'Master Inputs'!$C$32*'Master Inputs'!$D$40 -> 130421.34 | O13: =$C$13*'Master Inputs'!$C$32*'Master Inputs'!$E$40 -> 152158.23 | P13: =SUM(M13:O13) -> 434737.8 | Q13: =$C$13*'Master Inputs'!$C$33*'Master Inputs'!$C$41 -> 124210.8 | R13: =$C$13*'Master Inputs'!$C$33*'Master Inputs'!$D$41 -> 93158.1 | S13: =$C$13*'Master Inputs'!$C$33*'Master Inputs'!$E$41 -> 93158.1 | T13: =SUM(Q13:S13) -> 310527
A14: Counter Wall Painting | B14: 15% of East retailers | C14: ='Activity Costs'!C18*'Master Inputs'!$C$56*'Master Inputs'!$C$62*0.15 -> 1431000 | D14: =IF(C$24=0,0,C14/C$24) -> 0.020177259 | E14: =$C$14*'Master Inputs'!$C$30*'Master Inputs'!$C$38 -> 107325 | F14: =$C$14*'Master Inputs'!$C$30*'Master Inputs'!$D$38 -> 143100 | G14: =$C$14*'Master Inputs'!$C$30*'Master Inputs'!$E$38 -> 107325 | H14: =SUM(E14:G14) -> 357750 | I14: =$C$14*'Master Inputs'!$C$31*'Master Inputs'!$C$39 -> 64395 | J14: =$C$14*'Master Inputs'!$C$31*'Master Inputs'!$D$39 -> 75127.5 | K14: =$C$14*'Master Inputs'!$C$31*'Master Inputs'!$E$39 -> 75127.5 | L14: =SUM(I14:K14) -> 214650 | M14: =$C$14*'Master Inputs'!$C$32*'Master Inputs'!$C$40 -> 175297.5 | N14: =$C$14*'Master Inputs'!$C$32*'Master Inputs'!$D$40 -> 150255 | O14: =$C$14*'Master Inputs'!$C$32*'Master Inputs'!$E$40 -> 175297.5 | P14: =SUM(M14:O14) -> 500850 | Q14: =$C$14*'Master Inputs'!$C$33*'Master Inputs'!$C$41 -> 143100 | R14: =$C$14*'Master Inputs'!$C$33*'Master Inputs'!$D$41 -> 107325 | S14: =$C$14*'Master Inputs'!$C$33*'Master Inputs'!$E$41 -> 107325 | T14: =SUM(Q14:S14) -> 357750
A15: Architect/Engineer Meets | B15: 50 pax x East dist x 4 qtrs | C15: ='Activity Costs'!C20*50*'Master Inputs'!$C$52*'Master Inputs'!$C$62*4 -> 23520000 | D15: =IF(C$24=0,0,C15/C$24) -> 0.33163461 | E15: =$C$15*'Master Inputs'!$C$30*'Master Inputs'!$C$38 -> 1764000 | F15: =$C$15*'Master Inputs'!$C$30*'Master Inputs'!$D$38 -> 2352000 | G15: =$C$15*'Master Inputs'!$C$30*'Master Inputs'!$E$38 -> 1764000 | H15: =SUM(E15:G15) -> 5880000 | I15: =$C$15*'Master Inputs'!$C$31*'Master Inputs'!$C$39 -> 1058400 | J15: =$C$15*'Master Inputs'!$C$31*'Master Inputs'!$D$39 -> 1234800 | K15: =$C$15*'Master Inputs'!$C$31*'Master Inputs'!$E$39 -> 1234800 | L15: =SUM(I15:K15) -> 3528000 | M15: =$C$15*'Master Inputs'!$C$32*'Master Inputs'!$C$40 -> 2881200 | N15: =$C$15*'Master Inputs'!$C$32*'Master Inputs'!$D$40 -> 2469600 | O15: =$C$15*'Master Inputs'!$C$32*'Master Inputs'!$E$40 -> 2881200 | P15: =SUM(M15:O15) -> 8232000 | Q15: =$C$15*'Master Inputs'!$C$33*'Master Inputs'!$C$41 -> 2352000 | R15: =$C$15*'Master Inputs'!$C$33*'Master Inputs'!$D$41 -> 1764000 | S15: =$C$15*'Master Inputs'!$C$33*'Master Inputs'!$E$41 -> 1764000 | T15: =SUM(Q15:S15) -> 5880000
A16: Contractor Meets | B16: 50 pax x East dist x 4 qtrs | C16: ='Activity Costs'!C21*50*'Master Inputs'!$C$52*'Master Inputs'!$C$62*4 -> 6720000 | D16: =IF(C$24=0,0,C16/C$24) -> 0.094752745 | E16: =$C$16*'Master Inputs'!$C$30*'Master Inputs'!$C$38 -> 504000 | F16: =$C$16*'Master Inputs'!$C$30*'Master Inputs'!$D$38 -> 672000 | G16: =$C$16*'Master Inputs'!$C$30*'Master Inputs'!$E$38 -> 504000 | H16: =SUM(E16:G16) -> 1680000 | I16: =$C$16*'Master Inputs'!$C$31*'Master Inputs'!$C$39 -> 302400 | J16: =$C$16*'Master Inputs'!$C$31*'Master Inputs'!$D$39 -> 352800 | K16: =$C$16*'Master Inputs'!$C$31*'Master Inputs'!$E$39 -> 352800 | L16: =SUM(I16:K16) -> 1008000 | M16: =$C$16*'Master Inputs'!$C$32*'Master Inputs'!$C$40 -> 823200 | N16: =$C$16*'Master Inputs'!$C$32*'Master Inputs'!$D$40 -> 705600 | O16: =$C$16*'Master Inputs'!$C$32*'Master Inputs'!$E$40 -> 823200 | P16: =SUM(M16:O16) -> 2352000 | Q16: =$C$16*'Master Inputs'!$C$33*'Master Inputs'!$C$41 -> 672000 | R16: =$C$16*'Master Inputs'!$C$33*'Master Inputs'!$D$41 -> 504000 | S16: =$C$16*'Master Inputs'!$C$33*'Master Inputs'!$E$41 -> 504000 | T16: =SUM(Q16:S16) -> 1680000
A17: Mason Meets | B17: 30 pax x East dist x 4 qtrs | C17: ='Activity Costs'!C22*30*'Master Inputs'!$C$52*'Master Inputs'!$C$62*4 -> 1209600 | D17: =IF(C$24=0,0,C17/C$24) -> 0.017055494 | E17: =$C$17*'Master Inputs'!$C$30*'Master Inputs'!$C$38 -> 90720 | F17: =$C$17*'Master Inputs'!$C$30*'Master Inputs'!$D$38 -> 120960 | G17: =$C$17*'Master Inputs'!$C$30*'Master Inputs'!$E$38 -> 90720 | H17: =SUM(E17:G17) -> 302400 | I17: =$C$17*'Master Inputs'!$C$31*'Master Inputs'!$C$39 -> 54432 | J17: =$C$17*'Master Inputs'!$C$31*'Master Inputs'!$D$39 -> 63504 | K17: =$C$17*'Master Inputs'!$C$31*'Master Inputs'!$E$39 -> 63504 | L17: =SUM(I17:K17) -> 181440 | M17: =$C$17*'Master Inputs'!$C$32*'Master Inputs'!$C$40 -> 148176 | N17: =$C$17*'Master Inputs'!$C$32*'Master Inputs'!$D$40 -> 127008 | O17: =$C$17*'Master Inputs'!$C$32*'Master Inputs'!$E$40 -> 148176 | P17: =SUM(M17:O17) -> 423360 | Q17: =$C$17*'Master Inputs'!$C$33*'Master Inputs'!$C$41 -> 120960 | R17: =$C$17*'Master Inputs'!$C$33*'Master Inputs'!$D$41 -> 90720 | S17: =$C$17*'Master Inputs'!$C$33*'Master Inputs'!$E$41 -> 90720 | T17: =SUM(Q17:S17) -> 302400
A18: Construction Site Gate Boards | B18: 5 boards per district | C18: ='Activity Costs'!C24*'Master Inputs'!$C$59*5 -> 900000 | D18: =IF(C$24=0,0,C18/C$24) -> 0.0126901 | E18: =$C$18*'Master Inputs'!$C$30*'Master Inputs'!$C$38 -> 67500 | F18: =$C$18*'Master Inputs'!$C$30*'Master Inputs'!$D$38 -> 90000 | G18: =$C$18*'Master Inputs'!$C$30*'Master Inputs'!$E$38 -> 67500 | H18: =SUM(E18:G18) -> 225000 | I18: =$C$18*'Master Inputs'!$C$31*'Master Inputs'!$C$39 -> 40500 | J18: =$C$18*'Master Inputs'!$C$31*'Master Inputs'!$D$39 -> 47250 | K18: =$C$18*'Master Inputs'!$C$31*'Master Inputs'!$E$39 -> 47250 | L18: =SUM(I18:K18) -> 135000 | M18: =$C$18*'Master Inputs'!$C$32*'Master Inputs'!$C$40 -> 110250 | N18: =$C$18*'Master Inputs'!$C$32*'Master Inputs'!$D$40 -> 94500 | O18: =$C$18*'Master Inputs'!$C$32*'Master Inputs'!$E$40 -> 110250 | P18: =SUM(M18:O18) -> 315000 | Q18: =$C$18*'Master Inputs'!$C$33*'Master Inputs'!$C$41 -> 90000 | R18: =$C$18*'Master Inputs'!$C$33*'Master Inputs'!$D$41 -> 67500 | S18: =$C$18*'Master Inputs'!$C$33*'Master Inputs'!$E$41 -> 67500 | T18: =SUM(Q18:S18) -> 225000
A19: POP Materials Kit | B19: East distributors | C19: ='Activity Costs'!C25*'Master Inputs'!$C$52*'Master Inputs'!$C$62 -> 100800 | D19: =IF(C$24=0,0,C19/C$24) -> 0.0014212912 | E19: =$C$19*'Master Inputs'!$C$30*'Master Inputs'!$C$38 -> 7560 | F19: =$C$19*'Master Inputs'!$C$30*'Master Inputs'!$D$38 -> 10080 | G19: =$C$19*'Master Inputs'!$C$30*'Master Inputs'!$E$38 -> 7560 | H19: =SUM(E19:G19) -> 25200 | I19: =$C$19*'Master Inputs'!$C$31*'Master Inputs'!$C$39 -> 4536 | J19: =$C$19*'Master Inputs'!$C$31*'Master Inputs'!$D$39 -> 5292 | K19: =$C$19*'Master Inputs'!$C$31*'Master Inputs'!$E$39 -> 5292 | L19: =SUM(I19:K19) -> 15120 | M19: =$C$19*'Master Inputs'!$C$32*'Master Inputs'!$C$40 -> 12348 | N19: =$C$19*'Master Inputs'!$C$32*'Master Inputs'!$D$40 -> 10584 | O19: =$C$19*'Master Inputs'!$C$32*'Master Inputs'!$E$40 -> 12348 | P19: =SUM(M19:O19) -> 35280 | Q19: =$C$19*'Master Inputs'!$C$33*'Master Inputs'!$C$41 -> 10080 | R19: =$C$19*'Master Inputs'!$C$33*'Master Inputs'!$D$41 -> 7560 | S19: =$C$19*'Master Inputs'!$C$33*'Master Inputs'!$E$41 -> 7560 | T19: =SUM(Q19:S19) -> 25200
A20: Retailer Loyalty Program | B20: Per transacting retailer x 4 qtrs | C20: ='Activity Costs'!C28*'Master Inputs'!$C$57*'Master Inputs'!$C$62*4 -> 4958400 | D20: =IF(C$24=0,0,C20/C$24) -> 0.06991399 | E20: =$C$20*'Master Inputs'!$C$30*'Master Inputs'!$C$38 -> 371880 | F20: =$C$20*'Master Inputs'!$C$30*'Master Inputs'!$D$38 -> 495840 | G20: =$C$20*'Master Inputs'!$C$30*'Master Inputs'!$E$38 -> 371880 | H20: =SUM(E20:G20) -> 1239600 | I20: =$C$20*'Master Inputs'!$C$31*'Master Inputs'!$C$39 -> 223128 | J20: =$C$20*'Master Inputs'!$C$31*'Master Inputs'!$D$39 -> 260316 | K20: =$C$20*'Master Inputs'!$C$31*'Master Inputs'!$E$39 -> 260316 | L20: =SUM(I20:K20) -> 743760 | M20: =$C$20*'Master Inputs'!$C$32*'Master Inputs'!$C$40 -> 607404 | N20: =$C$20*'Master Inputs'!$C$32*'Master Inputs'!$D$40 -> 520632 | O20: =$C$20*'Master Inputs'!$C$32*'Master Inputs'!$E$40 -> 607404 | P20: =SUM(M20:O20) -> 1735440 | Q20: =$C$20*'Master Inputs'!$C$33*'Master Inputs'!$C$41 -> 495840 | R20: =$C$20*'Master Inputs'!$C$33*'Master Inputs'!$D$41 -> 371880 | S20: =$C$20*'Master Inputs'!$C$33*'Master Inputs'!$E$41 -> 371880 | T20: =SUM(Q20:S20) -> 1239600
A21: Dealer Certificates | B21: East active retailers | C21: ='Activity Costs'!C23*'Master Inputs'!$C$56*'Master Inputs'!$C$62 -> 381600 | D21: =IF(C$24=0,0,C21/C$24) -> 0.0053806023 | E21: =$C$21*'Master Inputs'!$C$30*'Master Inputs'!$C$38 -> 28620 | F21: =$C$21*'Master Inputs'!$C$30*'Master Inputs'!$D$38 -> 38160 | G21: =$C$21*'Master Inputs'!$C$30*'Master Inputs'!$E$38 -> 28620 | H21: =SUM(E21:G21) -> 95400 | I21: =$C$21*'Master Inputs'!$C$31*'Master Inputs'!$C$39 -> 17172 | J21: =$C$21*'Master Inputs'!$C$31*'Master Inputs'!$D$39 -> 20034 | K21: =$C$21*'Master Inputs'!$C$31*'Master Inputs'!$E$39 -> 20034 | L21: =SUM(I21:K21) -> 57240 | M21: =$C$21*'Master Inputs'!$C$32*'Master Inputs'!$C$40 -> 46746 | N21: =$C$21*'Master Inputs'!$C$32*'Master Inputs'!$D$40 -> 40068 | O21: =$C$21*'Master Inputs'!$C$32*'Master Inputs'!$E$40 -> 46746 | P21: =SUM(M21:O21) -> 133560 | Q21: =$C$21*'Master Inputs'!$C$33*'Master Inputs'!$C$41 -> 38160 | R21: =$C$21*'Master Inputs'!$C$33*'Master Inputs'!$D$41 -> 28620 | S21: =$C$21*'Master Inputs'!$C$33*'Master Inputs'!$E$41 -> 28620 | T21: =SUM(Q21:S21) -> 95400
A22: BTL ACTIVITIES TOTAL | C22: =SUM(C12:C21) -> 40921428 | D22: =IF(C$24=0,0,C22/C$24) -> 0.57699667 | E22: =SUM(E12:E21) -> 3069107.1 | F22: =SUM(F12:F21) -> 4092142.8 | G22: =SUM(G12:G21) -> 3069107.1 | H22: =SUM(H12:H21) -> 10230357 | I22: =SUM(I12:I21) -> 1841464.3 | J22: =SUM(J12:J21) -> 2148375 | K22: =SUM(K12:K21) -> 2148375 | L22: =SUM(L12:L21) -> 6138214.2 | ... T22: =SUM(T12:T21) -> 10230357
A24: GRAND TOTAL | C24: =C9+C22 -> 70921428 | D24: 100.0% | E24: =E9+E22 -> 5319107.1 | F24: =F9+F22 -> 7092142.8 | G24: =G9+G22 -> 5319107.1 | H24: =H9+H22 -> 17730357 | I24: =I9+I22 -> 3191464.3 | J24: =J9+J22 -> 3723375 | K24: =K9+K22 -> 3723375 | L24: =L9+L22 -> 10638214 | ... T24: =T9+T22 -> 17730357
A25: Allocated Budget | C25: ='Master Inputs'!$C$15 -> 11400000
A26: Variance (Budget - Spend) | C26: =C25-C24 -> -59521428
A27: Utilization % | C27: =IF(C25=0,0,C24/C25) -> 6.2211779

Sheet Obj2B UPHR
A1: OBJECTIVE 2B: JSW ONE TMT - UP & HARYANA INTENSIVE (2x Volume Target)
A2: Allocated Budget: | B2: ='Master Inputs'!$C$16 -> 7600000
A4: Activity | B4: Remarks | C4: Year Total | D4: % of Total | E4: Apr | F4: May | G4: Jun | H4: Q1 Total | I4: Jul | J4: Aug | K4: Sep | L4: Q2 Total | M4: Oct | N4: Nov | O4: Dec | P4: Q3 Total | Q4: Jan | R4: Feb | S4: Mar | T4: Q4 Total
A5: ATL ACTIVITIES
A6: Impact Wall Painting | B6: 15K sqft x UP+HR districts | C6: ='Activity Costs'!C5*'Master Inputs'!$C$60*15000 -> 16650000 | D6: =IF(C$26=0,0,C6/C$26) -> 0.063353583 | E6: =$C$6*'Master Inputs'!$C$30*'Master Inputs'!$C$38 -> 1248750 | F6: =$C$6*'Master Inputs'!$C$30*'Master Inputs'!$D$38 -> 1665000 | G6: =$C$6*'Master Inputs'!$C$30*'Master Inputs'!$E$38 -> 1248750 | H6: =SUM(E6:G6) -> 4162500 | I6: =$C$6*'Master Inputs'!$C$31*'Master Inputs'!$C$39 -> 749250 | J6: =$C$6*'Master Inputs'!$C$31*'Master Inputs'!$D$39 -> 874125 | K6: =$C$6*'Master Inputs'!$C$31*'Master Inputs'!$E$39 -> 874125 | L6: =SUM(I6:K6) -> 2497500 | M6: =$C$6*'Master Inputs'!$C$32*'Master Inputs'!$C$40 -> 2039625 | N6: =$C$6*'Master Inputs'!$C$32*'Master Inputs'!$D$40 -> 1748250 | O6: =$C$6*'Master Inputs'!$C$32*'Master Inputs'!$E$40 -> 2039625 | P6: =SUM(M6:O6) -> 5827500 | Q6: =$C$6*'Master Inputs'!$C$33*'Master Inputs'!$C$41 -> 1665000 | R6: =$C$6*'Master Inputs'!$C$33*'Master Inputs'!$D$41 -> 1248750 | S6: =$C$6*'Master Inputs'!$C$33*'Master Inputs'!$E$41 -> 1248750 | T6: =SUM(Q6:S6) -> 4162500
A7: Transit Auto Branding | B7: 200 autos in UP+HR | C7: ='Activity Costs'!C12*200 -> 140000 | D7: =IF(C$26=0,0,C7/C$26) -> 0.0005327028 | E7: =$C$7*'Master Inputs'!$C$30*'Master Inputs'!$C$38 -> 10500 | F7: =$C$7*'Master Inputs'!$C$30*'Master Inputs'!$D$38 -> 14000 | G7: =$C$7*'Master Inputs'!$C$30*'Master Inputs'!$E$38 -> 10500 | H7: =SUM(E7:G7) -> 35000 | I7: =$C$7*'Master Inputs'!$C$31*'Master Inputs'!$C$39 -> 6300 | J7: =$C$7*'Master Inputs'!$C$31*'Master Inputs'!$D$39 -> 7350 | K7: =$C$7*'Master Inputs'!$C$31*'Master Inputs'!$E$39 -> 7350 | L7: =SUM(I7:K7) -> 21000 | M7: =$C$7*'Master Inputs'!$C$32*'Master Inputs'!$C$40 -> 17150 | N7: =$C$7*'Master Inputs'!$C$32*'Master Inputs'!$D$40 -> 14700 | O7: =$C$7*'Master Inputs'!$C$32*'Master Inputs'!$E$40 -> 17150 | P7: =SUM(M7:O7) -> 49000 | Q7: =$C$7*'Master Inputs'!$C$33*'Master Inputs'!$C$41 -> 14000 | R7: =$C$7*'Master Inputs'!$C$33*'Master Inputs'!$D$41 -> 10500 | S7: =$C$7*'Master Inputs'!$C$33*'Master Inputs'!$E$41 -> 10500 | T7: =SUM(Q7:S7) -> 35000
A8: ATL ACTIVITIES TOTAL | C8: =SUM(C6:C7) -> 16790000 | D8: =IF(C$26=0,0,C8/C$26) -> 0.063886286 | E8: =SUM(E6:E7) -> 1259250 | F8: =SUM(F6:F7) -> 1679000 | G8: =SUM(G6:G7) -> 1259250 | H8: =SUM(H6:H7) -> 4197500 | I8: =SUM(I6:I7) -> 755550 | J8: =SUM(J6:J7) -> 881475 | K8: =SUM(K6:K7) -> 881475 | L8: =SUM(L6:L7) -> 2518500 | ... T8: =SUM(T6:T7) -> 4197500
A10: BTL ACTIVITIES
A11: NLB (Name/Lit Board) | B11: 50% UP+HR retailers | C11: ='Activity Costs'!C16*'Master Inputs'!$C$56*'Master Inputs'!$C$63*0.5 -> 381600 | D11: =IF(C$26=0,0,C11/C$26) -> 0.0014519956 | E11: =$C$11*'Master Inputs'!$C$30*'Master Inputs'!$C$38 -> 28620 | F11: =$C$11*'Master Inputs'!$C$30*'Master Inputs'!$D$38 -> 38160 | G11: =$C$11*'Master Inputs'!$C$30*'Master Inputs'!$E$38 -> 28620 | H11: =SUM(E11:G11) -> 95400 | I11: =$C$11*'Master Inputs'!$C$31*'Master Inputs'!$C$39 -> 17172 | J11: =$C$11*'Master Inputs'!$C$31*'Master Inputs'!$D$39 -> 20034 | K11: =$C$11*'Master Inputs'!$C$31*'Master Inputs'!$E$39 -> 20034 | L11: =SUM(I11:K11) -> 57240 | M11: =$C$11*'Master Inputs'!$C$32*'Master Inputs'!$C$40 -> 46746 | N11: =$C$11*'Master Inputs'!$C$32*'Master Inputs'!$D$40 -> 40068 | O11: =$C$11*'Master Inputs'!$C$32*'Master Inputs'!$E$40 -> 46746 | P11: =SUM(M11:O11) -> 133560 | Q11: =$C$11*'Master Inputs'!$C$33*'Master Inputs'!$C$41 -> 38160 | R11: =$C$11*'Master Inputs'!$C$33*'Master Inputs'!$D$41 -> 28620 | S11: =$C$11*'Master Inputs'!$C$33*'Master Inputs'!$E$41 -> 28620 | T11: =SUM(Q11:S11) -> 95400
A12: GSB (Glow Sign Board) | B12: 30% UP+HR retailers | C12: ='Activity Costs'!C17*'Master Inputs'!$C$56*'Master Inputs'!$C$63*0.3 -> 1242108 | D12: =IF(C$26=0,0,C12/C$26) -> 0.0047262458 | E12: =$C$12*'Master Inputs'!$C$30*'Master Inputs'!$C$38 -> 93158.1 | F12: =$C$12*'Master Inputs'!$C$30*'Master Inputs'!$D$38 -> 124210.8 | G12: =$C$12*'Master Inputs'!$C$30*'Master Inputs'!$E$38 -> 93158.1 | H12: =SUM(E12:G12) -> 310527 | I12: =$C$12*'Master Inputs'!$C$31*'Master Inputs'!$C$39 -> 55894.86 | J12: =$C$12*'Master Inputs'!$C$31*'Master Inputs'!$D$39 -> 65210.67 | K12: =$C$12*'Master Inputs'!$C$31*'Master Inputs'!$E$39 -> 65210.67 | L12: =SUM(I12:K12) -> 186316.2 | M12: =$C$12*'Master Inputs'!$C$32*'Master Inputs'!$C$40 -> 152158.23 | N12: =$C$12*'Master Inputs'!$C$32*'Master Inputs'!$D$40 -> 130421.34 | O12: =$C$12*'Master Inputs'!$C$32*'Master Inputs'!$E$40 -> 152158.23 | P12: =SUM(M12:O12) -> 434737.8 | Q12: =$C$12*'Master Inputs'!$C$33*'Master Inputs'!$C$41 -> 124210.8 | R12: =$C$12*'Master Inputs'!$C$33*'Master Inputs'!$D$41 -> 93158.1 | S12: =$C$12*'Master Inputs'!$C$33*'Master Inputs'!$E$41 -> 93158.1 | T12: =SUM(Q12:S12) -> 310527
A13: Counter Wall Painting | B13: 20% UP+HR retailers | C13: ='Activity Costs'!C18*'Master Inputs'!$C$56*'Master Inputs'!$C$63*0.2 -> 1272000 | D13: =IF(C$26=0,0,C13/C$26) -> 0.0048399854 | E13: =$C$13*'Master Inputs'!$C$30*'Master Inputs'!$C$38 -> 95400 | F13: =$C$13*'Master Inputs'!$C$30*'Master Inputs'!$D$38 -> 127200 | G13: =$C$13*'Master Inputs'!$C$30*'Master Inputs'!$E$38 -> 95400 | H13: =SUM(E13:G13) -> 318000 | I13: =$C$13*'Master Inputs'!$C$31*'Master Inputs'!$C$39 -> 57240 | J13: =$C$13*'Master Inputs'!$C$31*'Master Inputs'!$D$39 -> 66780 | K13: =$C$13*'Master Inputs'!$C$31*'Master Inputs'!$E$39 -> 66780 | L13: =SUM(I13:K13) -> 190800 | M13: =$C$13*'Master Inputs'!$C$32*'Master Inputs'!$C$40 -> 155820 | N13: =$C$13*'Master Inputs'!$C$32*'Master Inputs'!$D$40 -> 133560 | O13: =$C$13*'Master Inputs'!$C$32*'Master Inputs'!$E$40 -> 155820 | P13: =SUM(M13:O13) -> 445200 | Q13: =$C$13*'Master Inputs'!$C$33*'Master Inputs'!$C$41 -> 127200 | R13: =$C$13*'Master Inputs'!$C$33*'Master Inputs'!$D$41 -> 95400 | S13: =$C$13*'Master Inputs'!$C$33*'Master Inputs'!$E$41 -> 95400 | T13: =SUM(Q13:S13) -> 318000
A14: Inshop Branding | B14: 10% premium retailers | C14: ='Activity Costs'!C19*'Master Inputs'!$C$56*'Master Inputs'!$C$63*0.1 -> 2544000 | D14: =IF(C$26=0,0,C14/C$26) -> 0.0096799709 | E14: =$C$14*'Master Inputs'!$C$30*'Master Inputs'!$C$38 -> 190800 | F14: =$C$14*'Master Inputs'!$C$30*'Master Inputs'!$D$38 -> 254400 | G14: =$C$14*'Master Inputs'!$C$30*'Master Inputs'!$E$38 -> 190800 | H14: =SUM(E14:G14) -> 636000 | I14: =$C$14*'Master Inputs'!$C$31*'Master Inputs'!$C$39 -> 114480 | J14: =$C$14*'Master Inputs'!$C$31*'Master Inputs'!$D$39 -> 133560 | K14: =$C$14*'Master Inputs'!$C$31*'Master Inputs'!$E$39 -> 133560 | L14: =SUM(I14:K14) -> 381600 | M14: =$C$14*'Master Inputs'!$C$32*'Master Inputs'!$C$40 -> 311640 | N14: =$C$14*'Master Inputs'!$C$32*'Master Inputs'!$D$40 -> 267120 | O14: =$C$14*'Master Inputs'!$C$32*'Master Inputs'!$E$40 -> 311640 | P14: =SUM(M14:O14) -> 890400 | Q14: =$C$14*'Master Inputs'!$C$33*'Master Inputs'!$C$41 -> 254400 | R14: =$C$14*'Master Inputs'!$C$33*'Master Inputs'!$D$41 -> 190800 | S14: =$C$14*'Master Inputs'!$C$33*'Master Inputs'!$E$41 -> 190800 | T14: =SUM(Q14:S14) -> 636000
A15: Monthly Dealer Conclaves | B15: 30% dealers x 50 pax x 12 months | C15: ='Activity Costs'!C20*50*('Master Inputs'!$C$77+'Master Inputs'!$C$78)*0.3*12 -> 146790000 | D15: =IF(C$26=0,0,C15/C$26) -> 0.55853889 | E15: =$C$15*'Master Inputs'!$C$30*'Master Inputs'!$C$38 -> 11009250 | F15: =$C$15*'Master Inputs'!$C$30*'Master Inputs'!$D$38 -> 14679000 | G15: =$C$15*'Master Inputs'!$C$30*'Master Inputs'!$E$38 -> 11009250 | H15: =SUM(E15:G15) -> 36697500 | I15: =$C$15*'Master Inputs'!$C$31*'Master Inputs'!$C$39 -> 6605550 | J15: =$C$15*'Master Inputs'!$C$31*'Master Inputs'!$D$39 -> 7706475 | K15: =$C$15*'Master Inputs'!$C$31*'Master Inputs'!$E$39 -> 7706475 | L15: =SUM(I15:K15) -> 22018500 | M15: =$C$15*'Master Inputs'!$C$32*'Master Inputs'!$C$40 -> 17981775 | N15: =$C$15*'Master Inputs'!$C$32*'Master Inputs'!$D$40 -> 15412950 | O15: =$C$15*'Master Inputs'!$C$32*'Master Inputs'!$E$40 -> 17981775 | P15: =SUM(M15:O15) -> 51376500 | Q15: =$C$15*'Master Inputs'!$C$33*'Master Inputs'!$C$41 -> 14679000 | R15: =$C$15*'Master Inputs'!$C$33*'Master Inputs'!$D$41 -> 11009250 | S15: =$C$15*'Master Inputs'!$C$33*'Master Inputs'!$E$41 -> 11009250 | T15: =SUM(Q15:S15) -> 36697500
A16: Contractor Meets (Bi-weekly) | B16: 50% dealers x 30 pax x 24 meets | C16: ='Activity Costs'!C21*30*('Master Inputs'!$C$77+'Master Inputs'!$C$78)*0.5*24 -> 83880000 | D16: =IF(C$26=0,0,C16/C$26) -> 0.31916508 | E16: =$C$16*'Master Inputs'!$C$30*'Master Inputs'!$C$38 -> 6291000 | F16: =$C$16*'Master Inputs'!$C$30*'Master Inputs'!$D$38 -> 8388000 | G16: =$C$16*'Master Inputs'!$C$30*'Master Inputs'!$E$38 -> 6291000 | H16: =SUM(E16:G16) -> 20970000 | I16: =$C$16*'Master Inputs'!$C$31*'Master Inputs'!$C$39 -> 3774600 | J16: =$C$16*'Master Inputs'!$C$31*'Master Inputs'!$D$39 -> 4403700 | K16: =$C$16*'Master Inputs'!$C$31*'Master Inputs'!$E$39 -> 4403700 | L16: =SUM(I16:K16) -> 12582000 | M16: =$C$16*'Master Inputs'!$C$32*'Master Inputs'!$C$40 -> 10275300 | N16: =$C$16*'Master Inputs'!$C$32*'Master Inputs'!$D$40 -> 8807400 | O16: =$C$16*'Master Inputs'!$C$32*'Master Inputs'!$E$40 -> 10275300 | P16: =SUM(M16:O16) -> 29358000 | Q16: =$C$16*'Master Inputs'!$C$33*'Master Inputs'!$C$41 -> 8388000 | R16: =$C$16*'Master Inputs'!$C$33*'Master Inputs'!$D$41 -> 6291000 | S16: =$C$16*'Master Inputs'!$C$33*'Master Inputs'!$E$41 -> 6291000 | T16: =SUM(Q16:S16) -> 20970000
A17: Mason Training Camps | B17: 4 camps per district/year | C17: ='Activity Costs'!C29*'Master Inputs'!$C$60*4 -> 1480000 | D17: =IF(C$26=0,0,C17/C$26) -> 0.0056314296 | E17: =$C$17*'Master Inputs'!$C$30*'Master Inputs'!$C$38 -> 111000 | F17: =$C$17*'Master Inputs'!$C$30*'Master Inputs'!$D$38 -> 148000 | G17: =$C$17*'Master Inputs'!$C$30*'Master Inputs'!$E$38 -> 111000 | H17: =SUM(E17:G17) -> 370000 | I17: =$C$17*'Master Inputs'!$C$31*'Master Inputs'!$C$39 -> 66600 | J17: =$C$17*'Master Inputs'!$C$31*'Master Inputs'!$D$39 -> 77700 | K17: =$C$17*'Master Inputs'!$C$31*'Master Inputs'!$E$39 -> 77700 | L17: =SUM(I17:K17) -> 222000 | M17: =$C$17*'Master Inputs'!$C$32*'Master Inputs'!$C$40 -> 181300 | N17: =$C$17*'Master Inputs'!$C$32*'Master Inputs'!$D$40 -> 155400 | O17: =$C$17*'Master Inputs'!$C$32*'Master Inputs'!$E$40 -> 181300 | P17: =SUM(M17:O17) -> 518000 | Q17: =$C$17*'Master Inputs'!$C$33*'Master Inputs'!$C$41 -> 148000 | R17: =$C$17*'Master Inputs'!$C$33*'Master Inputs'!$D$41 -> 111000 | S17: =$C$17*'Master Inputs'!$C$33*'Master Inputs'!$E$41 -> 111000 | T17: =SUM(Q17:S17) -> 370000
A18: Construction Site Gate Boards | B18: 8 boards per district | C18: ='Activity Costs'!C24*'Master Inputs'!$C$60*8 -> 888000 | D18: =IF(C$26=0,0,C18/C$26) -> 0.0033788578 | E18: =$C$18*'Master Inputs'!$C$30*'Master Inputs'!$C$38 -> 66600 | F18: =$C$18*'Master Inputs'!$C$30*'Master Inputs'!$D$38 -> 88800 | G18: =$C$18*'Master Inputs'!$C$30*'Master Inputs'!$E$38 -> 66600 | H18: =SUM(E18:G18) -> 222000 | I18: =$C$18*'Master Inputs'!$C$31*'Master Inputs'!$C$39 -> 39960 | J18: =$C$18*'Master Inputs'!$C$31*'Master Inputs'!$D$39 -> 46620 | K18: =$C$18*'Master Inputs'!$C$31*'Master Inputs'!$E$39 -> 46620 | L18: =SUM(I18:K18) -> 133200 | M18: =$C$18*'Master Inputs'!$C$32*'Master Inputs'!$C$40 -> 108780 | N18: =$C$18*'Master Inputs'!$C$32*'Master Inputs'!$D$40 -> 93240 | O18: =$C$18*'Master Inputs'!$C$32*'Master Inputs'!$E$40 -> 108780 | P18: =SUM(M18:O18) -> 310800 | Q18: =$C$18*'Master Inputs'!$C$33*'Master Inputs'!$C$41 -> 88800 | R18: =$C$18*'Master Inputs'!$C$33*'Master Inputs'!$D$41 -> 66600 | S18: =$C$18*'Master Inputs'!$C$33*'Master Inputs'!$E$41 -> 66600 | T18: =SUM(Q18:S18) -> 222000
A19: POP Materials Kit | B19: All UP+HR dealers | C19: ='Activity Costs'!C25*('Master Inputs'!$C$77+'Master Inputs'!$C$78) -> 699000 | D19: =IF(C$26=0,0,C19/C$26) -> 0.002659709 | E19: =$C$19*'Master Inputs'!$C$30*'Master Inputs'!$C$38 -> 52425 | F19: =$C$19*'Master Inputs'!$C$30*'Master Inputs'!$D$38 -> 69900 | G19: =$C$19*'Master Inputs'!$C$30*'Master Inputs'!$E$38 -> 52425 | H19: =SUM(E19:G19) -> 174750 | I19: =$C$19*'Master Inputs'!$C$31*'Master Inputs'!$C$39 -> 31455 | J19: =$C$19*'Master Inputs'!$C$31*'Master Inputs'!$D$39 -> 36697.5 | K19: =$C$19*'Master Inputs'!$C$31*'Master Inputs'!$E$39 -> 36697.5 | L19: =SUM(I19:K19) -> 104850 | M19: =$C$19*'Master Inputs'!$C$32*'Master Inputs'!$C$40 -> 85627.5 | N19: =$C$19*'Master Inputs'!$C$32*'Master Inputs'!$D$40 -> 73395 | O19: =$C$19*'Master Inputs'!$C$32*'Master Inputs'!$E$40 -> 85627.5 | P19: =SUM(M19:O19) -> 244650 | Q19: =$C$19*'Master Inputs'!$C$33*'Master Inputs'!$C$41 -> 69900 | R19: =$C$19*'Master Inputs'!$C$33*'Master Inputs'!$D$41 -> 52425 | S19: =$C$19*'Master Inputs'!$C$33*'Master Inputs'!$E$41 -> 52425 | T19: =SUM(Q19:S19) -> 174750
A20: Retailer Loyalty Program | B20: Per transacting x 4 qtrs | C20: ='Activity Costs'!C28*'Master Inputs'!$C$57*'Master Inputs'!$C$63*4 -> 3305600 | D20: =IF(C$26=0,0,C20/C$26) -> 0.012577874 | E20: =$C$20*'Master Inputs'!$C$30*'Master Inputs'!$C$38 -> 247920 | F20: =$C$20*'Master Inputs'!$C$30*'Master Inputs'!$D$38 -> 330560 | G20: =$C$20*'Master Inputs'!$C$30*'Master Inputs'!$E$38 -> 247920 | H20: =SUM(E20:G20) -> 826400 | I20: =$C$20*'Master Inputs'!$C$31*'Master Inputs'!$C$39 -> 148752 | J20: =$C$20*'Master Inputs'!$C$31*'Master Inputs'!$D$39 -> 173544 | K20: =$C$20*'Master Inputs'!$C$31*'Master Inputs'!$E$39 -> 173544 | L20: =SUM(I20:K20) -> 495840 | M20: =$C$20*'Master Inputs'!$C$32*'Master Inputs'!$C$40 -> 404936 | N20: =$C$20*'Master Inputs'!$C$32*'Master Inputs'!$D$40 -> 347088 | O20: =$C$20*'Master Inputs'!$C$32*'Master Inputs'!$E$40 -> 404936 | P20: =SUM(M20:O20) -> 1156960 | Q20: =$C$20*'Master Inputs'!$C$33*'Master Inputs'!$C$41 -> 330560 | R20: =$C$20*'Master Inputs'!$C$33*'Master Inputs'!$D$41 -> 247920 | S20: =$C$20*'Master Inputs'!$C$33*'Master Inputs'!$E$41 -> 247920 | T20: =SUM(Q20:S20) -> 826400
A21: Competitive Conversion Scheme | B21: 15% target conversion | C21: ='Activity Costs'!C30*'Master Inputs'!$C$56*'Master Inputs'!$C$63*0.15 -> 954000 | D21: =IF(C$26=0,0,C21/C$26) -> 0.0036299891 | E21: =$C$21*'Master Inputs'!$C$30*'Master Inputs'!$C$38 -> 71550 | F21: =$C$21*'Master Inputs'!$C$30*'Master Inputs'!$D$38 -> 95400 | G21: =$C$21*'Master Inputs'!$C$30*'Master Inputs'!$E$38 -> 71550 | H21: =SUM(E21:G21) -> 238500 | I21: =$C$21*'Master Inputs'!$C$31*'Master Inputs'!$C$39 -> 42930 | J21: =$C$21*'Master Inputs'!$C$31*'Master Inputs'!$D$39 -> 50085 | K21: =$C$21*'Master Inputs'!$C$31*'Master Inputs'!$E$39 -> 50085 | L21: =SUM(I21:K21) -> 143100 | M21: =$C$21*'Master Inputs'!$C$32*'Master Inputs'!$C$40 -> 116865 | N21: =$C$21*'Master Inputs'!$C$32*'Master Inputs'!$D$40 -> 100170 | O21: =$C$21*'Master Inputs'!$C$32*'Master Inputs'!$E$40 -> 116865 | P21: =SUM(M21:O21) -> 333900 | Q21: =$C$21*'Master Inputs'!$C$33*'Master Inputs'!$C$41 -> 95400 | R21: =$C$21*'Master Inputs'!$C$33*'Master Inputs'!$D$41 -> 71550 | S21: =$C$21*'Master Inputs'!$C$33*'Master Inputs'!$E$41 -> 71550 | T21: =SUM(Q21:S21) -> 238500
A22: Dealer Certificates | B22: UP+HR active retailers | C22: ='Activity Costs'!C23*'Master Inputs'!$C$56*'Master Inputs'!$C$63 -> 254400 | D22: =IF(C$26=0,0,C22/C$26) -> 0.00096799709 | E22: =$C$22*'Master Inputs'!$C$30*'Master Inputs'!$C$38 -> 19080 | F22: =$C$22*'Master Inputs'!$C$30*'Master Inputs'!$D$38 -> 25440 | G22: =$C$22*'Master Inputs'!$C$30*'Master Inputs'!$E$38 -> 19080 | H22: =SUM(E22:G22) -> 63600 | I22: =$C$22*'Master Inputs'!$C$31*'Master Inputs'!$C$39 -> 11448 | J22: =$C$22*'Master Inputs'!$C$31*'Master Inputs'!$D$39 -> 13356 | K22: =$C$22*'Master Inputs'!$C$31*'Master Inputs'!$E$39 -> 13356 | L22: =SUM(I22:K22) -> 38160 | M22: =$C$22*'Master Inputs'!$C$32*'Master Inputs'!$C$40 -> 31164 | N22: =$C$22*'Master Inputs'!$C$32*'Master Inputs'!$D$40 -> 26712 | O22: =$C$22*'Master Inputs'!$C$32*'Master Inputs'!$E$40 -> 31164 | P22: =SUM(M22:O22) -> 89040 | Q22: =$C$22*'Master Inputs'!$C$33*'Master Inputs'!$C$41 -> 25440 | R22: =$C$22*'Master Inputs'!$C$33*'Master Inputs'!$D$41 -> 19080 | S22: =$C$22*'Master Inputs'!$C$33*'Master Inputs'!$E$41 -> 19080 | T22: =SUM(Q22:S22) -> 63600
A23: Distributor Meet | B23: 10% of dealers at annual meet | C23: ='Activity Costs'!C27*('Master Inputs'!$C$77+'Master Inputs'!$C$78)*0.1 -> 2330000 | D23: =IF(C$26=0,0,C23/C$26) -> 0.0088656966 | E23: =$C$23*'Master Inputs'!$C$30*'Master Inputs'!$C$38 -> 174750 | F23: =$C$23*'Master Inputs'!$C$30*'Master Inputs'!$D$38 -> 233000 | G23: =$C$23*'Master Inputs'!$C$30*'Master Inputs'!$E$38 -> 174750 | H23: =SUM(E23:G23) -> 582500 | I23: =$C$23*'Master Inputs'!$C$31*'Master Inputs'!$C$39 -> 104850 | J23: =$C$23*'Master Inputs'!$C$31*'Master Inputs'!$D$39 -> 122325 | K23: =$C$23*'Master Inputs'!$C$31*'Master Inputs'!$E$39 -> 122325 | L23: =SUM(I23:K23) -> 349500 | M23: =$C$23*'Master Inputs'!$C$32*'Master Inputs'!$C$40 -> 285425 | N23: =$C$23*'Master Inputs'!$C$32*'Master Inputs'!$D$40 -> 244650 | O23: =$C$23*'Master Inputs'!$C$32*'Master Inputs'!$E$40 -> 285425 | P23: =SUM(M23:O23) -> 815500 | Q23: =$C$23*'Master Inputs'!$C$33*'Master Inputs'!$C$41 -> 233000 | R23: =$C$23*'Master Inputs'!$C$33*'Master Inputs'!$D$41 -> 174750 | S23: =$C$23*'Master Inputs'!$C$33*'Master Inputs'!$E$41 -> 174750 | T23: =SUM(Q23:S23) -> 582500
A24: BTL ACTIVITIES TOTAL | C24: =SUM(C11:C23) -> 246020708 | D24: =IF(C$26=0,0,C24/C$26) -> 0.93611371 | E24: =SUM(E11:E23) -> 18451553 | F24: =SUM(F11:F23) -> 24602071 | G24: =SUM(G11:G23) -> 18451553 | H24: =SUM(H11:H23) -> 61505177 | I24: =SUM(I11:I23) -> 11070932 | J24: =SUM(J11:J23) -> 12916087 | K24: =SUM(K11:K23) -> 12916087 | L24: =SUM(L11:L23) -> 36903106 | ... T24: =SUM(T11:T23) -> 61505177
A26: GRAND TOTAL | C26: =C8+C24 -> 262810708 | D26: 100.0% | E26: =E8+E24 -> 19710803 | F26: =F8+F24 -> 26281071 | G26: =G8+G24 -> 19710803 | H26: =H8+H24 -> 65702677 | I26: =I8+I24 -> 11826482 | J26: =J8+J24 -> 13797562 | K26: =K8+K24 -> 13797562 | L26: =L8+L24 -> 39421606 | ... T26: =T8+T24 -> 65702677
A27: Allocated Budget | C27: ='Master Inputs'!$C$16 -> 7600000
A28: Variance (Budget - Spend) | C28: =C27-C26 -> -255210708
A29: Utilization % | C29: =IF(C27=0,0,C26/C27) -> 34.580356

Sheet Consolidated
A1: CONSOLIDATED BUDGET - ALL OBJECTIVES (FY 2026-27)
A3: Category | B3: Obj 1: Helix (India Launch) | C3: Obj 2A: JSW ONE (East Growth) | D3: Obj 2B: JSW ONE (UP+HR 2x) | E3: Obj 2 Total | F3: GRAND TOTAL | G3: Contingency | H3: % of Total
A5: Allocated Budget | B5: ='Master Inputs'!$C$13 -> 28500000 | C5: ='Master Inputs'!$C$15 -> 11400000 | D5: ='Master Inputs'!$C$16 -> 7600000 | E5: =C5+D5 -> 19000000 | F5: =B5+E5 -> 47500000 | G5: ='Master Inputs'!$C$17 -> 2500000 | H5: =IF(F$8=0,0,F5/F$8) -> 0.092357729
A6: ATL Spend | B6: ='Obj1 Helix'!C16 -> 134250000 | C6: ='Obj2A East'!C9 -> 30000000 | D6: ='Obj2B UPHR'!C8 -> 16790000 | E6: =C6+D6 -> 46790000 | F6: =B6+E6 -> 181040000 | H6: =IF(F$8=0,0,F6/F$8) -> 0.35200933
A7: BTL Spend | B7: ='Obj1 Helix'!C29 -> 46322412 | C7: ='Obj2A East'!C22 -> 40921428 | D7: ='Obj2B UPHR'!C24 -> 246020708 | E7: =C7+D7 -> 286942136 | F7: =B7+E7 -> 3.3326455e+08 | H7: =IF(F$8=0,0,F7/F$8) -> 0.64799067
A8: Total Spend | B8: ='Obj1 Helix'!C31 -> 1.8057241e+08 | C8: ='Obj2A East'!C24 -> 70921428 | D8: ='Obj2B UPHR'!C26 -> 262810708 | E8: =C8+D8 -> 333732136 | F8: =B8+E8 -> 5.1430455e+08 | H8: =IF(F$8=0,0,F8/F$8) -> 1
A10: Budget Variance | B10: =B4-B7 -> -46322412 | C10: =C4-C7 -> -40921428 | D10: =D4-D7 -> -246020708 | E10: =E4-E7 -> -286942136 | F10: =F4-F7 -> -3.3326455e+08
A11: Utilization % | B11: =IF(B4=0,0,B7/B4) -> 0 | C11: =IF(C4=0,0,C7/C4) -> 0 | D11: =IF(D4=0,0,D7/D4) -> 0 | E11: =IF(E4=0,0,E7/E4) -> 0 | F11: =IF(F4=0,0,F7/F4) -> 0
A13: QUARTERLY SPEND BREAKDOWN
A14: Quarter | B14: Obj 1: Helix | C14: Obj 2A: East | D14: Obj 2B: UP+HR | E14: Obj 2 Total | F14: Grand Total | H14: % of Annual
A15: Q1 | B15: ='Obj1 Helix'!H31 -> 45143103 | C15: ='Obj2A East'!H24 -> 17730357 | D15: ='Obj2B UPHR'!H26 -> 65702677 | E15: =C15+D15 -> 83433034 | F15: =B15+E15 -> 1.2857614e+08 | H15: =IF(F8=0,0,F15/F8) -> 0.25
A16: Q2 | B16: ='Obj1 Helix'!L31 -> 27085862 | C16: ='Obj2A East'!L24 -> 10638214 | D16: ='Obj2B UPHR'!L26 -> 39421606 | E16: =C16+D16 -> 50059820 | F16: =B16+E16 -> 77145682 | H16: =IF(F8=0,0,F16/F8) -> 0.15
A17: Q3 | B17: ='Obj1 Helix'!P31 -> 63200344 | C17: ='Obj2A East'!P24 -> 24822500 | D17: ='Obj2B UPHR'!P26 -> 91983748 | E17: =C17+D17 -> 1.1680625e+08 | F17: =B17+E17 -> 1.8000659e+08 | H17: =IF(F8=0,0,F17/F8) -> 0.35
A18: Q4 | B18: ='Obj1 Helix'!T31 -> 45143103 | C18: ='Obj2A East'!T24 -> 17730357 | D18: ='Obj2B UPHR'!T26 -> 65702677 | E18: =C18+D18 -> 83433034 | F18: =B18+E18 -> 1.2857614e+08 | H18: =IF(F8=0,0,F18/F8) -> 0.25
A19: Annual Total | B19: =SUM(B15:B18) -> 1.8057241e+08 | C19: =SUM(C15:C18) -> 70921428 | D19: =SUM(D15:D18) -> 262810708 | E19: =SUM(E15:E18) -> 333732136 | F19: =SUM(F15:F18) -> 5.1430455e+08

Sheet Vol Projections
A1: VOLUME PROJECTIONS & COST EFFICIENCY (FY 2026-27)
A3: VOLUME SUMMARY (MT)
A4: Brand | B4: Q1 | C4: Q2 | D4: Q3 | E4: Q4 | F4: Annual Total
A5: One Helix (New Launch) | B5: ='Master Inputs'!$C$45*0.1 -> 12100 | C5: ='Master Inputs'!$C$45*0.15 -> 18150 | D5: ='Master Inputs'!$C$45*0.3 -> 36300 | E5: ='Master Inputs'!$C$45*0.45 -> 54450 | F5: =SUM(B5:E5) -> 121000
A6: JSW ONE TMT (Total) | B6: ='Master Inputs'!$C$53*0.25 -> 67000 | C6: ='Master Inputs'!$C$53*0.19 -> 50920 | D6: ='Master Inputs'!$C$53*0.24 -> 64320 | E6: ='Master Inputs'!$C$53*0.32 -> 85760 | F6: =SUM(B6:E6) -> 268000
A7: COMBINED | B7: =B5+B6 -> 79100 | C7: =C5+C6 -> 69070 | D7: =D5+D6 -> 100620 | E7: =E5+E6 -> 140210 | F7: =F5+F6 -> 389000
A9: MARKETING COST PER MT (Rs.)
A10: Brand | B10: Q1 | C10: Q2 | D10: Q3 | E10: Q4 | F10: Annual Avg
A11: One Helix Cost/MT | B11: =IF(B5=0,0,Consolidated!B15/B5) -> 3730.835 | C11: =IF(B5=0,0,Consolidated!B16/B5) -> 2238.501 | D11: =IF(B5=0,0,Consolidated!B17/B5) -> 5223.169 | E11: =IF(B5=0,0,Consolidated!B18/B5) -> 3730.835 | F11: =IF(F5=0,0,Consolidated!B8/F5) -> 1492.334
A12: JSW ONE Cost/MT | B12: =IF(B6=0,0,(Consolidated!C15+Consolidated!D15)/B6) -> 1245.2692 | C12: =IF(B6=0,0,(Consolidated!C16+Consolidated!D16)/B6) -> 747.1615 | D12: =IF(B6=0,0,(Consolidated!C17+Consolidated!D17)/B6) -> 1743.3768 | E12: =IF(B6=0,0,(Consolidated!C18+Consolidated!D18)/B6) -> 1245.2692 | F12: =IF(F6=0,0,(Consolidated!C8+Consolidated!D8)/F6) -> 1245.2692
A13: Blended Cost/MT | B13: =IF(B7=0,0,Consolidated!F15/B7) -> 1625.4885 | C13: =IF(B7=0,0,Consolidated!F16/B7) -> 975.29308 | D13: =IF(B7=0,0,Consolidated!F17/B7) -> 2275.6838 | E13: =IF(B7=0,0,Consolidated!F18/B7) -> 1625.4885 | F13: =IF(F7=0,0,Consolidated!F8/F7) -> 1322.1197
A15: REVENUE & A/S (Advertising-to-Sales) RATIO
A16: Metric | B16: Helix | C16: JSW ONE | D16: Combined
A17: Projected Revenue (Rs.) | B17: =F5*'Master Inputs'!$C$51 -> 5913028000 | C17: =F6*'Master Inputs'!$C$61 -> 13400000000 | D17: =B17+C17 -> 19313028000
A18: Marketing Spend (Rs.) | B18: =Consolidated!B8 -> 1.8057241e+08 | C18: =Consolidated!E8 -> 333732136 | D18: =Consolidated!F8 -> 5.1430455e+08
A19: A/S Ratio (%) | B19: =IF(B17=0,0,B18/B17) -> 0.030538061 | C19: =IF(C17=0,0,C18/C17) -> 0.024905383 | D19: =IF(D17=0,0,D18/D17) -> 0.026629928
A21: RETAILER ACTIVATION FUNNEL
A22: Metric | B22: Helix | C22: JSW ONE
A23: Total Retailers (Mar 27) | B23: ='Master Inputs'!$C$48 -> 2015 | C23: ='Master Inputs'!$C$56 -> 1590
A24: Transacting Retailers | B24: ='Master Inputs'!$C$49 -> 1310 | C24: ='Master Inputs'!$C$57 -> 1033
A25: Conversion Rate | B25: =IF(B23=0,0,B24/B23) -> 0.65012407 | C25: =IF(C23=0,0,C24/C23) -> 0.64968553

Sheet Activity Costs
A1: ACTIVITY COST REFERENCE - MASTER PRICE LIST
A2: All unit costs are editable. Changes cascade to all objective tabs.
A3: # | B3: Activity | C3: Unit Cost (Rs.) | D3: Unit | E3: Remarks / Basis
A4: ATL ACTIVITIES (Above The Line)
A5: 1 | B5: Impact Wall Painting | C5: 15 | D5: Rs/sq ft | E5: 20,000 sq ft per district
A6: 2 | B6: FM Radio Campaign | C6: 250000 | D6: Rs/campaign | E6: Per district per quarter
A7: 3 | B7: Hoardings (Flex/Billboard) | C7: 50000 | D7: Rs/hoarding | E7: 5 per priority district
A8: 4 | B8: Digital Marketing Campaign | C8: 500000 | D8: Rs/campaign | E8: Social + YouTube + Display
A9: 5 | B9: Local Events / Trade Fairs | C9: 500000 | D9: Rs/event | E9: Zone-level events
A10: 6 | B10: Van Campaign (Mobile) | C10: 7000 | D10: Rs/day | E10: 2 months per state
A11: 7 | B11: Syndicate Launch Events | C11: 500000 | D11: Rs/event | E11: Per state launch
A12: 8 | B12: Transit Auto Branding | C12: 700 | D12: Rs/auto | E12: Auto rickshaw wraps
A13: 9 | B13: Tea Stall Branding | C13: 4000 | D13: Rs/stall | E13: 25 stalls per district
A14: 10 | B14: Paper Advertisement | C14: 100000 | D14: Rs/insert | E14: Regional dailies
A15: BTL ACTIVITIES (Below The Line)
A16: 11 | B16: NLB (Name/Lit Board) | C16: 1200 | D16: Rs/board | E16: 40/sqft x 30 sqft
A17: 12 | B17: GSB (Glow Sign Board) | C17: 6510 | D17: Rs/board | E17: 180x30 + 65x18
A18: 13 | B18: Counter Wall Painting | C18: 10000 | D18: Rs/counter | E18: Retailer counter branding
A19: 14 | B19: Inshop Branding | C19: 40000 | D19: Rs/counter | E19: Premium in-store display
A20: 15 | B20: Architect/Engineer Meet | C20: 3500 | D20: Rs/person | E20: 50 pax per meet
A21: 16 | B21: Contractor Meet | C21: 1000 | D21: Rs/person | E21: 50 pax per meet
A22: 17 | B22: Mason Meet | C22: 300 | D22: Rs/person | E22: 30 pax per meet
A23: 18 | B23: Dealer Certificates | C23: 400 | D23: Rs/certificate | E23: Recognition boards
A24: 19 | B24: Construction Site Gate Board | C24: 1500 | D24: Rs/board | E24: Per active site
A25: 20 | B25: POP Materials Kit | C25: 3000 | D25: Rs/dealer | E25: Standees, banners, flyers
A26: 21 | B26: Architect Gift/Engagement | C26: 500 | D26: Rs/gift | E26: Relationship building
A27: 22 | B27: Distributor Meet (Grand) | C27: 100000 | D27: Rs/person | E27: Annual convention per dist.
... A30: 25 | B30: Competitive Conversion Scheme | C30: 10000 | D30: Rs/retailer | E30: Switch-over incentive

Sheet ROI Metrics
A1: ROI & METRICS TRACKER (FY 2026-27)
A3: SCENARIO ANALYSIS - BUDGET SENSITIVITY
A4: Scenario | B4: Budget (Rs.) | C4: Helix Alloc | D4: JSW ONE Alloc | E4: Cost/MT (Helix) | F4: Cost/MT (JSW ONE) | G4: Blended Cost/MT
A5: Base Case (Current) | B5: ='Master Inputs'!$C$5*1 -> 50000000 | C5: =B5*'Master Inputs'!$C$6*(1-'Master Inputs'!$C$10) -> 28500000 | D5: =B5*'Master Inputs'!$C$7*(1-'Master Inputs'!$C$10) -> 19000000 | E5: =IF('Vol Projections'!F5=0,0,C5/'Vol Projections'!F5) -> 235.53719 | F5: =IF('Vol Projections'!F6=0,0,D5/'Vol Projections'!F6) -> 70.895522 | G5: =IF('Vol Projections'!F7=0,0,B5/'Vol Projections'!F7) -> 128.5347
A6: -20% Budget | B6: ='Master Inputs'!$C$5*0.8 -> 40000000 | C6: =B6*'Master Inputs'!$C$6*(1-'Master Inputs'!$C$10) -> 22800000 | D6: =B6*'Master Inputs'!$C$7*(1-'Master Inputs'!$C$10) -> 15200000 | E6: =IF('Vol Projections'!F5=0,0,C6/'Vol Projections'!F5) -> 188.42975 | F6: =IF('Vol Projections'!F6=0,0,D6/'Vol Projections'!F6) -> 56.716418 | G6: =IF('Vol Projections'!F7=0,0,B6/'Vol Projections'!F7) -> 102.82776
A7: -10% Budget | B7: ='Master Inputs'!$C$5*0.9 -> 45000000 | C7: =B7*'Master Inputs'!$C$6*(1-'Master Inputs'!$C$10) -> 25650000 | D7: =B7*'Master Inputs'!$C$7*(1-'Master Inputs'!$C$10) -> 17100000 | E7: =IF('Vol Projections'!F5=0,0,C7/'Vol Projections'!F5) -> 211.98347 | F7: =IF('Vol Projections'!F6=0,0,D7/'Vol Projections'!F6) -> 63.80597 | G7: =IF('Vol Projections'!F7=0,0,B7/'Vol Projections'!F7) -> 115.68123
A8: +10% Budget | B8: ='Master Inputs'!$C$5*1.1 -> 55000000 | C8: =B8*'Master Inputs'!$C$6*(1-'Master Inputs'!$C$10) -> 31350000 | D8: =B8*'Master Inputs'!$C$7*(1-'Master Inputs'!$C$10) -> 20900000 | E8: =IF('Vol Projections'!F5=0,0,C8/'Vol Projections'!F5) -> 259.09091 | F8: =IF('Vol Projections'!F6=0,0,D8/'Vol Projections'!F6) -> 77.985075 | G8: =IF('Vol Projections'!F7=0,0,B8/'Vol Projections'!F7) -> 141.38817
A9: +20% Budget | B9: ='Master Inputs'!$C$5*1.2 -> 60000000 | C9: =B9*'Master Inputs'!$C$6*(1-'Master Inputs'!$C$10) -> 34200000 | D9: =B9*'Master Inputs'!$C$7*(1-'Master Inputs'!$C$10) -> 22800000 | E9: =IF('Vol Projections'!F5=0,0,C9/'Vol Projections'!F5) -> 282.64463 | F9: =IF('Vol Projections'!F6=0,0,D9/'Vol Projections'!F6) -> 85.074627 | G9: =IF('Vol Projections'!F7=0,0,B9/'Vol Projections'!F7) -> 154.24165
A11: EFFICIENCY METRICS
A12: Metric | B12: Helix | C12: JSW ONE (2A) | D12: JSW ONE (2B) | E12: Combined
A13: Cost per Dealer Activated | B13: =IF('Master Inputs'!$C$48=0,0,Consolidated!B8/'Master Inputs'!$C$48) -> 89614.1 | C13: =IF('Master Inputs'!$C$56*'Master Inputs'!$C$62=0,0,Consolidated!C8/('Master Inputs'!$C$56*'Master Inputs'!$C$62)) -> 74341.119 | D13: =IF('Master Inputs'!$C$56*'Master Inputs'!$C$63=0,0,Consolidated!D8/('Master Inputs'!$C$56*'Master Inputs'!$C$63)) -> 413224.38
A14: Cost per Retailer Engaged | B14: =IF('Master Inputs'!$C$49=0,0,Consolidated!B8/'Master Inputs'!$C$49) -> 137841.54
A15: Marketing Spend per Distributor | B15: =IF('Master Inputs'!$C$44=0,0,Consolidated!B8/'Master Inputs'!$C$44) -> 4299343.2 | C15: =IF('Master Inputs'!$C$52*'Master Inputs'!$C$62=0,0,Consolidated!C8/('Master Inputs'!$C$52*'Master Inputs'!$C$62)) -> 2110756.8
A16: ATL Spend per Priority District
A18: OBJECTIVE-WISE COMPARISON
A19: Metric | B19: Obj 1: Helix | C19: Obj 2A: East | D19: Obj 2B: UP+HR | E19: Total
A20: Budget Allocated (Rs.) | B20: ='Master Inputs'!$C$13 -> 28500000 | C20: ='Master Inputs'!$C$15 -> 11400000 | D20: ='Master Inputs'!$C$16 -> 7600000 | E20: =B20+C20+D20 -> 47500000
A21: Total Spend (Rs.) | B21: =Consolidated!B8 -> 1.8057241e+08 | C21: =Consolidated!C8 -> 70921428 | D21: =Consolidated!D8 -> 262810708 | E21: =B21+C21+D21 -> 5.1430455e+08
A22: Budget Utilization % | B22: =IF(B20=0,0,B21/B20) -> 6.3358741 | C22: =IF(C20=0,0,C21/C20) -> 6.2211779 | D22: =IF(D20=0,0,D21/D20) -> 34.580356 | E22: =IF(E20=0,0,E21/E20) -> 10.827464

Sheet Quarterly Review
A1: QUARTERLY REVIEW TRACKER - ACTUAL vs PLAN (FY 2026-27)
A2: Enter actuals in yellow cells after each quarter. Variance auto-calculates.
A4: Q1 REVIEW (Apr-Jun 2026-27)
A5: Metric | B5: Obj1: Helix | C5: Obj2A: East | D5: Obj2B: UP+HR | E5: Total | F5: Variance | G5: Remarks
A6: Planned Spend (Rs.) | B6: =Consolidated!B15 -> 45143103 | C6: =Consolidated!C15 -> 17730357 | D6: =Consolidated!D15 -> 65702677 | E6: =SUM(B6:D6) -> 1.2857614e+08
A7: Actual Spend (Rs.) | B7: 0 | C7: 0 | D7: 0 | E7: =SUM(B7:D7) -> 0
A8: Variance (Plan - Actual) | B8: =B6-B7 -> 45143103 | C8: =C6-C7 -> 17730357 | D8: =D6-D7 -> 65702677 | E8: =E6-E7 -> 1.2857614e+08
A9: Variance % | B9: =IF(B6=0,0,B8/B6) -> 1 | C9: =IF(C6=0,0,C8/C6) -> 1 | D9: =IF(D6=0,0,D8/D6) -> 1 | E9: =IF(E6=0,0,E8/E6) -> 1
A10: Key Observations
A12: Q2 REVIEW (Jul-Sep 2026-27)
A13: Metric | B13: Obj1: Helix | C13: Obj2A: East | D13: Obj2B: UP+HR | E13: Total | F13: Variance | G13: Remarks
A14: Planned Spend (Rs.) | B14: =Consolidated!B16 -> 27085862 | C14: =Consolidated!C16 -> 10638214 | D14: =Consolidated!D16 -> 39421606 | E14: =SUM(B14:D14) -> 77145682
A15: Actual Spend (Rs.) | B15: 0 | C15: 0 | D15: 0 | E15: =SUM(B15:D15) -> 0
A16: Variance (Plan - Actual) | B16: =B14-B15 -> 27085862 | C16: =C14-C15 -> 10638214 | D16: =D14-D15 -> 39421606 | E16: =E14-E15 -> 77145682
A17: Variance % | B17: =IF(B14=0,0,B16/B14) -> 1 | C17: =IF(C14=0,0,C16/C14) -> 1 | D17: =IF(D14=0,0,D16/D14) -> 1 | E17: =IF(E14=0,0,E16/E14) -> 1
A18: Key Observations
A20: Q3 REVIEW (Oct-Dec 2026-27)
A21: Metric | B21: Obj1: Helix | C21: Obj2A: East | D21: Obj2B: UP+HR | E21: Total | F21: Variance | G21: Remarks
A22: Planned Spend (Rs.) | B22: =Consolidated!B17 -> 63200344 | C22: =Consolidated!C17 -> 24822500 | D22: =Consolidated!D17 -> 91983748 | E22: =SUM(B22:D22) -> 1.8000659e+08
A23: Actual Spend (Rs.) | B23: 0 | C23: 0 | D23: 0 | E23: =SUM(B23:D23) -> 0
A24: Variance (Plan - Actual) | B24: =B22-B23 -> 63200344 | C24: =C22-C23 -> 24822500 | D24: =D22-D23 -> 91983748 | E24: =E22-E23 -> 1.8000659e+08
A25: Variance % | B25: =IF(B22=0,0,B24/B22) -> 1 | C25: =IF(C22=0,0,C24/C22) -> 1 | D25: =IF(D22=0,0,D24/D22) -> 1 | E25: =IF(E22=0,0,E24/E22) -> 1
A26: Key Observations
A28: Q4 REVIEW (Jan-Mar 2026-27)
A29: Metric | B29: Obj1: Helix | C29: Obj2A: East | D29: Obj2B: UP+HR | E29: Total | F29: Variance | G29: Remarks
A30: Planned Spend (Rs.) | B30: =Consolidated!B18 -> 45143103 | C30: =Consolidated!C18 -> 17730357 | D30: =Consolidated!D18 -> 65702677 | E30: =SUM(B30:D30) -> 1.2857614e+08
A31: Actual Spend (Rs.) | B31: 0 | C31: 0 | D31: 0 | E31: =SUM(B31:D31) -> 0
A32: Variance (Plan - Actual) | B32: =B30-B31 -> 45143103 | C32: =C30-C31 -> 17730357 | D32: =D30-D31 -> 65702677 | E32: =E30-E31 -> 1.2857614e+08
A33: Variance % | B33: =IF(B30=0,0,B32/B30) -> 1 | C33: =IF(C30=0,0,C32/C30) -> 1 | D33: =IF(D30=0,0,D32/D30) -> 1 | E33: =IF(E30=0,0,E32/E30) -> 1
A34: Key Observations
A36: ANNUAL SUMMARY
A37: Total Planned | E37: =Consolidated!F8 -> 5.1430455e+08
