Workbook

Sheet #Dealers
D1: Quarter 1 | J1: Quarter 2 | P1: Quarter 3 | V1: Quarter 4
D2: One Helix | E2: JSW One | F2: One Helix | G2: JSW One | H2: One Helix | I2: JSW One | J2: One Helix | K2: JSW One | L2: One Helix | M2: JSW One | N2: One Helix | O2: JSW One | P2: One Helix | Q2: JSW One | R2: One Helix | S2: JSW One | T2: One Helix | U2: JSW One | V2: One Helix | W2: JSW One | X2: One Helix | Y2: JSW One | Z2: One Helix | AA2: JSW One
A3: # of Active Dealers | D3: 155 | E3: 742 | F3: 207 | G3: 995 | H3: 188 | I3: 789 | J3: 163 | K3: 735 | L3: 160 | M3: 641 | N3: 189 | O3: 643 | P3: 285 | Q3: 690 | R3: 404 | S3: 898 | T3: 490 | U3: 847 | V3: 646 | W3: 1067 | X3: 775 | Y3: 1173 | Z3: 972 | AA3: 1411
A4: Sr. No. | B4: State | C4: Zone | D4: 46138 | F4: 46168 | H4: 46199 | J4: 46229 | L4: 46260 | N4: 46291 | P4: 46321 | R4: 46352 | T4: 46382 | V4: 46049 | X4: 46080 | Z4: 46108
A5: 1 | B5: UTTAR PRADESH | C5: North | D5: 0 | E5: 152 | F5: 0 | G5: 184 | H5: 0 | I5: 168 | J5: 0 | K5: 152 | L5: 6 | M5: 101 | N5: 6 | O5: 108 | P5: 19 | Q5: 152 | R5: 38 | S5: 155 | T5: 60 | U5: 139 | V5: 89 | W5: 171 | X5: 114 | Y5: 171 | Z5: 165 | AA5: 184
A6: a# | B6: RAJASTHAN | C6: North | D6: 0 | E6: 59 | F6: 0 | G6: 71 | H6: 0 | I6: 67 | J6: 0 | K6: 59 | L6: 0 | M6: 54 | N6: 0 | O6: 57 | P6: 7 | Q6: 57 | R6: 10 | S6: 67 | T6: 22 | U6: 57 | V6: 27 | W6: 64 | X6: 44 | Y6: 54 | Z6: 71 | AA6: 67
A7: 3 | B7: DELHI | C7: North | D7: 0 | E7: 20 | F7: 0 | G7: 24 | H7: 0 | I7: 24 | J7: 0 | K7: 20 | L7: 0 | M7: 16 | N7: 0 | O7: 16 | P7: 4 | Q7: 20 | R7: 4 | S7: 20 | T7: 12 | U7: 16 | V7: 16 | W7: 16 | X7: 20 | Y7: 20 | Z7: 28 | AA7: 20
A8: 4 | B8: HARYANA | C8: North | D8: 0 | E8: 81 | F8: 0 | G8: 104 | H8: 0 | I8: 92 | J8: 0 | K8: 81 | L8: 0 | M8: 72 | N8: 0 | O8: 77 | P8: 7 | Q8: 86 | R8: 18 | S8: 90 | T8: 36 | U8: 77 | V8: 54 | W8: 99 | X8: 63 | Y8: 108 | Z8: 88 | AA8: 104
A9: 5 | B9: PUNJAB | C9: North | D9: 23 | E9: 0 | F9: 28 | G9: 0 | H9: 25 | I9: 0 | J9: 23 | K9: 0 | L9: 17 | M9: 0 | N9: 20 | O9: 0 | P9: 25 | Q9: 0 | R9: 31 | S9: 0 | T9: 34 | U9: 0 | V9: 42 | W9: 0 | X9: 48 | Y9: 0 | Z9: 57 | AA9: 28
A10: 6 | B10: UTTARAKHAND | C10: North | D10: 0 | E10: 26 | F10: 0 | G10: 39 | H10: 0 | I10: 32 | J10: 0 | K10: 26 | L10: 6 | M10: 19 | N10: 13 | O10: 13 | P10: 19 | Q10: 6 | R10: 39 | S10: 0 | T10: 39 | U10: 0 | V10: 52 | W10: 0 | X10: 58 | Y10: 0 | Z10: 64 | AA10: 0
A11: 7 | B11: JAMMU AND KASHMIR | C11: North | D11: 20 | E11: 0 | F11: 27 | G11: 0 | H11: 20 | I11: 0 | J11: 20 | K11: 0 | L11: 14 | M11: 0 | N11: 20 | O11: 0 | P11: 20 | Q11: 0 | R11: 27 | S11: 0 | T11: 27 | U11: 0 | V11: 41 | W11: 0 | X11: 41 | Y11: 0 | Z11: 54 | AA11: 0
A12: 8 | B12: HIMACHAL PRADESH | C12: North | D12: 5 | E12: 0 | F12: 5 | G12: 0 | H12: 5 | I12: 0 | J12: 5 | K12: 0 | L12: 5 | M12: 0 | N12: 5 | O12: 0 | P12: 5 | Q12: 0 | R12: 5 | S12: 0 | T12: 5 | U12: 0 | V12: 5 | W12: 0 | X12: 11 | Y12: 0 | Z12: 11 | AA12: 0
A13: 9 | B13: CHHATTISGARH | C13: Central | D13: 4 | E13: 0 | F13: 8 | G13: 0 | H13: 8 | I13: 0 | J13: 4 | K13: 0 | L13: 4 | M13: 0 | N13: 4 | O13: 0 | P13: 8 | Q13: 0 | R13: 8 | S13: 0 | T13: 8 | U13: 0 | V13: 12 | W13: 0 | X13: 16 | Y13: 0 | Z13: 16 | AA13: 0
A14: 10 | B14: ODISHA | C14: Central | D14: 38 | E14: 58 | F14: 53 | G14: 62 | H14: 48 | I14: 58 | J14: 38 | K14: 58 | L14: 34 | M14: 53 | N14: 38 | O14: 53 | P14: 53 | Q14: 53 | R14: 72 | S14: 48 | T14: 77 | U14: 48 | V14: 91 | W14: 48 | X14: 106 | Y14: 48 | Z14: 125 | AA14: 96
A15: 11 | B15: MADHYA PRADESH | C15: Central | D15: 12 | E15: 32 | F15: 16 | G15: 39 | H15: 20 | I15: 32 | J15: 20 | K15: 24 | L15: 20 | M15: 20 | N15: 20 | O15: 20 | P15: 36 | Q15: 20 | R15: 47 | S15: 16 | T15: 55 | U15: 8 | V15: 75 | W15: 47 | X15: 95 | Y15: 39 | Z15: 107 | AA15: 39
A16: 12 | B16: MADHYA PRADESH | C16: North | D16: 0 | E16: 0 | F16: 0 | G16: 0 | H16: 0 | I16: 0 | J16: 0 | K16: 0 | L16: 0 | M16: 0 | N16: 0 | O16: 0 | P16: 0 | Q16: 0 | R16: 0 | S16: 0 | T16: 4 | U16: 0 | V16: 4 | W16: 0 | X16: 4 | Y16: 0 | Z16: 4 | AA16: 0
A17: 12 | B17: MAHARASHTRA | C17: Central | D17: 0 | E17: 4 | F17: 0 | G17: 6 | H17: 0 | I17: 6 | J17: 0 | K17: 4 | L17: 2 | M17: 2 | N17: 2 | O17: 2 | P17: 4 | Q17: 2 | R17: 6 | S17: 0 | T17: 8 | U17: 0 | V17: 10 | W17: 0 | X17: 10 | Y17: 0 | Z17: 13 | AA17: 0
A18: 13 | B18: JHARKHAND | C18: East | D18: 0 | E18: 61 | F18: 0 | G18: 61 | H18: 0 | I18: 61 | J18: 0 | K18: 61 | L18: 0 | M18: 61 | N18: 0 | O18: 61 | P18: 0 | Q18: 61 | R18: 0 | S18: 122 | T18: 0 | U18: 122 | V18: 0 | W18: 122 | X18: 0 | Y18: 122 | Z18: 0 | AA18: 183
... A24: 19 | B24: ASSAM | C24: East | D24: 0 | E24: 0 | F24: 0 | G24: 0 | H24: 0 | I24: 0 | J24: 0 | K24: 0 | L24: 0 | M24: 0 | N24: 0 | O24: 0 | P24: 0 | Q24: 0 | R24: 0 | S24: 0 | T24: 0 | U24: 0 | V24: 0 | W24: 0 | X24: 0 | Y24: 40 | Z24: 0 | AA24: 40
A26: 3.8876712e+08

Sheet One Helix Budget
A1: #Distributors | B1: 42
A2: Volume projection (Mar'27 Exit) | B2: 27000
A3: Avg. volume/retailer/month | B3: 20
A4: Total retailers (Mar'27) | B4: 6230.7692
A5: Total Active retailers (Mar'27) | B5: 2015 | D5: In specific areas for longer
A6: Total transacting retailers (Mar'27) | B6: 1310 | D6: 15% discreationary cost
A7: #Priority districts | B7: 250
C8: Month | D8: 46048 | E8: 46168 | F8: 46199 | G8: 46229 | H8: 46260 | I8: 46291 | J8: 46321 | K8: 46352 | L8: 46382 | M8: 46413 | N8: 46444 | O8: 46472 | Q8: Left to Allocate | S8: Quarter | T8: Q1 | U8: Q2 | V8: Q3 | W8: Q4
S9: Marketing Cost | T9: =SUM(D54:F54) -> 66877908 | U9: =SUM(G54:I54) -> 31564253 | V9: =SUM(J54:L54) -> 76659596 | W9: =SUM(M54:O54) -> 52307088 | Z9: =121/(100/Z10) -> 30.25 | AA9: =121/(100/AA10) -> 18.15 | AB9: =121/(100/AB10) -> 42.35 | AC9: =121/(100/AC10) -> 30.25
A10: ATL Activities | B10: Remarks | C10: =SUM(C12:C20) -> 125600000 | D10: =SUM(D12:D20) -> 9342148.8 | E10: =SUM(E12:E20) -> 12456198 | F10: =SUM(F12:F20) -> 9342148.8 | G10: =SUM(G12:G20) -> 6228099.2 | H10: =SUM(H12:H20) -> 6228099.2 | I10: =SUM(I12:I20) -> 6228099.2 | J10: =SUM(J12:J20) -> 15570248 | ... O10: =SUM(O12:O20) -> 9342148.8 | S10: % Allocation | T10: =T9/$C$54 -> 0.28532795 | U10: =U9/$C$54 -> 0.13466575 | V10: =V9/$C$54 -> 0.32706055 | W10: =W9/$C$54 -> 0.22316299 | Z10: 25 | AA10: 15 | AB10: 35 | AC10: 25
A11: ATL Spends breakup | D11: 9 | E11: 12 | F11: 9 | G11: 6 | H11: 6 | I11: 6 | J11: 15 | K11: 13 | L11: 15 | M11: 12 | N11: 9 | O11: 9 | Q11: =121-SUM(D11:O11) -> 0 | S11: Cost / MT | T11: =W16 -> 5144.4545 | U11: =W21 -> 2630.3544 | V11: =W26 -> 2555.3199 | W11: =W31 -> 792.53164
A12: Impact Wall Painting | B12: 20,000 sq ft in high potential district @ Rs 15 | C12: ='One Helix'!C12 -> 16800000 | D12: =(D$11/121)*$C12 -> 1249586.8 | E12: =(E$11/121)*$C12 -> 1666115.7 | F12: =(F$11/121)*$C12 -> 1249586.8 | G12: =(G$11/121)*$C12 -> 833057.85 | H12: =(H$11/121)*$C12 -> 833057.85 | I12: =(I$11/121)*$C12 -> 833057.85 | J12: =(J$11/121)*$C12 -> 2082644.6 | K12: =(K$11/121)*$C12 -> 1804958.7 | ... O12: =(O$11/121)*$C12 -> 1249586.8 | S12: Q1 | T12: 46113 | U12: 46143 | V12: 46174 | W12: Total
A13: Integrated FM Radio Campaigns (Ad + Promotional Activity) | B13: To be done in Top 3 high potential districts for all operational states @Rs 2.5 Lac/campaign (No. of states: 15) for 3 months | C13: ='One Helix'!C13 -> 6000000 | D13: =(D$11/121)*$C13 -> 446280.99 | E13: =(E$11/121)*$C13 -> 595041.32 | F13: =(F$11/121)*$C13 -> 446280.99 | G13: =(G$11/121)*$C13 -> 297520.66 | H13: =(H$11/121)*$C13 -> 297520.66 | I13: =(I$11/121)*$C13 -> 297520.66 | J13: =(J$11/121)*$C13 -> 743801.65 | K13: =(K$11/121)*$C13 -> 644628.1 | ... O13: =(O$11/121)*$C13 -> 446280.99 | S13: % allocation | T13: =T14/$W14 -> 0.3390453 | U13: =U14/$W14 -> 0.36924732 | V13: =V14/$W14 -> 0.29170738 | Z13: 30.25 | AA13: =Z13*0.3 -> 9.075 | AB13: =0.4*Z13 -> 12.1 | AC13: =0.3*Z13 -> 9.075
A14: Hoardings (steel markets, cement shops cluster, construction zones) | B14: 5 hoardings in every high potential district @ Rs 50K | C14: ='One Helix'!C14 -> 15000000 | D14: =(D$11/121)*$C14 -> 1115702.5 | E14: =(E$11/121)*$C14 -> 1487603.3 | F14: =(F$11/121)*$C14 -> 1115702.5 | G14: =(G$11/121)*$C14 -> 743801.65 | H14: =(H$11/121)*$C14 -> 743801.65 | I14: =(I$11/121)*$C14 -> 743801.65 | J14: =(J$11/121)*$C14 -> 1859504.1 | K14: =(K$11/121)*$C14 -> 1611570.2 | ... O14: =(O$11/121)*$C14 -> 1115702.5 | S14: Marketing costs | T14: =D54 -> 22674641 | U14: =E54 -> 24694488 | V14: =F54 -> 19508779 | W14: =T9 -> 66877908 | Z14: 18.15 | AA14: =Z14*0.3 -> 5.445 | AB14: =Z14*0.35 -> 6.3525 | AC14: =Z14*0.35 -> 6.3525
A15: Digital Marketing Campaigns | B15: To be done in Top 3 high potential districts for all operational states @Rs 5 Lac/campaign (No. of states: 15) for 3 months | C15: ='One Helix'!C15 -> 14400000 | D15: =(D$11/121)*$C15 -> 1071074.4 | E15: =(E$11/121)*$C15 -> 1428099.2 | F15: =(F$11/121)*$C15 -> 1071074.4 | G15: =(G$11/121)*$C15 -> 714049.59 | H15: =(H$11/121)*$C15 -> 714049.59 | I15: =(I$11/121)*$C15 -> 714049.59 | J15: =(J$11/121)*$C15 -> 1785124 | K15: =(K$11/121)*$C15 -> 1547107.4 | ... O15: =(O$11/121)*$C15 -> 1071074.4 | S15: Vol. (in 000s MT) | T15: 4 | U15: 5 | V15: 4 | W15: =SUM(T15:V15) -> 13 | Z15: 42.35 | AA15: =Z15*0.35 -> 14.8225 | AB15: =Z15*0.3 -> 12.705 | AC15: =Z15*0.35 -> 14.8225
A16: Local Events/Fairs/Exhibitions | B16: For different Plant Launches, promotional exhibitions and mass events like Mahakumbh, etc - Total 10 events | C16: ='One Helix'!C16 -> 5000000 | D16: =(D$11/121)*$C16 -> 371900.83 | E16: =(E$11/121)*$C16 -> 495867.77 | F16: =(F$11/121)*$C16 -> 371900.83 | G16: =(G$11/121)*$C16 -> 247933.88 | H16: =(H$11/121)*$C16 -> 247933.88 | I16: =(I$11/121)*$C16 -> 247933.88 | J16: =(J$11/121)*$C16 -> 619834.71 | K16: =(K$11/121)*$C16 -> 537190.08 | ... O16: =(O$11/121)*$C16 -> 371900.83 | S16: Cost (in Rs./MT) | T16: =T14/(T15*1000) -> 5668.6602 | U16: =U14/(U15*1000) -> 4938.8976 | V16: =V14/(V15*1000) -> 4877.1949 | W16: =W14/(W15*1000) -> 5144.4545 | Z16: 30.25 | AA16: =Z16*0.4 -> 12.1 | AB16: =Z16*0.3 -> 9.075 | AC16: =Z16*0.3 -> 9.075
A17: Paper Advertisement | B17: 1 newspaper insert for onboarding 50% of new distributors @1 Lac | C17: ='One Helix'!C17 -> 0 | D17: =(D$11/121)*$C17 -> 0 | E17: =(E$11/121)*$C17 -> 0 | F17: =(F$11/121)*$C17 -> 0 | G17: =(G$11/121)*$C17 -> 0 | H17: =(H$11/121)*$C17 -> 0 | I17: =(I$11/121)*$C17 -> 0 | J17: =(J$11/121)*$C17 -> 0 | K17: =(K$11/121)*$C17 -> 0 | ... O17: =(O$11/121)*$C17 -> 0 | S17: Q2 | T17: 46204 | U17: 46235 | V17: 46266 | W17: Total
A18: Van Campaign | B18: To be done in Top 3 high potential districts for all operational states @ Rs 7000 /day (No. of states: 15) for 2 month | C18: ='One Helix'!C18 -> 18900000 | D18: =(D$11/121)*$C18 -> 1405785.1 | E18: =(E$11/121)*$C18 -> 1874380.2 | F18: =(F$11/121)*$C18 -> 1405785.1 | G18: =(G$11/121)*$C18 -> 937190.08 | H18: =(H$11/121)*$C18 -> 937190.08 | I18: =(I$11/121)*$C18 -> 937190.08 | J18: =(J$11/121)*$C18 -> 2342975.2 | K18: =(K$11/121)*$C18 -> 2030578.5 | ... O18: =(O$11/121)*$C18 -> 1405785.1 | S18: % allocation | T18: =T19/$W19 -> 0.33333333 | U18: =U19/$W19 -> 0.33333333 | V18: =V19/$W19 -> 0.33333333
A19: Syndicate Launch events | B19: Syndicate Launch events @15 states -Distributor base locations @Rs 5 Lac/event | C19: ='One Helix'!C19 -> 7500000 | D19: =(D$11/121)*$C19 -> 557851.24 | E19: =(E$11/121)*$C19 -> 743801.65 | F19: =(F$11/121)*$C19 -> 557851.24 | G19: =(G$11/121)*$C19 -> 371900.83 | H19: =(H$11/121)*$C19 -> 371900.83 | I19: =(I$11/121)*$C19 -> 371900.83 | J19: =(J$11/121)*$C19 -> 929752.07 | K19: =(K$11/121)*$C19 -> 805785.12 | ... O19: =(O$11/121)*$C19 -> 557851.24 | S19: Marketing costs | T19: =G54 -> 10521418 | U19: =H54 -> 10521418 | V19: =I54 -> 10521418 | W19: =U9 -> 31564253
A20: Transit Branding | B20: To be done in Top 3 high potential districts for all operational states @2000 autos @Rs. 700/auto (No. of states: 15) | C20: ='One Helix'!C20 -> 42000000 | D20: =(D$11/121)*$C20 -> 3123966.9 | E20: =(E$11/121)*$C20 -> 4165289.3 | F20: =(F$11/121)*$C20 -> 3123966.9 | G20: =(G$11/121)*$C20 -> 2082644.6 | H20: =(H$11/121)*$C20 -> 2082644.6 | I20: =(I$11/121)*$C20 -> 2082644.6 | J20: =(J$11/121)*$C20 -> 5206611.6 | K20: =(K$11/121)*$C20 -> 4512396.7 | ... O20: =(O$11/121)*$C20 -> 3123966.9 | S20: Vol. (in 000s MT) | T20: 4 | U20: 4 | V20: 4 | W20: =SUM(T20:V20) -> 12
A21: BTL Activities | B21: Remarks | C21: =SUM(C23:C39) -> 87364615 | D21: =SUM(D23:D39) -> 9157285.4 | E21: =SUM(E23:E39) -> 8286637 | F21: =SUM(F23:F39) -> 6214977.7 | G21: =SUM(G23:G39) -> 4143318.5 | H21: =SUM(H23:H39) -> 4143318.5 | I21: =SUM(I23:I39) -> 4143318.5 | J21: =SUM(J23:J39) -> 11742912 | ... O21: =SUM(O23:O39) -> 6214977.7 | S21: Cost (in Rs./MT) | T21: =T19/(T20*1000) -> 2630.3544 | U21: =U19/(U20*1000) -> 2630.3544 | V21: =V19/(V20*1000) -> 2630.3544 | W21: =W19/(W20*1000) -> 2630.3544
A22: BTL Spends breakup | D22: 9 | E22: 12 | F22: 9 | G22: 6 | H22: 6 | I22: 6 | J22: 15 | K22: 13 | L22: 15 | M22: 12 | N22: 9 | O22: 9 | Q22: =121-SUM(D22:O22) -> 0 | S22: Q3 | T22: 46296 | U22: 46327 | V22: 46357 | W22: Total
A23: NLBs | B23: To be given to 50% of active dealers (Cost is taken to be Rs.40/sqft. Avg size is taken to be 10*3=30 sqft) | C23: ='One Helix'!C23 -> 830769.23 | D23: =(D$22/121)*$C23 -> 61792.753 | E23: =(E$22/121)*$C23 -> 82390.337 | F23: =(F$22/121)*$C23 -> 61792.753 | G23: =(G$22/121)*$C23 -> 41195.168 | H23: =(H$22/121)*$C23 -> 41195.168 | I23: =(I$22/121)*$C23 -> 41195.168 | J23: =(J$22/121)*$C23 -> 102987.92 | K23: =(K$22/121)*$C23 -> 89256.198 | ... O23: =(O$22/121)*$C23 -> 61792.753 | S23: % allocation | T23: =T24/$W24 -> 0.36105654 | U23: =U24/$W24 -> 0.29724516 | V23: =V24/$W24 -> 0.34169829
A24: GSBs | B24: To be given to 25% of active dealers. Cost: (180 *size of flex + 65*length of iron angle), Avg size of flex taken to be 10*3. Avg iron angle length: 18 ft | C24: ='One Helix'!C24 -> 2274230.8 | D24: =(D$22/121)*$C24 -> 169157.66 | E24: =(E$22/121)*$C24 -> 225543.55 | F24: =(F$22/121)*$C24 -> 169157.66 | G24: =(G$22/121)*$C24 -> 112771.77 | H24: =(H$22/121)*$C24 -> 112771.77 | I24: =(I$22/121)*$C24 -> 112771.77 | J24: =(J$22/121)*$C24 -> 281929.43 | K24: =(K$22/121)*$C24 -> 244338.84 | ... O24: =(O$22/121)*$C24 -> 169157.66 | S24: Marketing costs | T24: =J54 -> 27678449 | U24: =K54 -> 22786694 | V24: =L54 -> 26194453 | W24: =V9 -> 76659596
A25: Counter Wall Painting | B25: To be given to exclusive 20% active counters @Rs 10000/counter | C25: ='One Helix'!C25 -> 2769230.8 | D25: =(D$22/121)*$C25 -> 205975.84 | E25: =(E$22/121)*$C25 -> 274634.46 | F25: =(F$22/121)*$C25 -> 205975.84 | G25: =(G$22/121)*$C25 -> 137317.23 | H25: =(H$22/121)*$C25 -> 137317.23 | I25: =(I$22/121)*$C25 -> 137317.23 | J25: =(J$22/121)*$C25 -> 343293.07 | K25: =(K$22/121)*$C25 -> 297520.66 | ... O25: =(O$22/121)*$C25 -> 205975.84 | S25: Vol. (in 000s MT) | T25: 7 | U25: 10 | V25: 13 | W25: =SUM(T25:V25) -> 30
A26: Inshop Branding | B26: To be given to exclusive 10% active counters @Rs 40000/counter | C26: ='One Helix'!C26 -> 5538461.5 | D26: =(D$22/121)*$C26 -> 411951.68 | E26: =(E$22/121)*$C26 -> 549268.91 | F26: =(F$22/121)*$C26 -> 411951.68 | G26: =(G$22/121)*$C26 -> 274634.46 | H26: =(H$22/121)*$C26 -> 274634.46 | I26: =(I$22/121)*$C26 -> 274634.46 | J26: =(J$22/121)*$C26 -> 686586.14 | K26: =(K$22/121)*$C26 -> 595041.32 | ... O26: =(O$22/121)*$C26 -> 411951.68 | S26: Cost (in Rs./MT) | T26: =T24/(T25*1000) -> 3954.0641 | U26: =U24/(U25*1000) -> 2278.6694 | V26: =V24/(V25*1000) -> 2014.9579 | W26: =W24/(W25*1000) -> 2555.3199
A27: Architect/Engineer Meets | B27: Considering every distributor does 1 meets with 50 architects @Rs 3500/pax every quarter | C27: ='One Helix'!C27 -> 29400000 | D27: =(D$22/121)*$C27 -> 2186776.9 | E27: =(E$22/121)*$C27 -> 2915702.5 | F27: =(F$22/121)*$C27 -> 2186776.9 | G27: =(G$22/121)*$C27 -> 1457851.2 | H27: =(H$22/121)*$C27 -> 1457851.2 | I27: =(I$22/121)*$C27 -> 1457851.2 | J27: =(J$22/121)*$C27 -> 3644628.1 | K27: =(K$22/121)*$C27 -> 3158677.7 | ... O27: =(O$22/121)*$C27 -> 2186776.9 | S27: Q4 | T27: 46388 | U27: 46419 | V27: 46447 | W27: Total
A28: Contractor Meets | B28: Considering every distributor does 2 meets with 50 contractors @Rs 1000/pax per quarter | C28: ='One Helix'!C28 -> 16800000 | D28: =(D$22/121)*$C28 -> 1249586.8 | E28: =(E$22/121)*$C28 -> 1666115.7 | F28: =(F$22/121)*$C28 -> 1249586.8 | G28: =(G$22/121)*$C28 -> 833057.85 | H28: =(H$22/121)*$C28 -> 833057.85 | I28: =(I$22/121)*$C28 -> 833057.85 | J28: =(J$22/121)*$C28 -> 2082644.6 | K28: =(K$22/121)*$C28 -> 1804958.7 | ... O28: =(O$22/121)*$C28 -> 1249586.8 | S28: % allocation | T28: =T29/$W29 -> 0.39942646 | U28: =U29/$W29 -> 0.30028677 | V28: =V29/$W29 -> 0.30028677
A29: Mason Meets | B29: 1 Mason meet for every transacting dealer, of 30 pax/meet Cost @ Rs 300/pax/meet | C29: ='One Helix'!C29 -> 8100000 | D29: =(D$22/121)*$C29 -> 602479.34 | E29: =(E$22/121)*$C29 -> 803305.79 | F29: =(F$22/121)*$C29 -> 602479.34 | G29: =(G$22/121)*$C29 -> 401652.89 | H29: =(H$22/121)*$C29 -> 401652.89 | I29: =(I$22/121)*$C29 -> 401652.89 | J29: =(J$22/121)*$C29 -> 1004132.2 | K29: =(K$22/121)*$C29 -> 870247.93 | ... O29: =(O$22/121)*$C29 -> 602479.34 | S29: Marketing costs | T29: =M54 -> 20892835 | U29: =N54 -> 15707127 | V29: =O54 -> 15707127 | W29: =W9 -> 52307088
A30: Dealer Certificates | B30: To be given to all active retailers @Rs 400 | C30: ='One Helix'!C30 -> 553846.15 | D30: =(D$22/121)*$C30 -> 41195.168 | E30: =(E$22/121)*$C30 -> 54926.891 | F30: =(F$22/121)*$C30 -> 41195.168 | G30: =(G$22/121)*$C30 -> 27463.446 | H30: =(H$22/121)*$C30 -> 27463.446 | I30: =(I$22/121)*$C30 -> 27463.446 | J30: =(J$22/121)*$C30 -> 68658.614 | K30: =(K$22/121)*$C30 -> 59504.132 | ... O30: =(O$22/121)*$C30 -> 41195.168 | S30: Vol. (in 000s MT) | T30: 18 | U30: 21 | V30: 27 | W30: =SUM(T30:V30) -> 66
A31: Architect one-to-one visit Gifts | B31: Considering 75 architects for every distributor with gift cost @ Rs 500 | C31: ='One Helix'!C31 -> 1575000 | D31: =(D$22/121)*$C31 -> 117148.76 | E31: =(E$22/121)*$C31 -> 156198.35 | F31: =(F$22/121)*$C31 -> 117148.76 | G31: =(G$22/121)*$C31 -> 78099.174 | H31: =(H$22/121)*$C31 -> 78099.174 | I31: =(I$22/121)*$C31 -> 78099.174 | J31: =(J$22/121)*$C31 -> 195247.93 | K31: =(K$22/121)*$C31 -> 169214.88 | ... O31: =(O$22/121)*$C31 -> 117148.76 | S31: Cost (in Rs./MT) | T31: =T29/(T30*1000) -> 1160.7131 | U31: =U29/(U30*1000) -> 747.95841 | V31: =V29/(V30*1000) -> 581.74543 | W31: =W29/(W30*1000) -> 792.53164
A32: Digital Factory visits to dealers via VR headset | B32: Digital headset for factory visit to 25% of active dealers @ Rs 5000 | C32: ='One Helix'!C33 -> 1730769.2 | D32: =(D$22/121)*$C32 -> 128734.9 | E32: =(E$22/121)*$C32 -> 171646.54 | F32: =(F$22/121)*$C32 -> 128734.9 | G32: =(G$22/121)*$C32 -> 85823.268 | H32: =(H$22/121)*$C32 -> 85823.268 | I32: =(I$22/121)*$C32 -> 85823.268 | J32: =(J$22/121)*$C32 -> 214558.17 | K32: =(K$22/121)*$C32 -> 185950.41 | ... O32: =(O$22/121)*$C32 -> 128734.9
A33: POP | B33: POP materials @Rs 3K to be given to every active dealer | C33: ='One Helix'!C34 -> 4153846.2 | D33: =(D$22/121)*$C33 -> 308963.76 | E33: =(E$22/121)*$C33 -> 411951.68 | F33: =(F$22/121)*$C33 -> 308963.76 | G33: =(G$22/121)*$C33 -> 205975.84 | H33: =(H$22/121)*$C33 -> 205975.84 | I33: =(I$22/121)*$C33 -> 205975.84 | J33: =(J$22/121)*$C33 -> 514939.61 | K33: =(K$22/121)*$C33 -> 446280.99 | ... O33: =(O$22/121)*$C33 -> 308963.76
A34: Vehicle Branding | B34: To be done at 10% of active dealers @Rs 5k/vehicle | C34: ='One Helix'!C35 -> 692307.69 | D34: =(D$22/121)*$C34 -> 51493.961 | E34: =(E$22/121)*$C34 -> 68658.614 | F34: =(F$22/121)*$C34 -> 51493.961 | G34: =(G$22/121)*$C34 -> 34329.307 | H34: =(H$22/121)*$C34 -> 34329.307 | I34: =(I$22/121)*$C34 -> 34329.307 | J34: =(J$22/121)*$C34 -> 85823.268 | K34: =(K$22/121)*$C34 -> 74380.165 | ... O34: =(O$22/121)*$C34 -> 51493.961
A35: Leaflets/Brochures | B35: 2000 units to be sent to all active retailers at Rs 4/pc | C35: ='One Helix'!C36 -> 5538461.5 | D35: =(D$22/121)*$C35 -> 411951.68 | E35: =(E$22/121)*$C35 -> 549268.91 | F35: =(F$22/121)*$C35 -> 411951.68 | G35: =(G$22/121)*$C35 -> 274634.46 | H35: =(H$22/121)*$C35 -> 274634.46 | I35: =(I$22/121)*$C35 -> 274634.46 | J35: =(J$22/121)*$C35 -> 686586.14 | K35: =(K$22/121)*$C35 -> 595041.32 | ... O35: =(O$22/121)*$C35 -> 411951.68
A36: Annual Diaries | B36: 3 annual diaries per active retailer@Rs250/diary | C36: ='One Helix'!C37 -> 1038461.5 | D36: 1557692.3 | E36: 0 | F36: 0 | G36: 0 | H36: 0 | I36: 0 | J36: 0 | K36: 0 | L36: 0 | M36: 0 | N36: 0 | O36: 0
A37: Festival Branding gifts (Diwali, Holi) | B37: To all active dealers and active influencers (3/retailer) | C37: ='One Helix'!C38 -> 2769230.8 | D37: =C37*0.5 -> 1384615.4 | E37: 0 | F37: 0 | G37: 0 | H37: 0 | I37: 0 | J37: =C37-D37 -> 1384615.4 | K37: 0 | L37: 0 | M37: 0 | N37: 0 | O37: 0
A38: Branded Tarpaulins | B38: 1 Branded Tarpaulins @ 1500/pc | C38: ='One Helix'!C39 -> 2076923.1 | D38: =(D$22/121)*$C38 -> 154481.88 | E38: =(E$22/121)*$C38 -> 205975.84 | F38: =(F$22/121)*$C38 -> 154481.88 | G38: =(G$22/121)*$C38 -> 102987.92 | H38: =(H$22/121)*$C38 -> 102987.92 | I38: =(I$22/121)*$C38 -> 102987.92 | J38: =(J$22/121)*$C38 -> 257469.8 | K38: =(K$22/121)*$C38 -> 223140.5 | ... O38: =(O$22/121)*$C38 -> 154481.88
A39: Cutout Standees from Ads | B39: For 50% of active retailer in size 5ft X 3ft; 5mm board with stand @ 2200/pc | C39: ='One Helix'!C40 -> 1523076.9 | D39: =(D$22/121)*$C39 -> 113286.71 | E39: =(E$22/121)*$C39 -> 151048.95 | F39: =(F$22/121)*$C39 -> 113286.71 | G39: =(G$22/121)*$C39 -> 75524.476 | H39: =(H$22/121)*$C39 -> 75524.476 | I39: =(I$22/121)*$C39 -> 75524.476 | J39: =(J$22/121)*$C39 -> 188811.19 | K39: =(K$22/121)*$C39 -> 163636.36 | ... O39: =(O$22/121)*$C39 -> 113286.71
A40: Project BTL Activities | B40: Remarks | C40: =SUM(C42:C45) -> 3625000 | D40: =SUM(D42:D45) -> 297933.88 | E40: =SUM(E42:E45) -> 165289.26 | F40: =SUM(F42:F45) -> 165289.26 | G40: =SUM(G42:G45) -> 0 | H40: =SUM(H42:H45) -> 0 | I40: =SUM(I42:I45) -> 0 | J40: =SUM(J42:J45) -> 215289.26 | ... O40: =SUM(O42:O45) -> 0
A41: Project BTL Spends breakup | D41: 30 | E41: 20 | F41: 20 | G41: 0 | H41: 0 | I41: 0 | J41: 20 | K41: 20 | L41: 11 | M41: 0 | N41: 0 | O41: 0 | Q41: =121-SUM(D41:O41) -> 0
A42: First visit to project customers | B42: 2000 customers @Rs500 | C42: ='One Helix'!C42 -> 1000000 | D42: =(D$41/121)*$C42 -> 247933.88 | E42: =(E$41/121)*$C42 -> 165289.26 | F42: =(F$41/121)*$C42 -> 165289.26 | G42: =(G$41/121)*$C42 -> 0 | H42: =(H$41/121)*$C42 -> 0 | I42: =(I$41/121)*$C42 -> 0 | J42: =(J$41/121)*$C42 -> 165289.26 | K42: =(K$41/121)*$C42 -> 165289.26 | ... O42: =(O$41/121)*$C42 -> 0
A43: Government Approvals | B43: 10 approvals @Rs 2.5 Lacs | C43: ='One Helix'!C43 -> 2500000
A44: Annual Diaries | B44: 1 annual diary per active project customer @Rs250/diary - 100 customers | C44: ='One Helix'!C44 -> 25000 | E44: 0 | F44: 0 | G44: 0 | H44: 0 | I44: 0 | J44: 0 | K44: 0 | L44: 25000 | M44: 0 | N44: =(N$41/121)*$C44 -> 0 | O44: =(O$41/121)*$C44 -> 0
A45: Festival Branding gifts (Diwali, Holi) | B45: 1 gift per active project customer @Rs500/festival - 100 customers | C45: ='One Helix'!C45 -> 100000 | D45: =C45*0.5 -> 50000 | E45: 0 | F45: 0 | G45: =(G$41/121)*$C45 -> 0 | H45: =(H$41/121)*$C45 -> 0 | I45: =(I$41/121)*$C45 -> 0 | J45: =C45*0.5 -> 50000 | K45: 0 | L45: 0 | M45: =(M$41/121)*$C45 -> 0 | N45: =(N$41/121)*$C45 -> 0 | O45: =(O$41/121)*$C45 -> 0
A46: Digital Marketing Collaterals | B46: Remarks | C46: =SUM(C48:C51) -> 12800000 | D46: =SUM(D48:D51) -> 3877272.7 | E46: =SUM(E48:E51) -> 3786363.6 | F46: =SUM(F48:F51) -> 3786363.6 | G46: =SUM(G48:G51) -> 150000 | H46: =SUM(H48:H51) -> 150000 | I46: =SUM(I48:I51) -> 150000 | J46: =SUM(J48:J51) -> 150000 | ... O46: =SUM(O48:O51) -> 150000
A47: Collateral Spends breakup | D47: 41 | E47: 40 | F47: 40 | G47: 0 | H47: 0 | I47: 0 | J47: 0 | K47: 0 | L47: 0 | M47: 0 | N47: 0 | O47: 0 | Q47: =121-SUM(D47:O47) -> 0
A48: Marketing Agencies | B48: 1.5L/month/agency | C48: ='One Helix'!C47 -> 1800000 | D48: 150000 | E48: 150000 | F48: 150000 | G48: 150000 | H48: 150000 | I48: 150000 | J48: 150000 | K48: 150000 | L48: 150000 | M48: 150000 | N48: 150000 | O48: 150000
A49: Product featuring video | C49: ='One Helix'!C48 -> 5000000 | D49: =(D$47/121)*$C49 -> 1694214.9 | E49: =(E$47/121)*$C49 -> 1652892.6 | F49: =(F$47/121)*$C49 -> 1652892.6 | G49: =(G$47/121)*$C49 -> 0 | H49: =(H$47/121)*$C49 -> 0 | I49: =(I$47/121)*$C49 -> 0 | J49: =(J$47/121)*$C49 -> 0 | K49: =(K$47/121)*$C49 -> 0 | ... O49: =(O$47/121)*$C49 -> 0
A50: Brand Film production | B50: Youtube Ad production | C50: ='One Helix'!C49 -> 5000000 | D50: =(D$47/121)*$C50 -> 1694214.9 | E50: =(E$47/121)*$C50 -> 1652892.6 | F50: =(F$47/121)*$C50 -> 1652892.6 | G50: =(G$47/121)*$C50 -> 0 | H50: =(H$47/121)*$C50 -> 0 | I50: =(I$47/121)*$C50 -> 0 | J50: =(J$47/121)*$C50 -> 0 | K50: =(K$47/121)*$C50 -> 0 | ... O50: =(O$47/121)*$C50 -> 0
A51: Factory visit AR video creation | C51: ='One Helix'!C50 -> 1000000 | D51: =(D$47/121)*$C51 -> 338842.98 | E51: =(E$47/121)*$C51 -> 330578.51 | F51: =(F$47/121)*$C51 -> 330578.51 | G51: =(G$47/121)*$C51 -> 0 | H51: =(H$47/121)*$C51 -> 0 | I51: =(I$47/121)*$C51 -> 0 | J51: =(J$47/121)*$C51 -> 0 | K51: =(K$47/121)*$C51 -> 0 | ... O51: =(O$47/121)*$C51 -> 0
A52: Discreationary Budget | B52: Remarks | C52: =C53 -> 5000000
C53: ='One Helix'!C52 -> 5000000
A54: TOTALS | C54: =SUM(C46+C40+C21+C10+C52) -> 2.3438962e+08 | D54: =SUM(D46+D40+D21+D10) -> 22674641 | E54: =SUM(E46+E40+E21+E10) -> 24694488 | F54: =SUM(F46+F40+F21+F10) -> 19508779 | G54: =SUM(G46+G40+G21+G10) -> 10521418 | H54: =SUM(H46+H40+H21+H10) -> 10521418 | I54: =SUM(I46+I40+I21+I10) -> 10521418 | J54: =SUM(J46+J40+J21+J10) -> 27678449 | K54: =SUM(K46+K40+K21+K10) -> 22786694 | ... O54: =SUM(O46+O40+O21+O10) -> 15707127
A56: Category | B56: Proposed Budget | C56: % of Budget
A57: ATL Activities | B57: =C10 -> 125600000 | C57: =B57/$C$54 -> 0.53585992
A58: BTL Activities | B58: =C21 -> 87364615 | C58: =B58/$C$54 -> 0.37273245
A59: Project BTL Activities | B59: =C40 -> 3625000 | C59: =B59/$C$54 -> 0.015465702
A60: Digital Marketing Collaterals | B60: =C46 -> 12800000 | C60: =B60/$C$54 -> 0.054609928

Sheet JSW ONE TMT Budget
A1: #Distributors | B1: 42
A2: Volume projection (Mar'27 Exit) | B2: 27000
A3: Avg. volume/retailer/month | B3: 20
A4: Total retailers (Mar'27) | B4: 6230.7692
A5: Total Active retailers (Mar'27) | B5: 2015
A6: Total transacting retailers (Mar'27) | B6: 1310
A7: #Priority districts | B7: 250
C8: Month | D8: 46048 | E8: 46168 | F8: 46199 | G8: 46229 | H8: 46260 | I8: 46291 | J8: 46321 | K8: 46352 | L8: 46382 | M8: 46413 | N8: 46444 | O8: 46472 | Q8: Left to Allocate | S8: Quarter | T8: Q1 | U8: Q2 | V8: Q3 | W8: Q4
S9: Marketing Cost | T9: =SUM(D50:F50) -> 70846502 | U9: =SUM(G50:I50) -> 42490141 | V9: =SUM(J50:L50) -> 55613732 | W9: =SUM(M50:O50) -> 47522204
A10: ATL Activities | B10: Remarks | C10: =SUM(C12:C20) -> 95050000 | D10: =SUM(D12:D20) -> 11783058 | E10: =SUM(E12:E20) -> 10997521 | F10: =SUM(F12:F20) -> 6284297.5 | G10: =SUM(G12:G20) -> 6284297.5 | H10: =SUM(H12:H20) -> 6284297.5 | I10: =SUM(I12:I20) -> 6284297.5 | J10: =SUM(J12:J20) -> 11783058 | ... O10: =SUM(O12:O20) -> 6284297.5 | S10: % Allocation | T10: =T9/$C$50 -> 0.32734725 | U10: =U9/$C$50 -> 0.19632629 | V10: =V9/$C$50 -> 0.25696403 | W10: =W9/$C$50 -> 0.21957701
A11: ATL Spends breakup | D11: 15 | E11: 14 | F11: 8 | G11: 8 | H11: 8 | I11: 8 | J11: 15 | K11: 10 | L11: 8 | M11: 11 | N11: 8 | O11: 8 | Q11: =121-SUM(D11:O11) -> 0 | S11: Cost / MT | T11: =W16 -> 874.64817 | U11: =W21 -> 674.44668 | V11: =W26 -> 585.40771 | W11: =W31 -> 314.71659
A12: Impact Wall Painting | B12: 20,000 sq ft in high potential district @ Rs 15 | C12: 75000000 | D12: =(D$11/121)*$C12 -> 9297520.7 | E12: =(E$11/121)*$C12 -> 8677686 | F12: =(F$11/121)*$C12 -> 4958677.7 | G12: =(G$11/121)*$C12 -> 4958677.7 | H12: =(H$11/121)*$C12 -> 4958677.7 | I12: =(I$11/121)*$C12 -> 4958677.7 | J12: =(J$11/121)*$C12 -> 9297520.7 | K12: =(K$11/121)*$C12 -> 6198347.1 | ... O12: =(O$11/121)*$C12 -> 4958677.7 | S12: Q1 | T12: 46113 | U12: 46143 | V12: 46174 | W12: Total
A13: Integrated FM Radio Campaigns (Ad + Promotional Activity) | B13: To be done in Top 3 high potential districts for all operational states @Rs 2.5 Lac/campaign (No. of states: 5) for 3 months | C13: =11250000/3 -> 3750000 | D13: =(D$11/121)*$C13 -> 464876.03 | E13: =(E$11/121)*$C13 -> 433884.3 | F13: =(F$11/121)*$C13 -> 247933.88 | G13: =(G$11/121)*$C13 -> 247933.88 | H13: =(H$11/121)*$C13 -> 247933.88 | I13: =(I$11/121)*$C13 -> 247933.88 | J13: =(J$11/121)*$C13 -> 464876.03 | K13: =(K$11/121)*$C13 -> 309917.36 | ... O13: =(O$11/121)*$C13 -> 247933.88 | S13: % allocation | T13: =T14/$W14 -> 0.42356841 | U13: =U14/$W14 -> 0.33406744 | V13: =V14/$W14 -> 0.24236415
D14: =(D$11/121)*$C14 -> 0 | E14: =(E$11/121)*$C14 -> 0 | F14: =(F$11/121)*$C14 -> 0 | G14: =(G$11/121)*$C14 -> 0 | H14: =(H$11/121)*$C14 -> 0 | I14: =(I$11/121)*$C14 -> 0 | J14: =(J$11/121)*$C14 -> 0 | K14: =(K$11/121)*$C14 -> 0 | ... O14: =(O$11/121)*$C14 -> 0 | S14: Marketing costs | T14: =D50 -> 30008340 | U14: =E50 -> 23667510 | V14: =F50 -> 17170652 | W14: =T9 -> 70846502
A15: Digital Marketing Campaigns | B15: To be done in Top 3 high potential districts for all operational states @Rs 5 Lac/campaign (No. of states: 5) for 3 months | C15: =22500000/3 -> 7500000 | D15: =(D$11/121)*$C15 -> 929752.07 | E15: =(E$11/121)*$C15 -> 867768.6 | F15: =(F$11/121)*$C15 -> 495867.77 | G15: =(G$11/121)*$C15 -> 495867.77 | H15: =(H$11/121)*$C15 -> 495867.77 | I15: =(I$11/121)*$C15 -> 495867.77 | J15: =(J$11/121)*$C15 -> 929752.07 | K15: =(K$11/121)*$C15 -> 619834.71 | ... O15: =(O$11/121)*$C15 -> 495867.77 | S15: Vol. (in 000s MT) | T15: 23 | U15: 31 | V15: 27 | W15: =SUM(T15:V15) -> 81
A16: Local Events/Fairs/Exhibitions | B16: For different Plant Launches, promotional exhibitions and mass events like Mahakumbh, etc - Total 5 events | C16: =5000000/2 -> 2500000 | D16: =(D$11/121)*$C16 -> 309917.36 | E16: =(E$11/121)*$C16 -> 289256.2 | F16: =(F$11/121)*$C16 -> 165289.26 | G16: =(G$11/121)*$C16 -> 165289.26 | H16: =(H$11/121)*$C16 -> 165289.26 | I16: =(I$11/121)*$C16 -> 165289.26 | J16: =(J$11/121)*$C16 -> 309917.36 | K16: =(K$11/121)*$C16 -> 206611.57 | ... O16: =(O$11/121)*$C16 -> 165289.26 | S16: Cost (in Rs./MT) | T16: =T14/(T15*1000) -> 1304.7105 | U16: =U14/(U15*1000) -> 763.46805 | V16: =V14/(V15*1000) -> 635.95007 | W16: =W14/(W15*1000) -> 874.64817
D17: =(D$11/121)*$C17 -> 0 | E17: =(E$11/121)*$C17 -> 0 | F17: =(F$11/121)*$C17 -> 0 | G17: =(G$11/121)*$C17 -> 0 | H17: =(H$11/121)*$C17 -> 0 | I17: =(I$11/121)*$C17 -> 0 | J17: =(J$11/121)*$C17 -> 0 | K17: =(K$11/121)*$C17 -> 0 | ... O17: =(O$11/121)*$C17 -> 0 | S17: Q2 | T17: 46204 | U17: 46235 | V17: 46266 | W17: Total
A18: Van Campaign | B18: To be done in Top 3 high potential districts for all operational states @ Rs 7000 /day (No. of states: 5) for 2 month | C18: =18900000/3 -> 6300000 | D18: =(D$11/121)*$C18 -> 780991.74 | E18: =(E$11/121)*$C18 -> 728925.62 | F18: =(F$11/121)*$C18 -> 416528.93 | G18: =(G$11/121)*$C18 -> 416528.93 | H18: =(H$11/121)*$C18 -> 416528.93 | I18: =(I$11/121)*$C18 -> 416528.93 | J18: =(J$11/121)*$C18 -> 780991.74 | K18: =(K$11/121)*$C18 -> 520661.16 | ... O18: =(O$11/121)*$C18 -> 416528.93 | S18: % allocation | T18: =T19/$W19 -> 0.36131841 | U18: =U19/$W19 -> 0.3193408 | V18: =V19/$W19 -> 0.3193408
D19: =(D$11/121)*$C19 -> 0 | E19: =(E$11/121)*$C19 -> 0 | F19: =(F$11/121)*$C19 -> 0 | G19: =(G$11/121)*$C19 -> 0 | H19: =(H$11/121)*$C19 -> 0 | I19: =(I$11/121)*$C19 -> 0 | J19: =(J$11/121)*$C19 -> 0 | K19: =(K$11/121)*$C19 -> 0 | ... O19: =(O$11/121)*$C19 -> 0 | S19: Marketing costs | T19: =G50 -> 15352470 | U19: =H50 -> 13568836 | V19: =I50 -> 13568836 | W19: =U9 -> 42490141
D20: =(D$11/121)*$C20 -> 0 | E20: =(E$11/121)*$C20 -> 0 | F20: =(F$11/121)*$C20 -> 0 | G20: =(G$11/121)*$C20 -> 0 | H20: =(H$11/121)*$C20 -> 0 | I20: =(I$11/121)*$C20 -> 0 | J20: =(J$11/121)*$C20 -> 0 | K20: =(K$11/121)*$C20 -> 0 | ... O20: =(O$11/121)*$C20 -> 0 | S20: Vol. (in 000s MT) | T20: 23 | U20: 19 | V20: 21 | W20: =SUM(T20:V20) -> 63
A21: BTL Activities | B21: Remarks | C21: =SUM(C23:C39) -> 1.1345114e+08 | D21: =SUM(D23:D39) -> 16058134 | E21: =SUM(E23:E39) -> 10701807 | F21: =SUM(F23:F39) -> 8918172.5 | G21: =SUM(G23:G39) -> 8918172.5 | H21: =SUM(H23:H39) -> 7134538 | I21: =SUM(I23:I39) -> 7134538 | J21: =SUM(J23:J39) -> 12716807 | ... O21: =SUM(O23:O39) -> 8026355.3 | S21: Cost (in Rs./MT) | T21: =T19/(T20*1000) -> 667.4987 | U21: =U19/(U20*1000) -> 714.14924 | V21: =V19/(V20*1000) -> 646.13503 | W21: =W19/(W20*1000) -> 674.44668
A22: BTL Spends breakup | D22: 14 | E22: 12 | F22: 10 | G22: 10 | H22: 8 | I22: 8 | J22: 12 | K22: 10 | L22: 8 | M22: 10 | N22: 10 | O22: 9 | Q22: =121-SUM(D22:O22) -> 0 | S22: Q3 | T22: 46296 | U22: 46327 | V22: 46357 | W22: Total
A23: NLBs | B23: To be given to 50% of active dealers (Cost is taken to be Rs.40/sqft. Avg size is taken to be 10*3=30 sqft) | C23: 1209000 | D23: =(D$22/121)*$C23 -> 139884.3 | E23: =(E$22/121)*$C23 -> 119900.83 | F23: =(F$22/121)*$C23 -> 99917.355 | G23: =(G$22/121)*$C23 -> 99917.355 | H23: =(H$22/121)*$C23 -> 79933.884 | I23: =(I$22/121)*$C23 -> 79933.884 | J23: =(J$22/121)*$C23 -> 119900.83 | K23: =(K$22/121)*$C23 -> 99917.355 | ... O23: =(O$22/121)*$C23 -> 89925.62 | S23: % allocation | T23: =T24/$W24 -> 0.44710457 | U23: =U24/$W24 -> 0.30727723 | V23: =V24/$W24 -> 0.2456182
A24: GSBs | B24: To be given to 25% of active dealers. Cost: (180 *size of flex + 65*length of iron angle), Avg size of flex taken to be 10*3. Avg iron angle length: 18 ft | C24: 3309637.5 | D24: =(D$22/121)*$C24 -> 382933.26 | E24: =(E$22/121)*$C24 -> 328228.51 | F24: =(F$22/121)*$C24 -> 273523.76 | G24: =(G$22/121)*$C24 -> 273523.76 | H24: =(H$22/121)*$C24 -> 218819.01 | I24: =(I$22/121)*$C24 -> 218819.01 | J24: =(J$22/121)*$C24 -> 328228.51 | K24: =(K$22/121)*$C24 -> 273523.76 | ... O24: =(O$22/121)*$C24 -> 246171.38 | S24: Marketing costs | T24: =J50 -> 24865154 | U24: =K50 -> 17088834 | V24: =L50 -> 13659745 | W24: =V9 -> 55613732
A25: Counter Wall Painting | B25: To be given to exclusive 20% active counters @Rs 10000/counter | C25: 4030000 | D25: =(D$22/121)*$C25 -> 466280.99 | E25: =(E$22/121)*$C25 -> 399669.42 | F25: =(F$22/121)*$C25 -> 333057.85 | G25: =(G$22/121)*$C25 -> 333057.85 | H25: =(H$22/121)*$C25 -> 266446.28 | I25: =(I$22/121)*$C25 -> 266446.28 | J25: =(J$22/121)*$C25 -> 399669.42 | K25: =(K$22/121)*$C25 -> 333057.85 | ... O25: =(O$22/121)*$C25 -> 299752.07 | S25: Vol. (in 000s MT) | T25: 27 | U25: 33 | V25: 35 | W25: =SUM(T25:V25) -> 95
A26: Inshop Branding | B26: To be given to exclusive 10% active counters @Rs 40000/counter | C26: 8060000 | D26: =(D$22/121)*$C26 -> 932561.98 | E26: =(E$22/121)*$C26 -> 799338.84 | F26: =(F$22/121)*$C26 -> 666115.7 | G26: =(G$22/121)*$C26 -> 666115.7 | H26: =(H$22/121)*$C26 -> 532892.56 | I26: =(I$22/121)*$C26 -> 532892.56 | J26: =(J$22/121)*$C26 -> 799338.84 | K26: =(K$22/121)*$C26 -> 666115.7 | ... O26: =(O$22/121)*$C26 -> 599504.13 | S26: Cost (in Rs./MT) | T26: =T24/(T25*1000) -> 920.93163 | U26: =U24/(U25*1000) -> 517.84344 | V26: =V24/(V25*1000) -> 390.27842 | W26: =W24/(W25*1000) -> 585.40771
A27: Architect/Engineer Meets | B27: Considering every distributor does 1 meets with 50 architects @Rs 3500/pax every quarter | C27: 29400000 | D27: =(D$22/121)*$C27 -> 3401652.9 | E27: =(E$22/121)*$C27 -> 2915702.5 | F27: =(F$22/121)*$C27 -> 2429752.1 | G27: =(G$22/121)*$C27 -> 2429752.1 | H27: =(H$22/121)*$C27 -> 1943801.7 | I27: =(I$22/121)*$C27 -> 1943801.7 | J27: =(J$22/121)*$C27 -> 2915702.5 | K27: =(K$22/121)*$C27 -> 2429752.1 | ... O27: =(O$22/121)*$C27 -> 2186776.9 | S27: Q4 | T27: 46388 | U27: 46419 | V27: 46447 | W27: Total
A28: Contractor Meets | B28: Considering every distributor does 2 meets with 50 contractors @Rs 1000/pax per quarter | C28: 16800000 | D28: =(D$22/121)*$C28 -> 1943801.7 | E28: =(E$22/121)*$C28 -> 1666115.7 | F28: =(F$22/121)*$C28 -> 1388429.8 | G28: =(G$22/121)*$C28 -> 1388429.8 | H28: =(H$22/121)*$C28 -> 1110743.8 | I28: =(I$22/121)*$C28 -> 1110743.8 | J28: =(J$22/121)*$C28 -> 1666115.7 | K28: =(K$22/121)*$C28 -> 1388429.8 | ... O28: =(O$22/121)*$C28 -> 1249586.8 | S28: % allocation | T28: =T29/$W29 -> 0.37264857 | U28: =U29/$W29 -> 0.32305888 | V28: =V29/$W29 -> 0.30429255
A29: Mason Meets | B29: 1 Mason meet for every transacting dealer, of 30 pax/meet Cost @ Rs 300/pax/meet | C29: 11790000 | D29: =(D$22/121)*$C29 -> 1364132.2 | E29: =(E$22/121)*$C29 -> 1169256.2 | F29: =(F$22/121)*$C29 -> 974380.17 | G29: =(G$22/121)*$C29 -> 974380.17 | H29: =(H$22/121)*$C29 -> 779504.13 | I29: =(I$22/121)*$C29 -> 779504.13 | J29: =(J$22/121)*$C29 -> 1169256.2 | K29: =(K$22/121)*$C29 -> 974380.17 | ... O29: =(O$22/121)*$C29 -> 876942.15 | S29: Marketing costs | T29: =M50 -> 17709082 | U29: =N50 -> 15352470 | V29: =O50 -> 14460653 | W29: =W9 -> 47522204
A30: Dealer Certificates | B30: To be given to all active retailers @Rs 400 | C30: 806000 | D30: =(D$22/121)*$C30 -> 93256.198 | E30: =(E$22/121)*$C30 -> 79933.884 | F30: =(F$22/121)*$C30 -> 66611.57 | G30: =(G$22/121)*$C30 -> 66611.57 | H30: =(H$22/121)*$C30 -> 53289.256 | I30: =(I$22/121)*$C30 -> 53289.256 | J30: =(J$22/121)*$C30 -> 79933.884 | K30: =(K$22/121)*$C30 -> 66611.57 | ... O30: =(O$22/121)*$C30 -> 59950.413 | S30: Vol. (in 000s MT) | T30: 44 | U30: 49 | V30: 58 | W30: =SUM(T30:V30) -> 151
A31: Architect one-to-one visit Gifts | B31: Considering 75 architects for every distributor with gift cost @ Rs 500 | C31: 1575000 | D31: =(D$22/121)*$C31 -> 182231.4 | E31: =(E$22/121)*$C31 -> 156198.35 | F31: =(F$22/121)*$C31 -> 130165.29 | G31: =(G$22/121)*$C31 -> 130165.29 | H31: =(H$22/121)*$C31 -> 104132.23 | I31: =(I$22/121)*$C31 -> 104132.23 | J31: =(J$22/121)*$C31 -> 156198.35 | K31: =(K$22/121)*$C31 -> 130165.29 | ... O31: =(O$22/121)*$C31 -> 117148.76 | S31: Cost (in Rs./MT) | T31: =T29/(T30*1000) -> 402.47913 | U31: =U29/(U30*1000) -> 313.31572 | V31: =V29/(V30*1000) -> 249.3216 | W31: =W29/(W30*1000) -> 314.71659
A32: Digital Factory visits to dealers via VR headset | B32: Digital headset for factory visit to 25% of active dealers @ Rs 5000 | C32: 2518750 | D32: =(D$22/121)*$C32 -> 291425.62 | E32: =(E$22/121)*$C32 -> 249793.39 | F32: =(F$22/121)*$C32 -> 208161.16 | G32: =(G$22/121)*$C32 -> 208161.16 | H32: =(H$22/121)*$C32 -> 166528.93 | I32: =(I$22/121)*$C32 -> 166528.93 | J32: =(J$22/121)*$C32 -> 249793.39 | K32: =(K$22/121)*$C32 -> 208161.16 | ... O32: =(O$22/121)*$C32 -> 187345.04
A33: POP | B33: POP materials @Rs 3K to be given to every active dealer | C33: 6045000 | D33: =(D$22/121)*$C33 -> 699421.49 | E33: =(E$22/121)*$C33 -> 599504.13 | F33: =(F$22/121)*$C33 -> 499586.78 | G33: =(G$22/121)*$C33 -> 499586.78 | H33: =(H$22/121)*$C33 -> 399669.42 | I33: =(I$22/121)*$C33 -> 399669.42 | J33: =(J$22/121)*$C33 -> 599504.13 | K33: =(K$22/121)*$C33 -> 499586.78 | ... O33: =(O$22/121)*$C33 -> 449628.1
A34: Vehicle Branding | B34: To be done at 10% of active dealers @Rs 5k/vehicle | C34: 1007500 | D34: =(D$22/121)*$C34 -> 116570.25 | E34: =(E$22/121)*$C34 -> 99917.355 | F34: =(F$22/121)*$C34 -> 83264.463 | G34: =(G$22/121)*$C34 -> 83264.463 | H34: =(H$22/121)*$C34 -> 66611.57 | I34: =(I$22/121)*$C34 -> 66611.57 | J34: =(J$22/121)*$C34 -> 99917.355 | K34: =(K$22/121)*$C34 -> 83264.463 | ... O34: =(O$22/121)*$C34 -> 74938.017
A35: Leaflets/Brochures | B35: 2000 units to be sent to all active retailers at Rs 4/pc | C35: 16120000 | D35: =(D$22/121)*$C35 -> 1865124 | E35: =(E$22/121)*$C35 -> 1598677.7 | F35: =(F$22/121)*$C35 -> 1332231.4 | G35: =(G$22/121)*$C35 -> 1332231.4 | H35: =(H$22/121)*$C35 -> 1065785.1 | I35: =(I$22/121)*$C35 -> 1065785.1 | J35: =(J$22/121)*$C35 -> 1598677.7 | K35: =(K$22/121)*$C35 -> 1332231.4 | ... O35: =(O$22/121)*$C35 -> 1199008.3
A36: Annual Diaries | B36: 3 annual diaries per active retailer@Rs250/diary | C36: 1511250 | D36: 1557692.3 | E36: 0 | F36: 0 | G36: 0 | H36: 0 | I36: 0 | J36: 0 | K36: 0 | L36: 0 | M36: 0 | N36: 0 | O36: 0
A37: Festival Branding gifts (Diwali, Holi) | B37: To all active dealers and active influencers (3/retailer) | C37: 4030000 | D37: =C37*0.5 -> 2015000 | E37: 0 | F37: 0 | G37: 0 | H37: 0 | I37: 0 | J37: =C37-D37 -> 2015000 | K37: 0 | L37: 0 | M37: 0 | N37: 0 | O37: 0
A38: Branded Tarpaulins | B38: 1 Branded Tarpaulins @ 1500/pc | C38: 3022500 | D38: =(D$22/121)*$C38 -> 349710.74 | E38: =(E$22/121)*$C38 -> 299752.07 | F38: =(F$22/121)*$C38 -> 249793.39 | G38: =(G$22/121)*$C38 -> 249793.39 | H38: =(H$22/121)*$C38 -> 199834.71 | I38: =(I$22/121)*$C38 -> 199834.71 | J38: =(J$22/121)*$C38 -> 299752.07 | K38: =(K$22/121)*$C38 -> 249793.39 | ... O38: =(O$22/121)*$C38 -> 224814.05
A39: Cutout Standees from Ads | B39: For 50% of active retailer in size 5ft X 3ft; 5mm board with stand @ 2200/pc | C39: 2216500 | D39: =(D$22/121)*$C39 -> 256454.55 | E39: =(E$22/121)*$C39 -> 219818.18 | F39: =(F$22/121)*$C39 -> 183181.82 | G39: =(G$22/121)*$C39 -> 183181.82 | H39: =(H$22/121)*$C39 -> 146545.45 | I39: =(I$22/121)*$C39 -> 146545.45 | J39: =(J$22/121)*$C39 -> 219818.18 | K39: =(K$22/121)*$C39 -> 183181.82 | ... O39: =(O$22/121)*$C39 -> 164863.64
A40: Project BTL Activities | B40: Remarks | C40: =SUM(C42:C44) -> 1125000 | D40: =SUM(D42:D44) -> 322933.88 | E40: =SUM(E42:E44) -> 165289.26 | F40: =SUM(F42:F44) -> 165289.26 | G40: =SUM(G42:G44) -> 0 | H40: =SUM(H42:H44) -> 0 | I40: =SUM(I42:I44) -> 0 | J40: =SUM(J42:J44) -> 215289.26 | ... O40: =SUM(O42:O44) -> 0
A41: Project BTL Spends breakup | D41: 30 | E41: 20 | F41: 20 | G41: 0 | H41: 0 | I41: 0 | J41: 20 | K41: 20 | L41: 11 | M41: 0 | N41: 0 | O41: 0 | Q41: =121-SUM(D41:O41) -> 0
A42: First visit to project customers | B42: 2000 customers @Rs500 | C42: ='One Helix'!C42 -> 1000000 | D42: =(D$41/121)*$C42 -> 247933.88 | E42: =(E$41/121)*$C42 -> 165289.26 | F42: =(F$41/121)*$C42 -> 165289.26 | G42: =(G$41/121)*$C42 -> 0 | H42: =(H$41/121)*$C42 -> 0 | I42: =(I$41/121)*$C42 -> 0 | J42: =(J$41/121)*$C42 -> 165289.26 | K42: =(K$41/121)*$C42 -> 165289.26 | ... O42: =(O$41/121)*$C42 -> 0
A43: Annual Diaries | B43: 1 annual diary per active project customer @Rs250/diary - 100 customers | C43: 25000 | D43: 25000 | E43: 0 | F43: 0 | G43: =(G$41/121)*$C43 -> 0 | H43: =(H$41/121)*$C43 -> 0 | I43: =(I$41/121)*$C43 -> 0 | J43: 0 | K43: 0 | L43: 0 | M43: =(M$41/121)*$C43 -> 0 | N43: =(N$41/121)*$C43 -> 0 | O43: =(O$41/121)*$C43 -> 0
A44: Festival Branding gifts (Diwali, Holi) | B44: 1 gift per active project customer @Rs500/festival - 100 customers | C44: 100000 | D44: =C44*0.5 -> 50000 | E44: 0 | F44: 0 | G44: =(G$41/121)*$C44 -> 0 | H44: =(H$41/121)*$C44 -> 0 | I44: =(I$41/121)*$C44 -> 0 | J44: =C44*0.5 -> 50000 | K44: 0 | L44: 0 | M44: =(M$41/121)*$C44 -> 0 | N44: =(N$41/121)*$C44 -> 0 | O44: =(O$41/121)*$C44 -> 0
A45: Digital Marketing Collaterals | B45: Remarks | C45: =SUM(C47:C49) -> 6800000 | D45: =SUM(D47:D49) -> 1844214.9 | E45: =SUM(E47:E49) -> 1802892.6 | F45: =SUM(F47:F49) -> 1802892.6 | G45: =SUM(G47:G49) -> 150000 | H45: =SUM(H47:H49) -> 150000 | I45: =SUM(I47:I49) -> 150000 | J45: =SUM(J47:J49) -> 150000 | ... O45: =SUM(O47:O49) -> 150000
A46: Collateral Spends breakup | D46: 41 | E46: 40 | F46: 40 | H46: 0 | I46: 0 | J46: 0 | K46: 0 | L46: 0 | M46: 0 | N46: 0 | O46: 0 | Q46: =121-SUM(D46:O46) -> 0
A47: Marketing Agencies | B47: 1.5L/month/agency | C47: 1800000 | D47: 150000 | E47: 150000 | F47: 150000 | G47: 150000 | H47: 150000 | I47: 150000 | J47: 150000 | K47: 150000 | L47: 150000 | M47: 150000 | N47: 150000 | O47: 150000
A48: Brand Film production | B48: Youtube Ad production highlighting Fe 550D product | C48: 5000000 | D48: =(D$46/121)*$C48 -> 1694214.9 | E48: =(E$46/121)*$C48 -> 1652892.6 | F48: =(F$46/121)*$C48 -> 1652892.6 | G48: =(G$46/121)*$C48 -> 0 | H48: =(H$46/121)*$C48 -> 0 | I48: =(I$46/121)*$C48 -> 0 | J48: =(J$46/121)*$C48 -> 0 | K48: =(K$46/121)*$C48 -> 0 | ... O48: =(O$46/121)*$C48 -> 0
A49: Factory visit AR video creation | D49: =(D$46/121)*$C49 -> 0 | E49: =(E$46/121)*$C49 -> 0 | F49: =(F$46/121)*$C49 -> 0 | G49: =(G$46/121)*$C49 -> 0 | H49: =(H$46/121)*$C49 -> 0 | I49: =(I$46/121)*$C49 -> 0 | J49: =(J$46/121)*$C49 -> 0 | K49: =(K$46/121)*$C49 -> 0 | ... O49: =(O$46/121)*$C49 -> 0
A50: TOTALS | C50: =SUM(C45+C40+C21+C10) -> 2.1642614e+08 | D50: =SUM(D45+D40+D21+D10) -> 30008340 | E50: =SUM(E45+E40+E21+E10) -> 23667510 | F50: =SUM(F45+F40+F21+F10) -> 17170652 | G50: =SUM(G45+G40+G21+G10) -> 15352470 | H50: =SUM(H45+H40+H21+H10) -> 13568836 | I50: =SUM(I45+I40+I21+I10) -> 13568836 | J50: =SUM(J45+J40+J21+J10) -> 24865154 | ... O50: =SUM(O45+O40+O21+O10) -> 14460653
A52: Category | B52: Proposed Budget | C52: % of Budget
A53: ATL Activities | B53: =C10 -> 95050000 | C53: =B53/$C$50 -> 0.43917986
A54: BTL Activities | B54: =C21 -> 1.1345114e+08 | C54: =B54/$C$50 -> 0.52420257
A55: Project BTL Activities | B55: =C40 -> 1125000 | C55: =B55/$C$50 -> 0.0051980783
A56: Digital Marketing Collaterals | B56: =C45 -> 6800000 | C56: =B56/$C$50 -> 0.031419495

Sheet One Helix
A1: Category | B1: Remarks | C1: YEAR TOTALS | D1: %age of totals - Bucketwise | E1: Q1 | I1: Q2 | M1: Q3 | Q1: Q4
E2: Apr | F2: May | G2: Jun | H2: Q1 Totals | I2: Jul | J2: Aug | K2: Sep | L2: Q2 Totals | M2: Oct | N2: Nov | O2: Dec | P2: Q3 Totals | Q2: Jan | R2: Feb | S2: Mar | T2: Q4 Totals
A3: Particulars
A4: #Distributors | B4: 42
A5: Volume projection (Mar'27 Exit) | B5: 27000
A6: Avg. volume/retailer/month | B6: 30
A7: Total retailers (Mar'27) | B7: =B8*3 -> 4153.8462
A8: Total Active retailers (Mar'27) | B8: =B9/65% -> 1384.6154
A9: Total transacting retailers (Mar'27) | B9: =B5/B6 -> 900
A10: #Priority districts | B10: 150
A11: ATL Activities | C11: =SUM(C12:C21) -> 140600000 | E11: =SUM(E12:E21) -> 10970250 | F11: =SUM(F12:F21) -> 14926250 | G11: =SUM(G12:G21) -> 10986000 | H11: =SUM(H12:H21) -> 36882500 | I11: =SUM(I12:I21) -> 4720500 | J11: =SUM(J12:J21) -> 5507250 | K11: =SUM(K12:K21) -> 7381500 | L11: =SUM(L12:L21) -> 17609250 | ... T11: =SUM(T12:T21) -> 35150000
A12: Impact Wall Painting | B12: 20,000 sq ft in 60 Very High and High priority district @ Rs 14 | C12: =60*20000*14 -> 16800000 | D12: =C12/$C$11 -> 0.11948791 | E12: =($D12*QuarterBreakup!C$10*'One Helix'!$C$56) -> 1260000 | F12: =$D12*QuarterBreakup!D$10*'One Helix'!$C$56+882000/2 -> 2121000 | G12: =$D12*QuarterBreakup!E$10*'One Helix'!$C$56+882000/2 -> 1701000 | H12: =E12+F12+G12 -> 5082000 | K12: =$D12*QuarterBreakup!E$16*'One Helix'!$C$56 -> 882000 | L12: =I12+J12+K12 -> 882000 | M12: =$D12*QuarterBreakup!C$22*'One Helix'!$C$56+756000/2 -> 2436000 | N12: =$D12*QuarterBreakup!D$22*'One Helix'!$C$56+756000/2 -> 2142000 | O12: =$D12*QuarterBreakup!E$22*'One Helix'!$C$56 -> 2058000 | P12: =M12+N12+O12 -> 6636000 | Q12: =$D12*QuarterBreakup!C$28*'One Helix'!$C$56 -> 1680000 | R12: =$D12*QuarterBreakup!D$28*'One Helix'!$C$56 -> 1260000 | S12: =$D12*QuarterBreakup!E$28*'One Helix'!$C$56 -> 1260000 | T12: =Q12+R12+S12 -> 4200000
A13: Integrated FM Radio Campaigns (Ad + Promotional Activity) | B13: To be done in Top 3 high priority districts for all 4 states @Rs 2.5 Lac/campaign/district/quarter (No. of states: 4) for 2 quarters | C13: =4*3*250000*2 -> 6000000 | D13: =C13/$C$11 -> 0.042674253 | E13: =$D13*QuarterBreakup!C$10*'One Helix'!$C$56 -> 450000 | F13: =$D13*QuarterBreakup!D$10*'One Helix'!$C$56 -> 600000 | G13: =$D13*QuarterBreakup!E$10*'One Helix'!$C$56 -> 450000 | H13: =E13+F13+G13 -> 1500000 | I13: =$D13*QuarterBreakup!C$16*'One Helix'!$C$56 -> 270000 | J13: =$D13*QuarterBreakup!D$16*'One Helix'!$C$56 -> 315000 | K13: =$D13*QuarterBreakup!E$16*'One Helix'!$C$56 -> 315000 | L13: =I13+J13+K13 -> 900000 | M13: =$D13*QuarterBreakup!C$22*'One Helix'!$C$56 -> 735000 | N13: =$D13*QuarterBreakup!D$22*'One Helix'!$C$56 -> 630000 | O13: =$D13*QuarterBreakup!E$22*'One Helix'!$C$56 -> 735000 | P13: =M13+N13+O13 -> 2100000 | Q13: =$D13*QuarterBreakup!C$28*'One Helix'!$C$56 -> 600000 | R13: =$D13*QuarterBreakup!D$28*'One Helix'!$C$56 -> 450000 | S13: =$D13*QuarterBreakup!E$28*'One Helix'!$C$56 -> 450000 | T13: =Q13+R13+S13 -> 1500000
A14: Hoardings (steel markets, cement shops cluster, construction zones) | B14: 5 hoardings in 60 Very High and High potential districts @ Rs 50K | C14: =60*5*50000 -> 15000000 | D14: =C14/$C$11 -> 0.10668563 | E14: =$D14*QuarterBreakup!C$10*'One Helix'!$C$56 -> 1125000 | F14: =$D14*QuarterBreakup!D$10*'One Helix'!$C$56 -> 1500000 | G14: =$D14*QuarterBreakup!E$10*'One Helix'!$C$56 -> 1125000 | H14: =E14+F14+G14 -> 3750000 | I14: =$D14*QuarterBreakup!C$16*'One Helix'!$C$56 -> 675000 | J14: =$D14*QuarterBreakup!D$16*'One Helix'!$C$56 -> 787500 | K14: =$D14*QuarterBreakup!E$16*'One Helix'!$C$56 -> 787500 | L14: =I14+J14+K14 -> 2250000 | M14: =$D14*QuarterBreakup!C$22*'One Helix'!$C$56 -> 1837500 | N14: =$D14*QuarterBreakup!D$22*'One Helix'!$C$56 -> 1575000 | O14: =$D14*QuarterBreakup!E$22*'One Helix'!$C$56 -> 1837500 | P14: =M14+N14+O14 -> 5250000 | Q14: =$D14*QuarterBreakup!C$28*'One Helix'!$C$56 -> 1500000 | R14: =$D14*QuarterBreakup!D$28*'One Helix'!$C$56 -> 1125000 | S14: =$D14*QuarterBreakup!E$28*'One Helix'!$C$56 -> 1125000 | T14: =Q14+R14+S14 -> 3750000
A15: Digital Marketing Campaigns | B15: To be done in Top 3 high potential districts for all 4 states @Rs 6 Lac/campaign/district/quarter (No. of states: 4) for 2 quarters | C15: =4*3*600000*2 -> 14400000 | D15: =C15/$C$11 -> 0.10241821 | E15: =$D15*QuarterBreakup!C$10*'One Helix'!$C$56 -> 1080000 | F15: =$D15*QuarterBreakup!D$10*'One Helix'!$C$56 -> 1440000 | G15: =$D15*QuarterBreakup!E$10*'One Helix'!$C$56 -> 1080000 | H15: =E15+F15+G15 -> 3600000 | I15: =$D15*QuarterBreakup!C$16*'One Helix'!$C$56 -> 648000 | J15: =$D15*QuarterBreakup!D$16*'One Helix'!$C$56 -> 756000 | K15: =$D15*QuarterBreakup!E$16*'One Helix'!$C$56 -> 756000 | L15: =I15+J15+K15 -> 2160000 | M15: =$D15*QuarterBreakup!C$22*'One Helix'!$C$56 -> 1764000 | N15: =$D15*QuarterBreakup!D$22*'One Helix'!$C$56 -> 1512000 | O15: =$D15*QuarterBreakup!E$22*'One Helix'!$C$56 -> 1764000 | P15: =M15+N15+O15 -> 5040000 | Q15: =$D15*QuarterBreakup!C$28*'One Helix'!$C$56 -> 1440000 | R15: =$D15*QuarterBreakup!D$28*'One Helix'!$C$56 -> 1080000 | S15: =$D15*QuarterBreakup!E$28*'One Helix'!$C$56 -> 1080000 | T15: =Q15+R15+S15 -> 3600000
A16: Local Events/Fairs/Exhibitions | B16: For different Plant Launches, promotional exhibitions and mass events like Mahakumbh, etc - Total 10 events | C16: 5000000 | D16: =C16/$C$11 -> 0.035561878 | E16: =$D16*QuarterBreakup!C$10*'One Helix'!$C$56 -> 375000 | F16: =$D16*QuarterBreakup!D$10*'One Helix'!$C$56 -> 500000 | G16: =$D16*QuarterBreakup!E$10*'One Helix'!$C$56 -> 375000 | H16: =E16+F16+G16 -> 1250000 | I16: =$D16*QuarterBreakup!C$16*'One Helix'!$C$56 -> 225000 | J16: =$D16*QuarterBreakup!D$16*'One Helix'!$C$56 -> 262500 | K16: =$D16*QuarterBreakup!E$16*'One Helix'!$C$56 -> 262500 | L16: =I16+J16+K16 -> 750000 | M16: =$D16*QuarterBreakup!C$22*'One Helix'!$C$56 -> 612500 | N16: =$D16*QuarterBreakup!D$22*'One Helix'!$C$56 -> 525000 | O16: =$D16*QuarterBreakup!E$22*'One Helix'!$C$56 -> 612500 | P16: =M16+N16+O16 -> 1750000 | Q16: =$D16*QuarterBreakup!C$28*'One Helix'!$C$56 -> 500000 | R16: =$D16*QuarterBreakup!D$28*'One Helix'!$C$56 -> 375000 | S16: =$D16*QuarterBreakup!E$28*'One Helix'!$C$56 -> 375000 | T16: =Q16+R16+S16 -> 1250000
A17: Paper Advertisement | B17: 1 newspaper insert for onboarding 50% of new distributors @1 Lac | C17: 0 | D17: =C17/$C$11 -> 0 | E17: =$D17*QuarterBreakup!C$10*'One Helix'!$C$56 -> 0 | F17: =$D17*QuarterBreakup!D$10*'One Helix'!$C$56 -> 0 | G17: =$D17*QuarterBreakup!E$10*'One Helix'!$C$56 -> 0 | H17: =E17+F17+G17 -> 0 | I17: =$D17*QuarterBreakup!C$16*'One Helix'!$C$56 -> 0 | J17: =$D17*QuarterBreakup!D$16*'One Helix'!$C$56 -> 0 | K17: =$D17*QuarterBreakup!E$16*'One Helix'!$C$56 -> 0 | L17: =I17+J17+K17 -> 0 | M17: =$D17*QuarterBreakup!C$22*'One Helix'!$C$56 -> 0 | N17: =$D17*QuarterBreakup!D$22*'One Helix'!$C$56 -> 0 | O17: =$D17*QuarterBreakup!E$22*'One Helix'!$C$56 -> 0 | P17: =M17+N17+O17 -> 0 | Q17: =$D17*QuarterBreakup!C$28*'One Helix'!$C$56 -> 0 | R17: =$D17*QuarterBreakup!D$28*'One Helix'!$C$56 -> 0 | S17: =$D17*QuarterBreakup!E$28*'One Helix'!$C$56 -> 0 | T17: =Q17+R17+S17 -> 0
A18: Van Campaign | B18: To be done in Top 3 high potential districts for all operational states @ Rs 7000 /day (No. of states: 15) for 2 month | C18: =15*3*7000*60 -> 18900000 | D18: =C18/$C$11 -> 0.1344239 | E18: =($D18*QuarterBreakup!C$10*'One Helix'!$C$56)+(850500/2) -> 1842750 | F18: =($D18*QuarterBreakup!D$10*'One Helix'!$C$56) + (850500/2) -> 2315250 | G18: =$D18*QuarterBreakup!E$10*'One Helix'!$C$56 -> 1417500 | H18: =E18+F18+G18 -> 5575500 | I18: 0 | J18: 0 | K18: =$D18*QuarterBreakup!E$16*'One Helix'!$C$56 -> 992250 | L18: =I18+J18+K18 -> 992250 | M18: =$D18*QuarterBreakup!C$22*'One Helix'!$C$56+(992250/2) -> 2811375 | N18: =$D18*QuarterBreakup!D$22*'One Helix'!$C$56+(992250/2) -> 2480625 | O18: =$D18*QuarterBreakup!E$22*'One Helix'!$C$56 -> 2315250 | P18: =M18+N18+O18 -> 7607250 | Q18: =$D18*QuarterBreakup!C$28*'One Helix'!$C$56 -> 1890000 | R18: =$D18*QuarterBreakup!D$28*'One Helix'!$C$56 -> 1417500 | S18: =$D18*QuarterBreakup!E$28*'One Helix'!$C$56 -> 1417500 | T18: =Q18+R18+S18 -> 4725000
A19: Syndicate Launch events | B19: Syndicate Launch events @15 states -Distributor base locations @Rs 5 Lac/event | C19: =15*500000 -> 7500000 | D19: =C19/$C$11 -> 0.053342817 | E19: =$D19*QuarterBreakup!C$10*'One Helix'!$C$56 -> 562500 | F19: =$D19*QuarterBreakup!D$10*'One Helix'!$C$56 -> 750000 | G19: =$D19*QuarterBreakup!E$10*'One Helix'!$C$56 -> 562500 | H19: =E19+F19+G19 -> 1875000 | I19: =$D19*QuarterBreakup!C$16*'One Helix'!$C$56 -> 337500 | J19: =$D19*QuarterBreakup!D$16*'One Helix'!$C$56 -> 393750 | K19: =$D19*QuarterBreakup!E$16*'One Helix'!$C$56 -> 393750 | L19: =I19+J19+K19 -> 1125000 | M19: =$D19*QuarterBreakup!C$22*'One Helix'!$C$56 -> 918750 | N19: =$D19*QuarterBreakup!D$22*'One Helix'!$C$56 -> 787500 | O19: =$D19*QuarterBreakup!E$22*'One Helix'!$C$56 -> 918750 | P19: =M19+N19+O19 -> 2625000 | Q19: =$D19*QuarterBreakup!C$28*'One Helix'!$C$56 -> 750000 | R19: =$D19*QuarterBreakup!D$28*'One Helix'!$C$56 -> 562500 | S19: =$D19*QuarterBreakup!E$28*'One Helix'!$C$56 -> 562500 | T19: =Q19+R19+S19 -> 1875000
A20: Transit Branding | B20: To be done in 60 priority districts (V.High & High Potential) @1000 autos @Rs. 700/auto | C20: =60*1000*700 -> 42000000 | D20: =C20/$C$11 -> 0.29871977 | E20: =$D20*QuarterBreakup!C$10*'One Helix'!$C$56 -> 3150000 | F20: =$D20*QuarterBreakup!D$10*'One Helix'!$C$56 -> 4200000 | G20: =$D20*QuarterBreakup!E$10*'One Helix'!$C$56 -> 3150000 | H20: =E20+F20+G20 -> 10500000 | I20: =$D20*QuarterBreakup!C$16*'One Helix'!$C$56 -> 1890000 | J20: =$D20*QuarterBreakup!D$16*'One Helix'!$C$56 -> 2205000 | K20: =$D20*QuarterBreakup!E$16*'One Helix'!$C$56 -> 2205000 | L20: =I20+J20+K20 -> 6300000 | M20: =$D20*QuarterBreakup!C$22*'One Helix'!$C$56 -> 5145000 | N20: =$D20*QuarterBreakup!D$22*'One Helix'!$C$56 -> 4410000 | O20: =$D20*QuarterBreakup!E$22*'One Helix'!$C$56 -> 5145000 | P20: =M20+N20+O20 -> 14700000 | Q20: =$D20*QuarterBreakup!C$28*'One Helix'!$C$56 -> 4200000 | R20: =$D20*QuarterBreakup!D$28*'One Helix'!$C$56 -> 3150000 | S20: =$D20*QuarterBreakup!E$28*'One Helix'!$C$56 -> 3150000 | T20: =Q20+R20+S20 -> 10500000
A21: Tea Stall / Chai Point /Dhaba Branding | B21: To be done in all high priority districts - 25 tea stalls/district @ Rs 4000/stall | C21: =B10*25*4000 -> 15000000 | D21: =C21/$C$11 -> 0.10668563 | E21: =$D21*QuarterBreakup!C$10*'One Helix'!$C$56 -> 1125000 | F21: =$D21*QuarterBreakup!D$10*'One Helix'!$C$56 -> 1500000 | G21: =$D21*QuarterBreakup!E$10*'One Helix'!$C$56 -> 1125000 | H21: =E21+F21+G21 -> 3750000 | I21: =$D21*QuarterBreakup!C$16*'One Helix'!$C$56 -> 675000 | J21: =$D21*QuarterBreakup!D$16*'One Helix'!$C$56 -> 787500 | K21: =$D21*QuarterBreakup!E$16*'One Helix'!$C$56 -> 787500 | L21: =I21+J21+K21 -> 2250000 | M21: =$D21*QuarterBreakup!C$22*'One Helix'!$C$56 -> 1837500 | N21: =$D21*QuarterBreakup!D$22*'One Helix'!$C$56 -> 1575000 | O21: =$D21*QuarterBreakup!E$22*'One Helix'!$C$56 -> 1837500 | P21: =M21+N21+O21 -> 5250000 | Q21: =$D21*QuarterBreakup!C$28*'One Helix'!$C$56 -> 1500000 | R21: =$D21*QuarterBreakup!D$28*'One Helix'!$C$56 -> 1125000 | S21: =$D21*QuarterBreakup!E$28*'One Helix'!$C$56 -> 1125000 | T21: =Q21+R21+S21 -> 3750000
A22: BTL Activities | C22: =SUM(C23:C40) -> 1.0086462e+08 | E22: =SUM(E23:E40) -> 7279269.2 | F22: =SUM(F23:F40) -> 9705692.3 | G22: =SUM(G23:G40) -> 7279269.2 | H22: =SUM(H23:H40) -> 24264231 | I22: =SUM(I23:I40) -> 4367561.5 | J22: =SUM(J23:J40) -> 5095488.5 | K22: =SUM(K23:K40) -> 5095488.5 | L22: =SUM(L23:L40) -> 14558538 | ... T22: =SUM(T23:T40) -> 26168077
A23: NLBs | B23: To be given to 50% of active dealers (Cost is taken to be Rs.40/sqft. Avg size is taken to be 10*3=30 sqft) | C23: =(B8*0.5)*40*30 -> 830769.23 | D23: =C23/$C$22 -> 0.0082364784 | E23: =QuarterBreakup!C$10*'One Helix'!$C$57*'One Helix'!$D23 -> 62307.692 | F23: =QuarterBreakup!D$10*'One Helix'!$C$57*'One Helix'!$D23 -> 83076.923 | G23: =QuarterBreakup!E$10*'One Helix'!$C$57*'One Helix'!$D23 -> 62307.692 | H23: =QuarterBreakup!F$10*'One Helix'!$C$57*'One Helix'!$D23 -> 207692.31 | I23: =QuarterBreakup!C$16*'One Helix'!$C$57*'One Helix'!$D23 -> 37384.615 | J23: =QuarterBreakup!D$16*'One Helix'!$C$57*'One Helix'!$D23 -> 43615.385 | K23: =QuarterBreakup!E$16*'One Helix'!$C$57*'One Helix'!$D23 -> 43615.385 | L23: =I23+J23+K23 -> 124615.38 | M23: =QuarterBreakup!C$22*'One Helix'!$C$57*'One Helix'!$D23 -> 101769.23 | N23: =QuarterBreakup!D$22*'One Helix'!$C$57*'One Helix'!$D23 -> 87230.769 | O23: =QuarterBreakup!E$22*'One Helix'!$C$57*'One Helix'!$D23 -> 101769.23 | P23: =SUM(M23:O23) -> 290769.23 | Q23: =QuarterBreakup!C$28*'One Helix'!$C$57*'One Helix'!$D23 -> 83076.923 | R23: =QuarterBreakup!D$28*'One Helix'!$C$57*'One Helix'!$D23 -> 62307.692 | S23: =QuarterBreakup!E$28*'One Helix'!$C$57*'One Helix'!$D23 -> 62307.692 | T23: =Q23+R23+S23 -> 207692.31
A24: GSBs | B24: To be given to 25% of active dealers. Cost: (180 *size of flex + 65*length of iron angle), Avg size of flex taken to be 10*3. Avg iron angle length: 18 ft | C24: =(B8*0.25)*(180*30+65*18) -> 2274230.8 | D24: =C24/$C$22 -> 0.02254736 | E24: =QuarterBreakup!C$10*'One Helix'!$C$57*'One Helix'!$D24 -> 170567.31 | F24: =QuarterBreakup!D$10*'One Helix'!$C$57*'One Helix'!$D24 -> 227423.08 | G24: =QuarterBreakup!E$10*'One Helix'!$C$57*'One Helix'!$D24 -> 170567.31 | H24: =SUM(E24:G24) -> 568557.69 | I24: =QuarterBreakup!C$16*'One Helix'!$C$57*'One Helix'!$D24 -> 102340.38 | J24: =QuarterBreakup!D$16*'One Helix'!$C$57*'One Helix'!$D24 -> 119397.12 | K24: =QuarterBreakup!E$16*'One Helix'!$C$57*'One Helix'!$D24 -> 119397.12 | L24: =I24+J24+K24 -> 341134.62 | M24: =QuarterBreakup!C$22*'One Helix'!$C$57*'One Helix'!$D24 -> 278593.27 | N24: =QuarterBreakup!D$22*'One Helix'!$C$57*'One Helix'!$D24 -> 238794.23 | O24: =QuarterBreakup!E$22*'One Helix'!$C$57*'One Helix'!$D24 -> 278593.27 | P24: =SUM(M24:O24) -> 795980.77 | Q24: =QuarterBreakup!C$28*'One Helix'!$C$57*'One Helix'!$D24 -> 227423.08 | R24: =QuarterBreakup!D$28*'One Helix'!$C$57*'One Helix'!$D24 -> 170567.31 | S24: =QuarterBreakup!E$28*'One Helix'!$C$57*'One Helix'!$D24 -> 170567.31 | T24: =Q24+R24+S24 -> 568557.69
A25: Counter Wall Painting | B25: To be given to exclusive 20% active counters @Rs 10000/counter | C25: =(B8*0.2)*10000 -> 2769230.8 | D25: =C25/$C$22 -> 0.027454928 | E25: =QuarterBreakup!C$10*'One Helix'!$C$57*'One Helix'!$D25 -> 207692.31 | F25: =QuarterBreakup!D$10*'One Helix'!$C$57*'One Helix'!$D25 -> 276923.08 | G25: =QuarterBreakup!E$10*'One Helix'!$C$57*'One Helix'!$D25 -> 207692.31 | H25: =SUM(E25:G25) -> 692307.69 | I25: =QuarterBreakup!C$16*'One Helix'!$C$57*'One Helix'!$D25 -> 124615.38 | J25: =QuarterBreakup!D$16*'One Helix'!$C$57*'One Helix'!$D25 -> 145384.62 | K25: =QuarterBreakup!E$16*'One Helix'!$C$57*'One Helix'!$D25 -> 145384.62 | L25: =I25+J25+K25 -> 415384.62 | M25: =QuarterBreakup!C$22*'One Helix'!$C$57*'One Helix'!$D25 -> 339230.77 | N25: =QuarterBreakup!D$22*'One Helix'!$C$57*'One Helix'!$D25 -> 290769.23 | O25: =QuarterBreakup!E$22*'One Helix'!$C$57*'One Helix'!$D25 -> 339230.77 | P25: =SUM(M25:O25) -> 969230.77 | Q25: =QuarterBreakup!C$28*'One Helix'!$C$57*'One Helix'!$D25 -> 276923.08 | R25: =QuarterBreakup!D$28*'One Helix'!$C$57*'One Helix'!$D25 -> 207692.31 | S25: =QuarterBreakup!E$28*'One Helix'!$C$57*'One Helix'!$D25 -> 207692.31 | T25: =Q25+R25+S25 -> 692307.69
A26: Inshop Branding | B26: To be given to exclusive 10% active counters @Rs 40000/counter | C26: =(B8*0.1)*40000 -> 5538461.5 | D26: =C26/$C$22 -> 0.054909856 | E26: =QuarterBreakup!C$10*'One Helix'!$C$57*'One Helix'!$D26 -> 415384.62 | F26: =QuarterBreakup!D$10*'One Helix'!$C$57*'One Helix'!$D26 -> 553846.15 | G26: =QuarterBreakup!E$10*'One Helix'!$C$57*'One Helix'!$D26 -> 415384.62 | H26: =SUM(E26:G26) -> 1384615.4 | I26: =QuarterBreakup!C$16*'One Helix'!$C$57*'One Helix'!$D26 -> 249230.77 | J26: =QuarterBreakup!D$16*'One Helix'!$C$57*'One Helix'!$D26 -> 290769.23 | K26: =QuarterBreakup!E$16*'One Helix'!$C$57*'One Helix'!$D26 -> 290769.23 | L26: =I26+J26+K26 -> 830769.23 | M26: =QuarterBreakup!C$22*'One Helix'!$C$57*'One Helix'!$D26 -> 678461.54 | N26: =QuarterBreakup!D$22*'One Helix'!$C$57*'One Helix'!$D26 -> 581538.46 | O26: =QuarterBreakup!E$22*'One Helix'!$C$57*'One Helix'!$D26 -> 678461.54 | P26: =SUM(M26:O26) -> 1938461.5 | Q26: =QuarterBreakup!C$28*'One Helix'!$C$57*'One Helix'!$D26 -> 553846.15 | R26: =QuarterBreakup!D$28*'One Helix'!$C$57*'One Helix'!$D26 -> 415384.62 | S26: =QuarterBreakup!E$28*'One Helix'!$C$57*'One Helix'!$D26 -> 415384.62 | T26: =Q26+R26+S26 -> 1384615.4
A27: Architect/Engineer Meets | B27: Considering every distributor does 1 meets with 50 architects @Rs 3500/pax every quarter | C27: =B4*1*4*50*3500 -> 29400000 | D27: =C27/$C$22 -> 0.29147982 | E27: =QuarterBreakup!C$10*'One Helix'!$C$57*'One Helix'!$D27 -> 2205000 | F27: =QuarterBreakup!D$10*'One Helix'!$C$57*'One Helix'!$D27 -> 2940000 | G27: =QuarterBreakup!E$10*'One Helix'!$C$57*'One Helix'!$D27 -> 2205000 | H27: =SUM(E27:G27) -> 7350000 | I27: =QuarterBreakup!C$16*'One Helix'!$C$57*'One Helix'!$D27 -> 1323000 | J27: =QuarterBreakup!D$16*'One Helix'!$C$57*'One Helix'!$D27 -> 1543500 | K27: =QuarterBreakup!E$16*'One Helix'!$C$57*'One Helix'!$D27 -> 1543500 | L27: =I27+J27+K27 -> 4410000 | M27: =QuarterBreakup!C$22*'One Helix'!$C$57*'One Helix'!$D27 -> 3601500 | N27: =QuarterBreakup!D$22*'One Helix'!$C$57*'One Helix'!$D27 -> 3087000 | O27: =QuarterBreakup!E$22*'One Helix'!$C$57*'One Helix'!$D27 -> 3601500 | P27: =SUM(M27:O27) -> 10290000 | Q27: =QuarterBreakup!C$28*'One Helix'!$C$57*'One Helix'!$D27 -> 2940000 | R27: =QuarterBreakup!D$28*'One Helix'!$C$57*'One Helix'!$D27 -> 2205000 | S27: =QuarterBreakup!E$28*'One Helix'!$C$57*'One Helix'!$D27 -> 2205000 | T27: =Q27+R27+S27 -> 7350000
A28: Contractor Meets | B28: Considering every distributor does 2 meets with 50 contractors @Rs 1000/pax per quarter | C28: =B4*2*4*50*1000 -> 16800000 | D28: =C28/$C$22 -> 0.1665599 | E28: =QuarterBreakup!C$10*'One Helix'!$C$57*'One Helix'!$D28 -> 1260000 | F28: =QuarterBreakup!D$10*'One Helix'!$C$57*'One Helix'!$D28 -> 1680000 | G28: =QuarterBreakup!E$10*'One Helix'!$C$57*'One Helix'!$D28 -> 1260000 | H28: =SUM(E28:G28) -> 4200000 | I28: =QuarterBreakup!C$16*'One Helix'!$C$57*'One Helix'!$D28 -> 756000 | J28: =QuarterBreakup!D$16*'One Helix'!$C$57*'One Helix'!$D28 -> 882000 | K28: =QuarterBreakup!E$16*'One Helix'!$C$57*'One Helix'!$D28 -> 882000 | L28: =I28+J28+K28 -> 2520000 | M28: =QuarterBreakup!C$22*'One Helix'!$C$57*'One Helix'!$D28 -> 2058000 | N28: =QuarterBreakup!D$22*'One Helix'!$C$57*'One Helix'!$D28 -> 1764000 | O28: =QuarterBreakup!E$22*'One Helix'!$C$57*'One Helix'!$D28 -> 2058000 | P28: =SUM(M28:O28) -> 5880000 | Q28: =QuarterBreakup!C$28*'One Helix'!$C$57*'One Helix'!$D28 -> 1680000 | R28: =QuarterBreakup!D$28*'One Helix'!$C$57*'One Helix'!$D28 -> 1260000 | S28: =QuarterBreakup!E$28*'One Helix'!$C$57*'One Helix'!$D28 -> 1260000 | T28: =Q28+R28+S28 -> 4200000
A29: Mason Meets | B29: 1 Mason meet for every transacting dealer, of 30 pax/meet Cost @ Rs 300/pax/meet | C29: =B9*1*30*300 -> 8100000 | D29: =C29/$C$22 -> 0.080305665 | E29: =QuarterBreakup!C$10*'One Helix'!$C$57*'One Helix'!$D29 -> 607500 | F29: =QuarterBreakup!D$10*'One Helix'!$C$57*'One Helix'!$D29 -> 810000 | G29: =QuarterBreakup!E$10*'One Helix'!$C$57*'One Helix'!$D29 -> 607500 | H29: =SUM(E29:G29) -> 2025000 | I29: =QuarterBreakup!C$16*'One Helix'!$C$57*'One Helix'!$D29 -> 364500 | J29: =QuarterBreakup!D$16*'One Helix'!$C$57*'One Helix'!$D29 -> 425250 | K29: =QuarterBreakup!E$16*'One Helix'!$C$57*'One Helix'!$D29 -> 425250 | L29: =I29+J29+K29 -> 1215000 | M29: =QuarterBreakup!C$22*'One Helix'!$C$57*'One Helix'!$D29 -> 992250 | N29: =QuarterBreakup!D$22*'One Helix'!$C$57*'One Helix'!$D29 -> 850500 | O29: =QuarterBreakup!E$22*'One Helix'!$C$57*'One Helix'!$D29 -> 992250 | P29: =SUM(M29:O29) -> 2835000 | Q29: =QuarterBreakup!C$28*'One Helix'!$C$57*'One Helix'!$D29 -> 810000 | R29: =QuarterBreakup!D$28*'One Helix'!$C$57*'One Helix'!$D29 -> 607500 | S29: =QuarterBreakup!E$28*'One Helix'!$C$57*'One Helix'!$D29 -> 607500 | T29: =Q29+R29+S29 -> 2025000
A30: Dealer Certificates | B30: To be given to all active retailers @Rs 400 | C30: =B8*400 -> 553846.15 | D30: =C30/$C$22 -> 0.0054909856 | E30: =QuarterBreakup!C$10*'One Helix'!$C$57*'One Helix'!$D30 -> 41538.462 | F30: =QuarterBreakup!D$10*'One Helix'!$C$57*'One Helix'!$D30 -> 55384.615 | G30: =QuarterBreakup!E$10*'One Helix'!$C$57*'One Helix'!$D30 -> 41538.462 | H30: =SUM(E30:G30) -> 138461.54 | I30: =QuarterBreakup!C$16*'One Helix'!$C$57*'One Helix'!$D30 -> 24923.077 | J30: =QuarterBreakup!D$16*'One Helix'!$C$57*'One Helix'!$D30 -> 29076.923 | K30: =QuarterBreakup!E$16*'One Helix'!$C$57*'One Helix'!$D30 -> 29076.923 | L30: =I30+J30+K30 -> 83076.923 | M30: =QuarterBreakup!C$22*'One Helix'!$C$57*'One Helix'!$D30 -> 67846.154 | N30: =QuarterBreakup!D$22*'One Helix'!$C$57*'One Helix'!$D30 -> 58153.846 | O30: =QuarterBreakup!E$22*'One Helix'!$C$57*'One Helix'!$D30 -> 67846.154 | P30: =SUM(M30:O30) -> 193846.15 | Q30: =QuarterBreakup!C$28*'One Helix'!$C$57*'One Helix'!$D30 -> 55384.615 | R30: =QuarterBreakup!D$28*'One Helix'!$C$57*'One Helix'!$D30 -> 41538.462 | S30: =QuarterBreakup!E$28*'One Helix'!$C$57*'One Helix'!$D30 -> 41538.462 | T30: =Q30+R30+S30 -> 138461.54
A31: Architect one-to-one visit Gifts | B31: Considering 75 architects for every distributor with gift cost @ Rs 500 | C31: =B4*75*500 -> 1575000 | D31: =C31/$C$22 -> 0.01561499 | E31: =QuarterBreakup!C$10*'One Helix'!$C$57*'One Helix'!$D31 -> 118125 | F31: =QuarterBreakup!D$10*'One Helix'!$C$57*'One Helix'!$D31 -> 157500 | G31: =QuarterBreakup!E$10*'One Helix'!$C$57*'One Helix'!$D31 -> 118125 | H31: =SUM(E31:G31) -> 393750 | I31: =QuarterBreakup!C$16*'One Helix'!$C$57*'One Helix'!$D31 -> 70875 | J31: =QuarterBreakup!D$16*'One Helix'!$C$57*'One Helix'!$D31 -> 82687.5 | K31: =QuarterBreakup!E$16*'One Helix'!$C$57*'One Helix'!$D31 -> 82687.5 | L31: =I31+J31+K31 -> 236250 | M31: =QuarterBreakup!C$22*'One Helix'!$C$57*'One Helix'!$D31 -> 192937.5 | N31: =QuarterBreakup!D$22*'One Helix'!$C$57*'One Helix'!$D31 -> 165375 | O31: =QuarterBreakup!E$22*'One Helix'!$C$57*'One Helix'!$D31 -> 192937.5 | P31: =SUM(M31:O31) -> 551250 | Q31: =QuarterBreakup!C$28*'One Helix'!$C$57*'One Helix'!$D31 -> 157500 | R31: =QuarterBreakup!D$28*'One Helix'!$C$57*'One Helix'!$D31 -> 118125 | S31: =QuarterBreakup!E$28*'One Helix'!$C$57*'One Helix'!$D31 -> 118125 | T31: =Q31+R31+S31 -> 393750
A32: Construction Site Gate Boards | B32: Assuming 5 active sites/month/priority district @Rs 1500/board | C32: =B10*5*12*1500 -> 13500000 | D32: =C32/$C$22 -> 0.13384277 | E32: =QuarterBreakup!C$10*'One Helix'!$C$57*'One Helix'!$D32 -> 1012500 | F32: =QuarterBreakup!D$10*'One Helix'!$C$57*'One Helix'!$D32 -> 1350000 | G32: =QuarterBreakup!E$10*'One Helix'!$C$57*'One Helix'!$D32 -> 1012500 | H32: =SUM(E32:G32) -> 3375000 | I32: =QuarterBreakup!C$16*'One Helix'!$C$57*'One Helix'!$D32 -> 607500 | J32: =QuarterBreakup!D$16*'One Helix'!$C$57*'One Helix'!$D32 -> 708750 | K32: =QuarterBreakup!E$16*'One Helix'!$C$57*'One Helix'!$D32 -> 708750 | L32: =I32+J32+K32 -> 2025000 | M32: =QuarterBreakup!C$22*'One Helix'!$C$57*'One Helix'!$D32 -> 1653750 | N32: =QuarterBreakup!D$22*'One Helix'!$C$57*'One Helix'!$D32 -> 1417500 | O32: =QuarterBreakup!E$22*'One Helix'!$C$57*'One Helix'!$D32 -> 1653750 | P32: =SUM(M32:O32) -> 4725000 | Q32: =QuarterBreakup!C$28*'One Helix'!$C$57*'One Helix'!$D32 -> 1350000 | R32: =QuarterBreakup!D$28*'One Helix'!$C$57*'One Helix'!$D32 -> 1012500 | S32: =QuarterBreakup!E$28*'One Helix'!$C$57*'One Helix'!$D32 -> 1012500 | T32: =Q32+R32+S32 -> 3375000
A33: Digital Factory visits to dealers via VR headset | B33: Digital headset for factory visit to 25% of active dealers @ Rs 5000 | C33: =B8*0.25*5000 -> 1730769.2 | D33: =C33/$C$22 -> 0.01715933 | E33: =QuarterBreakup!C$10*'One Helix'!$C$57*'One Helix'!$D33 -> 129807.69 | F33: =QuarterBreakup!D$10*'One Helix'!$C$57*'One Helix'!$D33 -> 173076.92 | G33: =QuarterBreakup!E$10*'One Helix'!$C$57*'One Helix'!$D33 -> 129807.69 | H33: =SUM(E33:G33) -> 432692.31 | I33: =QuarterBreakup!C$16*'One Helix'!$C$57*'One Helix'!$D33 -> 77884.615 | J33: =QuarterBreakup!D$16*'One Helix'!$C$57*'One Helix'!$D33 -> 90865.385 | K33: =QuarterBreakup!E$16*'One Helix'!$C$57*'One Helix'!$D33 -> 90865.385 | L33: =I33+J33+K33 -> 259615.38 | M33: =QuarterBreakup!C$22*'One Helix'!$C$57*'One Helix'!$D33 -> 212019.23 | N33: =QuarterBreakup!D$22*'One Helix'!$C$57*'One Helix'!$D33 -> 181730.77 | O33: =QuarterBreakup!E$22*'One Helix'!$C$57*'One Helix'!$D33 -> 212019.23 | P33: =SUM(M33:O33) -> 605769.23 | Q33: =QuarterBreakup!C$28*'One Helix'!$C$57*'One Helix'!$D33 -> 173076.92 | R33: =QuarterBreakup!D$28*'One Helix'!$C$57*'One Helix'!$D33 -> 129807.69 | S33: =QuarterBreakup!E$28*'One Helix'!$C$57*'One Helix'!$D33 -> 129807.69 | T33: =Q33+R33+S33 -> 432692.31
A34: POP | B34: POP materials @Rs 3K to be given to every active dealer | C34: =B8*3000 -> 4153846.2 | D34: =C34/$C$22 -> 0.041182392 | E34: =QuarterBreakup!C$10*'One Helix'!$C$57*'One Helix'!$D34 -> 311538.46 | F34: =QuarterBreakup!D$10*'One Helix'!$C$57*'One Helix'!$D34 -> 415384.62 | G34: =QuarterBreakup!E$10*'One Helix'!$C$57*'One Helix'!$D34 -> 311538.46 | H34: =SUM(E34:G34) -> 1038461.5 | I34: =QuarterBreakup!C$16*'One Helix'!$C$57*'One Helix'!$D34 -> 186923.08 | J34: =QuarterBreakup!D$16*'One Helix'!$C$57*'One Helix'!$D34 -> 218076.92 | K34: =QuarterBreakup!E$16*'One Helix'!$C$57*'One Helix'!$D34 -> 218076.92 | L34: =I34+J34+K34 -> 623076.92 | M34: =QuarterBreakup!C$22*'One Helix'!$C$57*'One Helix'!$D34 -> 508846.15 | N34: =QuarterBreakup!D$22*'One Helix'!$C$57*'One Helix'!$D34 -> 436153.85 | O34: =QuarterBreakup!E$22*'One Helix'!$C$57*'One Helix'!$D34 -> 508846.15 | P34: =SUM(M34:O34) -> 1453846.2 | Q34: =QuarterBreakup!C$28*'One Helix'!$C$57*'One Helix'!$D34 -> 415384.62 | R34: =QuarterBreakup!D$28*'One Helix'!$C$57*'One Helix'!$D34 -> 311538.46 | S34: =QuarterBreakup!E$28*'One Helix'!$C$57*'One Helix'!$D34 -> 311538.46 | T34: =Q34+R34+S34 -> 1038461.5
A35: Vehicle Branding (Truck/Tempo back panels) | B35: To be done at 10% of active dealers @Rs 5k/vehicle | C35: =(B8*0.1)*5000 -> 692307.69 | D35: =C35/$C$22 -> 0.006863732 | E35: =QuarterBreakup!C$10*'One Helix'!$C$57*'One Helix'!$D35 -> 51923.077 | F35: =QuarterBreakup!D$10*'One Helix'!$C$57*'One Helix'!$D35 -> 69230.769 | G35: =QuarterBreakup!E$10*'One Helix'!$C$57*'One Helix'!$D35 -> 51923.077 | H35: =SUM(E35:G35) -> 173076.92 | I35: =QuarterBreakup!C$16*'One Helix'!$C$57*'One Helix'!$D35 -> 31153.846 | J35: =QuarterBreakup!D$16*'One Helix'!$C$57*'One Helix'!$D35 -> 36346.154 | K35: =QuarterBreakup!E$16*'One Helix'!$C$57*'One Helix'!$D35 -> 36346.154 | L35: =I35+J35+K35 -> 103846.15 | M35: =QuarterBreakup!C$22*'One Helix'!$C$57*'One Helix'!$D35 -> 84807.692 | N35: =QuarterBreakup!D$22*'One Helix'!$C$57*'One Helix'!$D35 -> 72692.308 | O35: =QuarterBreakup!E$22*'One Helix'!$C$57*'One Helix'!$D35 -> 84807.692 | P35: =SUM(M35:O35) -> 242307.69 | Q35: =QuarterBreakup!C$28*'One Helix'!$C$57*'One Helix'!$D35 -> 69230.769 | R35: =QuarterBreakup!D$28*'One Helix'!$C$57*'One Helix'!$D35 -> 51923.077 | S35: =QuarterBreakup!E$28*'One Helix'!$C$57*'One Helix'!$D35 -> 51923.077 | T35: =Q35+R35+S35 -> 173076.92
A36: Leaflets/Brochures | B36: 1000 units to be sent to all active retailers at Rs 4/pc | C36: =B8*1000*4 -> 5538461.5 | D36: =C36/$C$22 -> 0.054909856 | E36: =QuarterBreakup!C$10*'One Helix'!$C$57*'One Helix'!$D36 -> 415384.62 | F36: =QuarterBreakup!D$10*'One Helix'!$C$57*'One Helix'!$D36 -> 553846.15 | G36: =QuarterBreakup!E$10*'One Helix'!$C$57*'One Helix'!$D36 -> 415384.62 | H36: =SUM(E36:G36) -> 1384615.4 | I36: =QuarterBreakup!C$16*'One Helix'!$C$57*'One Helix'!$D36 -> 249230.77 | J36: =QuarterBreakup!D$16*'One Helix'!$C$57*'One Helix'!$D36 -> 290769.23 | K36: =QuarterBreakup!E$16*'One Helix'!$C$57*'One Helix'!$D36 -> 290769.23 | L36: =I36+J36+K36 -> 830769.23 | M36: =QuarterBreakup!C$22*'One Helix'!$C$57*'One Helix'!$D36 -> 678461.54 | N36: =QuarterBreakup!D$22*'One Helix'!$C$57*'One Helix'!$D36 -> 581538.46 | O36: =QuarterBreakup!E$22*'One Helix'!$C$57*'One Helix'!$D36 -> 678461.54 | P36: =SUM(M36:O36) -> 1938461.5 | Q36: =QuarterBreakup!C$28*'One Helix'!$C$57*'One Helix'!$D36 -> 553846.15 | R36: =QuarterBreakup!D$28*'One Helix'!$C$57*'One Helix'!$D36 -> 415384.62 | S36: =QuarterBreakup!E$28*'One Helix'!$C$57*'One Helix'!$D36 -> 415384.62 | T36: =Q36+R36+S36 -> 1384615.4
A37: Annual Diaries | B37: 3 annual diaries per active retailer@Rs250/diary | C37: =B8*3*250 -> 1038461.5 | D37: =C37/$C$22 -> 0.010295598 | H37: =SUM(E37:G37) -> 0 | L37: =I37+J37+K37 -> 0 | M37: =C37/2 -> 519230.77 | P37: =SUM(M37:O37) -> 519230.77 | Q37: =C37/2 -> 519230.77 | T37: =Q37+R37+S37 -> 519230.77
A38: Festival Branding gifts (Diwali, Holi) | B38: To all active dealers and active influencers (3/retailer) | C38: =(B8+B8*3)*500 -> 2769230.8 | D38: =C38/$C$22 -> 0.027454928 | H38: =SUM(E38:G38) -> 0 | L38: =I38+J38+K38 -> 0 | M38: =C38/2 -> 1384615.4 | P38: =SUM(M38:O38) -> 1384615.4 | Q38: =C38/2 -> 1384615.4 | T38: =Q38+R38+S38 -> 1384615.4
A39: Branded Tarpaulins | B39: 1 Branded Tarpaulins @ 1500/pc | C39: =B8*1500*1 -> 2076923.1 | D39: =C39/$C$22 -> 0.020591196 | E39: =QuarterBreakup!C$10*'One Helix'!$C$57*'One Helix'!$D39 -> 155769.23 | F39: =QuarterBreakup!D$10*'One Helix'!$C$57*'One Helix'!$D39 -> 207692.31 | G39: =QuarterBreakup!E$10*'One Helix'!$C$57*'One Helix'!$D39 -> 155769.23 | H39: =SUM(E39:G39) -> 519230.77 | I39: =QuarterBreakup!C$16*'One Helix'!$C$57*'One Helix'!$D39 -> 93461.538 | J39: =QuarterBreakup!D$16*'One Helix'!$C$57*'One Helix'!$D39 -> 109038.46 | K39: =QuarterBreakup!E$16*'One Helix'!$C$57*'One Helix'!$D39 -> 109038.46 | L39: =I39+J39+K39 -> 311538.46 | M39: =QuarterBreakup!C$22*'One Helix'!$C$57*'One Helix'!$D39 -> 254423.08 | N39: =QuarterBreakup!D$22*'One Helix'!$C$57*'One Helix'!$D39 -> 218076.92 | O39: =QuarterBreakup!E$22*'One Helix'!$C$57*'One Helix'!$D39 -> 254423.08 | P39: =SUM(M39:O39) -> 726923.08 | Q39: =QuarterBreakup!C$28*'One Helix'!$C$57*'One Helix'!$D39 -> 207692.31 | R39: =QuarterBreakup!D$28*'One Helix'!$C$57*'One Helix'!$D39 -> 155769.23 | S39: =QuarterBreakup!E$28*'One Helix'!$C$57*'One Helix'!$D39 -> 155769.23 | T39: =Q39+R39+S39 -> 519230.77
A40: Cutout Standees from Ads | B40: For 50% of active retailer in size 5ft X 3ft; 5mm board with stand @ 2200/pc | C40: =(B8*0.5)*2200 -> 1523076.9 | D40: =C40/$C$22 -> 0.01510021 | E40: =QuarterBreakup!C$10*'One Helix'!$C$57*'One Helix'!$D40 -> 114230.77 | F40: =QuarterBreakup!D$10*'One Helix'!$C$57*'One Helix'!$D40 -> 152307.69 | G40: =QuarterBreakup!E$10*'One Helix'!$C$57*'One Helix'!$D40 -> 114230.77 | H40: =SUM(E40:G40) -> 380769.23 | I40: =QuarterBreakup!C$16*'One Helix'!$C$57*'One Helix'!$D40 -> 68538.462 | J40: =QuarterBreakup!D$16*'One Helix'!$C$57*'One Helix'!$D40 -> 79961.538 | K40: =QuarterBreakup!E$16*'One Helix'!$C$57*'One Helix'!$D40 -> 79961.538 | L40: =I40+J40+K40 -> 228461.54 | M40: =QuarterBreakup!C$22*'One Helix'!$C$57*'One Helix'!$D40 -> 186576.92 | N40: =QuarterBreakup!D$22*'One Helix'!$C$57*'One Helix'!$D40 -> 159923.08 | O40: =QuarterBreakup!E$22*'One Helix'!$C$57*'One Helix'!$D40 -> 186576.92 | P40: =SUM(M40:O40) -> 533076.92 | Q40: =QuarterBreakup!C$28*'One Helix'!$C$57*'One Helix'!$D40 -> 152307.69 | R40: =QuarterBreakup!D$28*'One Helix'!$C$57*'One Helix'!$D40 -> 114230.77 | S40: =QuarterBreakup!E$28*'One Helix'!$C$57*'One Helix'!$D40 -> 114230.77 | T40: =Q40+R40+S40 -> 380769.23
A41: Project BTL Activities | C41: =SUM(C42:C45) -> 3625000 | E41: =SUM(E42:E45) -> 262500 | F41: =SUM(F42:F45) -> 350000 | G41: =SUM(G42:G45) -> 262500 | H41: =SUM(H42:H45) -> 875000 | I41: =SUM(I42:I45) -> 157500 | J41: =SUM(J42:J45) -> 183750 | K41: =SUM(K42:K45) -> 183750 | L41: =SUM(L42:L45) -> 525000 | ... T41: =SUM(T42:T45) -> 950000
A42: First visit to project customers | B42: 2000 customers @Rs500 | C42: =2000*500 -> 1000000 | D42: =C42/$C$41 -> 0.27586207 | E42: =$D42*$C$58*QuarterBreakup!C$10 -> 75000 | F42: =$D42*$C$58*QuarterBreakup!D$10 -> 100000 | G42: =$D42*$C$58*QuarterBreakup!E$10 -> 75000 | H42: =SUM(E42:G42) -> 250000 | I42: =$D42*$C$58*QuarterBreakup!C$16 -> 45000 | J42: =$D42*$C$58*QuarterBreakup!D$16 -> 52500 | K42: =$D42*$C$58*QuarterBreakup!E$16 -> 52500 | L42: =I42+J42+K42 -> 150000 | M42: =$D42*$C$58*QuarterBreakup!C$22 -> 122500 | N42: =$D42*$C$58*QuarterBreakup!D$22 -> 105000 | O42: =$D42*$C$58*QuarterBreakup!E$22 -> 122500 | P42: =SUM(M42:O42) -> 350000 | Q42: =$D42*$C$58*QuarterBreakup!C$28 -> 100000 | R42: =$D42*$C$58*QuarterBreakup!D$28 -> 75000 | S42: =$D42*$C$58*QuarterBreakup!E$28 -> 75000 | T42: =Q42+R42+S42 -> 250000
A43: Government Approvals | B43: 10 approvals @Rs 2.5 Lacs | C43: =10*250000 -> 2500000 | D43: =C43/$C$41 -> 0.68965517 | E43: =$D43*$C$58*QuarterBreakup!C$10 -> 187500 | F43: =$D43*$C$58*QuarterBreakup!D$10 -> 250000 | G43: =$D43*$C$58*QuarterBreakup!E$10 -> 187500 | H43: =SUM(E43:G43) -> 625000 | I43: =$D43*$C$58*QuarterBreakup!C$16 -> 112500 | J43: =$D43*$C$58*QuarterBreakup!D$16 -> 131250 | K43: =$D43*$C$58*QuarterBreakup!E$16 -> 131250 | L43: =I43+J43+K43 -> 375000 | M43: =$D43*$C$58*QuarterBreakup!C$22 -> 306250 | N43: =$D43*$C$58*QuarterBreakup!D$22 -> 262500 | O43: =$D43*$C$58*QuarterBreakup!E$22 -> 306250 | P43: =SUM(M43:O43) -> 875000 | Q43: =$D43*$C$58*QuarterBreakup!C$28 -> 250000 | R43: =$D43*$C$58*QuarterBreakup!D$28 -> 187500 | S43: =$D43*$C$58*QuarterBreakup!E$28 -> 187500 | T43: =Q43+R43+S43 -> 625000
A44: Annual Diaries | B44: 1 annual diary per active project customer @Rs250/diary - 100 customers | C44: =100*250 -> 25000 | D44: =C44/$C$41 -> 0.0068965517 | H44: =SUM(E44:G44) -> 0 | L44: =I44+J44+K44 -> 0 | P44: =SUM(M44:O44) -> 0 | Q44: 25000 | T44: =Q44+R44+S44 -> 25000
A45: Festival Branding gifts (Diwali, Holi) | B45: 1 gift per active project customer @Rs500/festival - 100 customers | C45: =100*2*500 -> 100000 | D45: =C45/$C$41 -> 0.027586207 | H45: =SUM(E45:G45) -> 0 | L45: =I45+J45+K45 -> 0 | M45: 50000 | P45: =SUM(M45:O45) -> 50000 | Q45: 50000 | T45: =Q45+R45+S45 -> 50000
A46: Digital Marketing Collaterals | C46: =SUM(C47:C50) -> 12800000 | E46: =SUM(E47:E50) -> 585000 | F46: =SUM(F47:F50) -> 780000 | G46: =SUM(G47:G50) -> 5585000 | H46: =SUM(H47:H50) -> 6950000 | I46: =SUM(I47:I50) -> 351000 | J46: =SUM(J47:J50) -> 409500 | K46: =SUM(K47:K50) -> 409500 | L46: =SUM(L47:L50) -> 1170000 | ... T46: =SUM(T47:T50) -> 1950000
A47: Marketing Agencies | B47: 1.5L/month/agency | C47: =150000*12 -> 1800000 | D47: =C47/$C$46 -> 0.140625 | E47: =$D47*$C$59*QuarterBreakup!C$10 -> 135000 | F47: =$D47*$C$59*QuarterBreakup!D$10 -> 180000 | G47: =$D47*$C$59*QuarterBreakup!E$10 -> 135000 | H47: =SUM(E47:G47) -> 450000 | I47: =$D47*$C$59*QuarterBreakup!C$16 -> 81000 | J47: =$D47*$C$59*QuarterBreakup!D$16 -> 94500 | K47: =$D47*$C$59*QuarterBreakup!E$16 -> 94500 | L47: =I47+J47+K47 -> 270000 | M47: =$D47*$C$59*QuarterBreakup!C$22 -> 220500 | N47: =$D47*$C$59*QuarterBreakup!D$22 -> 189000 | O47: =$D47*$C$59*QuarterBreakup!E$22 -> 220500 | P47: =SUM(M47:O47) -> 630000 | Q47: =$D47*$C$59*QuarterBreakup!C$28 -> 180000 | R47: =$D47*$C$59*QuarterBreakup!D$28 -> 135000 | S47: =$D47*$C$59*QuarterBreakup!E$28 -> 135000 | T47: =SUM(Q47:S47) -> 450000
A48: Product featuring video | C48: 5000000 | D48: =C48/$C$46 -> 0.390625 | E48: =$D48*$C$59*QuarterBreakup!C$10 -> 375000 | F48: =$D48*$C$59*QuarterBreakup!D$10 -> 500000 | G48: =$D48*$C$59*QuarterBreakup!E$10 -> 375000 | H48: =SUM(E48:G48) -> 1250000 | I48: =$D48*$C$59*QuarterBreakup!C$16 -> 225000 | J48: =$D48*$C$59*QuarterBreakup!D$16 -> 262500 | K48: =$D48*$C$59*QuarterBreakup!E$16 -> 262500 | L48: =I48+J48+K48 -> 750000 | M48: =$D48*$C$59*QuarterBreakup!C$22 -> 612500 | N48: =$D48*$C$59*QuarterBreakup!D$22 -> 525000 | O48: =$D48*$C$59*QuarterBreakup!E$22 -> 612500 | P48: =SUM(M48:O48) -> 1750000 | Q48: =$D48*$C$59*QuarterBreakup!C$28 -> 500000 | R48: =$D48*$C$59*QuarterBreakup!D$28 -> 375000 | S48: =$D48*$C$59*QuarterBreakup!E$28 -> 375000 | T48: =SUM(Q48:S48) -> 1250000
A49: Brand Film production | B49: Youtube Ad production | C49: 5000000 | D49: =C49/$C$46 -> 0.390625 | G49: =C49 -> 5000000 | H49: =SUM(E49:G49) -> 5000000 | L49: =I49+J49+K49 -> 0 | P49: =SUM(M49:O49) -> 0 | T49: =SUM(Q49:S49) -> 0
A50: Factory visit AR video creation | C50: 1000000 | D50: =C50/$C$46 -> 0.078125 | E50: =$D50*$C$59*QuarterBreakup!C$10 -> 75000 | F50: =$D50*$C$59*QuarterBreakup!D$10 -> 100000 | G50: =$D50*$C$59*QuarterBreakup!E$10 -> 75000 | H50: =SUM(E50:G50) -> 250000 | I50: =$D50*$C$59*QuarterBreakup!C$16 -> 45000 | J50: =$D50*$C$59*QuarterBreakup!D$16 -> 52500 | K50: =$D50*$C$59*QuarterBreakup!E$16 -> 52500 | L50: =I50+J50+K50 -> 150000 | M50: =$D50*$C$59*QuarterBreakup!C$22 -> 122500 | N50: =$D50*$C$59*QuarterBreakup!D$22 -> 105000 | O50: =$D50*$C$59*QuarterBreakup!E$22 -> 122500 | P50: =SUM(M50:O50) -> 350000 | Q50: =$D50*$C$59*QuarterBreakup!C$28 -> 100000 | R50: =$D50*$C$59*QuarterBreakup!D$28 -> 75000 | S50: =$D50*$C$59*QuarterBreakup!E$28 -> 75000 | T50: =SUM(Q50:S50) -> 250000
A51: Discretionary Budget | C51: =SUM(C52) -> 5000000 | E51: =SUM(E52) -> 375000 | F51: =SUM(F52) -> 500000 | G51: =SUM(G52) -> 375000 | H51: =SUM(H52) -> 1250000 | I51: =SUM(I52) -> 225000 | J51: =SUM(J52) -> 262500 | K51: =SUM(K52) -> 262500 | L51: =SUM(L52) -> 750000 | ... T51: =SUM(T52) -> 1250000
A52: Miscellaneous Budget for immediate action | C52: 5000000 | D52: =C52/$C$51 -> 1 | E52: =$D52*$C$60*QuarterBreakup!C$10 -> 375000 | F52: =$D52*$C$60*QuarterBreakup!D$10 -> 500000 | G52: =$D52*$C$60*QuarterBreakup!E$10 -> 375000 | H52: =SUM(E52:G52) -> 1250000 | I52: =$D52*$C$60*QuarterBreakup!C$16 -> 225000 | J52: =$D52*$C$60*QuarterBreakup!D$16 -> 262500 | K52: =$D52*$C$60*QuarterBreakup!E$16 -> 262500 | L52: =I52+J52+K52 -> 750000 | M52: =$D52*$C$60*QuarterBreakup!C$22 -> 612500 | N52: =$D52*$C$60*QuarterBreakup!D$22 -> 525000 | O52: =$D52*$C$60*QuarterBreakup!E$22 -> 612500 | P52: =SUM(M52:O52) -> 1750000 | Q52: =$D52*$C$60*QuarterBreakup!C$28 -> 500000 | R52: =$D52*$C$60*QuarterBreakup!D$28 -> 375000 | S52: =$D52*$C$60*QuarterBreakup!E$28 -> 375000 | T52: =SUM(Q52:S52) -> 1250000
A53: TOTALS | C53: =SUM(C11,C22,C41,C46,C51) -> 2.6288962e+08 | E53: =SUM(E11,E22,E41,E46,E51) -> 19472019 | F53: =SUM(F11,F22,F41,F46,F51) -> 26261942 | G53: =SUM(G11,G22,G41,G46,G51) -> 24487769 | H53: =SUM(H11,H22,H41,H46,H51) -> 70221731 | I53: =SUM(I11,I22,I41,I46,I51) -> 9821561.5 | J53: =SUM(J11,J22,J41,J46,J51) -> 11458488 | K53: =SUM(K11,K22,K41,K46,K51) -> 13332738 | L53: =SUM(L11,L22,L41,L46,L51) -> 34612788 | ... T53: =SUM(T11,T22,T41,T46,T51) -> 65468077
A55: Category | B55: Projected Budget | C55: % of Total Budget
A56: =A11 -> ATL Activities | B56: =C11 -> 140600000 | C56: =B56/$B$61 -> 0.53482523
A57: =A22 -> BTL Activities | B57: =C22 -> 1.0086462e+08 | C57: =B57/$B$61 -> 0.38367668
A58: =A41 -> Project BTL Activities | B58: =C41 -> 3625000 | C58: =B58/$B$61 -> 0.013789057
A59: =A46 -> Digital Marketing Collaterals | B59: =C46 -> 12800000 | C59: =B59/$B$61 -> 0.048689637
A60: =A51 -> Discretionary Budget | B60: =C51 -> 5000000 | C60: =B60/$B$61 -> 0.01901939
A61: TOTALS | B61: =SUM(B56:B60) -> 2.6288962e+08
A63: Quarter-wise Budget Breakup | B63: Projected Budget | C63: % of Total Budget
A64: Q1 | B64: =H53 -> 70221731 | C64: =B64/$B$68 -> 0.26711489
A65: Q2 | B65: =L53 -> 34612788 | C65: =B65/$B$68 -> 0.13166282
A66: Q3 | B66: =P53 -> 92587019 | C66: =B66/$B$68 -> 0.35218972
A67: Q4 | B67: =T53 -> 65468077 | C67: =B67/$B$68 -> 0.24903257
A68: TOTALS | B68: =SUM(B64:B67) -> 2.6288962e+08

Sheet JSW One TMT (2)
A1: Category | B1: Remarks | C1: YEAR TOTALS | D1: %age of totals - Bucketwise | E1: Q1 | I1: Q2 | M1: Q3 | Q1: Q4
E2: Apr | F2: May | G2: Jun | H2: Q1 Totals | I2: Jul | J2: Aug | K2: Sep | L2: Q2 Totals | M2: Oct | N2: Nov | O2: Dec | P2: Q3 Totals | Q2: Jan | R2: Feb | S2: Mar | T2: Q4 Totals
A3: Particulars
A4: #Distributors | B4: 56
A5: Volume projection (Mar'27 Exit) | B5: 31000
A6: Avg. volume/retailer/month | B6: 30
A7: Total retailers (Mar'27) | B7: =B8*3 -> 4769.2308
A8: Total Active retailers (Mar'27) | B8: =B9/65% -> 1589.7436
A9: Total transacting retailers (Mar'27) | B9: =B5/B6 -> 1033.3333
A10: #Priority districts | B10: 194
A11: ATL Activities | C11: =SUM(C12:C21) -> 169520000 | E11: =SUM(E12:E21) -> 8064400.7 | F11: =SUM(F12:F21) -> 12231984 | G11: =SUM(G12:G21) -> 9207850.7 | H11: =SUM(H12:H21) -> 29504236 | I11: =SUM(I12:I21) -> 1901455.7 | J11: =SUM(J12:J21) -> 2218365 | K11: =SUM(K12:K21) -> 5088731.2 | L11: =SUM(L12:L21) -> 9208552 | ... T11: =SUM(T12:T21) -> 25408053
A12: Impact Wall Painting | B12: 20,000 sq ft in every priority district @ Rs 14 | C12: =B10*20000*14 -> 54320000 | D12: =C12/$C$11 -> 0.32043417 | E12: =($D12*QuarterBreakup!J$10*'JSW One TMT (2)'!$C$56) -> 2422610.7 | F12: =($D12*QuarterBreakup!K$10*'JSW One TMT (2)'!$C$56)+2444400/2 -> 4452347.6 | G12: =($D12*QuarterBreakup!L$10*'JSW One TMT (2)'!$C$56)+2444400/2 -> 3644810.7 | H12: =E12+F12+G12 -> 10519769 | K12: =($D12*QuarterBreakup!L$16*'JSW One TMT (2)'!$C$56) -> 1630603.4 | L12: =I12+J12+K12 -> 1630603.4 | M12: =$D12*QuarterBreakup!J$22*'JSW One TMT (2)'!$C$56 -> 3696034.3 | N12: =$D12*QuarterBreakup!K$22*'JSW One TMT (2)'!$C$56+2851800/2 -> 4593929.4 | O12: =$D12*QuarterBreakup!L$22*'JSW One TMT (2)'!$C$56+2851800/2 -> 5121934.3 | P12: =M12+N12+O12 -> 13411898 | Q12: =$D12*QuarterBreakup!J$28*'JSW One TMT (2)'!$C$56 -> 3105911.2 | R12: =$D12*QuarterBreakup!K$28*'JSW One TMT (2)'!$C$56 -> 2329433.4 | S12: =$D12*QuarterBreakup!L$28*'JSW One TMT (2)'!$C$56 -> 2329433.4 | T12: =Q12+R12+S12 -> 7764777.9
A13: Integrated FM Radio Campaigns (Ad + Promotional Activity) | B13: To be done in Top 3 high potential districts for Top 4 states @Rs 2.5 Lac/campaign/district/quarter (No. of states: 4) for 2 quarters (UP, RJ, Haryana, WB) | C13: =4*3*250000*2 -> 6000000 | D13: =C13/$C$11 -> 0.035394054 | E13: =($D13*QuarterBreakup!J$10*'JSW One TMT (2)'!$C$56) -> 267593.23 | F13: =($D13*QuarterBreakup!K$10*'JSW One TMT (2)'!$C$56) -> 356790.97 | G13: =($D13*QuarterBreakup!L$10*'JSW One TMT (2)'!$C$56) -> 267593.23 | H13: =E13+F13+G13 -> 891977.43 | I13: =($D13*QuarterBreakup!J$16*'JSW One TMT (2)'!$C$56) -> 154380.71 | J13: =($D13*QuarterBreakup!K$16*'JSW One TMT (2)'!$C$56) -> 180110.83 | K13: =($D13*QuarterBreakup!L$16*'JSW One TMT (2)'!$C$56) -> 180110.83 | L13: =I13+J13+K13 -> 514602.36 | M13: =$D13*QuarterBreakup!J$22*'JSW One TMT (2)'!$C$56 -> 408251.21 | N13: =$D13*QuarterBreakup!K$22*'JSW One TMT (2)'!$C$56 -> 349929.61 | O13: =$D13*QuarterBreakup!L$22*'JSW One TMT (2)'!$C$56 -> 408251.21 | P13: =M13+N13+O13 -> 1166432 | Q13: =$D13*QuarterBreakup!J$28*'JSW One TMT (2)'!$C$56 -> 343068.24 | R13: =$D13*QuarterBreakup!K$28*'JSW One TMT (2)'!$C$56 -> 257301.18 | S13: =$D13*QuarterBreakup!L$28*'JSW One TMT (2)'!$C$56 -> 257301.18 | T13: =Q13+R13+S13 -> 857670.61
A14: Hoardings (steel markets, cement shops cluster, construction zones) | B14: 5 hoardings in every high potential district @ Rs 50K | C14: =B10*5*50000 -> 48500000 | D14: =C14/$C$11 -> 0.28610193 | E14: =($D14*QuarterBreakup!J$10*'JSW One TMT (2)'!$C$56) -> 2163045.3 | F14: =($D14*QuarterBreakup!K$10*'JSW One TMT (2)'!$C$56) -> 2884060.4 | G14: =($D14*QuarterBreakup!L$10*'JSW One TMT (2)'!$C$56) -> 2163045.3 | H14: =E14+F14+G14 -> 7210150.9 | I14: =($D14*QuarterBreakup!J$16*'JSW One TMT (2)'!$C$56) -> 1247910.7 | J14: =($D14*QuarterBreakup!K$16*'JSW One TMT (2)'!$C$56) -> 1455895.9 | K14: =($D14*QuarterBreakup!L$16*'JSW One TMT (2)'!$C$56) -> 1455895.9 | L14: =I14+J14+K14 -> 4159702.4 | M14: =$D14*QuarterBreakup!J$22*'JSW One TMT (2)'!$C$56 -> 3300030.6 | N14: =$D14*QuarterBreakup!K$22*'JSW One TMT (2)'!$C$56 -> 2828597.7 | O14: =$D14*QuarterBreakup!L$22*'JSW One TMT (2)'!$C$56 -> 3300030.6 | P14: =M14+N14+O14 -> 9428658.9 | Q14: =$D14*QuarterBreakup!J$28*'JSW One TMT (2)'!$C$56 -> 2773135 | R14: =$D14*QuarterBreakup!K$28*'JSW One TMT (2)'!$C$56 -> 2079851.2 | S14: =$D14*QuarterBreakup!L$28*'JSW One TMT (2)'!$C$56 -> 2079851.2 | T14: =Q14+R14+S14 -> 6932837.4
A15: Digital Marketing Campaigns | B15: To be done in Top 3 high potential districts for all 4 states @Rs 6 Lac/campaign/district/quarter (No. of states: 4) for 2 quarters | C15: =4*3*600000*2 -> 14400000 | D15: =C15/$C$11 -> 0.084945729 | E15: =($D15*QuarterBreakup!J$10*'JSW One TMT (2)'!$C$56) -> 642223.75 | F15: =($D15*QuarterBreakup!K$10*'JSW One TMT (2)'!$C$56) -> 856298.33 | G15: =($D15*QuarterBreakup!L$10*'JSW One TMT (2)'!$C$56) -> 642223.75 | H15: =E15+F15+G15 -> 2140745.8 | I15: =($D15*QuarterBreakup!J$16*'JSW One TMT (2)'!$C$56) -> 370513.7 | J15: =($D15*QuarterBreakup!K$16*'JSW One TMT (2)'!$C$56) -> 432265.99 | K15: =($D15*QuarterBreakup!L$16*'JSW One TMT (2)'!$C$56) -> 432265.99 | L15: =I15+J15+K15 -> 1235045.7 | M15: =$D15*QuarterBreakup!J$22*'JSW One TMT (2)'!$C$56 -> 979802.9 | N15: =$D15*QuarterBreakup!K$22*'JSW One TMT (2)'!$C$56 -> 839831.06 | O15: =$D15*QuarterBreakup!L$22*'JSW One TMT (2)'!$C$56 -> 979802.9 | P15: =M15+N15+O15 -> 2799436.9 | Q15: =$D15*QuarterBreakup!J$28*'JSW One TMT (2)'!$C$56 -> 823363.78 | R15: =$D15*QuarterBreakup!K$28*'JSW One TMT (2)'!$C$56 -> 617522.84 | S15: =$D15*QuarterBreakup!L$28*'JSW One TMT (2)'!$C$56 -> 617522.84 | T15: =Q15+R15+S15 -> 2058409.5
A16: Local Events/Fairs/Exhibitions | B16: For different Plant Launches, promotional exhibitions and mass events like Mahakumbh, etc - Total 10 events | C16: 5000000 | D16: =C16/$C$11 -> 0.029495045 | E16: =($D16*QuarterBreakup!J$10*'JSW One TMT (2)'!$C$56) -> 222994.36 | F16: =($D16*QuarterBreakup!K$10*'JSW One TMT (2)'!$C$56) -> 297325.81 | G16: =($D16*QuarterBreakup!L$10*'JSW One TMT (2)'!$C$56) -> 222994.36 | H16: =E16+F16+G16 -> 743314.52 | I16: =($D16*QuarterBreakup!J$16*'JSW One TMT (2)'!$C$56) -> 128650.59 | J16: =($D16*QuarterBreakup!K$16*'JSW One TMT (2)'!$C$56) -> 150092.36 | K16: =($D16*QuarterBreakup!L$16*'JSW One TMT (2)'!$C$56) -> 150092.36 | L16: =I16+J16+K16 -> 428835.3 | M16: =$D16*QuarterBreakup!J$22*'JSW One TMT (2)'!$C$56 -> 340209.34 | N16: =$D16*QuarterBreakup!K$22*'JSW One TMT (2)'!$C$56 -> 291608.01 | O16: =$D16*QuarterBreakup!L$22*'JSW One TMT (2)'!$C$56 -> 340209.34 | P16: =M16+N16+O16 -> 972026.69 | Q16: =$D16*QuarterBreakup!J$28*'JSW One TMT (2)'!$C$56 -> 285890.2 | R16: =$D16*QuarterBreakup!K$28*'JSW One TMT (2)'!$C$56 -> 214417.65 | S16: =$D16*QuarterBreakup!L$28*'JSW One TMT (2)'!$C$56 -> 214417.65 | T16: =Q16+R16+S16 -> 714725.5
A17: Paper Advertisement | B17: 1 newspaper insert for onboarding 50% of new distributors @1 Lac | C17: 0 | D17: =C17/$C$11 -> 0 | E17: =($D17*QuarterBreakup!J$10*'JSW One TMT (2)'!$C$56) -> 0 | F17: =($D17*QuarterBreakup!K$10*'JSW One TMT (2)'!$C$56) -> 0 | G17: =($D17*QuarterBreakup!L$10*'JSW One TMT (2)'!$C$56) -> 0 | H17: =E17+F17+G17 -> 0 | I17: =($D17*QuarterBreakup!J$16*'JSW One TMT (2)'!$C$56) -> 0 | J17: =($D17*QuarterBreakup!K$16*'JSW One TMT (2)'!$C$56) -> 0 | K17: =($D17*QuarterBreakup!L$16*'JSW One TMT (2)'!$C$56) -> 0 | L17: =I17+J17+K17 -> 0 | M17: =$D17*QuarterBreakup!J$22*'JSW One TMT (2)'!$C$56 -> 0 | N17: =$D17*QuarterBreakup!K$22*'JSW One TMT (2)'!$C$56 -> 0 | O17: =$D17*QuarterBreakup!L$22*'JSW One TMT (2)'!$C$56 -> 0 | P17: =M17+N17+O17 -> 0 | Q17: =$D17*QuarterBreakup!J$28*'JSW One TMT (2)'!$C$56 -> 0 | R17: =$D17*QuarterBreakup!K$28*'JSW One TMT (2)'!$C$56 -> 0 | S17: =$D17*QuarterBreakup!L$28*'JSW One TMT (2)'!$C$56 -> 0 | T17: =Q17+R17+S17 -> 0
A18: Van Campaign | B18: To be done in Top 3 high potential districts for all operational states @ Rs 7000 /day (No. of states: 15) for 2 month | C18: =15*3*7000*60 -> 18900000 | D18: =C18/$C$11 -> 0.11149127 | E18: =($D18*QuarterBreakup!J$10*'JSW One TMT (2)'!$C$56) -> 842918.67 | F18: =($D18*QuarterBreakup!K$10*'JSW One TMT (2)'!$C$56)+850500/2 -> 1549141.6 | G18: =($D18*QuarterBreakup!L$10*'JSW One TMT (2)'!$C$56)+850500/2 -> 1268168.7 | H18: =E18+F18+G18 -> 3660228.9 | K18: =($D18*QuarterBreakup!L$16*'JSW One TMT (2)'!$C$56) -> 567349.11 | L18: =I18+J18+K18 -> 567349.11 | M18: =$D18*QuarterBreakup!J$22*'JSW One TMT (2)'!$C$56+992250/2 -> 1782116.3 | N18: =$D18*QuarterBreakup!K$22*'JSW One TMT (2)'!$C$56+992250/2 -> 1598403.3 | O18: =$D18*QuarterBreakup!L$22*'JSW One TMT (2)'!$C$56 -> 1285991.3 | P18: =M18+N18+O18 -> 4666510.9 | Q18: =$D18*QuarterBreakup!J$28*'JSW One TMT (2)'!$C$56 -> 1080665 | R18: =$D18*QuarterBreakup!K$28*'JSW One TMT (2)'!$C$56 -> 810498.72 | S18: =$D18*QuarterBreakup!L$28*'JSW One TMT (2)'!$C$56 -> 810498.72 | T18: =Q18+R18+S18 -> 2701662.4
A19: Syndicate Launch events | B19: Syndicate Launch events @15 states -Distributor base locations @Rs 5 Lac/event | C19: 0 | D19: =C19/$C$11 -> 0 | E19: =($D19*QuarterBreakup!J$10*'JSW One TMT (2)'!$C$56) -> 0 | F19: =($D19*QuarterBreakup!K$10*'JSW One TMT (2)'!$C$56) -> 0 | G19: =($D19*QuarterBreakup!L$10*'JSW One TMT (2)'!$C$56) -> 0 | H19: =E19+F19+G19 -> 0 | I19: =($D19*QuarterBreakup!J$16*'JSW One TMT (2)'!$C$56) -> 0 | K19: =($D19*QuarterBreakup!L$16*'JSW One TMT (2)'!$C$56) -> 0 | L19: =I19+J19+K19 -> 0 | M19: =$D19*QuarterBreakup!J$22*'JSW One TMT (2)'!$C$56 -> 0 | N19: =$D19*QuarterBreakup!K$22*'JSW One TMT (2)'!$C$56 -> 0 | O19: =$D19*QuarterBreakup!L$22*'JSW One TMT (2)'!$C$56 -> 0 | P19: =M19+N19+O19 -> 0 | Q19: =$D19*QuarterBreakup!J$28*'JSW One TMT (2)'!$C$56 -> 0 | R19: =$D19*QuarterBreakup!K$28*'JSW One TMT (2)'!$C$56 -> 0 | S19: =$D19*QuarterBreakup!L$28*'JSW One TMT (2)'!$C$56 -> 0 | T19: =Q19+R19+S19 -> 0
A20: Transit Branding (Auto) | B20: To be done in Top 2 high potential districts for top 8 high volume states @2000 autos @Rs. 700/auto (No. of states: 15) (UP, HR, RJ, Odisha, MP, JH, WB, Bihar) | C20: =8*2*2000*700 -> 22400000 | D20: =C20/$C$11 -> 0.1321378 | E20: =($D20*QuarterBreakup!J$10*'JSW One TMT (2)'!$C$56)+1008000/2 -> 1503014.7 | F20: =($D20*QuarterBreakup!K$10*'JSW One TMT (2)'!$C$56)+1008000/2 -> 1836019.6 | G20: =($D20*QuarterBreakup!L$10*'JSW One TMT (2)'!$C$56) -> 999014.72 | H20: =E20+F20+G20 -> 4338049.1 | K20: =($D20*QuarterBreakup!L$16*'JSW One TMT (2)'!$C$56) -> 672413.75 | L20: =I20+J20+K20 -> 672413.75 | M20: =$D20*QuarterBreakup!J$22*'JSW One TMT (2)'!$C$56 -> 1524137.8 | N20: =$D20*QuarterBreakup!K$22*'JSW One TMT (2)'!$C$56 -> 1306403.9 | O20: =$D20*QuarterBreakup!L$22*'JSW One TMT (2)'!$C$56 -> 1524137.8 | P20: =M20+N20+O20 -> 4354679.6 | Q20: =$D20*QuarterBreakup!J$28*'JSW One TMT (2)'!$C$56+1176000/2 -> 1868788.1 | R20: =$D20*QuarterBreakup!K$28*'JSW One TMT (2)'!$C$56+1176000/2 -> 1548591.1 | S20: =$D20*QuarterBreakup!L$28*'JSW One TMT (2)'!$C$56 -> 960591.08 | T20: =Q20+R20+S20 -> 4377970.3
A21: Tea Stall / Chai Point /Dhaba Branding | B21: To be done in all high priority districts - 25 tea stalls/district @ Rs 5000/stall | C21: 0 | D21: =C21/$C$11 -> 0 | E21: =($D21*QuarterBreakup!J$10*'JSW One TMT (2)'!$C$56) -> 0 | F21: =($D21*QuarterBreakup!K$10*'JSW One TMT (2)'!$C$56) -> 0 | G21: =($D21*QuarterBreakup!L$10*'JSW One TMT (2)'!$C$56) -> 0 | H21: =E21+F21+G21 -> 0 | I21: =($D21*QuarterBreakup!J$16*'JSW One TMT (2)'!$C$56) -> 0 | J21: =($D21*QuarterBreakup!K$16*'JSW One TMT (2)'!$C$56) -> 0 | K21: =($D21*QuarterBreakup!L$16*'JSW One TMT (2)'!$C$56) -> 0 | L21: =I21+J21+K21 -> 0 | M21: =$D21*QuarterBreakup!J$22*'JSW One TMT (2)'!$C$56 -> 0 | N21: =$D21*QuarterBreakup!K$22*'JSW One TMT (2)'!$C$56 -> 0 | O21: =$D21*QuarterBreakup!L$22*'JSW One TMT (2)'!$C$56 -> 0 | P21: =M21+N21+O21 -> 0 | Q21: =$D21*QuarterBreakup!J$28*'JSW One TMT (2)'!$C$56 -> 0 | R21: =$D21*QuarterBreakup!K$28*'JSW One TMT (2)'!$C$56 -> 0 | S21: =$D21*QuarterBreakup!L$28*'JSW One TMT (2)'!$C$56 -> 0 | T21: =Q21+R21+S21 -> 0
A22: BTL Activities | C22: =SUM(C23:C41) -> 1.3082756e+08 | E22: =SUM(E23:E41) -> 5639784.6 | F22: =SUM(F23:F41) -> 7519712.8 | G22: =SUM(G23:G41) -> 5639784.6 | H22: =SUM(H23:H41) -> 18799282 | I22: =SUM(I23:I41) -> 3253721.9 | J22: =SUM(J23:J41) -> 3796008.9 | K22: =SUM(K23:K41) -> 3796008.9 | L22: =SUM(L23:L41) -> 10845740 | ... T22: =SUM(T23:T41) -> 19665976
A23: NLBs | B23: To be given to 50% of active dealers (Cost is taken to be Rs.40/sqft. Avg size is taken to be 10*3=30 sqft) | C23: =(B8*0.5)*40*30 -> 953846.15 | D23: =C23/$C$22 -> 0.0072908653 | E23: =QuarterBreakup!J$10*'JSW One TMT (2)'!$C$57*'JSW One TMT (2)'!$D23 -> 42540.462 | F23: =QuarterBreakup!K$10*'JSW One TMT (2)'!$C$57*'JSW One TMT (2)'!$D23 -> 56720.616 | G23: =QuarterBreakup!L$10*'JSW One TMT (2)'!$C$57*'JSW One TMT (2)'!$D23 -> 42540.462 | H23: =SUM(E23:G23) -> 141801.54 | I23: =QuarterBreakup!J$16*'JSW One TMT (2)'!$C$57*'JSW One TMT (2)'!$D23 -> 24542.574 | J23: =QuarterBreakup!K$16*'JSW One TMT (2)'!$C$57*'JSW One TMT (2)'!$D23 -> 28633.003 | K23: =QuarterBreakup!L$16*'JSW One TMT (2)'!$C$57*'JSW One TMT (2)'!$D23 -> 28633.003 | L23: =I23+J23+K23 -> 81808.581 | M23: =QuarterBreakup!J$22*'JSW One TMT (2)'!$C$57*'JSW One TMT (2)'!$D23 -> 64901.474 | N23: =QuarterBreakup!K$22*'JSW One TMT (2)'!$C$57*'JSW One TMT (2)'!$D23 -> 55629.835 | O23: =QuarterBreakup!L$22*'JSW One TMT (2)'!$C$57*'JSW One TMT (2)'!$D23 -> 64901.474 | P23: =SUM(M23:O23) -> 185432.78 | Q23: =QuarterBreakup!J$28*'JSW One TMT (2)'!$C$57*'JSW One TMT (2)'!$D23 -> 54539.054 | R23: =QuarterBreakup!K$28*'JSW One TMT (2)'!$C$57*'JSW One TMT (2)'!$D23 -> 40904.29 | S23: =QuarterBreakup!L$28*'JSW One TMT (2)'!$C$57*'JSW One TMT (2)'!$D23 -> 40904.29 | T23: =Q23+R23+S23 -> 136347.63
A24: GSBs | B24: To be given to 25% of active dealers. Cost: (180 *size of flex + 65*length of iron angle), Avg size of flex taken to be 10*3. Avg iron angle length: 18 ft | C24: =(B8*0.25)*(180*30+65*18) -> 2611153.8 | D24: =C24/$C$22 -> 0.019958744 | E24: =QuarterBreakup!J$10*'JSW One TMT (2)'!$C$57*'JSW One TMT (2)'!$D24 -> 116454.51 | F24: =QuarterBreakup!K$10*'JSW One TMT (2)'!$C$57*'JSW One TMT (2)'!$D24 -> 155272.69 | G24: =QuarterBreakup!L$10*'JSW One TMT (2)'!$C$57*'JSW One TMT (2)'!$D24 -> 116454.51 | H24: =SUM(E24:G24) -> 388181.72 | I24: =QuarterBreakup!J$16*'JSW One TMT (2)'!$C$57*'JSW One TMT (2)'!$D24 -> 67185.297 | J24: =QuarterBreakup!K$16*'JSW One TMT (2)'!$C$57*'JSW One TMT (2)'!$D24 -> 78382.846 | K24: =QuarterBreakup!L$16*'JSW One TMT (2)'!$C$57*'JSW One TMT (2)'!$D24 -> 78382.846 | L24: =I24+J24+K24 -> 223950.99 | M24: =QuarterBreakup!J$22*'JSW One TMT (2)'!$C$57*'JSW One TMT (2)'!$D24 -> 177667.79 | N24: =QuarterBreakup!K$22*'JSW One TMT (2)'!$C$57*'JSW One TMT (2)'!$D24 -> 152286.67 | O24: =QuarterBreakup!L$22*'JSW One TMT (2)'!$C$57*'JSW One TMT (2)'!$D24 -> 177667.79 | P24: =SUM(M24:O24) -> 507622.24 | Q24: =QuarterBreakup!J$28*'JSW One TMT (2)'!$C$57*'JSW One TMT (2)'!$D24 -> 149300.66 | R24: =QuarterBreakup!K$28*'JSW One TMT (2)'!$C$57*'JSW One TMT (2)'!$D24 -> 111975.49 | S24: =QuarterBreakup!L$28*'JSW One TMT (2)'!$C$57*'JSW One TMT (2)'!$D24 -> 111975.49 | T24: =Q24+R24+S24 -> 373251.65
A25: Counter Wall Painting | B25: To be given to exclusive 20% active counters @Rs 10000/counter | C25: =(B8*0.2)*10000 -> 3179487.2 | D25: =C25/$C$22 -> 0.024302884 | E25: =QuarterBreakup!J$10*'JSW One TMT (2)'!$C$57*'JSW One TMT (2)'!$D25 -> 141801.54 | F25: =QuarterBreakup!K$10*'JSW One TMT (2)'!$C$57*'JSW One TMT (2)'!$D25 -> 189068.72 | G25: =QuarterBreakup!L$10*'JSW One TMT (2)'!$C$57*'JSW One TMT (2)'!$D25 -> 141801.54 | H25: =SUM(E25:G25) -> 472671.8 | I25: =QuarterBreakup!J$16*'JSW One TMT (2)'!$C$57*'JSW One TMT (2)'!$D25 -> 81808.581 | J25: =QuarterBreakup!K$16*'JSW One TMT (2)'!$C$57*'JSW One TMT (2)'!$D25 -> 95443.344 | K25: =QuarterBreakup!L$16*'JSW One TMT (2)'!$C$57*'JSW One TMT (2)'!$D25 -> 95443.344 | L25: =I25+J25+K25 -> 272695.27 | M25: =QuarterBreakup!J$22*'JSW One TMT (2)'!$C$57*'JSW One TMT (2)'!$D25 -> 216338.25 | N25: =QuarterBreakup!K$22*'JSW One TMT (2)'!$C$57*'JSW One TMT (2)'!$D25 -> 185432.78 | O25: =QuarterBreakup!L$22*'JSW One TMT (2)'!$C$57*'JSW One TMT (2)'!$D25 -> 216338.25 | P25: =SUM(M25:O25) -> 618109.28 | Q25: =QuarterBreakup!J$28*'JSW One TMT (2)'!$C$57*'JSW One TMT (2)'!$D25 -> 181796.85 | R25: =QuarterBreakup!K$28*'JSW One TMT (2)'!$C$57*'JSW One TMT (2)'!$D25 -> 136347.63 | S25: =QuarterBreakup!L$28*'JSW One TMT (2)'!$C$57*'JSW One TMT (2)'!$D25 -> 136347.63 | T25: =Q25+R25+S25 -> 454492.12
A26: Inshop Branding | B26: To be given to exclusive 10% active counters @Rs 40000/counter | C26: =(B8*0.1)*40000 -> 6358974.4 | D26: =C26/$C$22 -> 0.048605769 | E26: =QuarterBreakup!J$10*'JSW One TMT (2)'!$C$57*'JSW One TMT (2)'!$D26 -> 283603.08 | F26: =QuarterBreakup!K$10*'JSW One TMT (2)'!$C$57*'JSW One TMT (2)'!$D26 -> 378137.44 | G26: =QuarterBreakup!L$10*'JSW One TMT (2)'!$C$57*'JSW One TMT (2)'!$D26 -> 283603.08 | H26: =SUM(E26:G26) -> 945343.6 | I26: =QuarterBreakup!J$16*'JSW One TMT (2)'!$C$57*'JSW One TMT (2)'!$D26 -> 163617.16 | J26: =QuarterBreakup!K$16*'JSW One TMT (2)'!$C$57*'JSW One TMT (2)'!$D26 -> 190886.69 | K26: =QuarterBreakup!L$16*'JSW One TMT (2)'!$C$57*'JSW One TMT (2)'!$D26 -> 190886.69 | L26: =I26+J26+K26 -> 545390.54 | M26: =QuarterBreakup!J$22*'JSW One TMT (2)'!$C$57*'JSW One TMT (2)'!$D26 -> 432676.49 | N26: =QuarterBreakup!K$22*'JSW One TMT (2)'!$C$57*'JSW One TMT (2)'!$D26 -> 370865.57 | O26: =QuarterBreakup!L$22*'JSW One TMT (2)'!$C$57*'JSW One TMT (2)'!$D26 -> 432676.49 | P26: =SUM(M26:O26) -> 1236218.6 | Q26: =QuarterBreakup!J$28*'JSW One TMT (2)'!$C$57*'JSW One TMT (2)'!$D26 -> 363593.69 | R26: =QuarterBreakup!K$28*'JSW One TMT (2)'!$C$57*'JSW One TMT (2)'!$D26 -> 272695.27 | S26: =QuarterBreakup!L$28*'JSW One TMT (2)'!$C$57*'JSW One TMT (2)'!$D26 -> 272695.27 | T26: =Q26+R26+S26 -> 908984.23
A27: International Distributor Meet for Mou Signing and Agenda setting for FY27 | B27: Every distributor to be taken + 6 people from HO @Rs 1 Lac | C27: =(B4+6)*100000 -> 6200000 | D27: =C27/$C$22 -> 0.047390625 | E27: =QuarterBreakup!J$10*'JSW One TMT (2)'!$C$57*'JSW One TMT (2)'!$D27 -> 276513 | F27: =QuarterBreakup!K$10*'JSW One TMT (2)'!$C$57*'JSW One TMT (2)'!$D27 -> 368684 | G27: =QuarterBreakup!L$10*'JSW One TMT (2)'!$C$57*'JSW One TMT (2)'!$D27 -> 276513 | H27: =SUM(E27:G27) -> 921710.01 | I27: =QuarterBreakup!J$16*'JSW One TMT (2)'!$C$57*'JSW One TMT (2)'!$D27 -> 159526.73 | J27: =QuarterBreakup!K$16*'JSW One TMT (2)'!$C$57*'JSW One TMT (2)'!$D27 -> 186114.52 | K27: =QuarterBreakup!L$16*'JSW One TMT (2)'!$C$57*'JSW One TMT (2)'!$D27 -> 186114.52 | L27: =I27+J27+K27 -> 531755.78 | M27: =QuarterBreakup!J$22*'JSW One TMT (2)'!$C$57*'JSW One TMT (2)'!$D27 -> 421859.58 | N27: =QuarterBreakup!K$22*'JSW One TMT (2)'!$C$57*'JSW One TMT (2)'!$D27 -> 361593.93 | O27: =QuarterBreakup!L$22*'JSW One TMT (2)'!$C$57*'JSW One TMT (2)'!$D27 -> 421859.58 | P27: =SUM(M27:O27) -> 1205313.1 | Q27: =QuarterBreakup!J$28*'JSW One TMT (2)'!$C$57*'JSW One TMT (2)'!$D27 -> 354503.85 | R27: =QuarterBreakup!K$28*'JSW One TMT (2)'!$C$57*'JSW One TMT (2)'!$D27 -> 265877.89 | S27: =QuarterBreakup!L$28*'JSW One TMT (2)'!$C$57*'JSW One TMT (2)'!$D27 -> 265877.89 | T27: =Q27+R27+S27 -> 886259.63
A28: Architect/Engineer Meets | B28: Considering every distributor does 1 meets with 50 architects @Rs 3500/pax every quarter | C28: =B4*1*4*50*3500 -> 39200000 | D28: =C28/$C$22 -> 0.29963105 | E28: =QuarterBreakup!J$10*'JSW One TMT (2)'!$C$57*'JSW One TMT (2)'!$D28 -> 1748275.8 | F28: =QuarterBreakup!K$10*'JSW One TMT (2)'!$C$57*'JSW One TMT (2)'!$D28 -> 2331034.3 | G28: =QuarterBreakup!L$10*'JSW One TMT (2)'!$C$57*'JSW One TMT (2)'!$D28 -> 1748275.8 | H28: =SUM(E28:G28) -> 5827585.9 | I28: =QuarterBreakup!J$16*'JSW One TMT (2)'!$C$57*'JSW One TMT (2)'!$D28 -> 1008620.6 | J28: =QuarterBreakup!K$16*'JSW One TMT (2)'!$C$57*'JSW One TMT (2)'!$D28 -> 1176724.1 | K28: =QuarterBreakup!L$16*'JSW One TMT (2)'!$C$57*'JSW One TMT (2)'!$D28 -> 1176724.1 | L28: =I28+J28+K28 -> 3362068.8 | M28: =QuarterBreakup!J$22*'JSW One TMT (2)'!$C$57*'JSW One TMT (2)'!$D28 -> 2667241.2 | N28: =QuarterBreakup!K$22*'JSW One TMT (2)'!$C$57*'JSW One TMT (2)'!$D28 -> 2286206.8 | O28: =QuarterBreakup!L$22*'JSW One TMT (2)'!$C$57*'JSW One TMT (2)'!$D28 -> 2667241.2 | P28: =SUM(M28:O28) -> 7620689.2 | Q28: =QuarterBreakup!J$28*'JSW One TMT (2)'!$C$57*'JSW One TMT (2)'!$D28 -> 2241379.2 | R28: =QuarterBreakup!K$28*'JSW One TMT (2)'!$C$57*'JSW One TMT (2)'!$D28 -> 1681034.4 | S28: =QuarterBreakup!L$28*'JSW One TMT (2)'!$C$57*'JSW One TMT (2)'!$D28 -> 1681034.4 | T28: =Q28+R28+S28 -> 5603448
A29: Contractor Meets | B29: Considering every distributor does 2 meets with 50 contractors @Rs 1000/pax per quarter | C29: =B4*2*4*50*1000 -> 22400000 | D29: =C29/$C$22 -> 0.17121774 | E29: =QuarterBreakup!J$10*'JSW One TMT (2)'!$C$57*'JSW One TMT (2)'!$D29 -> 999014.72 | F29: =QuarterBreakup!K$10*'JSW One TMT (2)'!$C$57*'JSW One TMT (2)'!$D29 -> 1332019.6 | G29: =QuarterBreakup!L$10*'JSW One TMT (2)'!$C$57*'JSW One TMT (2)'!$D29 -> 999014.72 | H29: =SUM(E29:G29) -> 3330049.1 | I29: =QuarterBreakup!J$16*'JSW One TMT (2)'!$C$57*'JSW One TMT (2)'!$D29 -> 576354.65 | J29: =QuarterBreakup!K$16*'JSW One TMT (2)'!$C$57*'JSW One TMT (2)'!$D29 -> 672413.75 | K29: =QuarterBreakup!L$16*'JSW One TMT (2)'!$C$57*'JSW One TMT (2)'!$D29 -> 672413.75 | L29: =I29+J29+K29 -> 1921182.2 | M29: =QuarterBreakup!J$22*'JSW One TMT (2)'!$C$57*'JSW One TMT (2)'!$D29 -> 1524137.8 | N29: =QuarterBreakup!K$22*'JSW One TMT (2)'!$C$57*'JSW One TMT (2)'!$D29 -> 1306403.9 | O29: =QuarterBreakup!L$22*'JSW One TMT (2)'!$C$57*'JSW One TMT (2)'!$D29 -> 1524137.8 | P29: =SUM(M29:O29) -> 4354679.6 | Q29: =QuarterBreakup!J$28*'JSW One TMT (2)'!$C$57*'JSW One TMT (2)'!$D29 -> 1280788.1 | R29: =QuarterBreakup!K$28*'JSW One TMT (2)'!$C$57*'JSW One TMT (2)'!$D29 -> 960591.08 | S29: =QuarterBreakup!L$28*'JSW One TMT (2)'!$C$57*'JSW One TMT (2)'!$D29 -> 960591.08 | T29: =Q29+R29+S29 -> 3201970.3
A30: Mason Meets | B30: 1 Mason meet for every transacting dealer, of 30 pax/meet Cost @ Rs 300/pax/meet | C30: =B9*1*30*300 -> 9300000 | D30: =C30/$C$22 -> 0.071085937 | E30: =QuarterBreakup!J$10*'JSW One TMT (2)'!$C$57*'JSW One TMT (2)'!$D30 -> 414769.5 | F30: =QuarterBreakup!K$10*'JSW One TMT (2)'!$C$57*'JSW One TMT (2)'!$D30 -> 553026.01 | G30: =QuarterBreakup!L$10*'JSW One TMT (2)'!$C$57*'JSW One TMT (2)'!$D30 -> 414769.5 | H30: =SUM(E30:G30) -> 1382565 | I30: =QuarterBreakup!J$16*'JSW One TMT (2)'!$C$57*'JSW One TMT (2)'!$D30 -> 239290.1 | J30: =QuarterBreakup!K$16*'JSW One TMT (2)'!$C$57*'JSW One TMT (2)'!$D30 -> 279171.78 | K30: =QuarterBreakup!L$16*'JSW One TMT (2)'!$C$57*'JSW One TMT (2)'!$D30 -> 279171.78 | L30: =I30+J30+K30 -> 797633.66 | M30: =QuarterBreakup!J$22*'JSW One TMT (2)'!$C$57*'JSW One TMT (2)'!$D30 -> 632789.37 | N30: =QuarterBreakup!K$22*'JSW One TMT (2)'!$C$57*'JSW One TMT (2)'!$D30 -> 542390.89 | O30: =QuarterBreakup!L$22*'JSW One TMT (2)'!$C$57*'JSW One TMT (2)'!$D30 -> 632789.37 | P30: =SUM(M30:O30) -> 1807969.6 | Q30: =QuarterBreakup!J$28*'JSW One TMT (2)'!$C$57*'JSW One TMT (2)'!$D30 -> 531755.78 | R30: =QuarterBreakup!K$28*'JSW One TMT (2)'!$C$57*'JSW One TMT (2)'!$D30 -> 398816.83 | S30: =QuarterBreakup!L$28*'JSW One TMT (2)'!$C$57*'JSW One TMT (2)'!$D30 -> 398816.83 | T30: =Q30+R30+S30 -> 1329389.4
A31: Dealer Certificates | B31: To be given to all active retailers @Rs 400 | C31: =B8*400 -> 635897.44 | D31: =C31/$C$22 -> 0.0048605769 | E31: =QuarterBreakup!J$10*'JSW One TMT (2)'!$C$57*'JSW One TMT (2)'!$D31 -> 28360.308 | F31: =QuarterBreakup!K$10*'JSW One TMT (2)'!$C$57*'JSW One TMT (2)'!$D31 -> 37813.744 | G31: =QuarterBreakup!L$10*'JSW One TMT (2)'!$C$57*'JSW One TMT (2)'!$D31 -> 28360.308 | H31: =SUM(E31:G31) -> 94534.36 | I31: =QuarterBreakup!J$16*'JSW One TMT (2)'!$C$57*'JSW One TMT (2)'!$D31 -> 16361.716 | J31: =QuarterBreakup!K$16*'JSW One TMT (2)'!$C$57*'JSW One TMT (2)'!$D31 -> 19088.669 | K31: =QuarterBreakup!L$16*'JSW One TMT (2)'!$C$57*'JSW One TMT (2)'!$D31 -> 19088.669 | L31: =I31+J31+K31 -> 54539.054 | M31: =QuarterBreakup!J$22*'JSW One TMT (2)'!$C$57*'JSW One TMT (2)'!$D31 -> 43267.649 | N31: =QuarterBreakup!K$22*'JSW One TMT (2)'!$C$57*'JSW One TMT (2)'!$D31 -> 37086.557 | O31: =QuarterBreakup!L$22*'JSW One TMT (2)'!$C$57*'JSW One TMT (2)'!$D31 -> 43267.649 | P31: =SUM(M31:O31) -> 123621.86 | Q31: =QuarterBreakup!J$28*'JSW One TMT (2)'!$C$57*'JSW One TMT (2)'!$D31 -> 36359.369 | R31: =QuarterBreakup!K$28*'JSW One TMT (2)'!$C$57*'JSW One TMT (2)'!$D31 -> 27269.527 | S31: =QuarterBreakup!L$28*'JSW One TMT (2)'!$C$57*'JSW One TMT (2)'!$D31 -> 27269.527 | T31: =Q31+R31+S31 -> 90898.423
A32: Architect one-to-one visit Gifts | B32: Considering 75 architects for every distributor with gift cost @ Rs 500 | C32: =B4*75*500 -> 2100000 | D32: =C32/$C$22 -> 0.016051663 | E32: =QuarterBreakup!J$10*'JSW One TMT (2)'!$C$57*'JSW One TMT (2)'!$D32 -> 93657.63 | F32: =QuarterBreakup!K$10*'JSW One TMT (2)'!$C$57*'JSW One TMT (2)'!$D32 -> 124876.84 | G32: =QuarterBreakup!L$10*'JSW One TMT (2)'!$C$57*'JSW One TMT (2)'!$D32 -> 93657.63 | H32: =SUM(E32:G32) -> 312192.1 | I32: =QuarterBreakup!J$16*'JSW One TMT (2)'!$C$57*'JSW One TMT (2)'!$D32 -> 54033.248 | J32: =QuarterBreakup!K$16*'JSW One TMT (2)'!$C$57*'JSW One TMT (2)'!$D32 -> 63038.789 | K32: =QuarterBreakup!L$16*'JSW One TMT (2)'!$C$57*'JSW One TMT (2)'!$D32 -> 63038.789 | L32: =I32+J32+K32 -> 180110.83 | M32: =QuarterBreakup!J$22*'JSW One TMT (2)'!$C$57*'JSW One TMT (2)'!$D32 -> 142887.92 | N32: =QuarterBreakup!K$22*'JSW One TMT (2)'!$C$57*'JSW One TMT (2)'!$D32 -> 122475.36 | O32: =QuarterBreakup!L$22*'JSW One TMT (2)'!$C$57*'JSW One TMT (2)'!$D32 -> 142887.92 | P32: =SUM(M32:O32) -> 408251.21 | Q32: =QuarterBreakup!J$28*'JSW One TMT (2)'!$C$57*'JSW One TMT (2)'!$D32 -> 120073.88 | R32: =QuarterBreakup!K$28*'JSW One TMT (2)'!$C$57*'JSW One TMT (2)'!$D32 -> 90055.414 | S32: =QuarterBreakup!L$28*'JSW One TMT (2)'!$C$57*'JSW One TMT (2)'!$D32 -> 90055.414 | T32: =Q32+R32+S32 -> 300184.71
A33: Construction Site Gate Boards | B33: Assuming 5 active sites/month/priority district @Rs 1500/board | C33: =B10*5*12*1500 -> 17460000 | D33: =C33/$C$22 -> 0.13345811 | E33: =QuarterBreakup!J$10*'JSW One TMT (2)'!$C$57*'JSW One TMT (2)'!$D33 -> 778696.3 | F33: =QuarterBreakup!K$10*'JSW One TMT (2)'!$C$57*'JSW One TMT (2)'!$D33 -> 1038261.7 | G33: =QuarterBreakup!L$10*'JSW One TMT (2)'!$C$57*'JSW One TMT (2)'!$D33 -> 778696.3 | H33: =SUM(E33:G33) -> 2595654.3 | I33: =QuarterBreakup!J$16*'JSW One TMT (2)'!$C$57*'JSW One TMT (2)'!$D33 -> 449247.86 | J33: =QuarterBreakup!K$16*'JSW One TMT (2)'!$C$57*'JSW One TMT (2)'!$D33 -> 524122.51 | K33: =QuarterBreakup!L$16*'JSW One TMT (2)'!$C$57*'JSW One TMT (2)'!$D33 -> 524122.51 | L33: =I33+J33+K33 -> 1497492.9 | M33: =QuarterBreakup!J$22*'JSW One TMT (2)'!$C$57*'JSW One TMT (2)'!$D33 -> 1188011 | N33: =QuarterBreakup!K$22*'JSW One TMT (2)'!$C$57*'JSW One TMT (2)'!$D33 -> 1018295.2 | O33: =QuarterBreakup!L$22*'JSW One TMT (2)'!$C$57*'JSW One TMT (2)'!$D33 -> 1188011 | P33: =SUM(M33:O33) -> 3394317.2 | Q33: =QuarterBreakup!J$28*'JSW One TMT (2)'!$C$57*'JSW One TMT (2)'!$D33 -> 998328.58 | R33: =QuarterBreakup!K$28*'JSW One TMT (2)'!$C$57*'JSW One TMT (2)'!$D33 -> 748746.44 | S33: =QuarterBreakup!L$28*'JSW One TMT (2)'!$C$57*'JSW One TMT (2)'!$D33 -> 748746.44 | T33: =Q33+R33+S33 -> 2495821.5
A34: End Consumer Meets | B34: 1 consumer meet for every transacting dealer, of 30 pax/meet Cost @ Rs 1000/pax/meet | D34: =C34/$C$22 -> 0 | E34: =QuarterBreakup!J$10*'JSW One TMT (2)'!$C$57*'JSW One TMT (2)'!$D34 -> 0 | F34: =QuarterBreakup!K$10*'JSW One TMT (2)'!$C$57*'JSW One TMT (2)'!$D34 -> 0 | G34: =QuarterBreakup!L$10*'JSW One TMT (2)'!$C$57*'JSW One TMT (2)'!$D34 -> 0 | H34: =SUM(E34:G34) -> 0 | I34: =QuarterBreakup!J$16*'JSW One TMT (2)'!$C$57*'JSW One TMT (2)'!$D34 -> 0 | J34: =QuarterBreakup!K$16*'JSW One TMT (2)'!$C$57*'JSW One TMT (2)'!$D34 -> 0 | K34: =QuarterBreakup!L$16*'JSW One TMT (2)'!$C$57*'JSW One TMT (2)'!$D34 -> 0 | L34: =I34+J34+K34 -> 0 | M34: =QuarterBreakup!J$22*'JSW One TMT (2)'!$C$57*'JSW One TMT (2)'!$D34 -> 0 | N34: =QuarterBreakup!K$22*'JSW One TMT (2)'!$C$57*'JSW One TMT (2)'!$D34 -> 0 | O34: =QuarterBreakup!L$22*'JSW One TMT (2)'!$C$57*'JSW One TMT (2)'!$D34 -> 0 | P34: =SUM(M34:O34) -> 0 | Q34: =QuarterBreakup!J$28*'JSW One TMT (2)'!$C$57*'JSW One TMT (2)'!$D34 -> 0 | R34: =QuarterBreakup!K$28*'JSW One TMT (2)'!$C$57*'JSW One TMT (2)'!$D34 -> 0 | S34: =QuarterBreakup!L$28*'JSW One TMT (2)'!$C$57*'JSW One TMT (2)'!$D34 -> 0 | T34: =Q34+R34+S34 -> 0
A35: POP | B35: POP materials @Rs 3K to be given to every active dealer | C35: =B8*3000 -> 4769230.8 | D35: =C35/$C$22 -> 0.036454327 | E35: =QuarterBreakup!J$10*'JSW One TMT (2)'!$C$57*'JSW One TMT (2)'!$D35 -> 212702.31 | F35: =QuarterBreakup!K$10*'JSW One TMT (2)'!$C$57*'JSW One TMT (2)'!$D35 -> 283603.08 | G35: =QuarterBreakup!L$10*'JSW One TMT (2)'!$C$57*'JSW One TMT (2)'!$D35 -> 212702.31 | H35: =SUM(E35:G35) -> 709007.7 | I35: =QuarterBreakup!J$16*'JSW One TMT (2)'!$C$57*'JSW One TMT (2)'!$D35 -> 122712.87 | J35: =QuarterBreakup!K$16*'JSW One TMT (2)'!$C$57*'JSW One TMT (2)'!$D35 -> 143165.02 | K35: =QuarterBreakup!L$16*'JSW One TMT (2)'!$C$57*'JSW One TMT (2)'!$D35 -> 143165.02 | L35: =I35+J35+K35 -> 409042.9 | M35: =QuarterBreakup!J$22*'JSW One TMT (2)'!$C$57*'JSW One TMT (2)'!$D35 -> 324507.37 | N35: =QuarterBreakup!K$22*'JSW One TMT (2)'!$C$57*'JSW One TMT (2)'!$D35 -> 278149.17 | O35: =QuarterBreakup!L$22*'JSW One TMT (2)'!$C$57*'JSW One TMT (2)'!$D35 -> 324507.37 | P35: =SUM(M35:O35) -> 927163.92 | Q35: =QuarterBreakup!J$28*'JSW One TMT (2)'!$C$57*'JSW One TMT (2)'!$D35 -> 272695.27 | R35: =QuarterBreakup!K$28*'JSW One TMT (2)'!$C$57*'JSW One TMT (2)'!$D35 -> 204521.45 | S35: =QuarterBreakup!L$28*'JSW One TMT (2)'!$C$57*'JSW One TMT (2)'!$D35 -> 204521.45 | T35: =Q35+R35+S35 -> 681738.17
A36: Vehicle Branding (Truck/Tempo back panels) | B36: To be done at 10% of active dealers @Rs 5k/vehicle | C36: =(B8*0.1)*5000 -> 794871.79 | D36: =C36/$C$22 -> 0.0060757211 | E36: =QuarterBreakup!J$10*'JSW One TMT (2)'!$C$57*'JSW One TMT (2)'!$D36 -> 35450.385 | F36: =QuarterBreakup!K$10*'JSW One TMT (2)'!$C$57*'JSW One TMT (2)'!$D36 -> 47267.18 | G36: =QuarterBreakup!L$10*'JSW One TMT (2)'!$C$57*'JSW One TMT (2)'!$D36 -> 35450.385 | H36: =SUM(E36:G36) -> 118167.95 | I36: =QuarterBreakup!J$16*'JSW One TMT (2)'!$C$57*'JSW One TMT (2)'!$D36 -> 20452.145 | J36: =QuarterBreakup!K$16*'JSW One TMT (2)'!$C$57*'JSW One TMT (2)'!$D36 -> 23860.836 | K36: =QuarterBreakup!L$16*'JSW One TMT (2)'!$C$57*'JSW One TMT (2)'!$D36 -> 23860.836 | L36: =I36+J36+K36 -> 68173.817 | M36: =QuarterBreakup!J$22*'JSW One TMT (2)'!$C$57*'JSW One TMT (2)'!$D36 -> 54084.562 | N36: =QuarterBreakup!K$22*'JSW One TMT (2)'!$C$57*'JSW One TMT (2)'!$D36 -> 46358.196 | O36: =QuarterBreakup!L$22*'JSW One TMT (2)'!$C$57*'JSW One TMT (2)'!$D36 -> 54084.562 | P36: =SUM(M36:O36) -> 154527.32 | Q36: =QuarterBreakup!J$28*'JSW One TMT (2)'!$C$57*'JSW One TMT (2)'!$D36 -> 45449.212 | R36: =QuarterBreakup!K$28*'JSW One TMT (2)'!$C$57*'JSW One TMT (2)'!$D36 -> 34086.909 | S36: =QuarterBreakup!L$28*'JSW One TMT (2)'!$C$57*'JSW One TMT (2)'!$D36 -> 34086.909 | T36: =Q36+R36+S36 -> 113623.03
A37: Leaflets/Brochures | B37: 1000 units to be sent to all active retailers at Rs 4/pc | C37: =B8*1000*4 -> 6358974.4 | D37: =C37/$C$22 -> 0.048605769 | E37: =QuarterBreakup!J$10*'JSW One TMT (2)'!$C$57*'JSW One TMT (2)'!$D37 -> 283603.08 | F37: =QuarterBreakup!K$10*'JSW One TMT (2)'!$C$57*'JSW One TMT (2)'!$D37 -> 378137.44 | G37: =QuarterBreakup!L$10*'JSW One TMT (2)'!$C$57*'JSW One TMT (2)'!$D37 -> 283603.08 | H37: =SUM(E37:G37) -> 945343.6 | I37: =QuarterBreakup!J$16*'JSW One TMT (2)'!$C$57*'JSW One TMT (2)'!$D37 -> 163617.16 | J37: =QuarterBreakup!K$16*'JSW One TMT (2)'!$C$57*'JSW One TMT (2)'!$D37 -> 190886.69 | K37: =QuarterBreakup!L$16*'JSW One TMT (2)'!$C$57*'JSW One TMT (2)'!$D37 -> 190886.69 | L37: =I37+J37+K37 -> 545390.54 | M37: =QuarterBreakup!J$22*'JSW One TMT (2)'!$C$57*'JSW One TMT (2)'!$D37 -> 432676.49 | N37: =QuarterBreakup!K$22*'JSW One TMT (2)'!$C$57*'JSW One TMT (2)'!$D37 -> 370865.57 | O37: =QuarterBreakup!L$22*'JSW One TMT (2)'!$C$57*'JSW One TMT (2)'!$D37 -> 432676.49 | P37: =SUM(M37:O37) -> 1236218.6 | Q37: =QuarterBreakup!J$28*'JSW One TMT (2)'!$C$57*'JSW One TMT (2)'!$D37 -> 363593.69 | R37: =QuarterBreakup!K$28*'JSW One TMT (2)'!$C$57*'JSW One TMT (2)'!$D37 -> 272695.27 | S37: =QuarterBreakup!L$28*'JSW One TMT (2)'!$C$57*'JSW One TMT (2)'!$D37 -> 272695.27 | T37: =Q37+R37+S37 -> 908984.23
A38: Annual Diaries | B38: 3 annual diaries per active retailer@Rs250/diary | C38: =B8*3*250 -> 1192307.7 | D38: =C38/$C$22 -> 0.0091135817 | H38: =SUM(E38:G38) -> 0 | L38: =I38+J38+K38 -> 0 | O38: =C38 -> 1192307.7 | P38: =SUM(M38:O38) -> 1192307.7 | T38: =Q38+R38+S38 -> 0
A39: Festival Branding gifts (Diwali, Holi) | B39: To all active dealers and active influencers (3/retailer) | C39: =(B8+B8*3)*500 -> 3179487.2 | D39: =C39/$C$22 -> 0.024302884 | H39: =SUM(E39:G39) -> 0 | L39: =I39+J39+K39 -> 0 | M39: =C39/2 -> 1589743.6 | P39: =SUM(M39:O39) -> 1589743.6 | Q39: =C39/2 -> 1589743.6 | T39: =Q39+R39+S39 -> 1589743.6
A40: Branded Tarpaulins | B40: 1 Branded Tarpaulins @ 1500/pc | C40: =B8*1500*1 -> 2384615.4 | D40: =C40/$C$22 -> 0.018227163 | E40: =QuarterBreakup!J$10*'JSW One TMT (2)'!$C$57*'JSW One TMT (2)'!$D40 -> 106351.16 | F40: =QuarterBreakup!K$10*'JSW One TMT (2)'!$C$57*'JSW One TMT (2)'!$D40 -> 141801.54 | G40: =QuarterBreakup!L$10*'JSW One TMT (2)'!$C$57*'JSW One TMT (2)'!$D40 -> 106351.16 | H40: =SUM(E40:G40) -> 354503.85 | I40: =QuarterBreakup!J$16*'JSW One TMT (2)'!$C$57*'JSW One TMT (2)'!$D40 -> 61356.436 | J40: =QuarterBreakup!K$16*'JSW One TMT (2)'!$C$57*'JSW One TMT (2)'!$D40 -> 71582.508 | K40: =QuarterBreakup!L$16*'JSW One TMT (2)'!$C$57*'JSW One TMT (2)'!$D40 -> 71582.508 | L40: =I40+J40+K40 -> 204521.45 | M40: =QuarterBreakup!J$22*'JSW One TMT (2)'!$C$57*'JSW One TMT (2)'!$D40 -> 162253.69 | N40: =QuarterBreakup!K$22*'JSW One TMT (2)'!$C$57*'JSW One TMT (2)'!$D40 -> 139074.59 | O40: =QuarterBreakup!L$22*'JSW One TMT (2)'!$C$57*'JSW One TMT (2)'!$D40 -> 162253.69 | P40: =SUM(M40:O40) -> 463581.96 | Q40: =QuarterBreakup!J$28*'JSW One TMT (2)'!$C$57*'JSW One TMT (2)'!$D40 -> 136347.63 | R40: =QuarterBreakup!K$28*'JSW One TMT (2)'!$C$57*'JSW One TMT (2)'!$D40 -> 102260.73 | S40: =QuarterBreakup!L$28*'JSW One TMT (2)'!$C$57*'JSW One TMT (2)'!$D40 -> 102260.73 | T40: =Q40+R40+S40 -> 340869.09
A41: Cutout Standees from Ads | B41: For 50% of active retailer in size 5ft X 3ft; 5mm board with stand @ 2200/pc | C41: =(B8*0.5)*2200 -> 1748717.9 | D41: =C41/$C$22 -> 0.013366586 | E41: =QuarterBreakup!J$10*'JSW One TMT (2)'!$C$57*'JSW One TMT (2)'!$D41 -> 77990.847 | F41: =QuarterBreakup!K$10*'JSW One TMT (2)'!$C$57*'JSW One TMT (2)'!$D41 -> 103987.8 | G41: =QuarterBreakup!L$10*'JSW One TMT (2)'!$C$57*'JSW One TMT (2)'!$D41 -> 77990.847 | H41: =SUM(E41:G41) -> 259969.49 | I41: =QuarterBreakup!J$16*'JSW One TMT (2)'!$C$57*'JSW One TMT (2)'!$D41 -> 44994.719 | J41: =QuarterBreakup!K$16*'JSW One TMT (2)'!$C$57*'JSW One TMT (2)'!$D41 -> 52493.839 | K41: =QuarterBreakup!L$16*'JSW One TMT (2)'!$C$57*'JSW One TMT (2)'!$D41 -> 52493.839 | L41: =I41+J41+K41 -> 149982.4 | M41: =QuarterBreakup!J$22*'JSW One TMT (2)'!$C$57*'JSW One TMT (2)'!$D41 -> 118986.04 | N41: =QuarterBreakup!K$22*'JSW One TMT (2)'!$C$57*'JSW One TMT (2)'!$D41 -> 101988.03 | O41: =QuarterBreakup!L$22*'JSW One TMT (2)'!$C$57*'JSW One TMT (2)'!$D41 -> 118986.04 | P41: =SUM(M41:O41) -> 339960.1 | Q41: =QuarterBreakup!J$28*'JSW One TMT (2)'!$C$57*'JSW One TMT (2)'!$D41 -> 99988.265 | R41: =QuarterBreakup!K$28*'JSW One TMT (2)'!$C$57*'JSW One TMT (2)'!$D41 -> 74991.199 | S41: =QuarterBreakup!L$28*'JSW One TMT (2)'!$C$57*'JSW One TMT (2)'!$D41 -> 74991.199 | T41: =Q41+R41+S41 -> 249970.66
A42: Project BTL Activities | C42: =SUM(C43:C46) -> 3625000 | E42: =SUM(E43:E46) -> 156096.05 | F42: =SUM(F43:F46) -> 208128.07 | G42: =SUM(G43:G46) -> 156096.05 | H42: =SUM(H43:H46) -> 520320.17 | I42: =SUM(I43:I46) -> 90055.414 | J42: =SUM(J43:J46) -> 105064.65 | K42: =SUM(K43:K46) -> 105064.65 | L42: =SUM(L43:L46) -> 300184.71 | ... T42: =SUM(T43:T46) -> 550307.85
A43: First visit to project customers | B43: 2000 customers @Rs500 | C43: =2000*500 -> 1000000 | D43: =C43/$C$42 -> 0.27586207 | E43: =$D43*$C$58*QuarterBreakup!J$10 -> 44598.871 | F43: =$D43*$C$58*QuarterBreakup!K$10 -> 59465.162 | G43: =$D43*$C$58*QuarterBreakup!L$10 -> 44598.871 | H43: =SUM(E43:G43) -> 148662.9 | I43: =$D43*$C$58*QuarterBreakup!J$16 -> 25730.118 | J43: =$D43*$C$58*QuarterBreakup!K$16 -> 30018.471 | K43: =$D43*$C$58*QuarterBreakup!L$16 -> 30018.471 | L43: =I43+J43+K43 -> 85767.061 | M43: =$D43*$C$58*QuarterBreakup!J$22 -> 68041.868 | N43: =$D43*$C$58*QuarterBreakup!K$22 -> 58321.601 | O43: =$D43*$C$58*QuarterBreakup!L$22 -> 68041.868 | P43: =SUM(M43:O43) -> 194405.34 | Q43: =$D43*$C$58*QuarterBreakup!J$28 -> 57178.04 | R43: =$D43*$C$58*QuarterBreakup!K$28 -> 42883.53 | S43: =$D43*$C$58*QuarterBreakup!L$28 -> 42883.53 | T43: =Q43+R43+S43 -> 142945.1
A44: Government Approvals | B44: 10 approvals @Rs 2.5 Lacs | C44: =10*250000 -> 2500000 | D44: =C44/$C$42 -> 0.68965517 | E44: =$D44*$C$58*QuarterBreakup!J$10 -> 111497.18 | F44: =$D44*$C$58*QuarterBreakup!K$10 -> 148662.9 | G44: =$D44*$C$58*QuarterBreakup!L$10 -> 111497.18 | H44: =SUM(E44:G44) -> 371657.26 | I44: =$D44*$C$58*QuarterBreakup!J$16 -> 64325.295 | J44: =$D44*$C$58*QuarterBreakup!K$16 -> 75046.178 | K44: =$D44*$C$58*QuarterBreakup!L$16 -> 75046.178 | L44: =I44+J44+K44 -> 214417.65 | M44: =$D44*$C$58*QuarterBreakup!J$22 -> 170104.67 | N44: =$D44*$C$58*QuarterBreakup!K$22 -> 145804 | O44: =$D44*$C$58*QuarterBreakup!L$22 -> 170104.67 | P44: =SUM(M44:O44) -> 486013.34 | Q44: =$D44*$C$58*QuarterBreakup!J$28 -> 142945.1 | R44: =$D44*$C$58*QuarterBreakup!K$28 -> 107208.83 | S44: =$D44*$C$58*QuarterBreakup!L$28 -> 107208.83 | T44: =Q44+R44+S44 -> 357362.75
A45: Annual Diaries | B45: 1 annual diary per active project customer @Rs250/diary - 100 customers | C45: =100*250 -> 25000 | D45: =C45/$C$42 -> 0.0068965517 | H45: =SUM(E45:G45) -> 0 | L45: =I45+J45+K45 -> 0 | O45: 25000 | P45: =SUM(M45:O45) -> 25000 | T45: =Q45+R45+S45 -> 0
A46: Festival Branding gifts (Diwali, Holi) | B46: 1 gift per active project customer @Rs500/festival - 100 customers | C46: =100*2*500 -> 100000 | D46: =C46/$C$42 -> 0.027586207 | H46: =SUM(E46:G46) -> 0 | L46: =I46+J46+K46 -> 0 | M46: 50000 | P46: =SUM(M46:O46) -> 50000 | Q46: 50000 | T46: =Q46+R46+S46 -> 50000
A47: Digital Marketing Collaterals | C47: =SUM(C48:C50) -> 6800000 | E47: =SUM(E48:E50) -> 2650000 | F47: =SUM(F48:F50) -> 2650000 | G47: =SUM(G48:G50) -> 150000 | H47: =SUM(H48:H50) -> 5450000 | I47: =SUM(I48:I50) -> 150000 | J47: =SUM(J48:J50) -> 150000 | K47: =SUM(K48:K50) -> 150000 | L47: =SUM(L48:L50) -> 450000 | ... T47: =SUM(T48:T50) -> 450000
A48: Marketing Agencies | B48: 1.5L/month/agency | C48: =150000*12 -> 1800000 | D48: =C48/$C$47 -> 0.26470588 | E48: 150000 | F48: 150000 | G48: 150000 | H48: =SUM(E48:G48) -> 450000 | I48: 150000 | J48: 150000 | K48: 150000 | L48: =I48+J48+K48 -> 450000 | M48: 150000 | N48: 150000 | O48: 150000 | P48: =SUM(M48:O48) -> 450000 | Q48: 150000 | R48: 150000 | S48: 150000 | T48: =SUM(Q48:S48) -> 450000
A49: Product featuring video | D49: =C49/$C$47 -> 0 | E49: =$D49*$C$59*QuarterBreakup!J$10 -> 0 | F49: =$D49*$C$59*QuarterBreakup!K$10 -> 0 | G49: =$D49*$C$59*QuarterBreakup!L$10 -> 0 | H49: =SUM(E49:G49) -> 0 | I49: =$D49*$C$59*QuarterBreakup!J$16 -> 0 | J49: =$D49*$C$59*QuarterBreakup!K$16 -> 0 | K49: =$D49*$C$59*QuarterBreakup!L$16 -> 0 | L49: =I49+J49+K49 -> 0 | M49: =$D49*$C$59*QuarterBreakup!J$22 -> 0 | N49: =$D49*$C$59*QuarterBreakup!K$22 -> 0 | O49: =$D49*$C$59*QuarterBreakup!L$22 -> 0 | P49: =SUM(M49:O49) -> 0 | Q49: =$D49*$C$59*QuarterBreakup!J$28 -> 0 | R49: =$D49*$C$59*QuarterBreakup!K$28 -> 0 | S49: =$D49*$C$59*QuarterBreakup!L$28 -> 0 | T49: =SUM(Q49:S49) -> 0
A50: Brand Film production | B50: Youtube Ad production | C50: 5000000 | D50: =C50/$C$47 -> 0.73529412 | E50: 2500000 | F50: 2500000 | H50: =SUM(E50:G50) -> 5000000 | L50: =I50+J50+K50 -> 0 | P50: =SUM(M50:O50) -> 0 | T50: =SUM(Q50:S50) -> 0
A51: Discretionary Budget | C51: =SUM(C52) -> 5000000 | E51: =SUM(E52) -> 222994.36 | F51: =SUM(F52) -> 297325.81 | G51: =SUM(G52) -> 222994.36 | H51: =SUM(H52) -> 743314.52 | I51: =SUM(I52) -> 128650.59 | J51: =SUM(J52) -> 150092.36 | K51: =SUM(K52) -> 150092.36 | L51: =SUM(L52) -> 428835.3 | ... T51: =SUM(T52) -> 714725.5
A52: Miscellaneous Budget for immediate action | C52: 5000000 | D52: =C52/$C$51 -> 1 | E52: =$D52*$C$60*QuarterBreakup!J$10 -> 222994.36 | F52: =$D52*$C$60*QuarterBreakup!K$10 -> 297325.81 | G52: =$D52*$C$60*QuarterBreakup!L$10 -> 222994.36 | H52: =SUM(E52:G52) -> 743314.52 | I52: =$D52*$C$60*QuarterBreakup!J$16 -> 128650.59 | J52: =$D52*$C$60*QuarterBreakup!K$16 -> 150092.36 | K52: =$D52*$C$60*QuarterBreakup!L$16 -> 150092.36 | L52: =I52+J52+K52 -> 428835.3 | M52: =$D52*$C$60*QuarterBreakup!J$22 -> 340209.34 | N52: =$D52*$C$60*QuarterBreakup!K$22 -> 291608.01 | O52: =$D52*$C$60*QuarterBreakup!L$22 -> 340209.34 | P52: =SUM(M52:O52) -> 972026.69 | Q52: =$D52*$C$60*QuarterBreakup!J$28 -> 285890.2 | R52: =$D52*$C$60*QuarterBreakup!K$28 -> 214417.65 | S52: =$D52*$C$60*QuarterBreakup!L$28 -> 214417.65 | T52: =SUM(Q52:S52) -> 714725.5
A53: TOTALS | C53: =SUM(C11,C22,C42,C47,C51) -> 3.1577256e+08 | E53: =SUM(E11,E22,E42,E47,E51) -> 16733276 | F53: =SUM(F11,F22,F42,F47,F51) -> 22907151 | G53: =SUM(G11,G22,G42,G47,G51) -> 15376726 | H53: =SUM(H11,H22,H42,H47,H51) -> 55017152 | I53: =SUM(I11,I22,I42,I47,I51) -> 5523883.6 | J53: =SUM(J11,J22,J42,J47,J51) -> 6419530.9 | K53: =SUM(K11,K22,K42,K47,K51) -> 9289897.1 | L53: =SUM(L11,L22,L42,L47,L51) -> 21233312 | ... T53: =SUM(T11,T22,T42,T47,T51) -> 46789063
H54: =SUM(H53,L53,P53,T53) -> 1.8938234e+08
A55: Category | B55: Projected Budget | C55: % of Total Budget
A56: =A11 -> ATL Activities | B56: =C11 -> 169520000 | C56: =B56/$B$61 -> 0.53684208 | P56: =SUM(P11:P52)/2 -> 66342816 | T56: =SUM(T11:T52)/2 -> 46789063
A57: =A22 -> BTL Activities | B57: =C22 -> 1.3082756e+08 | C57: =B57/$B$61 -> 0.41430947
A58: =A42 -> Project BTL Activities | B58: =C42 -> 3625000 | C58: =B58/$B$61 -> 0.011479781
A59: =A47 -> Digital Marketing Collaterals | B59: =C47 -> 6800000 | C59: =B59/$B$61 -> 0.021534486
A60: =A51 -> Discretionary Budget | B60: =C51 -> 5000000 | C60: =B60/$B$61 -> 0.015834181
A61: TOTALS | B61: =SUM(B56:B60) -> 3.1577256e+08
A63: Quarter-wise Budget Breakup | B63: Projected Budget | C63: % of Total Budget
A64: Q1 | B64: =H53 -> 55017152 | C64: =B64/$B$68 -> 0.29050835
A65: Q2 | B65: =L53 -> 21233312 | C65: =B65/$B$68 -> 0.11211875
A66: Q3 | B66: =P53 -> 66342816 | C66: =B66/$B$68 -> 0.35031152
A67: Q4 | B67: =T53 -> 46789063 | C67: =B67/$B$68 -> 0.24706138
A68: TOTALS | B68: =SUM(B64:B67) -> 1.8938234e+08

Sheet JSW One TMT
A1: Category | B1: Remarks | C1: YEAR TOTALS | D1: %age of totals - Bucketwise | E1: Q1 | I1: Q2 | M1: Q3 | Q1: Q4
E2: Apr | F2: May | G2: Jun | H2: Q1 Totals | I2: Jul | J2: Aug | K2: Sep | L2: Q2 Totals | M2: Oct | N2: Nov | O2: Dec | P2: Q3 Totals | Q2: Jan | R2: Feb | S2: Mar | T2: Q4 Totals
A3: Particulars
A4: #Distributors | B4: 56
A5: Volume projection (Mar'27 Exit) | B5: 31000
A6: Avg. volume/retailer/month | B6: 30
A7: Total retailers (Mar'27) | B7: =B8*3 -> 4769.2308
A8: Total Active retailers (Mar'27) | B8: =B9/65% -> 1589.7436
A9: Total transacting retailers (Mar'27) | B9: =B5/B6 -> 1033.3333
A10: #Priority districts | B10: 194
A11: ATL Activities | C11: =SUM(C12:C17) -> 60540000 | E11: =SUM(E12:E17) -> 5350545 | F11: =SUM(F12:F17) -> 7176585 | G11: =SUM(G12:G17) -> 4974120 | H11: =SUM(H12:H17) -> 17501250 | I11: =SUM(I12:I17) -> 1143000 | J11: =SUM(J12:J17) -> 1333500 | K11: =SUM(K12:K17) -> 3178350 | L11: =SUM(L12:L17) -> 5654850 | ... T11: =SUM(T12:T17) -> 15723000
A12: Impact Wall Painting | B12: 15,000 sq ft in 82 V.High and High priority district @ Rs 14 | C12: =82*15000*14 -> 17220000 | D12: =C12/$C$11 -> 0.28444004 | E12: =($D12*QuarterBreakup!J$10*'JSW One TMT'!$C$51)+904050/2 -> 1795185 | F12: =($D12*QuarterBreakup!K$10*'JSW One TMT'!$C$51)+904050/2 -> 2242905 | G12: =($D12*QuarterBreakup!L$10*'JSW One TMT'!$C$51) -> 1343160 | H12: =E12+F12+G12 -> 5381250 | K12: =($D12*QuarterBreakup!L$16*'JSW One TMT'!$C$51) -> 904050 | L12: =I12+J12+K12 -> 904050 | M12: =$D12*QuarterBreakup!J$22*'JSW One TMT'!$C$51+774900/2 -> 2436630 | N12: =$D12*QuarterBreakup!K$22*'JSW One TMT'!$C$51+774900/2 -> 2143890 | O12: =$D12*QuarterBreakup!L$22*'JSW One TMT'!$C$51 -> 2049180 | P12: =M12+N12+O12 -> 6629700 | Q12: =$D12*QuarterBreakup!J$28*'JSW One TMT'!$C$51 -> 1722000 | R12: =$D12*QuarterBreakup!K$28*'JSW One TMT'!$C$51 -> 1291500 | S12: =$D12*QuarterBreakup!L$28*'JSW One TMT'!$C$51 -> 1291500 | T12: =Q12+R12+S12 -> 4305000
A13: Integrated FM Radio Campaigns (Ad + Promotional Activity) | B13: To be done in Top 3 high potential districts for Top 4 states @Rs 2.5 Lac/campaign/district/quarter (No. of states: 4) for 2 quarters (UP, RJ, Haryana, WB) | C13: =4*3*250000*2 -> 6000000 | D13: =C13/$C$11 -> 0.099108028 | E13: =($D13*QuarterBreakup!J$10*'JSW One TMT'!$C$51) -> 468000 | F13: =($D13*QuarterBreakup!K$10*'JSW One TMT'!$C$51) -> 624000 | G13: =($D13*QuarterBreakup!L$10*'JSW One TMT'!$C$51) -> 468000 | H13: =E13+F13+G13 -> 1560000 | I13: =($D13*QuarterBreakup!J$16*'JSW One TMT'!$C$51) -> 270000 | J13: =($D13*QuarterBreakup!K$16*'JSW One TMT'!$C$51) -> 315000 | K13: =($D13*QuarterBreakup!L$16*'JSW One TMT'!$C$51) -> 315000 | L13: =I13+J13+K13 -> 900000 | M13: =$D13*QuarterBreakup!J$22*'JSW One TMT'!$C$51 -> 714000 | N13: =$D13*QuarterBreakup!K$22*'JSW One TMT'!$C$51 -> 612000 | O13: =$D13*QuarterBreakup!L$22*'JSW One TMT'!$C$51 -> 714000 | P13: =M13+N13+O13 -> 2040000 | Q13: =$D13*QuarterBreakup!J$28*'JSW One TMT'!$C$51 -> 600000 | R13: =$D13*QuarterBreakup!K$28*'JSW One TMT'!$C$51 -> 450000 | S13: =$D13*QuarterBreakup!L$28*'JSW One TMT'!$C$51 -> 450000 | T13: =Q13+R13+S13 -> 1500000
A14: Digital Marketing Campaigns | B14: To be done in Top 3 high potential districts for all 4 states @Rs 6 Lac/campaign/district/quarter (No. of states: 4) for 2 quarters | C14: =4*3*600000*2 -> 14400000 | D14: =C14/$C$11 -> 0.23785927 | E14: =($D14*QuarterBreakup!J$10*'JSW One TMT'!$C$51) -> 1123200 | F14: =($D14*QuarterBreakup!K$10*'JSW One TMT'!$C$51) -> 1497600 | G14: =($D14*QuarterBreakup!L$10*'JSW One TMT'!$C$51) -> 1123200 | H14: =E14+F14+G14 -> 3744000 | I14: =($D14*QuarterBreakup!J$16*'JSW One TMT'!$C$51) -> 648000 | J14: =($D14*QuarterBreakup!K$16*'JSW One TMT'!$C$51) -> 756000 | K14: =($D14*QuarterBreakup!L$16*'JSW One TMT'!$C$51) -> 756000 | L14: =I14+J14+K14 -> 2160000 | M14: =$D14*QuarterBreakup!J$22*'JSW One TMT'!$C$51 -> 1713600 | N14: =$D14*QuarterBreakup!K$22*'JSW One TMT'!$C$51 -> 1468800 | O14: =$D14*QuarterBreakup!L$22*'JSW One TMT'!$C$51 -> 1713600 | P14: =M14+N14+O14 -> 4896000 | Q14: =$D14*QuarterBreakup!J$28*'JSW One TMT'!$C$51 -> 1440000 | R14: =$D14*QuarterBreakup!K$28*'JSW One TMT'!$C$51 -> 1080000 | S14: =$D14*QuarterBreakup!L$28*'JSW One TMT'!$C$51 -> 1080000 | T14: =Q14+R14+S14 -> 3600000
A15: Local Events/Fairs/Exhibitions | B15: For different Plant Launches, promotional exhibitions and mass events like Mahakumbh, etc - Total 10 events | C15: 5000000 | D15: =C15/$C$11 -> 0.082590023 | E15: =($D15*QuarterBreakup!J$10*'JSW One TMT'!$C$51) -> 390000 | F15: =($D15*QuarterBreakup!K$10*'JSW One TMT'!$C$51) -> 520000 | G15: =($D15*QuarterBreakup!L$10*'JSW One TMT'!$C$51) -> 390000 | H15: =E15+F15+G15 -> 1300000 | I15: =($D15*QuarterBreakup!J$16*'JSW One TMT'!$C$51) -> 225000 | J15: =($D15*QuarterBreakup!K$16*'JSW One TMT'!$C$51) -> 262500 | K15: =($D15*QuarterBreakup!L$16*'JSW One TMT'!$C$51) -> 262500 | L15: =I15+J15+K15 -> 750000 | M15: =$D15*QuarterBreakup!J$22*'JSW One TMT'!$C$51 -> 595000 | N15: =$D15*QuarterBreakup!K$22*'JSW One TMT'!$C$51 -> 510000 | O15: =$D15*QuarterBreakup!L$22*'JSW One TMT'!$C$51 -> 595000 | P15: =M15+N15+O15 -> 1700000 | Q15: =$D15*QuarterBreakup!J$28*'JSW One TMT'!$C$51 -> 500000 | R15: =$D15*QuarterBreakup!K$28*'JSW One TMT'!$C$51 -> 375000 | S15: =$D15*QuarterBreakup!L$28*'JSW One TMT'!$C$51 -> 375000 | T15: =Q15+R15+S15 -> 1250000
A16: Van Campaign | B16: To be done in Top 2 high potential districts for top 8 states @ Rs 7000 /day (No. of states: 8) for 2 month | C16: =8*2*7000*60 -> 6720000 | D16: =C16/$C$11 -> 0.11100099 | E16: =($D16*QuarterBreakup!J$10*'JSW One TMT'!$C$51)+352800/2 -> 700560 | F16: =($D16*QuarterBreakup!K$10*'JSW One TMT'!$C$51)+352800/2 -> 875280 | G16: =($D16*QuarterBreakup!L$10*'JSW One TMT'!$C$51) -> 524160 | H16: =E16+F16+G16 -> 2100000 | K16: =($D16*QuarterBreakup!L$16*'JSW One TMT'!$C$51) -> 352800 | L16: =I16+J16+K16 -> 352800 | M16: =$D16*QuarterBreakup!J$22*'JSW One TMT'!$C$51+302400/2 -> 950880 | N16: =$D16*QuarterBreakup!K$22*'JSW One TMT'!$C$51+302400/2 -> 836640 | O16: =$D16*QuarterBreakup!L$22*'JSW One TMT'!$C$51 -> 799680 | P16: =M16+N16+O16 -> 2587200 | Q16: =$D16*QuarterBreakup!J$28*'JSW One TMT'!$C$51 -> 672000 | R16: =$D16*QuarterBreakup!K$28*'JSW One TMT'!$C$51 -> 504000 | S16: =$D16*QuarterBreakup!L$28*'JSW One TMT'!$C$51 -> 504000 | T16: =Q16+R16+S16 -> 1680000
A17: Transit Branding (Auto) | B17: To be done in Top 2 high potential districts for top 8 high volume states @1000 autos @Rs. 700/auto (No. of states: 15) (UP, HR, RJ, Odisha, MP, JH, WB, Bihar) | C17: =8*2*1000*700 -> 11200000 | D17: =C17/$C$11 -> 0.18500165 | E17: =($D17*QuarterBreakup!J$10*'JSW One TMT'!$C$51) -> 873600 | F17: =($D17*QuarterBreakup!K$10*'JSW One TMT'!$C$51)+504000/2 -> 1416800 | G17: =($D17*QuarterBreakup!L$10*'JSW One TMT'!$C$51)+504000/2 -> 1125600 | H17: =E17+F17+G17 -> 3416000 | K17: =($D17*QuarterBreakup!L$16*'JSW One TMT'!$C$51) -> 588000 | L17: =I17+J17+K17 -> 588000 | M17: =$D17*QuarterBreakup!J$22*'JSW One TMT'!$C$51 -> 1332800 | N17: =$D17*QuarterBreakup!K$22*'JSW One TMT'!$C$51 -> 1142400 | O17: =$D17*QuarterBreakup!L$22*'JSW One TMT'!$C$51 -> 1332800 | P17: =M17+N17+O17 -> 3808000 | Q17: =$D17*QuarterBreakup!J$28*'JSW One TMT'!$C$51+588000/2 -> 1414000 | R17: =$D17*QuarterBreakup!K$28*'JSW One TMT'!$C$51+588000/2 -> 1134000 | S17: =$D17*QuarterBreakup!L$28*'JSW One TMT'!$C$51 -> 840000 | T17: =Q17+R17+S17 -> 3388000
A18: BTL Activities | C18: =SUM(C19:C36) -> 1.0158756e+08 | E18: =SUM(E19:E36) -> 7582830 | F18: =SUM(F19:F36) -> 10110440 | G18: =SUM(G19:G36) -> 7582830 | H18: =SUM(H19:H36) -> 25276100 | I18: =SUM(I19:I36) -> 4374709.6 | J18: =SUM(J19:J36) -> 5103827.9 | K18: =SUM(K19:K36) -> 5103827.9 | L18: =SUM(L19:L36) -> 14582365 | ... T18: =SUM(T19:T36) -> 25893686
A19: NLBs | B19: To be given to 50% of active dealers (Cost is taken to be Rs.40/sqft. Avg size is taken to be 10*3=30 sqft) | C19: =(B8*0.5)*40*30 -> 953846.15 | D19: =C19/$C$18 -> 0.0093893988 | E19: =QuarterBreakup!J$10*'JSW One TMT'!$C$52*'JSW One TMT'!$D19 -> 74400 | F19: =QuarterBreakup!K$10*'JSW One TMT'!$C$52*'JSW One TMT'!$D19 -> 99200 | G19: =QuarterBreakup!L$10*'JSW One TMT'!$C$52*'JSW One TMT'!$D19 -> 74400 | H19: =SUM(E19:G19) -> 248000 | I19: =QuarterBreakup!J$16*'JSW One TMT'!$C$52*'JSW One TMT'!$D19 -> 42923.077 | J19: =QuarterBreakup!K$16*'JSW One TMT'!$C$52*'JSW One TMT'!$D19 -> 50076.923 | K19: =QuarterBreakup!L$16*'JSW One TMT'!$C$52*'JSW One TMT'!$D19 -> 50076.923 | L19: =I19+J19+K19 -> 143076.92 | M19: =QuarterBreakup!J$22*'JSW One TMT'!$C$52*'JSW One TMT'!$D19 -> 113507.69 | N19: =QuarterBreakup!K$22*'JSW One TMT'!$C$52*'JSW One TMT'!$D19 -> 97292.308 | O19: =QuarterBreakup!L$22*'JSW One TMT'!$C$52*'JSW One TMT'!$D19 -> 113507.69 | P19: =SUM(M19:O19) -> 324307.69 | Q19: =QuarterBreakup!J$28*'JSW One TMT'!$C$52*'JSW One TMT'!$D19 -> 95384.615 | R19: =QuarterBreakup!K$28*'JSW One TMT'!$C$52*'JSW One TMT'!$D19 -> 71538.462 | S19: =QuarterBreakup!L$28*'JSW One TMT'!$C$52*'JSW One TMT'!$D19 -> 71538.462 | T19: =Q19+R19+S19 -> 238461.54
A20: GSBs | B20: To be given to 25% of active dealers. Cost: (180 *size of flex + 65*length of iron angle), Avg size of flex taken to be 10*3. Avg iron angle length: 18 ft | C20: =(B8*0.25)*(180*30+65*18) -> 2611153.8 | D20: =C20/$C$18 -> 0.025703479 | E20: =QuarterBreakup!J$10*'JSW One TMT'!$C$52*'JSW One TMT'!$D20 -> 203670 | F20: =QuarterBreakup!K$10*'JSW One TMT'!$C$52*'JSW One TMT'!$D20 -> 271560 | G20: =QuarterBreakup!L$10*'JSW One TMT'!$C$52*'JSW One TMT'!$D20 -> 203670 | H20: =SUM(E20:G20) -> 678900 | I20: =QuarterBreakup!J$16*'JSW One TMT'!$C$52*'JSW One TMT'!$D20 -> 117501.92 | J20: =QuarterBreakup!K$16*'JSW One TMT'!$C$52*'JSW One TMT'!$D20 -> 137085.58 | K20: =QuarterBreakup!L$16*'JSW One TMT'!$C$52*'JSW One TMT'!$D20 -> 137085.58 | L20: =I20+J20+K20 -> 391673.08 | M20: =QuarterBreakup!J$22*'JSW One TMT'!$C$52*'JSW One TMT'!$D20 -> 310727.31 | N20: =QuarterBreakup!K$22*'JSW One TMT'!$C$52*'JSW One TMT'!$D20 -> 266337.69 | O20: =QuarterBreakup!L$22*'JSW One TMT'!$C$52*'JSW One TMT'!$D20 -> 310727.31 | P20: =SUM(M20:O20) -> 887792.31 | Q20: =QuarterBreakup!J$28*'JSW One TMT'!$C$52*'JSW One TMT'!$D20 -> 261115.38 | R20: =QuarterBreakup!K$28*'JSW One TMT'!$C$52*'JSW One TMT'!$D20 -> 195836.54 | S20: =QuarterBreakup!L$28*'JSW One TMT'!$C$52*'JSW One TMT'!$D20 -> 195836.54 | T20: =Q20+R20+S20 -> 652788.46
A21: Counter Wall Painting | B21: To be given to exclusive 20% active counters @Rs 10000/counter | C21: =(B8*0.2)*10000 -> 3179487.2 | D21: =C21/$C$18 -> 0.031297996 | E21: =QuarterBreakup!J$10*'JSW One TMT'!$C$52*'JSW One TMT'!$D21 -> 248000 | F21: =QuarterBreakup!K$10*'JSW One TMT'!$C$52*'JSW One TMT'!$D21 -> 330666.67 | G21: =QuarterBreakup!L$10*'JSW One TMT'!$C$52*'JSW One TMT'!$D21 -> 248000 | H21: =SUM(E21:G21) -> 826666.67 | I21: =QuarterBreakup!J$16*'JSW One TMT'!$C$52*'JSW One TMT'!$D21 -> 143076.92 | J21: =QuarterBreakup!K$16*'JSW One TMT'!$C$52*'JSW One TMT'!$D21 -> 166923.08 | K21: =QuarterBreakup!L$16*'JSW One TMT'!$C$52*'JSW One TMT'!$D21 -> 166923.08 | L21: =I21+J21+K21 -> 476923.08 | M21: =QuarterBreakup!J$22*'JSW One TMT'!$C$52*'JSW One TMT'!$D21 -> 378358.97 | N21: =QuarterBreakup!K$22*'JSW One TMT'!$C$52*'JSW One TMT'!$D21 -> 324307.69 | O21: =QuarterBreakup!L$22*'JSW One TMT'!$C$52*'JSW One TMT'!$D21 -> 378358.97 | P21: =SUM(M21:O21) -> 1081025.6 | Q21: =QuarterBreakup!J$28*'JSW One TMT'!$C$52*'JSW One TMT'!$D21 -> 317948.72 | R21: =QuarterBreakup!K$28*'JSW One TMT'!$C$52*'JSW One TMT'!$D21 -> 238461.54 | S21: =QuarterBreakup!L$28*'JSW One TMT'!$C$52*'JSW One TMT'!$D21 -> 238461.54 | T21: =Q21+R21+S21 -> 794871.79
A22: Inshop Branding | B22: To be given to exclusive 10% active counters @Rs 40000/counter | C22: =(B8*0.1)*40000 -> 6358974.4 | D22: =C22/$C$18 -> 0.062595992 | E22: =QuarterBreakup!J$10*'JSW One TMT'!$C$52*'JSW One TMT'!$D22 -> 496000 | F22: =QuarterBreakup!K$10*'JSW One TMT'!$C$52*'JSW One TMT'!$D22 -> 661333.33 | G22: =QuarterBreakup!L$10*'JSW One TMT'!$C$52*'JSW One TMT'!$D22 -> 496000 | H22: =SUM(E22:G22) -> 1653333.3 | I22: =QuarterBreakup!J$16*'JSW One TMT'!$C$52*'JSW One TMT'!$D22 -> 286153.85 | J22: =QuarterBreakup!K$16*'JSW One TMT'!$C$52*'JSW One TMT'!$D22 -> 333846.15 | K22: =QuarterBreakup!L$16*'JSW One TMT'!$C$52*'JSW One TMT'!$D22 -> 333846.15 | L22: =I22+J22+K22 -> 953846.15 | M22: =QuarterBreakup!J$22*'JSW One TMT'!$C$52*'JSW One TMT'!$D22 -> 756717.95 | N22: =QuarterBreakup!K$22*'JSW One TMT'!$C$52*'JSW One TMT'!$D22 -> 648615.38 | O22: =QuarterBreakup!L$22*'JSW One TMT'!$C$52*'JSW One TMT'!$D22 -> 756717.95 | P22: =SUM(M22:O22) -> 2162051.3 | Q22: =QuarterBreakup!J$28*'JSW One TMT'!$C$52*'JSW One TMT'!$D22 -> 635897.44 | R22: =QuarterBreakup!K$28*'JSW One TMT'!$C$52*'JSW One TMT'!$D22 -> 476923.08 | S22: =QuarterBreakup!L$28*'JSW One TMT'!$C$52*'JSW One TMT'!$D22 -> 476923.08 | T22: =Q22+R22+S22 -> 1589743.6
A23: Distributor Meet for Mou Signing and Agenda setting for FY27 | C23: 10000000 | D23: =C23/$C$18 -> 0.098437246 | E23: =QuarterBreakup!J$10*'JSW One TMT'!$C$52*'JSW One TMT'!$D23 -> 780000 | F23: =QuarterBreakup!K$10*'JSW One TMT'!$C$52*'JSW One TMT'!$D23 -> 1040000 | G23: =QuarterBreakup!L$10*'JSW One TMT'!$C$52*'JSW One TMT'!$D23 -> 780000 | H23: =SUM(E23:G23) -> 2600000 | I23: =QuarterBreakup!J$16*'JSW One TMT'!$C$52*'JSW One TMT'!$D23 -> 450000 | J23: =QuarterBreakup!K$16*'JSW One TMT'!$C$52*'JSW One TMT'!$D23 -> 525000 | K23: =QuarterBreakup!L$16*'JSW One TMT'!$C$52*'JSW One TMT'!$D23 -> 525000 | L23: =I23+J23+K23 -> 1500000 | M23: =QuarterBreakup!J$22*'JSW One TMT'!$C$52*'JSW One TMT'!$D23 -> 1190000 | N23: =QuarterBreakup!K$22*'JSW One TMT'!$C$52*'JSW One TMT'!$D23 -> 1020000 | O23: =QuarterBreakup!L$22*'JSW One TMT'!$C$52*'JSW One TMT'!$D23 -> 1190000 | P23: =SUM(M23:O23) -> 3400000 | Q23: =QuarterBreakup!J$28*'JSW One TMT'!$C$52*'JSW One TMT'!$D23 -> 1000000 | R23: =QuarterBreakup!K$28*'JSW One TMT'!$C$52*'JSW One TMT'!$D23 -> 750000 | S23: =QuarterBreakup!L$28*'JSW One TMT'!$C$52*'JSW One TMT'!$D23 -> 750000 | T23: =Q23+R23+S23 -> 2500000
A24: Architect/Engineer Meets | B24: Considering every distributor does 1 meet with 70 architects @Rs 3500/pax every 6 months | C24: =B4*1*2*70*3500 -> 27440000 | D24: =C24/$C$18 -> 0.2701118 | E24: =QuarterBreakup!J$10*'JSW One TMT'!$C$52*'JSW One TMT'!$D24 -> 2140320 | F24: =QuarterBreakup!K$10*'JSW One TMT'!$C$52*'JSW One TMT'!$D24 -> 2853760 | G24: =QuarterBreakup!L$10*'JSW One TMT'!$C$52*'JSW One TMT'!$D24 -> 2140320 | H24: =SUM(E24:G24) -> 7134400 | I24: =QuarterBreakup!J$16*'JSW One TMT'!$C$52*'JSW One TMT'!$D24 -> 1234800 | J24: =QuarterBreakup!K$16*'JSW One TMT'!$C$52*'JSW One TMT'!$D24 -> 1440600 | K24: =QuarterBreakup!L$16*'JSW One TMT'!$C$52*'JSW One TMT'!$D24 -> 1440600 | L24: =I24+J24+K24 -> 4116000 | M24: =QuarterBreakup!J$22*'JSW One TMT'!$C$52*'JSW One TMT'!$D24 -> 3265360 | N24: =QuarterBreakup!K$22*'JSW One TMT'!$C$52*'JSW One TMT'!$D24 -> 2798880 | O24: =QuarterBreakup!L$22*'JSW One TMT'!$C$52*'JSW One TMT'!$D24 -> 3265360 | P24: =SUM(M24:O24) -> 9329600 | Q24: =QuarterBreakup!J$28*'JSW One TMT'!$C$52*'JSW One TMT'!$D24 -> 2744000 | R24: =QuarterBreakup!K$28*'JSW One TMT'!$C$52*'JSW One TMT'!$D24 -> 2058000 | S24: =QuarterBreakup!L$28*'JSW One TMT'!$C$52*'JSW One TMT'!$D24 -> 2058000 | T24: =Q24+R24+S24 -> 6860000
A25: Contractor Meets | B25: Considering every distributor does 2 meets with 50 contractors @Rs 1000/pax every 6 months | C25: =B4*2*2*50*1000 -> 11200000 | D25: =C25/$C$18 -> 0.11024972 | E25: =QuarterBreakup!J$10*'JSW One TMT'!$C$52*'JSW One TMT'!$D25 -> 873600 | F25: =QuarterBreakup!K$10*'JSW One TMT'!$C$52*'JSW One TMT'!$D25 -> 1164800 | G25: =QuarterBreakup!L$10*'JSW One TMT'!$C$52*'JSW One TMT'!$D25 -> 873600 | H25: =SUM(E25:G25) -> 2912000 | I25: =QuarterBreakup!J$16*'JSW One TMT'!$C$52*'JSW One TMT'!$D25 -> 504000 | J25: =QuarterBreakup!K$16*'JSW One TMT'!$C$52*'JSW One TMT'!$D25 -> 588000 | K25: =QuarterBreakup!L$16*'JSW One TMT'!$C$52*'JSW One TMT'!$D25 -> 588000 | L25: =I25+J25+K25 -> 1680000 | M25: =QuarterBreakup!J$22*'JSW One TMT'!$C$52*'JSW One TMT'!$D25 -> 1332800 | N25: =QuarterBreakup!K$22*'JSW One TMT'!$C$52*'JSW One TMT'!$D25 -> 1142400 | O25: =QuarterBreakup!L$22*'JSW One TMT'!$C$52*'JSW One TMT'!$D25 -> 1332800 | P25: =SUM(M25:O25) -> 3808000 | Q25: =QuarterBreakup!J$28*'JSW One TMT'!$C$52*'JSW One TMT'!$D25 -> 1120000 | R25: =QuarterBreakup!K$28*'JSW One TMT'!$C$52*'JSW One TMT'!$D25 -> 840000 | S25: =QuarterBreakup!L$28*'JSW One TMT'!$C$52*'JSW One TMT'!$D25 -> 840000 | T25: =Q25+R25+S25 -> 2800000
A26: Mason Meets | B26: 1 Mason meet for every transacting dealer, of 30 pax/meet Cost @ Rs 300/pax/meet | C26: =B9*1*30*300 -> 9300000 | D26: =C26/$C$18 -> 0.091546638 | E26: =QuarterBreakup!J$10*'JSW One TMT'!$C$52*'JSW One TMT'!$D26 -> 725400 | F26: =QuarterBreakup!K$10*'JSW One TMT'!$C$52*'JSW One TMT'!$D26 -> 967200 | G26: =QuarterBreakup!L$10*'JSW One TMT'!$C$52*'JSW One TMT'!$D26 -> 725400 | H26: =SUM(E26:G26) -> 2418000 | I26: =QuarterBreakup!J$16*'JSW One TMT'!$C$52*'JSW One TMT'!$D26 -> 418500 | J26: =QuarterBreakup!K$16*'JSW One TMT'!$C$52*'JSW One TMT'!$D26 -> 488250 | K26: =QuarterBreakup!L$16*'JSW One TMT'!$C$52*'JSW One TMT'!$D26 -> 488250 | L26: =I26+J26+K26 -> 1395000 | M26: =QuarterBreakup!J$22*'JSW One TMT'!$C$52*'JSW One TMT'!$D26 -> 1106700 | N26: =QuarterBreakup!K$22*'JSW One TMT'!$C$52*'JSW One TMT'!$D26 -> 948600 | O26: =QuarterBreakup!L$22*'JSW One TMT'!$C$52*'JSW One TMT'!$D26 -> 1106700 | P26: =SUM(M26:O26) -> 3162000 | Q26: =QuarterBreakup!J$28*'JSW One TMT'!$C$52*'JSW One TMT'!$D26 -> 930000 | R26: =QuarterBreakup!K$28*'JSW One TMT'!$C$52*'JSW One TMT'!$D26 -> 697500 | S26: =QuarterBreakup!L$28*'JSW One TMT'!$C$52*'JSW One TMT'!$D26 -> 697500 | T26: =Q26+R26+S26 -> 2325000
A27: Dealer Certificates | B27: To be given to all active retailers @Rs 400 | C27: =B8*400 -> 635897.44 | D27: =C27/$C$18 -> 0.0062595992 | E27: =QuarterBreakup!J$10*'JSW One TMT'!$C$52*'JSW One TMT'!$D27 -> 49600 | F27: =QuarterBreakup!K$10*'JSW One TMT'!$C$52*'JSW One TMT'!$D27 -> 66133.333 | G27: =QuarterBreakup!L$10*'JSW One TMT'!$C$52*'JSW One TMT'!$D27 -> 49600 | H27: =SUM(E27:G27) -> 165333.33 | I27: =QuarterBreakup!J$16*'JSW One TMT'!$C$52*'JSW One TMT'!$D27 -> 28615.385 | J27: =QuarterBreakup!K$16*'JSW One TMT'!$C$52*'JSW One TMT'!$D27 -> 33384.615 | K27: =QuarterBreakup!L$16*'JSW One TMT'!$C$52*'JSW One TMT'!$D27 -> 33384.615 | L27: =I27+J27+K27 -> 95384.615 | M27: =QuarterBreakup!J$22*'JSW One TMT'!$C$52*'JSW One TMT'!$D27 -> 75671.795 | N27: =QuarterBreakup!K$22*'JSW One TMT'!$C$52*'JSW One TMT'!$D27 -> 64861.538 | O27: =QuarterBreakup!L$22*'JSW One TMT'!$C$52*'JSW One TMT'!$D27 -> 75671.795 | P27: =SUM(M27:O27) -> 216205.13 | Q27: =QuarterBreakup!J$28*'JSW One TMT'!$C$52*'JSW One TMT'!$D27 -> 63589.744 | R27: =QuarterBreakup!K$28*'JSW One TMT'!$C$52*'JSW One TMT'!$D27 -> 47692.308 | S27: =QuarterBreakup!L$28*'JSW One TMT'!$C$52*'JSW One TMT'!$D27 -> 47692.308 | T27: =Q27+R27+S27 -> 158974.36
A28: Architect one-to-one visit Gifts | B28: Considering 75 architects for every distributor with gift cost @ Rs 500 | C28: =B4*75*500 -> 2100000 | D28: =C28/$C$18 -> 0.020671822 | E28: =QuarterBreakup!J$10*'JSW One TMT'!$C$52*'JSW One TMT'!$D28 -> 163800 | F28: =QuarterBreakup!K$10*'JSW One TMT'!$C$52*'JSW One TMT'!$D28 -> 218400 | G28: =QuarterBreakup!L$10*'JSW One TMT'!$C$52*'JSW One TMT'!$D28 -> 163800 | H28: =SUM(E28:G28) -> 546000 | I28: =QuarterBreakup!J$16*'JSW One TMT'!$C$52*'JSW One TMT'!$D28 -> 94500 | J28: =QuarterBreakup!K$16*'JSW One TMT'!$C$52*'JSW One TMT'!$D28 -> 110250 | K28: =QuarterBreakup!L$16*'JSW One TMT'!$C$52*'JSW One TMT'!$D28 -> 110250 | L28: =I28+J28+K28 -> 315000 | M28: =QuarterBreakup!J$22*'JSW One TMT'!$C$52*'JSW One TMT'!$D28 -> 249900 | N28: =QuarterBreakup!K$22*'JSW One TMT'!$C$52*'JSW One TMT'!$D28 -> 214200 | O28: =QuarterBreakup!L$22*'JSW One TMT'!$C$52*'JSW One TMT'!$D28 -> 249900 | P28: =SUM(M28:O28) -> 714000 | Q28: =QuarterBreakup!J$28*'JSW One TMT'!$C$52*'JSW One TMT'!$D28 -> 210000 | R28: =QuarterBreakup!K$28*'JSW One TMT'!$C$52*'JSW One TMT'!$D28 -> 157500 | S28: =QuarterBreakup!L$28*'JSW One TMT'!$C$52*'JSW One TMT'!$D28 -> 157500 | T28: =Q28+R28+S28 -> 525000
A29: Construction Site Gate Boards | B29: Assuming 5 active sites/month/priority district @Rs 1500/board (Taking 82 V.high and High priority districts) | C29: =82*5*12*1500 -> 7380000 | D29: =C29/$C$18 -> 0.072646687 | E29: =QuarterBreakup!J$10*'JSW One TMT'!$C$52*'JSW One TMT'!$D29 -> 575640 | F29: =QuarterBreakup!K$10*'JSW One TMT'!$C$52*'JSW One TMT'!$D29 -> 767520 | G29: =QuarterBreakup!L$10*'JSW One TMT'!$C$52*'JSW One TMT'!$D29 -> 575640 | H29: =SUM(E29:G29) -> 1918800 | I29: =QuarterBreakup!J$16*'JSW One TMT'!$C$52*'JSW One TMT'!$D29 -> 332100 | J29: =QuarterBreakup!K$16*'JSW One TMT'!$C$52*'JSW One TMT'!$D29 -> 387450 | K29: =QuarterBreakup!L$16*'JSW One TMT'!$C$52*'JSW One TMT'!$D29 -> 387450 | L29: =I29+J29+K29 -> 1107000 | M29: =QuarterBreakup!J$22*'JSW One TMT'!$C$52*'JSW One TMT'!$D29 -> 878220 | N29: =QuarterBreakup!K$22*'JSW One TMT'!$C$52*'JSW One TMT'!$D29 -> 752760 | O29: =QuarterBreakup!L$22*'JSW One TMT'!$C$52*'JSW One TMT'!$D29 -> 878220 | P29: =SUM(M29:O29) -> 2509200 | Q29: =QuarterBreakup!J$28*'JSW One TMT'!$C$52*'JSW One TMT'!$D29 -> 738000 | R29: =QuarterBreakup!K$28*'JSW One TMT'!$C$52*'JSW One TMT'!$D29 -> 553500 | S29: =QuarterBreakup!L$28*'JSW One TMT'!$C$52*'JSW One TMT'!$D29 -> 553500 | T29: =Q29+R29+S29 -> 1845000
A30: POP | B30: POP materials @Rs 3K to be given to every active dealer | C30: =B8*3000 -> 4769230.8 | D30: =C30/$C$18 -> 0.046946994 | E30: =QuarterBreakup!J$10*'JSW One TMT'!$C$52*'JSW One TMT'!$D30 -> 372000 | F30: =QuarterBreakup!K$10*'JSW One TMT'!$C$52*'JSW One TMT'!$D30 -> 496000 | G30: =QuarterBreakup!L$10*'JSW One TMT'!$C$52*'JSW One TMT'!$D30 -> 372000 | H30: =SUM(E30:G30) -> 1240000 | I30: =QuarterBreakup!J$16*'JSW One TMT'!$C$52*'JSW One TMT'!$D30 -> 214615.38 | J30: =QuarterBreakup!K$16*'JSW One TMT'!$C$52*'JSW One TMT'!$D30 -> 250384.62 | K30: =QuarterBreakup!L$16*'JSW One TMT'!$C$52*'JSW One TMT'!$D30 -> 250384.62 | L30: =I30+J30+K30 -> 715384.62 | M30: =QuarterBreakup!J$22*'JSW One TMT'!$C$52*'JSW One TMT'!$D30 -> 567538.46 | N30: =QuarterBreakup!K$22*'JSW One TMT'!$C$52*'JSW One TMT'!$D30 -> 486461.54 | O30: =QuarterBreakup!L$22*'JSW One TMT'!$C$52*'JSW One TMT'!$D30 -> 567538.46 | P30: =SUM(M30:O30) -> 1621538.5 | Q30: =QuarterBreakup!J$28*'JSW One TMT'!$C$52*'JSW One TMT'!$D30 -> 476923.08 | R30: =QuarterBreakup!K$28*'JSW One TMT'!$C$52*'JSW One TMT'!$D30 -> 357692.31 | S30: =QuarterBreakup!L$28*'JSW One TMT'!$C$52*'JSW One TMT'!$D30 -> 357692.31 | T30: =Q30+R30+S30 -> 1192307.7
A31: Vehicle Branding (Truck/Tempo back panels) | B31: To be done at 10% of active dealers @Rs 5k/vehicle | C31: =(B8*0.1)*5000 -> 794871.79 | D31: =C31/$C$18 -> 0.007824499 | E31: =QuarterBreakup!J$10*'JSW One TMT'!$C$52*'JSW One TMT'!$D31 -> 62000 | F31: =QuarterBreakup!K$10*'JSW One TMT'!$C$52*'JSW One TMT'!$D31 -> 82666.667 | G31: =QuarterBreakup!L$10*'JSW One TMT'!$C$52*'JSW One TMT'!$D31 -> 62000 | H31: =SUM(E31:G31) -> 206666.67 | I31: =QuarterBreakup!J$16*'JSW One TMT'!$C$52*'JSW One TMT'!$D31 -> 35769.231 | J31: =QuarterBreakup!K$16*'JSW One TMT'!$C$52*'JSW One TMT'!$D31 -> 41730.769 | K31: =QuarterBreakup!L$16*'JSW One TMT'!$C$52*'JSW One TMT'!$D31 -> 41730.769 | L31: =I31+J31+K31 -> 119230.77 | M31: =QuarterBreakup!J$22*'JSW One TMT'!$C$52*'JSW One TMT'!$D31 -> 94589.744 | N31: =QuarterBreakup!K$22*'JSW One TMT'!$C$52*'JSW One TMT'!$D31 -> 81076.923 | O31: =QuarterBreakup!L$22*'JSW One TMT'!$C$52*'JSW One TMT'!$D31 -> 94589.744 | P31: =SUM(M31:O31) -> 270256.41 | Q31: =QuarterBreakup!J$28*'JSW One TMT'!$C$52*'JSW One TMT'!$D31 -> 79487.179 | R31: =QuarterBreakup!K$28*'JSW One TMT'!$C$52*'JSW One TMT'!$D31 -> 59615.385 | S31: =QuarterBreakup!L$28*'JSW One TMT'!$C$52*'JSW One TMT'!$D31 -> 59615.385 | T31: =Q31+R31+S31 -> 198717.95
A32: Leaflets/Brochures | B32: 1000 units to be sent to all active retailers at Rs 4/pc | C32: =B8*1000*4 -> 6358974.4 | D32: =C32/$C$18 -> 0.062595992 | E32: =QuarterBreakup!J$10*'JSW One TMT'!$C$52*'JSW One TMT'!$D32 -> 496000 | F32: =QuarterBreakup!K$10*'JSW One TMT'!$C$52*'JSW One TMT'!$D32 -> 661333.33 | G32: =QuarterBreakup!L$10*'JSW One TMT'!$C$52*'JSW One TMT'!$D32 -> 496000 | H32: =SUM(E32:G32) -> 1653333.3 | I32: =QuarterBreakup!J$16*'JSW One TMT'!$C$52*'JSW One TMT'!$D32 -> 286153.85 | J32: =QuarterBreakup!K$16*'JSW One TMT'!$C$52*'JSW One TMT'!$D32 -> 333846.15 | K32: =QuarterBreakup!L$16*'JSW One TMT'!$C$52*'JSW One TMT'!$D32 -> 333846.15 | L32: =I32+J32+K32 -> 953846.15 | M32: =QuarterBreakup!J$22*'JSW One TMT'!$C$52*'JSW One TMT'!$D32 -> 756717.95 | N32: =QuarterBreakup!K$22*'JSW One TMT'!$C$52*'JSW One TMT'!$D32 -> 648615.38 | O32: =QuarterBreakup!L$22*'JSW One TMT'!$C$52*'JSW One TMT'!$D32 -> 756717.95 | P32: =SUM(M32:O32) -> 2162051.3 | Q32: =QuarterBreakup!J$28*'JSW One TMT'!$C$52*'JSW One TMT'!$D32 -> 635897.44 | R32: =QuarterBreakup!K$28*'JSW One TMT'!$C$52*'JSW One TMT'!$D32 -> 476923.08 | S32: =QuarterBreakup!L$28*'JSW One TMT'!$C$52*'JSW One TMT'!$D32 -> 476923.08 | T32: =Q32+R32+S32 -> 1589743.6
A33: Annual Diaries | B33: 3 annual diaries per active retailer@Rs250/diary | C33: =B8*3*250 -> 1192307.7 | D33: =C33/$C$18 -> 0.011736749 | H33: =SUM(E33:G33) -> 0 | L33: =I33+J33+K33 -> 0 | O33: =C33 -> 1192307.7 | P33: =SUM(M33:O33) -> 1192307.7 | T33: =Q33+R33+S33 -> 0
A34: Festival Branding gifts (Diwali, Holi) | B34: To all active dealers and active influencers (3/retailer) | C34: =(B8+B8*3)*500 -> 3179487.2 | D34: =C34/$C$18 -> 0.031297996 | H34: =SUM(E34:G34) -> 0 | L34: =I34+J34+K34 -> 0 | M34: =C34/2 -> 1589743.6 | P34: =SUM(M34:O34) -> 1589743.6 | Q34: =C34/2 -> 1589743.6 | T34: =Q34+R34+S34 -> 1589743.6
A35: Branded Tarpaulins | B35: 1 Branded Tarpaulins @ 1500/pc | C35: =B8*1500*1 -> 2384615.4 | D35: =C35/$C$18 -> 0.023473497 | E35: =QuarterBreakup!J$10*'JSW One TMT'!$C$52*'JSW One TMT'!$D35 -> 186000 | F35: =QuarterBreakup!K$10*'JSW One TMT'!$C$52*'JSW One TMT'!$D35 -> 248000 | G35: =QuarterBreakup!L$10*'JSW One TMT'!$C$52*'JSW One TMT'!$D35 -> 186000 | H35: =SUM(E35:G35) -> 620000 | I35: =QuarterBreakup!J$16*'JSW One TMT'!$C$52*'JSW One TMT'!$D35 -> 107307.69 | J35: =QuarterBreakup!K$16*'JSW One TMT'!$C$52*'JSW One TMT'!$D35 -> 125192.31 | K35: =QuarterBreakup!L$16*'JSW One TMT'!$C$52*'JSW One TMT'!$D35 -> 125192.31 | L35: =I35+J35+K35 -> 357692.31 | M35: =QuarterBreakup!J$22*'JSW One TMT'!$C$52*'JSW One TMT'!$D35 -> 283769.23 | N35: =QuarterBreakup!K$22*'JSW One TMT'!$C$52*'JSW One TMT'!$D35 -> 243230.77 | O35: =QuarterBreakup!L$22*'JSW One TMT'!$C$52*'JSW One TMT'!$D35 -> 283769.23 | P35: =SUM(M35:O35) -> 810769.23 | Q35: =QuarterBreakup!J$28*'JSW One TMT'!$C$52*'JSW One TMT'!$D35 -> 238461.54 | R35: =QuarterBreakup!K$28*'JSW One TMT'!$C$52*'JSW One TMT'!$D35 -> 178846.15 | S35: =QuarterBreakup!L$28*'JSW One TMT'!$C$52*'JSW One TMT'!$D35 -> 178846.15 | T35: =Q35+R35+S35 -> 596153.85
A36: Cutout Standees from Ads | B36: For 50% of active retailer in size 5ft X 3ft; 5mm board with stand @ 2200/pc | C36: =(B8*0.5)*2200 -> 1748717.9 | D36: =C36/$C$18 -> 0.017213898 | E36: =QuarterBreakup!J$10*'JSW One TMT'!$C$52*'JSW One TMT'!$D36 -> 136400 | F36: =QuarterBreakup!K$10*'JSW One TMT'!$C$52*'JSW One TMT'!$D36 -> 181866.67 | G36: =QuarterBreakup!L$10*'JSW One TMT'!$C$52*'JSW One TMT'!$D36 -> 136400 | H36: =SUM(E36:G36) -> 454666.67 | I36: =QuarterBreakup!J$16*'JSW One TMT'!$C$52*'JSW One TMT'!$D36 -> 78692.308 | J36: =QuarterBreakup!K$16*'JSW One TMT'!$C$52*'JSW One TMT'!$D36 -> 91807.692 | K36: =QuarterBreakup!L$16*'JSW One TMT'!$C$52*'JSW One TMT'!$D36 -> 91807.692 | L36: =I36+J36+K36 -> 262307.69 | M36: =QuarterBreakup!J$22*'JSW One TMT'!$C$52*'JSW One TMT'!$D36 -> 208097.44 | N36: =QuarterBreakup!K$22*'JSW One TMT'!$C$52*'JSW One TMT'!$D36 -> 178369.23 | O36: =QuarterBreakup!L$22*'JSW One TMT'!$C$52*'JSW One TMT'!$D36 -> 208097.44 | P36: =SUM(M36:O36) -> 594564.1 | Q36: =QuarterBreakup!J$28*'JSW One TMT'!$C$52*'JSW One TMT'!$D36 -> 174871.79 | R36: =QuarterBreakup!K$28*'JSW One TMT'!$C$52*'JSW One TMT'!$D36 -> 131153.85 | S36: =QuarterBreakup!L$28*'JSW One TMT'!$C$52*'JSW One TMT'!$D36 -> 131153.85 | T36: =Q36+R36+S36 -> 437179.49
A37: Project BTL Activities | C37: =SUM(C38:C41) -> 3625000 | E37: =SUM(E38:E41) -> 273000 | F37: =SUM(F38:F41) -> 364000 | G37: =SUM(G38:G41) -> 273000 | H37: =SUM(H38:H41) -> 910000 | I37: =SUM(I38:I41) -> 157500 | J37: =SUM(J38:J41) -> 183750 | K37: =SUM(K38:K41) -> 183750 | L37: =SUM(L38:L41) -> 525000 | ... T37: =SUM(T38:T41) -> 925000
A38: First visit to project customers | B38: 2000 customers @Rs500 | C38: =2000*500 -> 1000000 | D38: =C38/$C$37 -> 0.27586207 | E38: =$D38*$C$53*QuarterBreakup!J$10 -> 78000 | F38: =$D38*$C$53*QuarterBreakup!K$10 -> 104000 | G38: =$D38*$C$53*QuarterBreakup!L$10 -> 78000 | H38: =SUM(E38:G38) -> 260000 | I38: =$D38*$C$53*QuarterBreakup!J$16 -> 45000 | J38: =$D38*$C$53*QuarterBreakup!K$16 -> 52500 | K38: =$D38*$C$53*QuarterBreakup!L$16 -> 52500 | L38: =I38+J38+K38 -> 150000 | M38: =$D38*$C$53*QuarterBreakup!J$22 -> 119000 | N38: =$D38*$C$53*QuarterBreakup!K$22 -> 102000 | O38: =$D38*$C$53*QuarterBreakup!L$22 -> 119000 | P38: =SUM(M38:O38) -> 340000 | Q38: =$D38*$C$53*QuarterBreakup!J$28 -> 100000 | R38: =$D38*$C$53*QuarterBreakup!K$28 -> 75000 | S38: =$D38*$C$53*QuarterBreakup!L$28 -> 75000 | T38: =Q38+R38+S38 -> 250000
A39: Government Approvals | B39: 10 approvals @Rs 2.5 Lacs | C39: =10*250000 -> 2500000 | D39: =C39/$C$37 -> 0.68965517 | E39: =$D39*$C$53*QuarterBreakup!J$10 -> 195000 | F39: =$D39*$C$53*QuarterBreakup!K$10 -> 260000 | G39: =$D39*$C$53*QuarterBreakup!L$10 -> 195000 | H39: =SUM(E39:G39) -> 650000 | I39: =$D39*$C$53*QuarterBreakup!J$16 -> 112500 | J39: =$D39*$C$53*QuarterBreakup!K$16 -> 131250 | K39: =$D39*$C$53*QuarterBreakup!L$16 -> 131250 | L39: =I39+J39+K39 -> 375000 | M39: =$D39*$C$53*QuarterBreakup!J$22 -> 297500 | N39: =$D39*$C$53*QuarterBreakup!K$22 -> 255000 | O39: =$D39*$C$53*QuarterBreakup!L$22 -> 297500 | P39: =SUM(M39:O39) -> 850000 | Q39: =$D39*$C$53*QuarterBreakup!J$28 -> 250000 | R39: =$D39*$C$53*QuarterBreakup!K$28 -> 187500 | S39: =$D39*$C$53*QuarterBreakup!L$28 -> 187500 | T39: =Q39+R39+S39 -> 625000
A40: Annual Diaries | B40: 1 annual diary per active project customer @Rs250/diary - 100 customers | C40: =100*250 -> 25000 | D40: =C40/$C$37 -> 0.0068965517 | H40: =SUM(E40:G40) -> 0 | L40: =I40+J40+K40 -> 0 | O40: 25000 | P40: =SUM(M40:O40) -> 25000 | T40: =Q40+R40+S40 -> 0
A41: Festival Branding gifts (Diwali, Holi) | B41: 1 gift per active project customer @Rs500/festival - 100 customers | C41: =100*2*500 -> 100000 | D41: =C41/$C$37 -> 0.027586207 | H41: =SUM(E41:G41) -> 0 | L41: =I41+J41+K41 -> 0 | M41: 50000 | P41: =SUM(M41:O41) -> 50000 | Q41: 50000 | T41: =Q41+R41+S41 -> 50000
A42: Digital Marketing Collaterals | C42: =SUM(C43:C45) -> 9800000 | E42: =SUM(E43:E45) -> 2884000 | F42: =SUM(F43:F45) -> 2962000 | G42: =SUM(G43:G45) -> 384000 | H42: =SUM(H43:H45) -> 6230000 | I42: =SUM(I43:I45) -> 285000 | J42: =SUM(J43:J45) -> 307500 | K42: =SUM(K43:K45) -> 307500 | L42: =SUM(L43:L45) -> 900000 | ... T42: =SUM(T43:T45) -> 1200000
A43: Marketing Agencies | B43: 1.5L/month/agency | C43: =150000*12 -> 1800000 | D43: =C43/$C$42 -> 0.18367347 | E43: 150000 | F43: 150000 | G43: 150000 | H43: =SUM(E43:G43) -> 450000 | I43: 150000 | J43: 150000 | K43: 150000 | L43: =I43+J43+K43 -> 450000 | M43: 150000 | N43: 150000 | O43: 150000 | P43: =SUM(M43:O43) -> 450000 | Q43: 150000 | R43: 150000 | S43: 150000 | T43: =SUM(Q43:S43) -> 450000
A44: Product featuring video | B44: For 550D and LRF introduction | C44: 3000000 | D44: =C44/$C$42 -> 0.30612245 | E44: =$D44*$C$54*QuarterBreakup!J$10 -> 234000 | F44: =$D44*$C$54*QuarterBreakup!K$10 -> 312000 | G44: =$D44*$C$54*QuarterBreakup!L$10 -> 234000 | H44: =SUM(E44:G44) -> 780000 | I44: =$D44*$C$54*QuarterBreakup!J$16 -> 135000 | J44: =$D44*$C$54*QuarterBreakup!K$16 -> 157500 | K44: =$D44*$C$54*QuarterBreakup!L$16 -> 157500 | L44: =I44+J44+K44 -> 450000 | M44: =$D44*$C$54*QuarterBreakup!J$22 -> 357000 | N44: =$D44*$C$54*QuarterBreakup!K$22 -> 306000 | O44: =$D44*$C$54*QuarterBreakup!L$22 -> 357000 | P44: =SUM(M44:O44) -> 1020000 | Q44: =$D44*$C$54*QuarterBreakup!J$28 -> 300000 | R44: =$D44*$C$54*QuarterBreakup!K$28 -> 225000 | S44: =$D44*$C$54*QuarterBreakup!L$28 -> 225000 | T44: =SUM(Q44:S44) -> 750000
A45: Brand Film production | B45: Youtube Ad production | C45: 5000000 | D45: =C45/$C$42 -> 0.51020408 | E45: 2500000 | F45: 2500000 | H45: =SUM(E45:G45) -> 5000000 | L45: =I45+J45+K45 -> 0 | P45: =SUM(M45:O45) -> 0 | T45: =SUM(Q45:S45) -> 0
A46: Discretionary Budget | C46: =SUM(C47) -> 5000000 | E46: =SUM(E47) -> 390000 | F46: =SUM(F47) -> 520000 | G46: =SUM(G47) -> 390000 | H46: =SUM(H47) -> 1300000 | I46: =SUM(I47) -> 225000 | J46: =SUM(J47) -> 262500 | K46: =SUM(K47) -> 262500 | L46: =SUM(L47) -> 750000 | ... T46: =SUM(T47) -> 1250000
A47: Miscellaneous Budget for immediate action | C47: 5000000 | D47: =C47/$C$46 -> 1 | E47: =$D47*$C$55*QuarterBreakup!J$10 -> 390000 | F47: =$D47*$C$55*QuarterBreakup!K$10 -> 520000 | G47: =$D47*$C$55*QuarterBreakup!L$10 -> 390000 | H47: =SUM(E47:G47) -> 1300000 | I47: =$D47*$C$55*QuarterBreakup!J$16 -> 225000 | J47: =$D47*$C$55*QuarterBreakup!K$16 -> 262500 | K47: =$D47*$C$55*QuarterBreakup!L$16 -> 262500 | L47: =I47+J47+K47 -> 750000 | M47: =$D47*$C$55*QuarterBreakup!J$22 -> 595000 | N47: =$D47*$C$55*QuarterBreakup!K$22 -> 510000 | O47: =$D47*$C$55*QuarterBreakup!L$22 -> 595000 | P47: =SUM(M47:O47) -> 1700000 | Q47: =$D47*$C$55*QuarterBreakup!J$28 -> 500000 | R47: =$D47*$C$55*QuarterBreakup!K$28 -> 375000 | S47: =$D47*$C$55*QuarterBreakup!L$28 -> 375000 | T47: =SUM(Q47:S47) -> 1250000
A48: TOTALS | C48: =SUM(C11,C18,C37,C42,C46) -> 1.8055256e+08 | E48: =SUM(E11,E18,E37,E42,E46) -> 16480375 | F48: =SUM(F11,F18,F37,F42,F46) -> 21133025 | G48: =SUM(G11,G18,G37,G42,G46) -> 13603950 | H48: =SUM(H11,H18,H37,H42,H46) -> 51217350 | I48: =SUM(I11,I18,I37,I42,I46) -> 6185209.6 | J48: =SUM(J11,J18,J37,J42,J46) -> 7191077.9 | K48: =SUM(K11,K18,K37,K42,K46) -> 9035927.9 | L48: =SUM(L11,L18,L37,L42,L46) -> 22412215 | ... T48: =SUM(T11,T18,T37,T42,T46) -> 44991686
H49: =SUM(H48,L48,P48,T48) -> 1.8055256e+08
A50: Category | B50: Projected Budget | C50: % of Total Budget
A51: =A11 -> ATL Activities | B51: =C11 -> 60540000 | C51: =B51/$B$56 -> 0.33530402
A52: =A18 -> BTL Activities | B52: =C18 -> 1.0158756e+08 | C52: =B52/$B$56 -> 0.56264814
A53: =A37 -> Project BTL Activities | B53: =C37 -> 3625000 | C53: =B53/$B$56 -> 0.020077256
A54: =A42 -> Digital Marketing Collaterals | B54: =C42 -> 9800000 | C54: =B54/$B$56 -> 0.054277822
A55: =A46 -> Discretionary Budget | B55: =C46 -> 5000000 | C55: =B55/$B$56 -> 0.027692767
A56: TOTALS | B56: =SUM(B51:B55) -> 1.8055256e+08
A58: Quarter-wise Budget Breakup | B58: Projected Budget | C58: % of Total Budget
A59: Q1 | B59: =H48 -> 51217350 | C59: =B59/$B$63 -> 0.28367002
A60: Q2 | B60: =L48 -> 22412215 | C60: =B60/$B$63 -> 0.12413125
A61: Q3 | B61: =P48 -> 61931313 | C61: =B61/$B$63 -> 0.34300988
A62: Q4 | B62: =T48 -> 44991686 | C62: =B62/$B$63 -> 0.24918885
A63: TOTALS | B63: =SUM(B59:B62) -> 1.8055256e+08

Sheet QuarterBreakup
B1: One Helix | I1: JSW One TMT
B2: Quarter | C2: Q1 | D2: Q2 | E2: Q3 | F2: Q4 | G2: Total | I2: Quarter | J2: Q1 | K2: Q2 | L2: Q3 | M2: Q4 | N2: Total | Q2: Selling Price (per MT) | R2: Volumes ('000s) | S2: Revenue | T2: Budget Proposed | U2: A/S | V2: /MT cost
B3: % allocation | C3: 0.25 | D3: 0.15 | E3: 0.35 | F3: 0.25 | I3: % allocation | J3: 0.26 | K3: 0.15 | L3: 0.34 | M3: 0.25 | P3: JSW One TMT | Q3: 50000 | R3: 268 | S3: =Q3*R3*1000 -> 13400000000 | T3: ='JSW One TMT'!B56 -> 1.8055256e+08 | U3: =T3/S3 -> 0.013474072 | V3: =T3/(R3*1000) -> 673.7036
B4: Marketing costs | C4: =$G$4*C3 -> 65722404 | D4: =$G$4*D3 -> 39433442 | E4: =$G$4*E3 -> 92011365 | F4: =$G$4*F3 -> 65722404 | G4: ='One Helix'!B61 -> 2.6288962e+08 | I4: Marketing costs | J4: =J3*N4 -> 46943667 | K4: =K3*N4 -> 27082885 | L4: =L3*N4 -> 61387872 | M4: =M3*N4 -> 45138141 | N4: ='JSW One TMT'!C48 -> 1.8055256e+08 | P4: One Helix | Q4: 48868.048 | R4: 121 | S4: =Q4*R4*1000 -> 5.9130338e+09 | T4: ='One Helix'!B61 -> 2.6288962e+08 | U4: =T4/S4 -> 0.044459346 | V4: =T4/(R4*1000) -> 2172.6414
B5: Vol. (in 000s MT) | C5: 13 | D5: 11 | E5: 31 | F5: 66 | G5: 121 | I5: Vol. (in 000s MT) | J5: =M11 -> 67.995 | K5: =M17 -> 51.273 | L5: =M23 -> 64.6225 | M5: =M29 -> 84.254 | N5: =SUM(J5:M5) -> 268.1445 | P5: Total | R5: =SUM(R3:R4) -> 389 | S5: =SUM(S3:S4) -> 1.9313034e+10 | T5: =SUM(T3:T4) -> 4.4344218e+08 | U5: =T5/S5 -> 0.022960773 | V5: =T5/(R5*1000) -> 1139.9542
B6: Cost / MT | C6: =C4/(C5*1000) -> 5055.5695 | D6: =D4/(D5*1000) -> 3584.8584 | E6: =E4/(E5*1000) -> 2968.1086 | F6: =F4/(F5*1000) -> 995.794 | G6: =G4/(G5*1000) -> 2172.6414 | I6: Cost / MT | J6: =J4/(J5*1000) -> 690.3988 | K6: =K4/(K5*1000) -> 528.20948 | L6: =L4/(L5*1000) -> 949.94579 | M6: =M4/(M5*1000) -> 535.73885 | N6: =N4/(N5*1000) -> 673.34055
P7: Quarter | Q7: Q1 | R7: Q2 | S7: Q3 | T7: Q4 | U7: Total
B8: Q1 | C8: 46113 | D8: 46143 | E8: 46174 | F8: Total | I8: Q1 | J8: 46113 | K8: 46143 | L8: 46174 | M8: Total | P8: % allocation | Q8: 0.25 | R8: 0.15 | S8: 0.35 | T8: 0.25
B9: % allocation | C9: 0.3 | D9: 0.4 | E9: 0.3 | I9: % allocation | J9: 0.3 | K9: 0.4 | L9: 0.3 | P9: Marketing costs (in Cr) | Q9: 7 | R9: 3 | S9: 9 | T9: 7 | U9: =262889615.384615/10000000 -> 26.288962
B10: Marketing costs | C10: =$F$10*C9 -> 19716721 | D10: =$F$10*D9 -> 26288962 | E10: =$F$10*E9 -> 19716721 | F10: =C4 -> 65722404 | G10: =G4/(G5*1000) -> 2172.6414 | I10: Marketing costs | J10: =J9*M10 -> 14083100 | K10: =K9*M10 -> 18777467 | L10: =L9*M10 -> 14083100 | M10: =J4 -> 46943667 | P10: Vol. (in 000s MT) | Q10: 13 | R10: 11 | S10: 30.7275 | T10: 65.846 | U10: 121.4055
B11: Vol. (in 000s MT) | C11: 3.606 | D11: 4.935 | E11: 4.464 | F11: =SUM(C11:E11) -> 13.005 | I11: Vol. (in 000s MT) | J11: 19.244 | K11: 26.165 | L11: 22.586 | M11: =SUM(J11:L11) -> 67.995 | P11: Cost / MT | Q11: 5402 | R11: 3147 | S11: 2987 | T11: 992 | U11: 2172.6414
B12: Cost (in Rs./MT) | C12: =C10/(C11*1000) -> 5467.7541 | D12: =D10/(D11*1000) -> 5327.0439 | E12: =E10/(E11*1000) -> 4416.8282 | F12: =F10/(F11*1000) -> 5053.6258 | I12: Cost (in Rs./MT) | J12: =J10/(J11*1000) -> 731.81771 | K12: =K10/(K11*1000) -> 717.6559 | L12: =L10/(L11*1000) -> 623.53228 | M12: =M10/(M11*1000) -> 690.3988
P13: Quarter | Q13: Q1 | R13: Q2 | S13: Q3 | T13: Q4 | U13: Total
B14: Q2 | C14: 46204 | D14: 46235 | E14: 46266 | F14: Total | I14: Q2 | J14: 46204 | K14: 46235 | L14: 46266 | M14: Total | P14: % allocation | Q14: =Q$15/$U$15 -> 0.28454083 | R14: =R$15/$U$15 -> 0.12451231 | S14: =S$15/$U$15 -> 0.34406285 | T14: =T$15/$U$15 -> 0.24995381
B15: % allocation | C15: 0.3 | D15: 0.35 | E15: 0.35 | I15: % allocation | J15: 0.3 | K15: 0.35 | L15: 0.35 | P15: Marketing costs (in Cr) | Q15: =51217350/10000000 -> 5.121735 | R15: =22412215.3846154/10000000 -> 2.2412215 | S15: =61931312.8205128/10000000 -> 6.1931313 | T15: =44991685.8974359/10000000 -> 4.4991686 | U15: 18
B16: Marketing costs | C16: =$F$16*C15 -> 11830033 | D16: =$F$16*D15 -> 13801705 | E16: =$F$16*E15 -> 13801705 | F16: =D4 -> 39433442 | I16: Marketing costs | J16: =M16*J15 -> 8124865.4 | K16: =M16*K15 -> 9479009.6 | L16: =M16*L15 -> 9479009.6 | M16: =K4 -> 27082885 | N16: 70221731 | P16: Vol. (in 000s MT) | Q16: 68 | R16: 51 | S16: 65 | T16: 84 | U16: 268
B17: Vol. (in 000s MT) | C17: 3.774 | D17: 3.709 | E17: 4.344 | F17: =SUM(C17:E17) -> 11.827 | I17: Vol. (in 000s MT) | J17: 19.076 | K17: 15.391 | L17: 16.806 | M17: =SUM(J17:L17) -> 51.273 | N17: 34612788 | P17: Cost / MT | Q17: 753 | R17: 439 | S17: 953 | T17: 536 | U17: 674
B18: Cost (in Rs./MT) | C18: =C16/(C17*1000) -> 3134.6139 | D18: =D16/(D17*1000) -> 3721.1391 | E18: =E16/(E17*1000) -> 3177.188 | F18: =F16/(F17*1000) -> 3334.1881 | I18: Cost (in Rs./MT) | J18: =J16/(J17*1000) -> 425.92081 | K18: =K16/(K17*1000) -> 615.88003 | L18: =L16/(L17*1000) -> 564.02533 | M18: =M16/(M17*1000) -> 528.20948 | N18: 92587019
N19: 65468077
B20: Q3 | C20: 46296 | D20: 46327 | E20: 46357 | F20: Total | I20: Q3 | J20: 46296 | K20: 46327 | L20: 46357 | M20: Total | N20: =SUM(N16:N19) -> 2.6288962e+08
B21: % allocation | C21: 0.35 | D21: 0.3 | E21: 0.35 | I21: % allocation | J21: 0.35 | K21: 0.3 | L21: 0.35
B22: Marketing costs | C22: =$F$22*C21 -> 32203978 | D22: =$F$22*D21 -> 27603410 | E22: =$F$22*E21 -> 32203978 | F22: =E4 -> 92011365 | I22: Marketing costs | J22: =J21*M22 -> 21485755 | K22: =K21*M22 -> 18416362 | L22: =M22*L21 -> 21485755 | M22: =L4 -> 61387872
B23: Vol. (in 000s MT) | C23: 7.1685 | D23: 10.3825 | E23: 13.1765 | F23: =SUM(C23:E23) -> 30.7275 | I23: Vol. (in 000s MT) | J23: 19.8815 | K23: 22.7675 | L23: 21.9735 | M23: =SUM(J23:L23) -> 64.6225
B24: Cost (in Rs./MT) | C24: =C22/(C23*1000) -> 4492.4291 | D24: =D22/(D23*1000) -> 2658.6477 | E24: =E22/(E23*1000) -> 2444.0464 | F24: =F22/(F23*1000) -> 2994.4306 | I24: Cost (in Rs./MT) | J24: =J22/(J23*1000) -> 1080.6908 | K24: =K22/(K23*1000) -> 808.88818 | L24: =L22/(L23*1000) -> 977.80304 | M24: =M22/(M23*1000) -> 949.94579
B26: Q4 | C26: 46388 | D26: 46419 | E26: 46447 | F26: Total | I26: Q4 | J26: 46388 | K26: 46419 | L26: 46447 | M26: Total
B27: % allocation | C27: 0.4 | D27: 0.3 | E27: 0.3 | I27: % allocation | J27: 0.4 | K27: 0.3 | L27: 0.3
B28: Marketing costs | C28: =$F$28*C27 -> 26288962 | D28: =$F$28*D27 -> 19716721 | E28: =$F$28*E27 -> 19716721 | F28: =F4 -> 65722404 | I28: Marketing costs | J28: =J27*M28 -> 18055256 | K28: =K27*M28 -> 13541442 | L28: =L27*M28 -> 13541442 | M28: =M4 -> 45138141
B29: Vol. (in 000s MT) | C29: 17.538 | D29: 21.254 | E29: 27.054 | F29: =SUM(C29:E29) -> 65.846 | I29: Vol. (in 000s MT) | J29: 25.862 | K29: 28.146 | L29: 30.246 | M29: =SUM(J29:L29) -> 84.254
B30: Cost (in Rs./MT) | C30: =C28/(C29*1000) -> 1498.9715 | D30: =D28/(D29*1000) -> 927.67108 | E30: =E28/(E29*1000) -> 728.79135 | F30: =F28/(F29*1000) -> 998.12295 | I30: Cost (in Rs./MT) | J30: =J28/(J29*1000) -> 698.13844 | K30: =K28/(K29*1000) -> 481.11427 | L30: =L28/(L29*1000) -> 447.71019 | M30: =M28/(M29*1000) -> 535.73885

Sheet Sheet3
A1: Quarter | B1: Q1 | C1: Q2 | D1: Q3 | E1: Q4 | G1: Q1 | H1: Q2 | I1: Q3 | J1: Q4
A2: % allocation | B2: 0.3 | C2: 0.1 | D2: 0.2 | E2: 0.4 | G2: 128518055 | H2: 86749687 | I2: 102814444 | J2: 70684930 | L2: 3.8876712e+08
A3: Marketing costs (in Rs. 000s) | B3: 110332.32 | C3: 36777.44 | D3: 73554.88 | E3: 147109.76 | G3: =G2/$L$2 -> 0.33057851 | H3: =H2/$L$2 -> 0.2231405 | I3: =I2/$L$2 -> 0.26446281 | J3: =J2/$L$2 -> 0.18181818
A4: Vol. (in 000s MT) | B4: 93.138143 | C4: 97.426569 | D4: 179.27037 | E4: 270.75492
A5: Cost / MT | B5: 1184.6094 | C5: 377.48881 | D5: 410.30138 | E5: 543.33181
A7: Q1 | B7: 45748 | C7: 45778 | D7: 45809 | E7: Total
A8: % allocation | B8: 0.3 | C8: 0.4 | D8: 0.3 | E8: 1
A9: Marketing costs (in Rs. 000s) | B9: 33099.696 | C9: 44132.928 | D9: 33099.696 | E9: 110332.32
A10: Vol. (in 000s MT) | B10: 24.756783 | C10: 31.503126 | D10: 36.878233 | E10: 93.138143
A11: Cost (in Rs./MT) | B11: 1336.995 | C11: 1400.9063 | D11: 897.54019 | E11: 1184.6094
A13: Q2 | B13: 45839 | C13: 45870 | D13: 45901 | E13: Total
A14: % allocation | B14: 0.25 | C14: 0.25 | D14: 0.5 | E14: 1
A15: Marketing costs (in Rs. 000s) | B15: 9194.36 | C15: 9194.36 | D15: 18388.72 | E15: 36777.44
A16: Vol. (in 000s MT) | B16: 28.391703 | C16: 28.898823 | D16: 40.136043 | E16: 97.426569
A17: Cost (in Rs./MT) | B17: 323.83968 | C17: 318.1569 | D17: 458.15977 | E17: 377.48881
A19: Q3 | B19: 45931 | C19: 45962 | D19: 45992 | E19: Total
A20: % allocation | B20: 0.3 | C20: 0.3 | D20: 0.4 | E20: 1
A21: Marketing costs (in Rs. 000s) | B21: 22066.464 | C21: 22066.464 | D21: 29421.952 | E21: 73554.88
A22: Vol. (in 000s MT) | B22: 52.44766 | C22: 59.793315 | D22: 67.029397 | E22: 179.27037
A23: Cost (in Rs./MT) | B23: 420.73305 | C23: 369.04567 | D23: 438.94102 | E23: 410.30138
A25: Q4 | B25: 46023 | C25: 46054 | D25: 46082 | E25: Total
A26: % allocation | B26: 0.4 | C26: 0.3 | D26: 0.3 | E26: 1
A27: Marketing costs (in Rs. 000s) | B27: 58843.904 | C27: 44132.928 | D27: 44132.928 | E27: 147109.76
A28: Vol. (in 000s MT) | B28: 77.872845 | C28: 90.773824 | D28: 102.10825 | E28: 270.75492
A29: Cost (in Rs./MT) | B29: 755.64087 | C29: 486.18562 | D29: 432.21707 | E29: 543.33181
