Workbook

Sheet Minutes of Meeting
B1: Sr. No. | C1: Point of discussion | D1: Brief description of activity/Actionables | E1: Responsibilities | F1: Timelines/ Remarks
B2: 1 | C2: Supply chain design | D2: Create a supply chain design (for 1 state - Uttar Pradesh) comprising of the following - 1. Create a brand-wise distribution / supply 2. Current distributor stocking points + additional stockyards (wherever required) 3. How do we incentivice stocking - current stocking vs ship to is (38 / 62); What will be our ratio [this should differ for Western UP + Eastern, Central UP] 4. Nodal agency approvals required in the state [identification of key nodal agency bodies] 5. Wholeseller -> smaller dealers [identification of wholesellers + associated smaller dealers] | E2: Kunal, Shariq, Satyam/Ajay/Mohit | F2: 46065
B3: =B2+1 -> 2 | C3: Nodal agency approach | D3: - Designing of Nodal Agency approval process - Budget requirements + approvals - Manpower requirements - senior resource is required to handle key project customers - Credit facilities (BG/LC) - Separate deck to be shared on the work that is done + plan for FY 27 | E3: Sumit, Bhrugesh, Ashu | F3: Feb 3rd week
B4: =B3+1 -> 3 | C4: Gaurav's Market visit plan | D4: Detailed visit plan for East | E4: Mohit | F4: March 1st/2nd week
B5: =B4+1 -> 4 | C5: Channel | D5: Rework numbers (at a brand level) for UP, HR, East, RJ + revised market share in these markets [at a premium price point, non-premium price point] - Idealogy: Replace Fe550 fully with Fe550D; price of One Helix to be fixed (~INR 2,000 lower) | E5: Kunal, Mohit, Ajay Swami | F5: Feb 4th week
B6: =B5+1 -> 5 | D6: Reassess low-priority states (J&K, HP, Assam, CG) - do we want to supply to these states? If yes, what brand and at what price position? | E6: Mohit, Sumit | F6: Feb 4th week
B7: =B6+1 -> 6 | D7: One Helix launch in 3 key markets + phase-wise plan for the other states | E7: Kunal, Mohit, Sumit | F7: Feb 4th week
B8: =B7+1 -> 7 | D8: Design the MoU for FY 27 [focus should be on incentivising higher for One Helix TMT] | E8: Sumit, Mohit, Kunal | F8: Feb 4th week
B9: =B8+1 -> 8 | D9: Retailer app. - - Additional functionalities required? [to be discussed with the product team] - sales, MTD, YTD, marketing collaterals, smart nudges - to look at the current messaging functionality available with the org. - How do we use the retailer app. to engage the dealers | E9: Mohit, Kunal, Puneet, Rajeshwar | F9: Feb 3rd week
B10: =B9+1 -> 9 | D10: Distributor MoU signing [+ meeting to be set up at a central location] | E10: Mohit, Kunal, Sumit | F10: TBD
B11: =B10+1 -> 10 | C11: Influencer Engagement | D11: Create a structured program for 'ACE' [Architects, Contractors, Engineers] - Structure + initiatives need to be defined | E11: Mohit, Jagdish, Tanvi | F11: Feb 4th week
B12: =B11+1 -> 11 | D12: Rework the approach for mason meets - train the DSRs/DGOs for this | E12: Jagdish, HR | F12: TBD
B13: =B12+1 -> 12 | C13: Marketing & Branding | D13: State-level marketing plans to be developed [start with UP, HR, RJ, East] - Plan for East [with a focus on brand-awareness] - District-wise plan needs to be created [as is status today vs plan for FY 27] - Co-branded assets for One Helix TMT + JSW One TMT / evaluate co-branding between One Helix P&T and One Helix TMT [what is the overlap] - Basic branding activites [GSB/NLB, Inshop, Counter branding, POP] to be executed without special approval [auto approved] | E13: Channel team | F13: Feb 4th week
B14: =B13+1 -> 13 | C14: Kathmandu trip - communication | D14: Conduct technical knowledge sessions - Dealer meet deck + LRF (Arijit) | E14: Arijit | F14: 46065
B15: =B14+1 -> 14 | D15: Review last year lifting vs current year plan - FY'26 Performance | E15: Kunal
B16: =B15+1 -> 15 | D16: Define clear trip objectives and KPIs (Internal) - Qualifiers for FY'26, Prospects for FY'27 | E16: Kunal
B17: =B16+1 -> 16 | D17: Puneet to lead product and influencer engagement session | E17: Puneet
B18: =B17+1 -> 17 | D18: Channel Finance discussion - Kunal | E18: Kunal
B19: =B18+1 -> 18 | D19: Show nodal agency approvals and project progress - Dealer meet deck | E19: Tanvi, Mohit
B20: =B19+1 -> 19 | D20: Present branding plan | E20: Tanvi, Mohit
B21: =B20+1 -> 20 | D21: Present DGO strategy | E21: Mohit
B22: =B21+1 -> 21 | D22: Launch of One Helix Brand | E22: Mohit
B23: =B22+1 -> 22 | C23: Manpower alignment | D23: Manpower requirements were aligned in principle; Finance to come back with an accurate manpower costing | E23: Karan, Shreyas | F23: TBD
B24: =B23+1 -> 23 | C24: Vendor Management system | D24: Align vendors across One Helix and JSW One TMT; conduct best-practice meeting | E24: Somen, Tanvi | F24: TBD
B25: =B24+1 -> 24 | C25: Pipes and Tube Business | D25: Terminologies (in terms of distributor/channel performance KPIs, metrics) to be synced between P&T and TMT | E25: Deepak, Somen, Kunal | F25: Feb 2nd week

Sheet Sheet4
A2: FY 25-26 | E2: 45748 | F2: 45778 | G2: 45809 | H2: 45839 | I2: 45870 | J2: 45901 | K2: 45931 | L2: 45962 | M2: 45992 | N2: 46023 | O2: 46054 | P2: 46082 | Q2: Total
A4: Volume (in '000) | D4: 1000 | E4: 18.775 | F4: 19.409 | G4: 15.623 | H4: 18.857 | I4: 15.51 | J4: 11.637 | K4: 11.419 | L4: 18.13 | M4: 23.571 | N4: 24.402 | O4: 30 | P4: 35 | Q4: =(SUM(E4:P4)) -> 242.333
A5: Sales (in Cr) | D5: =10^7 -> 10000000 | E5: 106.14158 | F5: 108.11101 | G5: 82.482233 | H5: 90.88609 | I5: 73.704581 | J5: 55.811387 | K5: 53.346405 | L5: 82.912999 | M5: 110.14637 | N5: 121.09498 | O5: =(53000*O4*1000)/10000000 -> 159 | P5: =(52000*P4*1000)/10000000 -> 182 | Q5: =SUM(E5:P5) -> 1225.6376
A7: Margin PMT | E7: 2886 | F7: 2991 | G7: 1453 | H7: -963 | I7: -981 | J7: 93 | K7: -18 | L7: 686 | M7: 258 | N7: 1778.95 | O7: 2000 | P7: 1800 | Q7: =SUMPRODUCT(E7:P7,E4:P4)/SUM(E4:P4) -> 1185.8382
A9: Project
A10: Qty (in '000) | D10: 1000 | E10: 3.846 | F10: 5.211 | G10: 2.99 | H10: 4.793 | I10: 6.2 | J10: 3.393 | K10: 3.447 | L10: 4.738 | M10: 6.243 | N10: 7.990435 | O10: 11 | P10: 12.833333 | Q10: 72.684768
A11: CM/MT | E11: =E56 -> 2398 | F11: =F56 -> 3089 | G11: =G56 -> 1895 | H11: =H56 -> -1553 | I11: =I56 -> -1804 | J11: =J56 -> -349 | K11: =K56 -> -642 | L11: =L56 -> -215 | M11: =M56 -> -233 | N11: 551.37558 | O11: =N11 -> 551.37558 | P11: =N11 -> 551.37558 | Q11: =SUMPRODUCT(E11:P11,E10:P10)/SUM(E10:P10) -> 330.65575
A13: Retail
A14: Qty (in '000) | E14: =E4-E10 -> 14.929 | F14: =F4-F10 -> 14.198 | G14: =G4-G10 -> 12.633 | H14: =H4-H10 -> 14.064 | I14: =I4-I10 -> 9.31 | J14: =J4-J10 -> 8.244 | K14: =K4-K10 -> 7.972 | L14: =L4-L10 -> 13.392 | ... P14: =P4-P10 -> 22.166667 | Q14: =SUM(E14:P14) -> 169.64823
A15: CM/MT | E15: 3012 | F15: 2955 | G15: 1344 | H15: -757 | I15: -415 | J15: 277 | K15: 252 | L15: 1005 | M15: 436 | N15: 2376.6294 | O15: 2376.6294 | P15: 2376.6294 | Q15: 1482.7063
A17: FY 26-27 | E17: 46113 | F17: =EOMONTH(E17,0)+1 -> 46143 | G17: =EOMONTH(F17,0)+1 -> 46174 | H17: =EOMONTH(G17,0)+1 -> 46204 | I17: =EOMONTH(H17,0)+1 -> 46235 | J17: =EOMONTH(I17,0)+1 -> 46266 | K17: =EOMONTH(J17,0)+1 -> 46296 | L17: =EOMONTH(K17,0)+1 -> 46327 | M17: =EOMONTH(L17,0)+1 -> 46357 | ... P17: =EOMONTH(O17,0)+1 -> 46447 | Q17: Total
A18: ='P&L-month wise (One TMT)'!A3 -> Volume (in '000 MT)
A19: Retail
A20: 550D | E20: 9.725 | F20: 13.28 | G20: 11.58 | H20: 9.725 | I20: 8.135 | J20: 9.075 | K20: 11.58 | L20: 14.145 | M20: 15.07 | N20: 18.615 | O20: 21.17 | P20: 24.595 | Q20: 166.695
A21: 550 | E21: 9.519 | F21: 12.885 | G21: 11.006 | H21: 9.351 | I21: 7.256 | J21: 7.731 | K21: 8.3015 | L21: 8.6225 | M21: 6.9035 | N21: 7.247 | O21: 6.976 | P21: 5.651 | Q21: 101.4495
A22: Sub-Total | E22: =SUM(E20:E21) -> 19.244 | F22: =SUM(F20:F21) -> 26.165 | G22: =SUM(G20:G21) -> 22.586 | H22: =SUM(H20:H21) -> 19.076 | I22: =SUM(I20:I21) -> 15.391 | J22: =SUM(J20:J21) -> 16.806 | K22: =SUM(K20:K21) -> 19.8815 | L22: =SUM(L20:L21) -> 22.7675 | ... Q22: =SUM(Q20:Q21) -> 268.1445
A24: Project
A25: 550D | E25: 11.025 | F25: 12.94 | G25: 12.675 | H25: 10.195 | I25: 9.915 | J25: 10.045 | K25: 11.225 | L25: 12.755 | M25: 15.285 | N25: 18.3 | O25: 21.7 | P25: 25.325 | Q25: 171.385
A26: 550 | E26: 4.475 | F26: 4.91 | G26: 5.225 | H26: 5.055 | I26: 5.185 | J26: 5.855 | K26: 7.25 | L26: 8.095 | M26: 9.015 | N26: 10.1 | O26: 11.55 | P26: 13.075 | Q26: 89.79
A27: Sub-Total | E27: =SUM(E25:E26) -> 15.5 | F27: =SUM(F25:F26) -> 17.85 | G27: =SUM(G25:G26) -> 17.9 | H27: =SUM(H25:H26) -> 15.25 | I27: =SUM(I25:I26) -> 15.1 | J27: =SUM(J25:J26) -> 15.9 | K27: =SUM(K25:K26) -> 18.475 | L27: =SUM(L25:L26) -> 20.85 | ... Q27: =SUM(Q25:Q26) -> 261.175
A29: JSW One Qty | E29: =SUM(E25:E26,E20:E21) -> 34.744 | F29: =SUM(F25:F26,F20:F21) -> 44.015 | G29: =SUM(G25:G26,G20:G21) -> 40.486 | H29: =SUM(H25:H26,H20:H21) -> 34.326 | I29: =SUM(I25:I26,I20:I21) -> 30.491 | J29: =SUM(J25:J26,J20:J21) -> 32.706 | K29: =SUM(K25:K26,K20:K21) -> 38.3565 | L29: =SUM(L25:L26,L20:L21) -> 43.6175 | ... Q29: =SUM(Q25:Q26,Q20:Q21) -> 529.3195
A31: One Helix 550 | E31: 3.606 | F31: 4.935 | G31: 4.464 | H31: 3.774 | I31: 3.709 | J31: 4.344 | K31: 7.1685 | L31: 10.3825 | M31: 13.1765 | N31: 17.538 | O31: 21.254 | P31: 27.054 | Q31: 121.4055
A33: Overall Qty | E33: =SUM(E29,E31) -> 38.35 | F33: =SUM(F29,F31) -> 48.95 | G33: =SUM(G29,G31) -> 44.95 | H33: =SUM(H29,H31) -> 38.1 | I33: =SUM(I29,I31) -> 34.2 | J33: =SUM(J29,J31) -> 37.05 | K33: =SUM(K29,K31) -> 45.525 | L33: =SUM(L29,L31) -> 54 | ... Q33: =SUM(Q29,Q31) -> 650.725
A37: Retail- Margin
A38: =A20 -> 550D | D38: 1000 | E38: =E39-$D$38 -> 500 | F38: =F39-$D$38 -> 500 | G38: =G39-$D$38 -> 500 | H38: 150 | I38: 150 | J38: 150 | K38: =K39-$D$38 -> 500 | L38: =L39-$D$38 -> 500 | M38: =M39-$D$38 -> 750 | N38: =N39-$D$38 -> 1000 | O38: =O39-$D$38 -> 1250 | P38: =P39-$D$38 -> 1500 | Q38: =SUMPRODUCT(E38:P38,E20:P20)/Q20 -> 764.6765
A39: =A21 -> 550 | E39: 1500 | F39: 1500 | G39: 1500 | H39: 1000 | I39: 1000 | J39: 1000 | K39: 1500 | L39: 1500 | M39: 1750 | N39: 2000 | O39: 2250 | P39: 2500 | Q39: =SUMPRODUCT(E39:P39,E21:P21)/Q21 -> 1540.0532
A40: Total | E40: =((E38*E20)+(E39*E21))/E22 -> 994.64768 | F40: =((F38*F20)+(F39*F21))/F22 -> 992.45175 | G40: =((G38*G20)+(G39*G21))/G22 -> 987.29301 | H40: =((H38*H20)+(H39*H21))/H22 -> 566.66754 | I40: =((I38*I20)+(I39*I21))/I22 -> 550.7277 | J40: =((J38*J20)+(J39*J21))/J22 -> 541.01214 | K40: =((K38*K20)+(K39*K21))/K22 -> 917.54898 | L40: =((L38*L20)+(L39*L21))/L22 -> 878.71967 | ... Q40: =((Q38*Q20)+(Q39*Q21))/Q22 -> 1058.0317
A42: Project-Margin
A43: =A25 -> 550D | D43: 500 | E43: 100 | F43: 100 | G43: 100 | H43: 100 | I43: 100 | J43: 100 | K43: 100 | L43: 150 | M43: 200 | N43: 250 | O43: 300 | P43: 400 | Q43: =SUMPRODUCT(E43:P43,E25:P25)/Q25 -> 198.30936
A44: =A26 -> 550 | E44: =E39-$D$43 -> 1000 | F44: =F39-$D$43 -> 1000 | G44: =G39-$D$43 -> 1000 | H44: =H39-$D$43 -> 500 | I44: =I39-$D$43 -> 500 | J44: =J39-$D$43 -> 500 | K44: =K39-$D$43 -> 1000 | L44: =L39-$D$43 -> 1000 | ... P44: =P39-$D$43 -> 2000 | Q44: =SUMPRODUCT(E44:P44,E26:P26)/Q26 -> 1233.8094
A45: Total | E45: =((E43*E25)+(E44*E26))/E27 -> 359.83871 | F45: =((F43*F25)+(F44*F26))/F27 -> 347.56303 | G45: =((G43*G25)+(G44*G26))/G27 -> 362.7095 | H45: =((H43*H25)+(H44*H26))/H27 -> 232.59016 | I45: =((I43*I25)+(I44*I26))/I27 -> 237.35099 | J45: =((J43*J25)+(J44*J26))/J27 -> 247.2956 | K45: =((K43*K25)+(K44*K26))/K27 -> 453.17997 | L45: =((L43*L25)+(L44*L26))/L27 -> 480.01199 | ... Q45: =((Q43*Q25)+(Q44*Q26))/Q27 -> 554.3065
A47: JSW One margin | E47: =((E40*E22)+(E45*E27))/SUM(E22,E27) -> 711.44658 | F47: =((F40*F22)+(F45*F27))/SUM(F22,F27) -> 730.92128 | G47: =((G40*G22)+(G45*G27))/SUM(G22,G27) -> 711.14706 | H47: =((H40*H22)+(H45*H27))/SUM(H22,H27) -> 418.2471 | I47: =((I40*I22)+(I45*I27))/SUM(I22,I27) -> 395.53475 | J47: =((J40*J22)+(J45*J27))/SUM(J22,J27) -> 398.22204 | K47: =((K40*K22)+(K45*K27))/SUM(K22,K27) -> 693.87848 | L47: =((L40*L22)+(L45*L27))/SUM(L22,L27) -> 688.12976 | ... Q47: =((Q40*Q22)+(Q45*Q27))/SUM(Q22,Q27) -> 809.48534
A49: One Helix | D49: 750 | E49: =E39-$D$49 -> 750 | F49: =F39-$D$49 -> 750 | G49: 650 | H49: =H39-$D$49 -> 250 | I49: =I39-$D$49 -> 250 | J49: =J39-$D$49 -> 250 | K49: 400 | L49: 500 | M49: 700 | N49: 900 | O49: 900 | P49: 1150 | Q49: =SUMPRODUCT(E49:P49,E31:P31)/Q31 -> 787.20651
A51: Overall margin | E51: =((E47*E29)+(E49*E31))/E33 -> 715.07171 | F51: =((F47*F29)+(F49*F31))/F33 -> 732.84474 | G51: =((G47*G29)+(G49*G31))/G33 -> 705.07453 | H51: =((H47*H29)+(H49*H31))/H33 -> 401.58136 | I51: =((I47*I29)+(I49*I31))/I33 -> 379.75146 | J51: =((J47*J29)+(J49*J31))/J33 -> 380.84345 | K51: =((K47*K29)+(K49*K31))/K33 -> 647.60351 | L51: =((L47*L29)+(L49*L31))/L33 -> 651.95833 | ... Q51: =((Q47*Q29)+(Q49*Q31))/Q33 -> 805.32879
B54: FY25-26 | C54: Projects | D54: Unit | E54: April'25 | F54: May'25 | G54: June'25 | H54: July'25 | I54: Aug'25 | J54: Sep'25 | K54: Oct'25 | L54: Nov’25 | M54: Dec'25 | N54: Jan'26 | O54: Feb'26 | P54: Mar'26 | Q54: Overall
C55: Sales quantity | D55: MT (in '000) | E55: =E10 -> 3.846 | F55: =F10 -> 5.211 | G55: =G10 -> 2.99 | H55: =H10 -> 4.793 | I55: =I10 -> 6.2 | J55: =J10 -> 3.393 | K55: =K10 -> 3.447 | L55: =L10 -> 4.738 | ... Q55: =Q10 -> 72.684768
C56: CM/MT | D56: INR | E56: 2398 | F56: 3089 | G56: 1895 | H56: -1553 | I56: -1804 | J56: -349 | K56: -642 | L56: -215 | M56: -233 | N56: =N11 -> 551.37558 | O56: =O11 -> 551.37558 | P56: =P11 -> 551.37558 | Q56: =Q11 -> 330.65575
C59: Retail | D59: Metric | E59: April'25 | F59: May'25 | G59: June'25 | H59: July'25 | I59: Aug'25 | J59: Sep'25 | K59: Oct'25 | L59: Nov’25 | M59: Dec'25 | N59: Jan'26 | O59: Feb'26 | P59: Mar'26 | Q59: Overall
C60: Sales quantity | D60: MT (in '000) | E60: =E14 -> 14.929 | F60: =F14 -> 14.198 | G60: =G14 -> 12.633 | H60: =H14 -> 14.064 | I60: =I14 -> 9.31 | J60: =J14 -> 8.244 | K60: =K14 -> 7.972 | L60: =L14 -> 13.392 | ... P60: =P14 -> 22.166667 | Q60: 169.64823
C61: CM/MT | D61: INR | E61: =E15 -> 3012 | F61: =F15 -> 2955 | G61: =G15 -> 1344 | H61: =H15 -> -757 | I61: =I15 -> -415 | J61: =J15 -> 277 | K61: =K15 -> 252 | L61: =L15 -> 1005 | ... Q61: =Q15 -> 1482.7063
C64: Overall | D64: Metric | E64: April'25 | F64: May'25 | G64: June'25 | H64: July'25 | I64: Aug'25 | J64: Sep'25 | K64: Oct'25 | L64: Nov’25 | M64: Dec'25 | N64: Jan'26 | O64: Feb'26 | P64: Mar'26 | Q64: Overall
C65: Sales quantity | D65: MT (in '000) | E65: =SUM(E55,E60) -> 18.775 | F65: =SUM(F55,F60) -> 19.409 | G65: =SUM(G55,G60) -> 15.623 | H65: =SUM(H55,H60) -> 18.857 | I65: =SUM(I55,I60) -> 15.51 | J65: =SUM(J55,J60) -> 11.637 | K65: =SUM(K55,K60) -> 11.419 | L65: =SUM(L55,L60) -> 18.13 | ... Q65: =SUM(Q55,Q60) -> 242.333
C66: CM/MT | D66: INR | E66: =((E55*E56)+(E60*E61))/E65 -> 2886.224 | F66: =((F55*F56)+(F60*F61))/F65 -> 2990.9768 | G66: =((G55*G56)+(G60*G61))/G65 -> 1449.4529 | H66: =((H55*H56)+(H60*H61))/H65 -> -959.32423 | I66: =((I55*I56)+(I60*I61))/I65 -> -970.24178 | J66: =((J55*J56)+(J60*J61))/J65 -> 94.477185 | K66: =((K55*K56)+(K60*K61))/K65 -> -17.867589 | L66: =((L55*L56)+(L60*L61))/L65 -> 686.17154 | ... Q66: =((Q55*Q56)+(Q60*Q61))/Q65 -> 1137.1631
B69: FY 26-27 | C69: Projects | D69: Unit | E69: =E17 -> 46113 | F69: =F17 -> 46143 | G69: =G17 -> 46174 | H69: =H17 -> 46204 | I69: =I17 -> 46235 | J69: =J17 -> 46266 | K69: =K17 -> 46296 | L69: =L17 -> 46327 | ... P69: =P17 -> 46447 | Q69: Overall
C70: Sales quantity | D70: MT (in '000) | E70: =E27 -> 15.5 | F70: =F27 -> 17.85 | G70: =G27 -> 17.9 | H70: =H27 -> 15.25 | I70: =I27 -> 15.1 | J70: =J27 -> 15.9 | K70: =K27 -> 18.475 | L70: =L27 -> 20.85 | ... Q70: =Q27 -> 261.175
C71: CM/MT | D71: INR | E71: =E45 -> 359.83871 | F71: =F45 -> 347.56303 | G71: =G45 -> 362.7095 | H71: =H45 -> 232.59016 | I71: =I45 -> 237.35099 | J71: =J45 -> 247.2956 | K71: =K45 -> 453.17997 | L71: =L45 -> 480.01199 | ... Q71: =Q45 -> 554.3065
C73: Retail | D73: Unit | E73: =E69 -> 46113 | F73: =F69 -> 46143 | G73: =G69 -> 46174 | H73: =H69 -> 46204 | I73: =I69 -> 46235 | J73: =J69 -> 46266 | K73: =K69 -> 46296 | L73: =L69 -> 46327 | ... Q73: =Q69 -> Overall
C74: Sales quantity | D74: MT (in '000) | E74: =E22 -> 19.244 | F74: =F22 -> 26.165 | G74: =G22 -> 22.586 | H74: =H22 -> 19.076 | I74: =I22 -> 15.391 | J74: =J22 -> 16.806 | K74: =K22 -> 19.8815 | L74: =L22 -> 22.7675 | ... Q74: =Q22 -> 268.1445
C75: CM/MT | D75: INR | E75: =E40 -> 994.64768 | F75: =F40 -> 992.45175 | G75: =G40 -> 987.29301 | H75: =H40 -> 566.66754 | I75: =I40 -> 550.7277 | J75: =J40 -> 541.01214 | K75: =K40 -> 917.54898 | L75: =L40 -> 878.71967 | ... Q75: =Q40 -> 1058.0317
C77: Overall-JSW one TMT | D77: Unit | E77: =E73 -> 46113 | F77: =F73 -> 46143 | G77: =G73 -> 46174 | H77: =H73 -> 46204 | I77: =I73 -> 46235 | J77: =J73 -> 46266 | K77: =K73 -> 46296 | L77: =L73 -> 46327 | ... Q77: =Q73 -> Overall
C78: Sales quantity | D78: MT (in '000) | E78: =E29 -> 34.744 | F78: =F29 -> 44.015 | G78: =G29 -> 40.486 | H78: =H29 -> 34.326 | I78: =I29 -> 30.491 | J78: =J29 -> 32.706 | K78: =K29 -> 38.3565 | L78: =L29 -> 43.6175 | ... Q78: =Q29 -> 529.3195
C79: CM/MT | D79: INR | E79: =E47 -> 711.44658 | F79: =F47 -> 730.92128 | G79: =G47 -> 711.14706 | H79: =H47 -> 418.2471 | I79: =I47 -> 395.53475 | J79: =J47 -> 398.22204 | K79: =K47 -> 693.87848 | L79: =L47 -> 688.12976 | ... Q79: =Q47 -> 809.48534
C81: One Helix TMT | D81: Unit | E81: =E77 -> 46113 | F81: =F77 -> 46143 | G81: =G77 -> 46174 | H81: =H77 -> 46204 | I81: =I77 -> 46235 | J81: =J77 -> 46266 | K81: =K77 -> 46296 | L81: =L77 -> 46327 | ... Q81: =Q77 -> Overall
C82: Sales quantity | D82: MT (in '000) | E82: =E31 -> 3.606 | F82: =F31 -> 4.935 | G82: =G31 -> 4.464 | H82: =H31 -> 3.774 | I82: =I31 -> 3.709 | J82: =J31 -> 4.344 | K82: =K31 -> 7.1685 | L82: =L31 -> 10.3825 | ... Q82: =Q31 -> 121.4055
C83: CM/MT | D83: INR | E83: =E49 -> 750 | F83: =F49 -> 750 | G83: =G49 -> 650 | H83: =H49 -> 250 | I83: =I49 -> 250 | J83: =J49 -> 250 | K83: =K49 -> 400 | L83: =L49 -> 500 | ... Q83: =Q49 -> 787.20651
C85: Overall TMT | D85: Unit | E85: =E81 -> 46113 | F85: =F81 -> 46143 | G85: =G81 -> 46174 | H85: =H81 -> 46204 | I85: =I81 -> 46235 | J85: =J81 -> 46266 | K85: =K81 -> 46296 | L85: =L81 -> 46327 | ... Q85: =Q81 -> Overall
C86: Sales quantity | D86: MT (in '000) | E86: =E33 -> 38.35 | F86: =F33 -> 48.95 | G86: =G33 -> 44.95 | H86: =H33 -> 38.1 | I86: =I33 -> 34.2 | J86: =J33 -> 37.05 | K86: =K33 -> 45.525 | L86: =L33 -> 54 | ... Q86: =Q33 -> 650.725
C87: CM/MT | D87: INR | E87: =E51 -> 715.07171 | F87: =F51 -> 732.84474 | G87: =G51 -> 705.07453 | H87: =H51 -> 401.58136 | I87: =I51 -> 379.75146 | J87: =J51 -> 380.84345 | K87: =K51 -> 647.60351 | L87: =L51 -> 651.95833 | ... Q87: =Q51 -> 805.32879

Sheet Jan Actuals-P&L-Output
A1: Project/retail | B1: (All)
A2: Grade | B2: (All)
B4: CM Name 2
A5: Values | B5: Aditya | C5: AIC | D5: Amba Shakti | E5: Amba Shakti Udyog | F5: API | G5: German Steel | H5: Real Ispat | I5: SKA | J5: Grand Total | K5: 30th jan
A6: Quantity | B6: 1372.31 | C6: 781.06 | D6: 8521.71 | E6: 4848.6 | F6: 2110.075 | G6: 143.7 | H6: 1847.63 | I6: 4897.21 | J6: 24522.295
A7: Sales incl. freight | B7: 72910820 | C7: 40532696 | D7: 4.4995443e+08 | E7: 250196486 | F7: 1.0517513e+08 | G7: 7433269 | H7: 92475554 | I7: 2.4499577e+08 | J7: 1.2636742e+09 | K7: 51531.643
A8: Purchase price ex-works | B8: 63492030 | C8: 34059605 | D8: 3.9654529e+08 | E8: 2.2913632e+08 | F8: 85640427 | G8: 6441566 | H8: 83622115 | I8: 2.1117413e+08 | J8: 1.1101115e+09 | K8: 45269.477
A9: Price Difference-Purchase | B9: 882316.74 | C9: 795876.74 | D9: 13238614 | E9: 7297997 | F9: 1632902.1 | G9: 84052.86 | H9: 3144166.1 | I9: 6196892.3 | J9: 33272817 | K9: 1356.8395
A10: 3PL cost (actual/estimated as per JOTS team) | B10: 2155254.5 | C10: 1528126.2 | D10: 13323373 | E10: 8277810.9 | F10: 5345181.9 | G10: 215550 | H10: 4736534.9 | I10: 9324396.5 | J10: 44906228 | K10: 1831.2408 | L10: =K7-K8-K9-K10 -> 3074.0856
A11: Gross margin | B11: 6381217.8 | C11: 4149088.3 | D11: 26839073 | E11: 5484360.6 | F11: 6942914.6 | G11: 692100.14 | H11: 1065735.3 | I11: 17186193 | J11: 68740683 | K11: 2803.1913
A12: MOU | B12: 745248 | C12: 386316 | D12: 4480908 | E12: 1302762 | F12: 943980 | G12: 45702 | H12: 309900 | I12: 1704300 | J12: 9919116 | K12: 404.49379
A13: SFDC | B13: 62104 | C13: 32193 | D13: 373409 | E13: 108563.5 | F13: 78665 | G13: 3808.5 | H13: 25825 | I13: 142025 | J13: 826593 | K13: 33.707816
A14: Price difference-Sales | B14: 0 | C14: 0 | D14: 0 | E14: 0 | F14: 0 | G14: 0 | H14: 0 | I14: 0 | J14: 0 | K14: 0
A15: Service charges | B15: 748628.69 | C15: 426087.35 | D15: 4648801.4 | E15: 2645030 | F15: 1151097.6 | G15: 78391.867 | H15: 1007927.4 | I15: 2671547.9 | J15: 13377512 | K15: 545.52448
A16: Price support | K16: 0
A17: QD from CM | B17: 0 | C17: 0 | D17: 2982598.5 | E17: 1697010 | F17: 0 | G17: 0 | H17: 0 | I17: 1469163 | J17: 6148771.5 | K17: 250.74209
A18: Contribution margin | B18: 4825237.1 | C18: 3304492 | D18: 14353356 | E18: -269004.88 | F18: 4769172.1 | G18: 564197.77 | H18: -277917.1 | I18: 11199157 | J18: 38468690 | K18: =J18/J6 -> 1568.7231
A24: Project/retail | B24: Retail
A25: Grade | B25: (All)
B27: CM Name 2
A28: Values | B28: Aditya | C28: AIC | D28: Amba Shakti | E28: Amba Shakti Udyog | F28: API | G28: German Steel | H28: Real Ispat | I28: SKA | J28: Grand Total
A29: Quantity | B29: 1242.08 | C29: 643.86 | D29: 7468.18 | E29: 2171.27 | F29: 1573.3 | G29: 76.17 | H29: 516.5 | I29: 2840.5 | J29: 16531.86
A30: Sales incl. freight | B30: 65792146 | C30: 33246604 | D30: 3.9454903e+08 | E30: 1.1648246e+08 | F30: 79166330 | G30: 3917943 | H30: 26997568 | I30: 1.439419e+08 | J30: 8.6409399e+08 | K30: 52268.407
A31: Purchase price ex-works | B31: 57378603 | C31: 27922731 | D31: 3.4748121e+08 | E31: 103245970 | F31: 67626255 | G31: 3362652 | H31: 23130306 | I31: 1.2226357e+08 | J31: 7.5241129e+08 | K31: 45512.803
A32: Price Difference-Purchase | B32: 810704.31 | C32: 678707.94 | D32: 11677509 | E32: 3356546.1 | F32: 1193145.4 | G32: 65369.4 | H32: 976163.56 | I32: 3772619.3 | J32: 22530765 | K32: 1362.8693
A33: 3PL cost (actual/estimated as per JOTS team) | B33: 1959909.5 | C33: 1279530.8 | D33: 11671189 | E33: 3784411.8 | F33: 4288494.6 | G33: 114255 | H33: 1464286.1 | I33: 6305653 | J33: 30867730 | K33: 1867.1662
A34: Gross margin | B34: 5642929.7 | C34: 3365634 | D34: 23719121 | E34: 6095534.6 | F34: 6001054.7 | G34: 375666.6 | H34: 1420709.1 | I34: 11432510 | J34: 58053160 | K34: 3511.5928
A35: MOU | B35: 745248 | C35: 386316 | D35: 4480908 | E35: 1302762 | F35: 943980 | G35: 45702 | H35: 309900 | I35: 1704300 | J35: 9919116 | K35: 600
A36: SFDC | B36: 62104 | C36: 32193 | D36: 373409 | E36: 108563.5 | F36: 78665 | G36: 3808.5 | H36: 25825 | I36: 142025 | J36: 826593 | K36: 50
A37: Price difference-Sales | B37: 0 | C37: 0 | D37: 0 | E37: 0 | F37: 0 | G37: 0 | H37: 0 | I37: 0 | J37: 0 | K37: 0
A38: Service charges | B38: 677585.04 | C38: 351241.39 | D38: 4074075 | E38: 1184480.9 | F38: 858273.66 | G38: 41552.599 | H38: 281763.39 | I38: 1549562.3 | J38: 9018534.3 | K38: 545.52448
A39: Price support | K39: 0
A40: QD from CM | B40: 0 | C40: 0 | D40: 2613863 | E40: 759944.5 | F40: 0 | G40: 0 | H40: 0 | I40: 852150 | J40: 4225957.5 | K40: 255.62505
A41: Contribution margin | B41: 4157992.7 | C41: 2595883.6 | D41: 12176866 | E41: 2739783.7 | F41: 4120136.1 | G41: 284603.5 | H41: 803220.75 | I41: 7184473.1 | J41: 34062960 | K41: =J41/J29 -> 2060.4433
A45: Project/retail | B45: Retail
A46: Grade | B46: 550
B48: CM Name 2
A49: Values | B49: Aditya | C49: AIC | D49: Amba Shakti | E49: Amba Shakti Udyog | F49: API | G49: SKA | H49: Grand Total
A50: Quantity | B50: 1206.49 | C50: 643.86 | D50: 7468.18 | E50: 39.8 | F50: 1481.79 | G50: 2830.82 | H50: 13670.94
A51: Sales incl. freight | B51: 63866728 | C51: 33246604 | D51: 3.9454903e+08 | E51: 1942240 | F51: 74454155 | G51: 1.4345645e+08 | H51: 7.1151521e+08 | I51: 52045.815
A52: Purchase price ex-works | B52: 55751752 | C52: 27922731 | D52: 3.4748121e+08 | E52: 1882540 | F52: 63828666 | G52: 1.2186247e+08 | H52: 6.1872937e+08 | I52: 45258.729
A53: Price Difference-Purchase | B53: 801122.66 | C53: 678707.94 | D53: 11677509 | E53: -14686.2 | F53: 1265255.3 | G53: 3770097.3 | H53: 18178006 | I53: 1329.6822
A54: 3PL cost (actual/estimated as per JOTS team) | B54: 1906524.5 | C54: 1279530.8 | D54: 11671189 | E54: 62884 | F54: 4037940.6 | G54: 6276613 | H54: 25234682 | I54: 1845.863
A55: Gross margin | B55: 5407328.8 | C55: 3365634 | D55: 23719121 | E55: 11502.2 | F55: 5264912.5 | G55: 11379714 | H55: 49148213 | I55: 3595.0866
A56: MOU | B56: 723894 | C56: 386316 | D56: 4480908 | E56: 23880 | F56: 889074 | G56: 1698492 | H56: 8202564 | I56: 600
A57: SFDC | B57: 60324.5 | C57: 32193 | D57: 373409 | E57: 1990 | F57: 74089.5 | G57: 141541 | H57: 683547 | I57: 50
A58: Price difference-Sales | B58: 0 | C58: 0 | D58: 0 | E58: 0 | F58: 0 | G58: 0 | H58: 0 | I58: 0
A59: Service charges | B59: 658169.82 | C59: 351241.39 | D59: 4074075 | E59: 21711.874 | F59: 808352.71 | G59: 1544281.6 | H59: 7457832.4 | I59: 545.52448
A60: Price support | I60: 0
A61: QD from CM | B61: 0 | C61: 0 | D61: 2613863 | E61: 13930 | F61: 0 | G61: 849246 | H61: 3477039 | I61: 254.33796
A62: Contribution margin | B62: 3964940.5 | C62: 2595883.6 | D62: 12176866 | E62: -50009.674 | F62: 3493396.3 | G62: 7146153.8 | H62: 29327231 | I62: 2145.2242
A66: Project/retail | B66: Retail
A67: Grade | B67: 550D
B69: CM Name 2
A70: Values | B70: Aditya | C70: Amba Shakti Udyog | D70: API | E70: German Steel | F70: Real Ispat | G70: SKA | H70: Grand Total
A71: Quantity | B71: 35.59 | C71: 2131.47 | D71: 91.51 | E71: 76.17 | F71: 516.5 | G71: 9.68 | H71: 2860.92
A72: Sales incl. freight | B72: 1925419 | C72: 1.1454022e+08 | D72: 4712175.5 | E72: 3917943 | F72: 26997568 | G72: 485452 | H72: 1.5257878e+08
A73: Purchase price ex-works | B73: 1626851.5 | C73: 101363430 | D73: 3797589.1 | E73: 3362652 | F73: 23130306 | G73: 401094 | H73: 1.3368192e+08
A74: Price Difference-Purchase | B74: 9581.65 | C74: 3371232.3 | D74: -72109.88 | E74: 65369.4 | F74: 976163.56 | G74: 2522.02 | H74: 4352759.1
A75: 3PL cost (actual/estimated as per JOTS team) | B75: 53385 | C75: 3721527.8 | D75: 250554 | E75: 114255 | F75: 1464286.1 | G75: 29040 | H75: 5633047.9 | I75: 1968.9638
A76: Gross margin | B76: 235600.85 | C76: 6084032.4 | D76: 736142.23 | E76: 375666.6 | F76: 1420709.1 | G76: 52795.98 | H76: 8904947.2
A77: MOU | B77: 21354 | C77: 1278882 | D77: 54906 | E77: 45702 | F77: 309900 | G77: 5808 | H77: 1716552
A78: SFDC | B78: 1779.5 | C78: 106573.5 | D78: 4575.5 | E78: 3808.5 | F78: 25825 | G78: 484 | H78: 143046
A79: Price difference-Sales | B79: 0 | C79: 0 | D79: 0 | E79: 0 | F79: 0 | G79: 0 | H79: 0
A80: Service charges | B80: 19415.216 | C80: 1162769.1 | D80: 49920.945 | E80: 41552.599 | F80: 281763.39 | G80: 5280.6769 | H80: 1560701.9
A81: Price support
A82: QD from CM | B82: 0 | C82: 746014.5 | D82: 0 | E82: 0 | F82: 0 | G82: 2904 | H82: 748918.5
A83: Contribution margin | B83: 193052.13 | C83: 2789793.4 | D83: 626739.79 | E83: 284603.5 | F83: 803220.75 | G83: 38319.303 | H83: 4735728.8
A87: Project/retail | B87: Project
A88: Grade | B88: (All)
B90: CM Name 2
A91: Values | B91: Aditya | C91: AIC | D91: Amba Shakti | E91: Amba Shakti Udyog | F91: API | G91: German Steel | H91: Real Ispat | I91: SKA | J91: Grand Total
A92: Quantity | B92: 130.23 | C92: 137.2 | D92: 1053.53 | E92: 2677.33 | F92: 536.775 | G92: 67.53 | H92: 1331.13 | I92: 2056.71 | J92: 7990.435
A93: Sales incl. freight | B93: 7118673 | C93: 7286092.5 | D93: 55405401 | E93: 1.3371402e+08 | F93: 26008796 | G93: 3515326 | H93: 65477987 | I93: 101053869 | J93: 3.9958017e+08
A94: Purchase price ex-works | B94: 6113427.5 | C94: 6136874 | D94: 49064080 | E94: 1.2589035e+08 | F94: 18014172 | G94: 3078914 | H94: 60491809 | I94: 88910558 | J94: 3.5770018e+08
A95: Price Difference-Purchase | B95: 71612.43 | C95: 117168.8 | D95: 1561105 | E95: 3941450.9 | F95: 439756.71 | G95: 18683.46 | H95: 2168002.5 | I95: 2424272.9 | J95: 10742053
A96: 3PL cost (actual/estimated as per JOTS team) | B96: 195345 | C96: 248595.4 | D96: 1652183.8 | E96: 4493399.1 | F96: 1056687.3 | G96: 101295 | H96: 3272248.8 | I96: 3018743.5 | J96: 14038498
A97: Gross margin | B97: 738288.07 | C97: 783454.3 | D97: 3119952.1 | E97: -611174.02 | F97: 941859.93 | G97: 316433.54 | H97: -354973.85 | I97: 5753682.5 | J97: 10687523
A98: MOU | B98: 0 | C98: 0 | D98: 0 | E98: 0 | F98: 0 | G98: 0 | H98: 0 | I98: 0 | J98: 0
A99: SFDC | B99: 0 | C99: 0 | D99: 0 | E99: 0 | F99: 0 | G99: 0 | H99: 0 | I99: 0 | J99: 0
A100: Price difference-Sales | B100: 0 | C100: 0 | D100: 0 | E100: 0 | F100: 0 | G100: 0 | H100: 0 | I100: 0 | J100: 0
A101: Service charges | B101: 71043.652 | C101: 74845.958 | D101: 574726.4 | E101: 1460549 | F101: 292823.9 | G101: 36839.268 | H101: 726164 | I101: 1121985.6 | J101: 4358977.9
A102: Price support
A103: QD from CM | B103: 0 | C103: 0 | D103: 368735.5 | E103: 937065.5 | F103: 0 | G103: 0 | H103: 0 | I103: 617013 | J103: 1922814
A104: Contribution margin | B104: 667244.42 | C104: 708608.34 | D104: 2176490.2 | E104: -3008788.6 | F104: 649036.03 | G104: 279594.27 | H104: -1081137.8 | I104: 4014683.9 | J104: 4405730.7 | K104: =J104/J92 -> 551.37558
A108: Project/retail | B108: Project
A109: Grade | B109: 550
B111: CM Name 2
A112: Values | B112: Aditya | C112: AIC | D112: Amba Shakti | E112: API | F112: SKA | G112: Grand Total
A113: Quantity | B113: 89.23 | C113: 137.2 | D113: 988.37 | E113: 536.775 | F113: 1561.99 | G113: 3313.565
A114: Sales incl. freight | B114: 4866523 | C114: 7286092.5 | D114: 52191710 | E114: 26008796 | F114: 76839395 | G114: 1.6719252e+08 | J114: 0
A115: Purchase price ex-works | B115: 4189737.5 | C115: 6136874 | D115: 45936400 | E115: 18014172 | F115: 66620852 | G115: 1.4089804e+08 | J115: 0
A116: Price Difference-Purchase | B116: 49269.81 | C116: 117168.8 | D116: 1561105 | E116: 439756.71 | F116: 2001998.7 | G116: 4169299 | J116: 0
A117: 3PL cost (actual/estimated as per JOTS team) | B117: 133845 | C117: 248595.4 | D117: 1554443.8 | E117: 1056687.3 | F117: 2657248.5 | G117: 5650819.9 | J117: 0
A118: Gross margin | B118: 493670.69 | C118: 783454.3 | D118: 3131680.9 | E118: 941859.93 | F118: 4612683.8 | G118: 9963349.6 | J118: 0
A119: MOU | B119: 0 | C119: 0 | D119: 0 | E119: 0 | F119: 0 | G119: 0 | J119: 0
A120: SFDC | B120: 0 | C120: 0 | D120: 0 | E120: 0 | F120: 0 | G120: 0 | J120: 0
A121: Price difference-Sales | B121: 0 | C121: 0 | D121: 0 | E121: 0 | F121: 0 | G121: 0 | J121: 0
A122: Service charges | B122: 48677.149 | C122: 74845.958 | D122: 539180.03 | E122: 292823.9 | F122: 852103.78 | G122: 1807630.8 | J122: 0
A123: Price support | J123: 0
...

Sheet P&L-month wise (One TMT)
A2: Particulars | B2: =Summary!B3 -> 46113 | C2: =Summary!C3 -> 46143 | D2: =Summary!D3 -> 46174 | E2: =Summary!E3 -> 46204 | F2: =Summary!F3 -> 46235 | G2: =Summary!G3 -> 46266 | H2: =Summary!H3 -> 46296 | I2: =Summary!I3 -> 46327 | ... N2: =Summary!N3 -> Total
A3: Volume (in '000 MT)
A4: =Summary!A17 -> JSW One TMT (Fe550D) | B4: =Summary!B17 -> 20.61 | C4: =Summary!C17 -> 26.105 | D4: =Summary!D17 -> 24.11 | E4: =Summary!E17 -> 19.78 | F4: =Summary!F17 -> 17.885 | G4: =Summary!G17 -> 18.975 | H4: =Summary!H17 -> 22.66 | ... M4: =Summary!M17 -> 49.48 | N4: =SUM(B4:M4) -> 335.365
A5: =Summary!A18 -> JSW One TMT (Fe550) | B5: =Summary!B18 -> 13.849 | C5: =Summary!C18 -> 17.401 | D5: =Summary!D18 -> 15.988 | E5: =Summary!E18 -> 14.169 | F5: =Summary!F18 -> 12.408 | G5: =Summary!G18 -> 13.4325 | H5: =Summary!H18 -> 15.339 | ... M5: =Summary!M18 -> 16.166 | N5: =SUM(B5:M5) -> 182.337
A6: Total | B6: =B4+B5 -> 34.459 | C6: =C4+C5 -> 43.506 | D6: =D4+D5 -> 40.098 | E6: =E4+E5 -> 33.949 | F6: =F4+F5 -> 30.293 | G6: =G4+G5 -> 32.4075 | H6: =H4+H5 -> 37.999 | I6: =I4+I5 -> 42.9565 | ... M6: =M4+M5 -> 65.646 | N6: =SUM(B6:M6) -> 517.702
A8: Retail | B8: =Summary!B24+Summary!B25 -> 18.959 | C8: =Summary!C24+Summary!C25 -> 25.656 | D8: =Summary!D24+Summary!D25 -> 22.198 | E8: =Summary!E24+Summary!E25 -> 18.699 | F8: =Summary!F24+Summary!F25 -> 15.193 | G8: =Summary!G24+Summary!G25 -> 16.5075 | H8: =Summary!H24+Summary!H25 -> 19.524 | I8: =Summary!I24+Summary!I25 -> 22.1065 | ... M8: =Summary!M24+Summary!M25 -> 27.246 | N8: =SUM(B8:M8) -> 256.527
A9: Projects-PB | B9: =B6-B8-B10 -> 11.9 | C9: =C6-C8-C10 -> 13.6 | D9: =D6-D8-D10 -> 13.2 | E9: =E6-E8-E10 -> 10.3 | F9: =F6-F8-F10 -> 9.4 | G9: =G6-G8-G10 -> 9 | H9: =H6-H8-H10 -> 10.7 | I9: =I6-I8-I10 -> 12.5 | ... M9: =M6-M8-M10 -> 27.7 | N9: =(SUM(B9:M9)) -> 175.5
A10: Projects-Distributor | B10: =(Distributor_projects!I3)/1000 -> 3.6 | C10: =(Distributor_projects!J3)/1000 -> 4.25 | D10: =(Distributor_projects!K3)/1000 -> 4.7 | E10: =(Distributor_projects!L3)/1000 -> 4.95 | F10: =(Distributor_projects!M3)/1000 -> 5.7 | G10: =(Distributor_projects!N3)/1000 -> 6.9 | H10: =(Distributor_projects!O3)/1000 -> 7.775 | I10: =(Distributor_projects!P3)/1000 -> 8.35 | ... M10: =(Distributor_projects!T3)/1000 -> 10.7 | N10: =(SUM(B10:M10)) -> 85.675
A11: Total | B11: =SUM(B8:B10) -> 34.459 | C11: =SUM(C8:C10) -> 43.506 | D11: =SUM(D8:D10) -> 40.098 | E11: =SUM(E8:E10) -> 33.949 | F11: =SUM(F8:F10) -> 30.293 | G11: =SUM(G8:G10) -> 32.4075 | H11: =SUM(H8:H10) -> 37.999 | I11: =SUM(I8:I10) -> 42.9565 | ... N11: =SUM(N8:N10) -> 517.702
A13: GM | B13: ='Wt average prices'!E46 -> 1692.6012 | C13: ='Wt average prices'!F46 -> 1752.2224 | D13: ='Wt average prices'!G46 -> 1179.3977 | E13: ='Wt average prices'!H46 -> 530.95335 | F13: ='Wt average prices'!I46 -> -356.79175 | G13: ='Wt average prices'!J46 -> 553.51293 | H13: ='Wt average prices'!K46 -> 2612.8332 | I13: ='Wt average prices'!L46 -> 2569.5425 | ... N13: ='Wt average prices'!Q46 -> 1309.0396
A14: Less: MOU | B14: ='MOu calculation'!B10 -> 330.11405 | C14: ='MOu calculation'!C10 -> 353.82706 | D14: ='MOu calculation'!D10 -> 332.15622 | E14: ='MOu calculation'!E10 -> 330.47807 | F14: ='MOu calculation'!F10 -> 300.921 | G14: ='MOu calculation'!G10 -> 305.6237 | H14: ='MOu calculation'!H10 -> 308.2818 | I14: ='MOu calculation'!I10 -> 308.77516 | ... N14: ='MOu calculation'!N10 -> 297.30656
A15: Less: Project Management Fees | B15: ='MOu calculation'!B14 -> 500 | C15: ='MOu calculation'!C14 -> 500 | D15: ='MOu calculation'!D14 -> 500 | E15: ='MOu calculation'!E14 -> 500 | F15: ='MOu calculation'!F14 -> 500 | G15: ='MOu calculation'!G14 -> 500 | H15: ='MOu calculation'!H14 -> 500 | I15: ='MOu calculation'!I14 -> 500 | ... N15: ='MOu calculation'!N14 -> 500
A16: Add: QD from CM | B16: =_xlfn.XLOOKUP(B2,'QD from CM'!$F$50:$R$50,'QD from CM'!$F$64:$R$64,"Not found",0) -> 171.91808 | C16: =_xlfn.XLOOKUP(C2,'QD from CM'!$F$50:$R$50,'QD from CM'!$F$64:$R$64,"Not found",0) -> 174.32165 | D16: =_xlfn.XLOOKUP(D2,'QD from CM'!$F$50:$R$50,'QD from CM'!$F$64:$R$64,"Not found",0) -> 177.21824 | E16: =_xlfn.XLOOKUP(E2,'QD from CM'!$F$50:$R$50,'QD from CM'!$F$64:$R$64,"Not found",0) -> 166.92397 | F16: =_xlfn.XLOOKUP(F2,'QD from CM'!$F$50:$R$50,'QD from CM'!$F$64:$R$64,"Not found",0) -> 159.26783 | G16: =_xlfn.XLOOKUP(G2,'QD from CM'!$F$50:$R$50,'QD from CM'!$F$64:$R$64,"Not found",0) -> 167.8372 | H16: =_xlfn.XLOOKUP(H2,'QD from CM'!$F$50:$R$50,'QD from CM'!$F$64:$R$64,"Not found",0) -> 175.18044 | I16: =_xlfn.XLOOKUP(I2,'QD from CM'!$F$50:$R$50,'QD from CM'!$F$64:$R$64,"Not found",0) -> 175.7855 | ... N16: =_xlfn.XLOOKUP(N2,'QD from CM'!$F$50:$R$50,'QD from CM'!$F$64:$R$64,"Not found",0) -> 179.72822
A17: CM1 | B17: =B13-B14-B15+B16 -> 1034.4052 | C17: =C13-C14-C15+C16 -> 1072.717 | D17: =D13-D14-D15+D16 -> 524.45968 | E17: =E13-E14-E15+E16 -> -132.60075 | F17: =F13-F14-F15+F16 -> -998.44492 | G17: =G13-G14-G15+G16 -> -84.273572 | H17: =H13-H14-H15+H16 -> 1979.7318 | I17: =I13-I14-I15+I16 -> 1936.5528 | ... N17: =N13-N14-N15+N16 -> 691.46123 | O17: =N17*N11*1000 -> 3.5797086e+08
A28: Marketing cost
A30: Manpower cost
A31: ESOP
A32: Others
A34: Admin cost
A35: Rent
A36: Travel
A37: Others
A39: Interest on Working Capital
A41: CM2

Sheet MOu calculation
A1: ='P&L-month wise (One TMT)'!A14 -> Less: MOU | B1: ='P&L-month wise (One TMT)'!B2 -> 46113 | C1: ='P&L-month wise (One TMT)'!C2 -> 46143 | D1: ='P&L-month wise (One TMT)'!D2 -> 46174 | E1: ='P&L-month wise (One TMT)'!E2 -> 46204 | F1: ='P&L-month wise (One TMT)'!F2 -> 46235 | G1: ='P&L-month wise (One TMT)'!G2 -> 46266 | H1: ='P&L-month wise (One TMT)'!H2 -> 46296 | I1: ='P&L-month wise (One TMT)'!I2 -> 46327 | ... N1: ='P&L-month wise (One TMT)'!N2 -> Total
A2: ='P&L-month wise (One TMT)'!A8 -> Retail | B2: ='P&L-month wise (One TMT)'!B8 -> 18.959 | C2: ='P&L-month wise (One TMT)'!C8 -> 25.656 | D2: ='P&L-month wise (One TMT)'!D8 -> 22.198 | E2: ='P&L-month wise (One TMT)'!E8 -> 18.699 | F2: ='P&L-month wise (One TMT)'!F8 -> 15.193 | G2: ='P&L-month wise (One TMT)'!G8 -> 16.5075 | H2: ='P&L-month wise (One TMT)'!H8 -> 19.524 | ... N2: ='P&L-month wise (One TMT)'!N8 -> 256.527
A3: ='P&L-month wise (One TMT)'!A9 -> Projects-PB | B3: ='P&L-month wise (One TMT)'!B9 -> 11.9 | C3: ='P&L-month wise (One TMT)'!C9 -> 13.6 | D3: ='P&L-month wise (One TMT)'!D9 -> 13.2 | E3: ='P&L-month wise (One TMT)'!E9 -> 10.3 | F3: ='P&L-month wise (One TMT)'!F9 -> 9.4 | G3: ='P&L-month wise (One TMT)'!G9 -> 9 | H3: ='P&L-month wise (One TMT)'!H9 -> 10.7 | ... N3: ='P&L-month wise (One TMT)'!N9 -> 175.5
A4: ='P&L-month wise (One TMT)'!A10 -> Projects-Distributor | B4: ='P&L-month wise (One TMT)'!B10 -> 3.6 | C4: ='P&L-month wise (One TMT)'!C10 -> 4.25 | D4: ='P&L-month wise (One TMT)'!D10 -> 4.7 | E4: ='P&L-month wise (One TMT)'!E10 -> 4.95 | F4: ='P&L-month wise (One TMT)'!F10 -> 5.7 | G4: ='P&L-month wise (One TMT)'!G10 -> 6.9 | H4: ='P&L-month wise (One TMT)'!H10 -> 7.775 | ... N4: ='P&L-month wise (One TMT)'!N10 -> 85.675
A5: ='P&L-month wise (One TMT)'!A11 -> Total | B5: ='P&L-month wise (One TMT)'!B11 -> 34.459 | C5: ='P&L-month wise (One TMT)'!C11 -> 43.506 | D5: ='P&L-month wise (One TMT)'!D11 -> 40.098 | E5: ='P&L-month wise (One TMT)'!E11 -> 33.949 | F5: ='P&L-month wise (One TMT)'!F11 -> 30.293 | G5: ='P&L-month wise (One TMT)'!G11 -> 32.4075 | H5: ='P&L-month wise (One TMT)'!H11 -> 37.999 | ... N5: ='P&L-month wise (One TMT)'!N11 -> 517.702
A7: MOU PMT | B7: 600 | C7: 600 | D7: 600 | E7: 600 | F7: 600 | G7: 600 | H7: 600 | I7: 600 | J7: 600 | K7: 600 | L7: 600 | M7: 600 | N7: 600
A8: Retail | B8: =B2 -> 18.959 | C8: =C2 -> 25.656 | D8: =D2 -> 22.198 | E8: =E2 -> 18.699 | F8: =F2 -> 15.193 | G8: =G2 -> 16.5075 | H8: =H2 -> 19.524 | I8: =I2 -> 22.1065 | ... N8: =N2 -> 256.527
A10: Average MOU PMT | B10: =(B7*B8)/B5 -> 330.11405 | C10: =(C7*C8)/C5 -> 353.82706 | D10: =(D7*D8)/D5 -> 332.15622 | E10: =(E7*E8)/E5 -> 330.47807 | F10: =(F7*F8)/F5 -> 300.921 | G10: =(G7*G8)/G5 -> 305.6237 | H10: =(H7*H8)/H5 -> 308.2818 | I10: =(I7*I8)/I5 -> 308.77516 | ... N10: =(N7*N8)/N5 -> 297.30656
A13: ='P&L-month wise (One TMT)'!A15 -> Less: Project Management Fees | B13: =B1 -> 46113 | C13: =C1 -> 46143 | D13: =D1 -> 46174 | E13: =E1 -> 46204 | F13: =F1 -> 46235 | G13: =G1 -> 46266 | H13: =H1 -> 46296 | I13: =I1 -> 46327 | ... N13: =N1 -> Total
A14: PMT | B14: 500 | C14: 500 | D14: 500 | E14: 500 | F14: 500 | G14: 500 | H14: 500 | I14: 500 | J14: 500 | K14: 500 | L14: 500 | M14: 500 | N14: 500

Sheet Steelmint prices for last 36m
A1: Grade | B1: CM | C1: BIS | D1: Loading | E1: Price
A2: 550 | B2: AIC IRON INDUSTRIES PRIVATE LIMITED | C2: 2700 | D2: 270 | E2: =SUM(C2:D2) -> 2970
A3: 550 | B3: Aditya Industries | C3: 400 | D3: 250 | E3: =SUM(C3:D3) -> 650
A4: 550 | B4: Ambashakti Industries Limited | C4: 1200 | D4: 200 | E4: =SUM(C4:D4) -> 1400
A5: 550 | B5: AMBASHAKTI UDYOG LIMITED- GWALIOR | C5: 1200 | D5: 200 | E5: =SUM(C5:D5) -> 1400
A6: 550 | B6: API Ispat And Powertech Private Limited | C6: 2150 | D6: 265 | E6: =SUM(C6:D6) -> 2415
A7: 550 | B7: GERMAN GREEN STEEL AND POWER LIMITED | C7: 0 | D7: 200 | E7: =SUM(C7:D7) -> 200
A8: 550 | B8: SKA Ispat Private Limited | C8: 1800 | D8: 275 | E8: =SUM(C8:D8) -> 2075
A9: 550 | B9: Real Ispat | C9: 0 | D9: 0 | E9: =SUM(C9:D9) -> 0
A10: 550 | B10: Rashmi Steel | C10: =C$6 -> 2150 | D10: =D$6 -> 265 | E10: =SUM(C10:D10) -> 2415
A11: 550 | B11: Telangana - New Plant | C11: =C$6 -> 2150 | D11: =D$6 -> 265 | E11: =SUM(C11:D11) -> 2415
A12: 550 | B12: Maharashtra - New Plant | C12: =C$6 -> 2150 | D12: =D$6 -> 265 | E12: =SUM(C12:D12) -> 2415
A14: 550D | B14: =B2 -> AIC IRON INDUSTRIES PRIVATE LIMITED | C14: 3500 | D14: 270 | E14: =SUM(C14:D14) -> 3770
A15: 550D | B15: =B3 -> Aditya Industries | C15: 1200 | D15: 250 | E15: =SUM(C15:D15) -> 1450
A16: 550D | B16: =B4 -> Ambashakti Industries Limited | C16: 2200 | D16: 200 | E16: =SUM(C16:D16) -> 2400
A17: 550D | B17: =B5 -> AMBASHAKTI UDYOG LIMITED- GWALIOR | C17: 3200 | D17: 200 | E17: =SUM(C17:D17) -> 3400
A18: 550D | B18: =B6 -> API Ispat And Powertech Private Limited | C18: 3400 | D18: 265 | E18: =SUM(C18:D18) -> 3665
A19: 550D | B19: =B7 -> GERMAN GREEN STEEL AND POWER LIMITED | C19: 1000 | D19: 200 | E19: =SUM(C19:D19) -> 1200
A20: 550D | B20: =B8 -> SKA Ispat Private Limited | C20: 2800 | D20: 275 | E20: =SUM(C20:D20) -> 3075
A21: 550D | B21: =B9 -> Real Ispat | C21: 4500 | D21: 0 | E21: =SUM(C21:D21) -> 4500
A22: 550D | B22: =B10 -> Rashmi Steel | C22: =C$18 -> 3400 | D22: =D$18 -> 265 | E22: =SUM(C22:D22) -> 3665
A23: 550D | B23: =B11 -> Telangana - New Plant | C23: =C$18 -> 3400 | D23: =D$18 -> 265 | E23: =SUM(C23:D23) -> 3665
A24: 550D | B24: =B12 -> Maharashtra - New Plant | C24: =C$18 -> 3400 | D24: =D$18 -> 265 | E24: =SUM(C24:D24) -> 3665
A27: Loading charges
A28: BIS charges
A29: Month | B29: Delhi/NCR | C29: Mumbai | D29: Ahmedabad | E29: Mandi Gobindgarh | F29: Raipur | G29: Hyderabad | H29: Jaipur | I29: Muzaffarnagar | J29: Rourkela | K29: Patna | L29: Durgapur | M29: Hyderabad | N29: Mumbai
A30: 44927 | B30: 55332 | C30: 57116 | D30: 55917 | E30: 54444 | F30: 51764 | G30: 53640 | H30: 55016 | I30: 53688 | J30: 51416 | K30: 52864 | L30: 51684 | M30: 53640 | N30: 57116
A31: 44958 | B31: 53392 | C31: 56917 | D31: 54363 | E31: 53383 | F31: 50621 | G31: 53538 | H31: 53571 | I31: 51567 | J31: 50325 | K31: 51746 | L31: 50171 | M31: 45418 | N31: 48700
A32: 44986 | B32: 52668 | C32: 55933 | D32: 53088 | E32: 53744 | F32: 50280 | G32: 53424 | H32: 52900 | I32: 51736 | J32: 50192 | K32: 52048 | L32: 50658 | M32: 44084.615 | N32: 47074.074
A33: 45017 | B33: 52452 | C33: 54880 | D33: 53652 | E33: 53312 | F33: 50264 | G33: 53428 | H33: 52924 | I33: 51208 | J33: 50320 | K33: 52164 | L33: 50872 | M33: 45320 | N33: 49228.571
A34: 45047 | B34: 51519 | C34: 53326 | D34: 51763 | E34: 52215 | F34: 47793 | G34: 50870 | H34: 51352 | I34: 50411 | J34: 48181 | K34: 49926 | L34: 48033 | M34: 53537.5 | N34: 56916.667
A35: 45078 | B35: 51015 | C35: 50796 | D35: 50946 | E35: 52158 | F35: 47215 | G35: 48577 | H35: 50804 | I35: 50069 | J35: 47065 | K35: 48546 | L35: 46988 | M35: 44772 | N35: 48240
A36: 45108 | B36: 48396 | C36: 46969 | D36: 47708 | E36: 49835 | F36: 43969 | G36: 46308 | H36: 47812 | I36: 47777 | J36: 44408 | K36: 45912 | L36: 44127 | M36: 44708.333 | N36: 47945.833
A37: 45139 | B37: 48576 | C37: 48860 | D37: 49020 | E37: 50444 | F37: 45616 | G37: 47732 | H37: 48820 | I37: 47876 | J37: 45984 | K37: 46916 | L37: 45404 | M37: 53424 | N37: 55933.333
A38: 45170 | B38: 50477 | C38: 51988 | D38: 51312 | E38: 51558 | F38: 47365 | G38: 51260 | H38: 50204 | I38: 49788 | J38: 48050 | K38: 48596 | L38: 47250 | M38: 46089.583 | N38: 49250
A39: 45200 | B39: 48190 | C39: 50800 | D39: 49613 | E39: 49638 | F39: 45904 | G39: 49656 | H39: 47854 | I39: 47296 | J39: 45870 | K39: 46758 | L39: 45391 | M39: 46425 | N39: 49358.333
A40: 45231 | B40: 46992 | C40: 49044 | D40: 48239 | E40: 48340 | F40: 44276 | G40: 47500 | H40: 46700 | I40: 46060 | J40: 44248 | K40: 45757 | L40: 44036 | M40: 53428 | N40: 54880
A41: 45261 | B41: 46604 | C41: 48748 | D41: 47900 | E41: 47860 | F41: 43520 | G41: 46740 | H41: 46080 | I41: 45844 | J41: 43548 | K41: 44800 | L41: 43388 | M41: 48511.538 | N41: 50542.308
... A66: 46023 | B66: 47364 | C66: 49229 | D66: 49471 | E66: 48045 | F66: 43773 | G66: 45320 | H66: 46086 | I66: 46600 | J66: 43350 | K66: 47068 | L66: 42839 | M66: 41861.538 | N66: 44965.385
A67: 46054 | B67: =AVERAGE(B31,B43,B55) -> 48629.333 | C67: =AVERAGE(C31,C43,C55) -> 51034.333 | D67: =AVERAGE(D31,D43,D55) -> 49680 | E67: =AVERAGE(E31,E43,E55) -> 49142.333 | F67: =AVERAGE(F31,F43,F55) -> 45303 | G67: =AVERAGE(G31,G43,G55) -> 47672.667 | H67: =AVERAGE(H31,H43,H55) -> 47973 | I67: =AVERAGE(I31,I43,I55) -> 47379 | ... L67: =AVERAGE(L31,L43,L55) -> 45317.333
A68: 46082 | B68: =AVERAGE(B32,B44,B56) -> 48786.667 | C68: =AVERAGE(C32,C44,C56) -> 51513.667 | D68: =AVERAGE(D32,D44,D56) -> 49568.333 | E68: =AVERAGE(E32,E44,E56) -> 49507.667 | F68: =AVERAGE(F32,F44,F56) -> 45976.667 | G68: =AVERAGE(G32,G44,G56) -> 48646.333 | H68: =AVERAGE(H32,H44,H56) -> 48143 | I68: =AVERAGE(I32,I44,I56) -> 47609.333 | ... L68: =AVERAGE(L32,L44,L56) -> 46069.333
A69: 46113 | B69: =AVERAGE(B33,B45,B57) -> 50440.333 | C69: =AVERAGE(C33,C45,C57) -> 51608.667 | D69: =AVERAGE(D33,D45,D57) -> 50322.333 | E69: =AVERAGE(E33,E45,E57) -> 50924.333 | F69: =AVERAGE(F33,F45,F57) -> 47358.333 | G69: =AVERAGE(G33,G45,G57) -> 49673.667 | H69: =AVERAGE(H33,H45,H57) -> 49831 | I69: =AVERAGE(I33,I45,I57) -> 49349 | ... L69: =AVERAGE(L33,L45,L57) -> 47844.333
A70: 46143 | B70: =AVERAGE(B34,B46,B58) -> 49797.667 | C70: =AVERAGE(C34,C46,C58) -> 51348 | D70: =AVERAGE(D34,D46,D58) -> 49913.667 | E70: =AVERAGE(E34,E46,E58) -> 50534.667 | F70: =AVERAGE(F34,F46,F58) -> 46368 | G70: =AVERAGE(G34,G46,G58) -> 48756 | H70: =AVERAGE(H34,H46,H58) -> 49196.333 | I70: =AVERAGE(I34,I46,I58) -> 48800 | ... L70: =AVERAGE(L34,L46,L58) -> 46166.667
A71: 46174 | B71: =AVERAGE(B35,B47,B59) -> 48637 | C71: =AVERAGE(C35,C47,C59) -> 48694.667 | D71: =AVERAGE(D35,D47,D59) -> 48520.667 | E71: =AVERAGE(E35,E47,E59) -> 49712.333 | F71: =AVERAGE(F35,F47,F59) -> 44909 | G71: =AVERAGE(G35,G47,G59) -> 46797.667 | H71: =AVERAGE(H35,H47,H59) -> 47833.333 | I71: =AVERAGE(I35,I47,I59) -> 47621.667 | ... L71: =AVERAGE(L35,L47,L59) -> 44392
A72: 46204 | B72: =AVERAGE(B36,B48,B60) -> 46497.333 | C72: =AVERAGE(C36,C48,C60) -> 45745.333 | D72: =AVERAGE(D36,D48,D60) -> 45967 | E72: =AVERAGE(E36,E48,E60) -> 47798 | F72: =AVERAGE(F36,F48,F60) -> 42005.667 | G72: =AVERAGE(G36,G48,G60) -> 45036 | H72: =AVERAGE(H36,H48,H60) -> 45457.667 | I72: =AVERAGE(I36,I48,I60) -> 45733 | ... L72: =AVERAGE(L36,L48,L60) -> 42156
A73: 46235 | B73: =AVERAGE(B37,B49,B61) -> 45973 | C73: =AVERAGE(C37,C49,C61) -> 46515.333 | D73: =AVERAGE(D37,D49,D61) -> 46257.333 | E73: =AVERAGE(E37,E49,E61) -> 47495.667 | F73: =AVERAGE(F37,F49,F61) -> 42310 | G73: =AVERAGE(G37,G49,G61) -> 44642.333 | H73: =AVERAGE(H37,H49,H61) -> 45341 | I73: =AVERAGE(I37,I49,I61) -> 44985.333 | ... L73: =AVERAGE(L37,L49,L61) -> 42114.333
A74: 46266 | B74: =AVERAGE(B38,B50,B62) -> 45928.667 | C74: =AVERAGE(C38,C50,C62) -> 47287.333 | D74: =AVERAGE(D38,D50,D62) -> 46615.333 | E74: =AVERAGE(E38,E50,E62) -> 47359.667 | F74: =AVERAGE(F38,F50,F62) -> 42985.667 | G74: =AVERAGE(G38,G50,G62) -> 45460.667 | H74: =AVERAGE(H38,H50,H62) -> 45449.333 | I74: =AVERAGE(I38,I50,I62) -> 44999.667 | ... L74: =AVERAGE(L38,L50,L62) -> 42390
A75: 46296 | B75: =AVERAGE(B39,B51,B63) -> 45753 | C75: =AVERAGE(C39,C51,C63) -> 47096.333 | D75: =AVERAGE(D39,D51,D63) -> 46281.333 | E75: =AVERAGE(E39,E51,E63) -> 47096.333 | F75: =AVERAGE(F39,F51,F63) -> 42769.333 | G75: =AVERAGE(G39,G51,G63) -> 45104 | H75: =AVERAGE(H39,H51,H63) -> 44949.333 | I75: =AVERAGE(I39,I51,I63) -> 44745 | ... L75: =AVERAGE(L39,L51,L63) -> 42379
A76: 46327 | B76: =AVERAGE(B40,B52,B64) -> 44874 | C76: =AVERAGE(C40,C52,C64) -> 46410.333 | D76: =AVERAGE(D40,D52,D64) -> 45582.667 | E76: =AVERAGE(E40,E52,E64) -> 46326 | F76: =AVERAGE(F40,F52,F64) -> 41708 | G76: =AVERAGE(G40,G52,G64) -> 44154 | H76: =AVERAGE(H40,H52,H64) -> 44186.333 | I76: =AVERAGE(I40,I52,I64) -> 43912 | ... L76: =AVERAGE(L40,L52,L64) -> 41367.667
A77: 46357 | B77: =AVERAGE(B41,B53,B65) -> 45096.667 | C77: =AVERAGE(C41,C53,C65) -> 46869.667 | D77: =AVERAGE(D41,D53,D65) -> 46748.333 | E77: =AVERAGE(E41,E53,E65) -> 46570 | F77: =AVERAGE(F41,F53,F65) -> 41851.667 | G77: =AVERAGE(G41,G53,G65) -> 44268.667 | H77: =AVERAGE(H41,H53,H65) -> 44530 | I77: =AVERAGE(I41,I53,I65) -> 44238.667 | ... L77: =AVERAGE(L41,L53,L65) -> 41501.333
A78: 46388 | B78: =AVERAGE(B42,B54,B66) -> 46481.667 | C78: =AVERAGE(C42,C54,C66) -> 48334.333 | D78: =AVERAGE(D42,D54,D66) -> 48308.333 | E78: =AVERAGE(E42,E54,E66) -> 47462 | F78: =AVERAGE(F42,F54,F66) -> 42897 | G78: =AVERAGE(G42,G54,G66) -> 44941 | H78: =AVERAGE(H42,H54,H66) -> 45669.667 | I78: =AVERAGE(I42,I54,I66) -> 45935.333 | ... L78: =AVERAGE(L42,L54,L66) -> 42691.333
... A80: 46447 | B80: =AVERAGE(B44,B56,B68) -> 47492.889 | C80: =AVERAGE(C44,C56,C68) -> 50040.556 | D80: =AVERAGE(D44,D56,D68) -> 48395.111 | E80: =AVERAGE(E44,E56,E68) -> 48095.556 | F80: =AVERAGE(F44,F56,F68) -> 44542.222 | G80: =AVERAGE(G44,G56,G68) -> 47053.778 | H80: =AVERAGE(H44,H56,H68) -> 46557.333 | I80: =AVERAGE(I44,I56,I68) -> 46233.778 | ... L80: =AVERAGE(L44,L56,L68) -> 44539.778

Sheet Plant wise prices
A1: Base Prices
A2: Grade | B2: CM | C2: Loading+BIS | D2: City for Steelmint pricing | E2: 46113 | F2: 46143 | G2: 46174 | H2: 46204 | I2: 46235 | J2: 46266 | K2: 46296 | L2: 46327 | M2: 46357 | N2: 46388 | O2: 46419 | P2: 46447
A3: 550 | B3: AIC IRON INDUSTRIES PRIVATE LIMITED | C3: 2970 | D3: ='Steelmint prices for last 36m'!L29 -> Durgapur | E3: =INDEX('Steelmint prices for last 36m'!$A$29:$N$80,MATCH('Plant wise prices'!E$2,'Steelmint prices for last 36m'!$A$29:$A$80,0),MATCH('Plant wise prices'!$D3,'Steelmint prices for last 36m'!$A$29:$N$29,0)) -> 47844.333 | F3: =INDEX('Steelmint prices for last 36m'!$A$29:$N$80,MATCH('Plant wise prices'!F$2,'Steelmint prices for last 36m'!$A$29:$A$80,0),MATCH('Plant wise prices'!$D3,'Steelmint prices for last 36m'!$A$29:$N$29,0)) -> 46166.667 | G3: =INDEX('Steelmint prices for last 36m'!$A$29:$N$80,MATCH('Plant wise prices'!G$2,'Steelmint prices for last 36m'!$A$29:$A$80,0),MATCH('Plant wise prices'!$D3,'Steelmint prices for last 36m'!$A$29:$N$29,0)) -> 44392 | H3: =INDEX('Steelmint prices for last 36m'!$A$29:$N$80,MATCH('Plant wise prices'!H$2,'Steelmint prices for last 36m'!$A$29:$A$80,0),MATCH('Plant wise prices'!$D3,'Steelmint prices for last 36m'!$A$29:$N$29,0)) -> 42156 | I3: =INDEX('Steelmint prices for last 36m'!$A$29:$N$80,MATCH('Plant wise prices'!I$2,'Steelmint prices for last 36m'!$A$29:$A$80,0),MATCH('Plant wise prices'!$D3,'Steelmint prices for last 36m'!$A$29:$N$29,0)) -> 42114.333 | J3: =INDEX('Steelmint prices for last 36m'!$A$29:$N$80,MATCH('Plant wise prices'!J$2,'Steelmint prices for last 36m'!$A$29:$A$80,0),MATCH('Plant wise prices'!$D3,'Steelmint prices for last 36m'!$A$29:$N$29,0)) -> 42390 | K3: =INDEX('Steelmint prices for last 36m'!$A$29:$N$80,MATCH('Plant wise prices'!K$2,'Steelmint prices for last 36m'!$A$29:$A$80,0),MATCH('Plant wise prices'!$D3,'Steelmint prices for last 36m'!$A$29:$N$29,0)) -> 42379 | L3: =INDEX('Steelmint prices for last 36m'!$A$29:$N$80,MATCH('Plant wise prices'!L$2,'Steelmint prices for last 36m'!$A$29:$A$80,0),MATCH('Plant wise prices'!$D3,'Steelmint prices for last 36m'!$A$29:$N$29,0)) -> 41367.667 | ... P3: =INDEX('Steelmint prices for last 36m'!$A$29:$N$80,MATCH('Plant wise prices'!P$2,'Steelmint prices for last 36m'!$A$29:$A$80,0),MATCH('Plant wise prices'!$D3,'Steelmint prices for last 36m'!$A$29:$N$29,0)) -> 44539.778
A4: 550 | B4: Aditya Industries | C4: 650 | D4: ='Steelmint prices for last 36m'!E29 -> Mandi Gobindgarh | E4: =INDEX('Steelmint prices for last 36m'!$A$29:$N$80,MATCH('Plant wise prices'!E$2,'Steelmint prices for last 36m'!$A$29:$A$80,0),MATCH('Plant wise prices'!$D4,'Steelmint prices for last 36m'!$A$29:$N$29,0)) -> 50924.333 | F4: =INDEX('Steelmint prices for last 36m'!$A$29:$N$80,MATCH('Plant wise prices'!F$2,'Steelmint prices for last 36m'!$A$29:$A$80,0),MATCH('Plant wise prices'!$D4,'Steelmint prices for last 36m'!$A$29:$N$29,0)) -> 50534.667 | G4: =INDEX('Steelmint prices for last 36m'!$A$29:$N$80,MATCH('Plant wise prices'!G$2,'Steelmint prices for last 36m'!$A$29:$A$80,0),MATCH('Plant wise prices'!$D4,'Steelmint prices for last 36m'!$A$29:$N$29,0)) -> 49712.333 | H4: =INDEX('Steelmint prices for last 36m'!$A$29:$N$80,MATCH('Plant wise prices'!H$2,'Steelmint prices for last 36m'!$A$29:$A$80,0),MATCH('Plant wise prices'!$D4,'Steelmint prices for last 36m'!$A$29:$N$29,0)) -> 47798 | I4: =INDEX('Steelmint prices for last 36m'!$A$29:$N$80,MATCH('Plant wise prices'!I$2,'Steelmint prices for last 36m'!$A$29:$A$80,0),MATCH('Plant wise prices'!$D4,'Steelmint prices for last 36m'!$A$29:$N$29,0)) -> 47495.667 | J4: =INDEX('Steelmint prices for last 36m'!$A$29:$N$80,MATCH('Plant wise prices'!J$2,'Steelmint prices for last 36m'!$A$29:$A$80,0),MATCH('Plant wise prices'!$D4,'Steelmint prices for last 36m'!$A$29:$N$29,0)) -> 47359.667 | K4: =INDEX('Steelmint prices for last 36m'!$A$29:$N$80,MATCH('Plant wise prices'!K$2,'Steelmint prices for last 36m'!$A$29:$A$80,0),MATCH('Plant wise prices'!$D4,'Steelmint prices for last 36m'!$A$29:$N$29,0)) -> 47096.333 | L4: =INDEX('Steelmint prices for last 36m'!$A$29:$N$80,MATCH('Plant wise prices'!L$2,'Steelmint prices for last 36m'!$A$29:$A$80,0),MATCH('Plant wise prices'!$D4,'Steelmint prices for last 36m'!$A$29:$N$29,0)) -> 46326 | ... P4: =INDEX('Steelmint prices for last 36m'!$A$29:$N$80,MATCH('Plant wise prices'!P$2,'Steelmint prices for last 36m'!$A$29:$A$80,0),MATCH('Plant wise prices'!$D4,'Steelmint prices for last 36m'!$A$29:$N$29,0)) -> 48095.556
A5: 550 | B5: Ambashakti Industries Limited | C5: 1400 | D5: ='Steelmint prices for last 36m'!B29 -> Delhi/NCR | E5: =INDEX('Steelmint prices for last 36m'!$A$29:$N$80,MATCH('Plant wise prices'!E$2,'Steelmint prices for last 36m'!$A$29:$A$80,0),MATCH('Plant wise prices'!$D5,'Steelmint prices for last 36m'!$A$29:$N$29,0)) -> 50440.333 | F5: =INDEX('Steelmint prices for last 36m'!$A$29:$N$80,MATCH('Plant wise prices'!F$2,'Steelmint prices for last 36m'!$A$29:$A$80,0),MATCH('Plant wise prices'!$D5,'Steelmint prices for last 36m'!$A$29:$N$29,0)) -> 49797.667 | G5: =INDEX('Steelmint prices for last 36m'!$A$29:$N$80,MATCH('Plant wise prices'!G$2,'Steelmint prices for last 36m'!$A$29:$A$80,0),MATCH('Plant wise prices'!$D5,'Steelmint prices for last 36m'!$A$29:$N$29,0)) -> 48637 | H5: =INDEX('Steelmint prices for last 36m'!$A$29:$N$80,MATCH('Plant wise prices'!H$2,'Steelmint prices for last 36m'!$A$29:$A$80,0),MATCH('Plant wise prices'!$D5,'Steelmint prices for last 36m'!$A$29:$N$29,0)) -> 46497.333 | I5: =INDEX('Steelmint prices for last 36m'!$A$29:$N$80,MATCH('Plant wise prices'!I$2,'Steelmint prices for last 36m'!$A$29:$A$80,0),MATCH('Plant wise prices'!$D5,'Steelmint prices for last 36m'!$A$29:$N$29,0)) -> 45973 | J5: =INDEX('Steelmint prices for last 36m'!$A$29:$N$80,MATCH('Plant wise prices'!J$2,'Steelmint prices for last 36m'!$A$29:$A$80,0),MATCH('Plant wise prices'!$D5,'Steelmint prices for last 36m'!$A$29:$N$29,0)) -> 45928.667 | K5: =INDEX('Steelmint prices for last 36m'!$A$29:$N$80,MATCH('Plant wise prices'!K$2,'Steelmint prices for last 36m'!$A$29:$A$80,0),MATCH('Plant wise prices'!$D5,'Steelmint prices for last 36m'!$A$29:$N$29,0)) -> 45753 | L5: =INDEX('Steelmint prices for last 36m'!$A$29:$N$80,MATCH('Plant wise prices'!L$2,'Steelmint prices for last 36m'!$A$29:$A$80,0),MATCH('Plant wise prices'!$D5,'Steelmint prices for last 36m'!$A$29:$N$29,0)) -> 44874 | ... P5: =INDEX('Steelmint prices for last 36m'!$A$29:$N$80,MATCH('Plant wise prices'!P$2,'Steelmint prices for last 36m'!$A$29:$A$80,0),MATCH('Plant wise prices'!$D5,'Steelmint prices for last 36m'!$A$29:$N$29,0)) -> 47492.889
A6: 550 | B6: AMBASHAKTI UDYOG LIMITED- GWALIOR | C6: 1400 | E6: =E5-800 -> 49640.333 | F6: =F5-800 -> 48997.667 | G6: =G5-800 -> 47837 | H6: =H5-800 -> 45697.333 | I6: =I5-800 -> 45173 | J6: =J5-800 -> 45128.667 | K6: =K5-800 -> 44953 | L6: =L5-800 -> 44074 | ... P6: =P5-800 -> 46692.889
A7: 550 | B7: API Ispat And Powertech Private Limited | C7: 2415 | D7: ='Steelmint prices for last 36m'!F29 -> Raipur | E7: =INDEX('Steelmint prices for last 36m'!$A$29:$N$80,MATCH('Plant wise prices'!E$2,'Steelmint prices for last 36m'!$A$29:$A$80,0),MATCH('Plant wise prices'!$D7,'Steelmint prices for last 36m'!$A$29:$N$29,0)) -> 47358.333 | F7: =INDEX('Steelmint prices for last 36m'!$A$29:$N$80,MATCH('Plant wise prices'!F$2,'Steelmint prices for last 36m'!$A$29:$A$80,0),MATCH('Plant wise prices'!$D7,'Steelmint prices for last 36m'!$A$29:$N$29,0)) -> 46368 | G7: =INDEX('Steelmint prices for last 36m'!$A$29:$N$80,MATCH('Plant wise prices'!G$2,'Steelmint prices for last 36m'!$A$29:$A$80,0),MATCH('Plant wise prices'!$D7,'Steelmint prices for last 36m'!$A$29:$N$29,0)) -> 44909 | H7: =INDEX('Steelmint prices for last 36m'!$A$29:$N$80,MATCH('Plant wise prices'!H$2,'Steelmint prices for last 36m'!$A$29:$A$80,0),MATCH('Plant wise prices'!$D7,'Steelmint prices for last 36m'!$A$29:$N$29,0)) -> 42005.667 | I7: =INDEX('Steelmint prices for last 36m'!$A$29:$N$80,MATCH('Plant wise prices'!I$2,'Steelmint prices for last 36m'!$A$29:$A$80,0),MATCH('Plant wise prices'!$D7,'Steelmint prices for last 36m'!$A$29:$N$29,0)) -> 42310 | J7: =INDEX('Steelmint prices for last 36m'!$A$29:$N$80,MATCH('Plant wise prices'!J$2,'Steelmint prices for last 36m'!$A$29:$A$80,0),MATCH('Plant wise prices'!$D7,'Steelmint prices for last 36m'!$A$29:$N$29,0)) -> 42985.667 | K7: =INDEX('Steelmint prices for last 36m'!$A$29:$N$80,MATCH('Plant wise prices'!K$2,'Steelmint prices for last 36m'!$A$29:$A$80,0),MATCH('Plant wise prices'!$D7,'Steelmint prices for last 36m'!$A$29:$N$29,0)) -> 42769.333 | L7: =INDEX('Steelmint prices for last 36m'!$A$29:$N$80,MATCH('Plant wise prices'!L$2,'Steelmint prices for last 36m'!$A$29:$A$80,0),MATCH('Plant wise prices'!$D7,'Steelmint prices for last 36m'!$A$29:$N$29,0)) -> 41708 | ... P7: =INDEX('Steelmint prices for last 36m'!$A$29:$N$80,MATCH('Plant wise prices'!P$2,'Steelmint prices for last 36m'!$A$29:$A$80,0),MATCH('Plant wise prices'!$D7,'Steelmint prices for last 36m'!$A$29:$N$29,0)) -> 44542.222
A8: 550 | B8: GERMAN GREEN STEEL AND POWER LIMITED | C8: 200 | D8: ='Steelmint prices for last 36m'!D29 -> Ahmedabad | E8: =INDEX('Steelmint prices for last 36m'!$A$29:$N$80,MATCH('Plant wise prices'!E$2,'Steelmint prices for last 36m'!$A$29:$A$80,0),MATCH('Plant wise prices'!$D8,'Steelmint prices for last 36m'!$A$29:$N$29,0)) -> 50322.333 | F8: =INDEX('Steelmint prices for last 36m'!$A$29:$N$80,MATCH('Plant wise prices'!F$2,'Steelmint prices for last 36m'!$A$29:$A$80,0),MATCH('Plant wise prices'!$D8,'Steelmint prices for last 36m'!$A$29:$N$29,0)) -> 49913.667 | G8: =INDEX('Steelmint prices for last 36m'!$A$29:$N$80,MATCH('Plant wise prices'!G$2,'Steelmint prices for last 36m'!$A$29:$A$80,0),MATCH('Plant wise prices'!$D8,'Steelmint prices for last 36m'!$A$29:$N$29,0)) -> 48520.667 | H8: =INDEX('Steelmint prices for last 36m'!$A$29:$N$80,MATCH('Plant wise prices'!H$2,'Steelmint prices for last 36m'!$A$29:$A$80,0),MATCH('Plant wise prices'!$D8,'Steelmint prices for last 36m'!$A$29:$N$29,0)) -> 45967 | I8: =INDEX('Steelmint prices for last 36m'!$A$29:$N$80,MATCH('Plant wise prices'!I$2,'Steelmint prices for last 36m'!$A$29:$A$80,0),MATCH('Plant wise prices'!$D8,'Steelmint prices for last 36m'!$A$29:$N$29,0)) -> 46257.333 | J8: =INDEX('Steelmint prices for last 36m'!$A$29:$N$80,MATCH('Plant wise prices'!J$2,'Steelmint prices for last 36m'!$A$29:$A$80,0),MATCH('Plant wise prices'!$D8,'Steelmint prices for last 36m'!$A$29:$N$29,0)) -> 46615.333 | K8: =INDEX('Steelmint prices for last 36m'!$A$29:$N$80,MATCH('Plant wise prices'!K$2,'Steelmint prices for last 36m'!$A$29:$A$80,0),MATCH('Plant wise prices'!$D8,'Steelmint prices for last 36m'!$A$29:$N$29,0)) -> 46281.333 | L8: =INDEX('Steelmint prices for last 36m'!$A$29:$N$80,MATCH('Plant wise prices'!L$2,'Steelmint prices for last 36m'!$A$29:$A$80,0),MATCH('Plant wise prices'!$D8,'Steelmint prices for last 36m'!$A$29:$N$29,0)) -> 45582.667 | ... P8: =INDEX('Steelmint prices for last 36m'!$A$29:$N$80,MATCH('Plant wise prices'!P$2,'Steelmint prices for last 36m'!$A$29:$A$80,0),MATCH('Plant wise prices'!$D8,'Steelmint prices for last 36m'!$A$29:$N$29,0)) -> 48395.111
A9: 550 | B9: SKA Ispat Private Limited | C9: 2075 | D9: ='Steelmint prices for last 36m'!F29 -> Raipur | E9: =INDEX('Steelmint prices for last 36m'!$A$29:$N$80,MATCH('Plant wise prices'!E$2,'Steelmint prices for last 36m'!$A$29:$A$80,0),MATCH('Plant wise prices'!$D9,'Steelmint prices for last 36m'!$A$29:$N$29,0)) -> 47358.333 | F9: =INDEX('Steelmint prices for last 36m'!$A$29:$N$80,MATCH('Plant wise prices'!F$2,'Steelmint prices for last 36m'!$A$29:$A$80,0),MATCH('Plant wise prices'!$D9,'Steelmint prices for last 36m'!$A$29:$N$29,0)) -> 46368 | G9: =INDEX('Steelmint prices for last 36m'!$A$29:$N$80,MATCH('Plant wise prices'!G$2,'Steelmint prices for last 36m'!$A$29:$A$80,0),MATCH('Plant wise prices'!$D9,'Steelmint prices for last 36m'!$A$29:$N$29,0)) -> 44909 | H9: =INDEX('Steelmint prices for last 36m'!$A$29:$N$80,MATCH('Plant wise prices'!H$2,'Steelmint prices for last 36m'!$A$29:$A$80,0),MATCH('Plant wise prices'!$D9,'Steelmint prices for last 36m'!$A$29:$N$29,0)) -> 42005.667 | I9: =INDEX('Steelmint prices for last 36m'!$A$29:$N$80,MATCH('Plant wise prices'!I$2,'Steelmint prices for last 36m'!$A$29:$A$80,0),MATCH('Plant wise prices'!$D9,'Steelmint prices for last 36m'!$A$29:$N$29,0)) -> 42310 | J9: =INDEX('Steelmint prices for last 36m'!$A$29:$N$80,MATCH('Plant wise prices'!J$2,'Steelmint prices for last 36m'!$A$29:$A$80,0),MATCH('Plant wise prices'!$D9,'Steelmint prices for last 36m'!$A$29:$N$29,0)) -> 42985.667 | K9: =INDEX('Steelmint prices for last 36m'!$A$29:$N$80,MATCH('Plant wise prices'!K$2,'Steelmint prices for last 36m'!$A$29:$A$80,0),MATCH('Plant wise prices'!$D9,'Steelmint prices for last 36m'!$A$29:$N$29,0)) -> 42769.333 | L9: =INDEX('Steelmint prices for last 36m'!$A$29:$N$80,MATCH('Plant wise prices'!L$2,'Steelmint prices for last 36m'!$A$29:$A$80,0),MATCH('Plant wise prices'!$D9,'Steelmint prices for last 36m'!$A$29:$N$29,0)) -> 41708 | ... P9: =INDEX('Steelmint prices for last 36m'!$A$29:$N$80,MATCH('Plant wise prices'!P$2,'Steelmint prices for last 36m'!$A$29:$A$80,0),MATCH('Plant wise prices'!$D9,'Steelmint prices for last 36m'!$A$29:$N$29,0)) -> 44542.222
A10: 550 | B10: Real Ispat | C10: 0 | D10: ='Steelmint prices for last 36m'!F29 -> Raipur | E10: =INDEX('Steelmint prices for last 36m'!$A$29:$N$80,MATCH('Plant wise prices'!E$2,'Steelmint prices for last 36m'!$A$29:$A$80,0),MATCH('Plant wise prices'!$D10,'Steelmint prices for last 36m'!$A$29:$N$29,0)) -> 47358.333 | F10: =INDEX('Steelmint prices for last 36m'!$A$29:$N$80,MATCH('Plant wise prices'!F$2,'Steelmint prices for last 36m'!$A$29:$A$80,0),MATCH('Plant wise prices'!$D10,'Steelmint prices for last 36m'!$A$29:$N$29,0)) -> 46368 | G10: =INDEX('Steelmint prices for last 36m'!$A$29:$N$80,MATCH('Plant wise prices'!G$2,'Steelmint prices for last 36m'!$A$29:$A$80,0),MATCH('Plant wise prices'!$D10,'Steelmint prices for last 36m'!$A$29:$N$29,0)) -> 44909 | H10: =INDEX('Steelmint prices for last 36m'!$A$29:$N$80,MATCH('Plant wise prices'!H$2,'Steelmint prices for last 36m'!$A$29:$A$80,0),MATCH('Plant wise prices'!$D10,'Steelmint prices for last 36m'!$A$29:$N$29,0)) -> 42005.667 | I10: =INDEX('Steelmint prices for last 36m'!$A$29:$N$80,MATCH('Plant wise prices'!I$2,'Steelmint prices for last 36m'!$A$29:$A$80,0),MATCH('Plant wise prices'!$D10,'Steelmint prices for last 36m'!$A$29:$N$29,0)) -> 42310 | J10: =INDEX('Steelmint prices for last 36m'!$A$29:$N$80,MATCH('Plant wise prices'!J$2,'Steelmint prices for last 36m'!$A$29:$A$80,0),MATCH('Plant wise prices'!$D10,'Steelmint prices for last 36m'!$A$29:$N$29,0)) -> 42985.667 | K10: =INDEX('Steelmint prices for last 36m'!$A$29:$N$80,MATCH('Plant wise prices'!K$2,'Steelmint prices for last 36m'!$A$29:$A$80,0),MATCH('Plant wise prices'!$D10,'Steelmint prices for last 36m'!$A$29:$N$29,0)) -> 42769.333 | L10: =INDEX('Steelmint prices for last 36m'!$A$29:$N$80,MATCH('Plant wise prices'!L$2,'Steelmint prices for last 36m'!$A$29:$A$80,0),MATCH('Plant wise prices'!$D10,'Steelmint prices for last 36m'!$A$29:$N$29,0)) -> 41708 | ... P10: =INDEX('Steelmint prices for last 36m'!$A$29:$N$80,MATCH('Plant wise prices'!P$2,'Steelmint prices for last 36m'!$A$29:$A$80,0),MATCH('Plant wise prices'!$D10,'Steelmint prices for last 36m'!$A$29:$N$29,0)) -> 44542.222
A11: 550 | B11: Rashmi Steel | C11: 2415 | D11: ='Steelmint prices for last 36m'!L29 -> Durgapur | E11: =INDEX('Steelmint prices for last 36m'!$A$29:$N$80,MATCH('Plant wise prices'!E$2,'Steelmint prices for last 36m'!$A$29:$A$80,0),MATCH('Plant wise prices'!$D11,'Steelmint prices for last 36m'!$A$29:$N$29,0)) -> 47844.333 | F11: =INDEX('Steelmint prices for last 36m'!$A$29:$N$80,MATCH('Plant wise prices'!F$2,'Steelmint prices for last 36m'!$A$29:$A$80,0),MATCH('Plant wise prices'!$D11,'Steelmint prices for last 36m'!$A$29:$N$29,0)) -> 46166.667 | G11: =INDEX('Steelmint prices for last 36m'!$A$29:$N$80,MATCH('Plant wise prices'!G$2,'Steelmint prices for last 36m'!$A$29:$A$80,0),MATCH('Plant wise prices'!$D11,'Steelmint prices for last 36m'!$A$29:$N$29,0)) -> 44392 | H11: =INDEX('Steelmint prices for last 36m'!$A$29:$N$80,MATCH('Plant wise prices'!H$2,'Steelmint prices for last 36m'!$A$29:$A$80,0),MATCH('Plant wise prices'!$D11,'Steelmint prices for last 36m'!$A$29:$N$29,0)) -> 42156 | I11: =INDEX('Steelmint prices for last 36m'!$A$29:$N$80,MATCH('Plant wise prices'!I$2,'Steelmint prices for last 36m'!$A$29:$A$80,0),MATCH('Plant wise prices'!$D11,'Steelmint prices for last 36m'!$A$29:$N$29,0)) -> 42114.333 | J11: =INDEX('Steelmint prices for last 36m'!$A$29:$N$80,MATCH('Plant wise prices'!J$2,'Steelmint prices for last 36m'!$A$29:$A$80,0),MATCH('Plant wise prices'!$D11,'Steelmint prices for last 36m'!$A$29:$N$29,0)) -> 42390 | K11: =INDEX('Steelmint prices for last 36m'!$A$29:$N$80,MATCH('Plant wise prices'!K$2,'Steelmint prices for last 36m'!$A$29:$A$80,0),MATCH('Plant wise prices'!$D11,'Steelmint prices for last 36m'!$A$29:$N$29,0)) -> 42379 | L11: =INDEX('Steelmint prices for last 36m'!$A$29:$N$80,MATCH('Plant wise prices'!L$2,'Steelmint prices for last 36m'!$A$29:$A$80,0),MATCH('Plant wise prices'!$D11,'Steelmint prices for last 36m'!$A$29:$N$29,0)) -> 41367.667 | ... P11: =INDEX('Steelmint prices for last 36m'!$A$29:$N$80,MATCH('Plant wise prices'!P$2,'Steelmint prices for last 36m'!$A$29:$A$80,0),MATCH('Plant wise prices'!$D11,'Steelmint prices for last 36m'!$A$29:$N$29,0)) -> 44539.778
A12: 550 | B12: Telangana - New Plant | C12: 2415 | D12: Hyderabad | E12: =INDEX('Steelmint prices for last 36m'!$A$29:$N$80,MATCH('Plant wise prices'!E$2,'Steelmint prices for last 36m'!$A$29:$A$80,0),MATCH('Plant wise prices'!$D12,'Steelmint prices for last 36m'!$A$29:$N$29,0)) -> 49673.667 | F12: =INDEX('Steelmint prices for last 36m'!$A$29:$N$80,MATCH('Plant wise prices'!F$2,'Steelmint prices for last 36m'!$A$29:$A$80,0),MATCH('Plant wise prices'!$D12,'Steelmint prices for last 36m'!$A$29:$N$29,0)) -> 48756 | G12: =INDEX('Steelmint prices for last 36m'!$A$29:$N$80,MATCH('Plant wise prices'!G$2,'Steelmint prices for last 36m'!$A$29:$A$80,0),MATCH('Plant wise prices'!$D12,'Steelmint prices for last 36m'!$A$29:$N$29,0)) -> 46797.667 | H12: =INDEX('Steelmint prices for last 36m'!$A$29:$N$80,MATCH('Plant wise prices'!H$2,'Steelmint prices for last 36m'!$A$29:$A$80,0),MATCH('Plant wise prices'!$D12,'Steelmint prices for last 36m'!$A$29:$N$29,0)) -> 45036 | I12: =INDEX('Steelmint prices for last 36m'!$A$29:$N$80,MATCH('Plant wise prices'!I$2,'Steelmint prices for last 36m'!$A$29:$A$80,0),MATCH('Plant wise prices'!$D12,'Steelmint prices for last 36m'!$A$29:$N$29,0)) -> 44642.333 | J12: =INDEX('Steelmint prices for last 36m'!$A$29:$N$80,MATCH('Plant wise prices'!J$2,'Steelmint prices for last 36m'!$A$29:$A$80,0),MATCH('Plant wise prices'!$D12,'Steelmint prices for last 36m'!$A$29:$N$29,0)) -> 45460.667 | K12: =INDEX('Steelmint prices for last 36m'!$A$29:$N$80,MATCH('Plant wise prices'!K$2,'Steelmint prices for last 36m'!$A$29:$A$80,0),MATCH('Plant wise prices'!$D12,'Steelmint prices for last 36m'!$A$29:$N$29,0)) -> 45104 | L12: =INDEX('Steelmint prices for last 36m'!$A$29:$N$80,MATCH('Plant wise prices'!L$2,'Steelmint prices for last 36m'!$A$29:$A$80,0),MATCH('Plant wise prices'!$D12,'Steelmint prices for last 36m'!$A$29:$N$29,0)) -> 44154 | ... P12: =INDEX('Steelmint prices for last 36m'!$A$29:$N$80,MATCH('Plant wise prices'!P$2,'Steelmint prices for last 36m'!$A$29:$A$80,0),MATCH('Plant wise prices'!$D12,'Steelmint prices for last 36m'!$A$29:$N$29,0)) -> 47053.778
A13: 550 | B13: Maharashtra - New Plant | C13: 2415 | D13: Mumbai | E13: =INDEX('Steelmint prices for last 36m'!$A$29:$N$80,MATCH('Plant wise prices'!E$2,'Steelmint prices for last 36m'!$A$29:$A$80,0),MATCH('Plant wise prices'!$D13,'Steelmint prices for last 36m'!$A$29:$N$29,0)) -> 51608.667 | F13: =INDEX('Steelmint prices for last 36m'!$A$29:$N$80,MATCH('Plant wise prices'!F$2,'Steelmint prices for last 36m'!$A$29:$A$80,0),MATCH('Plant wise prices'!$D13,'Steelmint prices for last 36m'!$A$29:$N$29,0)) -> 51348 | G13: =INDEX('Steelmint prices for last 36m'!$A$29:$N$80,MATCH('Plant wise prices'!G$2,'Steelmint prices for last 36m'!$A$29:$A$80,0),MATCH('Plant wise prices'!$D13,'Steelmint prices for last 36m'!$A$29:$N$29,0)) -> 48694.667 | H13: =INDEX('Steelmint prices for last 36m'!$A$29:$N$80,MATCH('Plant wise prices'!H$2,'Steelmint prices for last 36m'!$A$29:$A$80,0),MATCH('Plant wise prices'!$D13,'Steelmint prices for last 36m'!$A$29:$N$29,0)) -> 45745.333 | I13: =INDEX('Steelmint prices for last 36m'!$A$29:$N$80,MATCH('Plant wise prices'!I$2,'Steelmint prices for last 36m'!$A$29:$A$80,0),MATCH('Plant wise prices'!$D13,'Steelmint prices for last 36m'!$A$29:$N$29,0)) -> 46515.333 | J13: =INDEX('Steelmint prices for last 36m'!$A$29:$N$80,MATCH('Plant wise prices'!J$2,'Steelmint prices for last 36m'!$A$29:$A$80,0),MATCH('Plant wise prices'!$D13,'Steelmint prices for last 36m'!$A$29:$N$29,0)) -> 47287.333 | K13: =INDEX('Steelmint prices for last 36m'!$A$29:$N$80,MATCH('Plant wise prices'!K$2,'Steelmint prices for last 36m'!$A$29:$A$80,0),MATCH('Plant wise prices'!$D13,'Steelmint prices for last 36m'!$A$29:$N$29,0)) -> 47096.333 | L13: =INDEX('Steelmint prices for last 36m'!$A$29:$N$80,MATCH('Plant wise prices'!L$2,'Steelmint prices for last 36m'!$A$29:$A$80,0),MATCH('Plant wise prices'!$D13,'Steelmint prices for last 36m'!$A$29:$N$29,0)) -> 46410.333 | ... P13: =INDEX('Steelmint prices for last 36m'!$A$29:$N$80,MATCH('Plant wise prices'!P$2,'Steelmint prices for last 36m'!$A$29:$A$80,0),MATCH('Plant wise prices'!$D13,'Steelmint prices for last 36m'!$A$29:$N$29,0)) -> 50040.556
A15: 550D | B15: =B3 -> AIC IRON INDUSTRIES PRIVATE LIMITED | C15: 3770 | D15: =D3 -> Durgapur | E15: =INDEX('Steelmint prices for last 36m'!$A$29:$N$80,MATCH('Plant wise prices'!E$2,'Steelmint prices for last 36m'!$A$29:$A$80,0),MATCH('Plant wise prices'!$D15,'Steelmint prices for last 36m'!$A$29:$N$29,0)) -> 47844.333 | F15: =INDEX('Steelmint prices for last 36m'!$A$29:$N$80,MATCH('Plant wise prices'!F$2,'Steelmint prices for last 36m'!$A$29:$A$80,0),MATCH('Plant wise prices'!$D15,'Steelmint prices for last 36m'!$A$29:$N$29,0)) -> 46166.667 | G15: =INDEX('Steelmint prices for last 36m'!$A$29:$N$80,MATCH('Plant wise prices'!G$2,'Steelmint prices for last 36m'!$A$29:$A$80,0),MATCH('Plant wise prices'!$D15,'Steelmint prices for last 36m'!$A$29:$N$29,0)) -> 44392 | H15: =INDEX('Steelmint prices for last 36m'!$A$29:$N$80,MATCH('Plant wise prices'!H$2,'Steelmint prices for last 36m'!$A$29:$A$80,0),MATCH('Plant wise prices'!$D15,'Steelmint prices for last 36m'!$A$29:$N$29,0)) -> 42156 | I15: =INDEX('Steelmint prices for last 36m'!$A$29:$N$80,MATCH('Plant wise prices'!I$2,'Steelmint prices for last 36m'!$A$29:$A$80,0),MATCH('Plant wise prices'!$D15,'Steelmint prices for last 36m'!$A$29:$N$29,0)) -> 42114.333 | J15: =INDEX('Steelmint prices for last 36m'!$A$29:$N$80,MATCH('Plant wise prices'!J$2,'Steelmint prices for last 36m'!$A$29:$A$80,0),MATCH('Plant wise prices'!$D15,'Steelmint prices for last 36m'!$A$29:$N$29,0)) -> 42390 | K15: =INDEX('Steelmint prices for last 36m'!$A$29:$N$80,MATCH('Plant wise prices'!K$2,'Steelmint prices for last 36m'!$A$29:$A$80,0),MATCH('Plant wise prices'!$D15,'Steelmint prices for last 36m'!$A$29:$N$29,0)) -> 42379 | L15: =INDEX('Steelmint prices for last 36m'!$A$29:$N$80,MATCH('Plant wise prices'!L$2,'Steelmint prices for last 36m'!$A$29:$A$80,0),MATCH('Plant wise prices'!$D15,'Steelmint prices for last 36m'!$A$29:$N$29,0)) -> 41367.667 | ... P15: =INDEX('Steelmint prices for last 36m'!$A$29:$N$80,MATCH('Plant wise prices'!P$2,'Steelmint prices for last 36m'!$A$29:$A$80,0),MATCH('Plant wise prices'!$D15,'Steelmint prices for last 36m'!$A$29:$N$29,0)) -> 44539.778
A16: 550D | B16: =B4 -> Aditya Industries | C16: 1450 | D16: =D4 -> Mandi Gobindgarh | E16: =INDEX('Steelmint prices for last 36m'!$A$29:$N$80,MATCH('Plant wise prices'!E$2,'Steelmint prices for last 36m'!$A$29:$A$80,0),MATCH('Plant wise prices'!$D16,'Steelmint prices for last 36m'!$A$29:$N$29,0)) -> 50924.333 | F16: =INDEX('Steelmint prices for last 36m'!$A$29:$N$80,MATCH('Plant wise prices'!F$2,'Steelmint prices for last 36m'!$A$29:$A$80,0),MATCH('Plant wise prices'!$D16,'Steelmint prices for last 36m'!$A$29:$N$29,0)) -> 50534.667 | G16: =INDEX('Steelmint prices for last 36m'!$A$29:$N$80,MATCH('Plant wise prices'!G$2,'Steelmint prices for last 36m'!$A$29:$A$80,0),MATCH('Plant wise prices'!$D16,'Steelmint prices for last 36m'!$A$29:$N$29,0)) -> 49712.333 | H16: =INDEX('Steelmint prices for last 36m'!$A$29:$N$80,MATCH('Plant wise prices'!H$2,'Steelmint prices for last 36m'!$A$29:$A$80,0),MATCH('Plant wise prices'!$D16,'Steelmint prices for last 36m'!$A$29:$N$29,0)) -> 47798 | I16: =INDEX('Steelmint prices for last 36m'!$A$29:$N$80,MATCH('Plant wise prices'!I$2,'Steelmint prices for last 36m'!$A$29:$A$80,0),MATCH('Plant wise prices'!$D16,'Steelmint prices for last 36m'!$A$29:$N$29,0)) -> 47495.667 | J16: =INDEX('Steelmint prices for last 36m'!$A$29:$N$80,MATCH('Plant wise prices'!J$2,'Steelmint prices for last 36m'!$A$29:$A$80,0),MATCH('Plant wise prices'!$D16,'Steelmint prices for last 36m'!$A$29:$N$29,0)) -> 47359.667 | K16: =INDEX('Steelmint prices for last 36m'!$A$29:$N$80,MATCH('Plant wise prices'!K$2,'Steelmint prices for last 36m'!$A$29:$A$80,0),MATCH('Plant wise prices'!$D16,'Steelmint prices for last 36m'!$A$29:$N$29,0)) -> 47096.333 | L16: =INDEX('Steelmint prices for last 36m'!$A$29:$N$80,MATCH('Plant wise prices'!L$2,'Steelmint prices for last 36m'!$A$29:$A$80,0),MATCH('Plant wise prices'!$D16,'Steelmint prices for last 36m'!$A$29:$N$29,0)) -> 46326 | ... P16: =INDEX('Steelmint prices for last 36m'!$A$29:$N$80,MATCH('Plant wise prices'!P$2,'Steelmint prices for last 36m'!$A$29:$A$80,0),MATCH('Plant wise prices'!$D16,'Steelmint prices for last 36m'!$A$29:$N$29,0)) -> 48095.556
A17: 550D | B17: =B5 -> Ambashakti Industries Limited | C17: 2400 | D17: =D5 -> Delhi/NCR | E17: =INDEX('Steelmint prices for last 36m'!$A$29:$N$80,MATCH('Plant wise prices'!E$2,'Steelmint prices for last 36m'!$A$29:$A$80,0),MATCH('Plant wise prices'!$D17,'Steelmint prices for last 36m'!$A$29:$N$29,0)) -> 50440.333 | F17: =INDEX('Steelmint prices for last 36m'!$A$29:$N$80,MATCH('Plant wise prices'!F$2,'Steelmint prices for last 36m'!$A$29:$A$80,0),MATCH('Plant wise prices'!$D17,'Steelmint prices for last 36m'!$A$29:$N$29,0)) -> 49797.667 | G17: =INDEX('Steelmint prices for last 36m'!$A$29:$N$80,MATCH('Plant wise prices'!G$2,'Steelmint prices for last 36m'!$A$29:$A$80,0),MATCH('Plant wise prices'!$D17,'Steelmint prices for last 36m'!$A$29:$N$29,0)) -> 48637 | H17: =INDEX('Steelmint prices for last 36m'!$A$29:$N$80,MATCH('Plant wise prices'!H$2,'Steelmint prices for last 36m'!$A$29:$A$80,0),MATCH('Plant wise prices'!$D17,'Steelmint prices for last 36m'!$A$29:$N$29,0)) -> 46497.333 | I17: =INDEX('Steelmint prices for last 36m'!$A$29:$N$80,MATCH('Plant wise prices'!I$2,'Steelmint prices for last 36m'!$A$29:$A$80,0),MATCH('Plant wise prices'!$D17,'Steelmint prices for last 36m'!$A$29:$N$29,0)) -> 45973 | J17: =INDEX('Steelmint prices for last 36m'!$A$29:$N$80,MATCH('Plant wise prices'!J$2,'Steelmint prices for last 36m'!$A$29:$A$80,0),MATCH('Plant wise prices'!$D17,'Steelmint prices for last 36m'!$A$29:$N$29,0)) -> 45928.667 | K17: =INDEX('Steelmint prices for last 36m'!$A$29:$N$80,MATCH('Plant wise prices'!K$2,'Steelmint prices for last 36m'!$A$29:$A$80,0),MATCH('Plant wise prices'!$D17,'Steelmint prices for last 36m'!$A$29:$N$29,0)) -> 45753 | L17: =INDEX('Steelmint prices for last 36m'!$A$29:$N$80,MATCH('Plant wise prices'!L$2,'Steelmint prices for last 36m'!$A$29:$A$80,0),MATCH('Plant wise prices'!$D17,'Steelmint prices for last 36m'!$A$29:$N$29,0)) -> 44874 | ... P17: =INDEX('Steelmint prices for last 36m'!$A$29:$N$80,MATCH('Plant wise prices'!P$2,'Steelmint prices for last 36m'!$A$29:$A$80,0),MATCH('Plant wise prices'!$D17,'Steelmint prices for last 36m'!$A$29:$N$29,0)) -> 47492.889
A18: 550D | B18: =B6 -> AMBASHAKTI UDYOG LIMITED- GWALIOR | C18: 3400 | E18: =E17-800 -> 49640.333 | F18: =F17-800 -> 48997.667 | G18: =G17-800 -> 47837 | H18: =H17-800 -> 45697.333 | I18: =I17-800 -> 45173 | J18: =J17-800 -> 45128.667 | K18: =K17-800 -> 44953 | L18: =L17-800 -> 44074 | ... P18: =P17-800 -> 46692.889
A19: 550D | B19: =B7 -> API Ispat And Powertech Private Limited | C19: 3665 | D19: =D7 -> Raipur | E19: =INDEX('Steelmint prices for last 36m'!$A$29:$N$80,MATCH('Plant wise prices'!E$2,'Steelmint prices for last 36m'!$A$29:$A$80,0),MATCH('Plant wise prices'!$D19,'Steelmint prices for last 36m'!$A$29:$N$29,0)) -> 47358.333 | F19: =INDEX('Steelmint prices for last 36m'!$A$29:$N$80,MATCH('Plant wise prices'!F$2,'Steelmint prices for last 36m'!$A$29:$A$80,0),MATCH('Plant wise prices'!$D19,'Steelmint prices for last 36m'!$A$29:$N$29,0)) -> 46368 | G19: =INDEX('Steelmint prices for last 36m'!$A$29:$N$80,MATCH('Plant wise prices'!G$2,'Steelmint prices for last 36m'!$A$29:$A$80,0),MATCH('Plant wise prices'!$D19,'Steelmint prices for last 36m'!$A$29:$N$29,0)) -> 44909 | H19: =INDEX('Steelmint prices for last 36m'!$A$29:$N$80,MATCH('Plant wise prices'!H$2,'Steelmint prices for last 36m'!$A$29:$A$80,0),MATCH('Plant wise prices'!$D19,'Steelmint prices for last 36m'!$A$29:$N$29,0)) -> 42005.667 | I19: =INDEX('Steelmint prices for last 36m'!$A$29:$N$80,MATCH('Plant wise prices'!I$2,'Steelmint prices for last 36m'!$A$29:$A$80,0),MATCH('Plant wise prices'!$D19,'Steelmint prices for last 36m'!$A$29:$N$29,0)) -> 42310 | J19: =INDEX('Steelmint prices for last 36m'!$A$29:$N$80,MATCH('Plant wise prices'!J$2,'Steelmint prices for last 36m'!$A$29:$A$80,0),MATCH('Plant wise prices'!$D19,'Steelmint prices for last 36m'!$A$29:$N$29,0)) -> 42985.667 | K19: =INDEX('Steelmint prices for last 36m'!$A$29:$N$80,MATCH('Plant wise prices'!K$2,'Steelmint prices for last 36m'!$A$29:$A$80,0),MATCH('Plant wise prices'!$D19,'Steelmint prices for last 36m'!$A$29:$N$29,0)) -> 42769.333 | L19: =INDEX('Steelmint prices for last 36m'!$A$29:$N$80,MATCH('Plant wise prices'!L$2,'Steelmint prices for last 36m'!$A$29:$A$80,0),MATCH('Plant wise prices'!$D19,'Steelmint prices for last 36m'!$A$29:$N$29,0)) -> 41708 | ... P19: =INDEX('Steelmint prices for last 36m'!$A$29:$N$80,MATCH('Plant wise prices'!P$2,'Steelmint prices for last 36m'!$A$29:$A$80,0),MATCH('Plant wise prices'!$D19,'Steelmint prices for last 36m'!$A$29:$N$29,0)) -> 44542.222
A20: 550D | B20: =B8 -> GERMAN GREEN STEEL AND POWER LIMITED | C20: 1200 | D20: =D8 -> Ahmedabad | E20: =INDEX('Steelmint prices for last 36m'!$A$29:$N$80,MATCH('Plant wise prices'!E$2,'Steelmint prices for last 36m'!$A$29:$A$80,0),MATCH('Plant wise prices'!$D20,'Steelmint prices for last 36m'!$A$29:$N$29,0)) -> 50322.333 | F20: =INDEX('Steelmint prices for last 36m'!$A$29:$N$80,MATCH('Plant wise prices'!F$2,'Steelmint prices for last 36m'!$A$29:$A$80,0),MATCH('Plant wise prices'!$D20,'Steelmint prices for last 36m'!$A$29:$N$29,0)) -> 49913.667 | G20: =INDEX('Steelmint prices for last 36m'!$A$29:$N$80,MATCH('Plant wise prices'!G$2,'Steelmint prices for last 36m'!$A$29:$A$80,0),MATCH('Plant wise prices'!$D20,'Steelmint prices for last 36m'!$A$29:$N$29,0)) -> 48520.667 | H20: =INDEX('Steelmint prices for last 36m'!$A$29:$N$80,MATCH('Plant wise prices'!H$2,'Steelmint prices for last 36m'!$A$29:$A$80,0),MATCH('Plant wise prices'!$D20,'Steelmint prices for last 36m'!$A$29:$N$29,0)) -> 45967 | I20: =INDEX('Steelmint prices for last 36m'!$A$29:$N$80,MATCH('Plant wise prices'!I$2,'Steelmint prices for last 36m'!$A$29:$A$80,0),MATCH('Plant wise prices'!$D20,'Steelmint prices for last 36m'!$A$29:$N$29,0)) -> 46257.333 | J20: =INDEX('Steelmint prices for last 36m'!$A$29:$N$80,MATCH('Plant wise prices'!J$2,'Steelmint prices for last 36m'!$A$29:$A$80,0),MATCH('Plant wise prices'!$D20,'Steelmint prices for last 36m'!$A$29:$N$29,0)) -> 46615.333 | K20: =INDEX('Steelmint prices for last 36m'!$A$29:$N$80,MATCH('Plant wise prices'!K$2,'Steelmint prices for last 36m'!$A$29:$A$80,0),MATCH('Plant wise prices'!$D20,'Steelmint prices for last 36m'!$A$29:$N$29,0)) -> 46281.333 | L20: =INDEX('Steelmint prices for last 36m'!$A$29:$N$80,MATCH('Plant wise prices'!L$2,'Steelmint prices for last 36m'!$A$29:$A$80,0),MATCH('Plant wise prices'!$D20,'Steelmint prices for last 36m'!$A$29:$N$29,0)) -> 45582.667 | ... P20: =INDEX('Steelmint prices for last 36m'!$A$29:$N$80,MATCH('Plant wise prices'!P$2,'Steelmint prices for last 36m'!$A$29:$A$80,0),MATCH('Plant wise prices'!$D20,'Steelmint prices for last 36m'!$A$29:$N$29,0)) -> 48395.111
A21: 550D | B21: =B9 -> SKA Ispat Private Limited | C21: 3075 | D21: =D9 -> Raipur | E21: =INDEX('Steelmint prices for last 36m'!$A$29:$N$80,MATCH('Plant wise prices'!E$2,'Steelmint prices for last 36m'!$A$29:$A$80,0),MATCH('Plant wise prices'!$D21,'Steelmint prices for last 36m'!$A$29:$N$29,0)) -> 47358.333 | F21: =INDEX('Steelmint prices for last 36m'!$A$29:$N$80,MATCH('Plant wise prices'!F$2,'Steelmint prices for last 36m'!$A$29:$A$80,0),MATCH('Plant wise prices'!$D21,'Steelmint prices for last 36m'!$A$29:$N$29,0)) -> 46368 | G21: =INDEX('Steelmint prices for last 36m'!$A$29:$N$80,MATCH('Plant wise prices'!G$2,'Steelmint prices for last 36m'!$A$29:$A$80,0),MATCH('Plant wise prices'!$D21,'Steelmint prices for last 36m'!$A$29:$N$29,0)) -> 44909 | H21: =INDEX('Steelmint prices for last 36m'!$A$29:$N$80,MATCH('Plant wise prices'!H$2,'Steelmint prices for last 36m'!$A$29:$A$80,0),MATCH('Plant wise prices'!$D21,'Steelmint prices for last 36m'!$A$29:$N$29,0)) -> 42005.667 | I21: =INDEX('Steelmint prices for last 36m'!$A$29:$N$80,MATCH('Plant wise prices'!I$2,'Steelmint prices for last 36m'!$A$29:$A$80,0),MATCH('Plant wise prices'!$D21,'Steelmint prices for last 36m'!$A$29:$N$29,0)) -> 42310 | J21: =INDEX('Steelmint prices for last 36m'!$A$29:$N$80,MATCH('Plant wise prices'!J$2,'Steelmint prices for last 36m'!$A$29:$A$80,0),MATCH('Plant wise prices'!$D21,'Steelmint prices for last 36m'!$A$29:$N$29,0)) -> 42985.667 | K21: =INDEX('Steelmint prices for last 36m'!$A$29:$N$80,MATCH('Plant wise prices'!K$2,'Steelmint prices for last 36m'!$A$29:$A$80,0),MATCH('Plant wise prices'!$D21,'Steelmint prices for last 36m'!$A$29:$N$29,0)) -> 42769.333 | L21: =INDEX('Steelmint prices for last 36m'!$A$29:$N$80,MATCH('Plant wise prices'!L$2,'Steelmint prices for last 36m'!$A$29:$A$80,0),MATCH('Plant wise prices'!$D21,'Steelmint prices for last 36m'!$A$29:$N$29,0)) -> 41708 | ... P21: =INDEX('Steelmint prices for last 36m'!$A$29:$N$80,MATCH('Plant wise prices'!P$2,'Steelmint prices for last 36m'!$A$29:$A$80,0),MATCH('Plant wise prices'!$D21,'Steelmint prices for last 36m'!$A$29:$N$29,0)) -> 44542.222
A22: 550D | B22: =B10 -> Real Ispat | C22: 4500 | D22: =D10 -> Raipur | E22: =INDEX('Steelmint prices for last 36m'!$A$29:$N$80,MATCH('Plant wise prices'!E$2,'Steelmint prices for last 36m'!$A$29:$A$80,0),MATCH('Plant wise prices'!$D22,'Steelmint prices for last 36m'!$A$29:$N$29,0)) -> 47358.333 | F22: =INDEX('Steelmint prices for last 36m'!$A$29:$N$80,MATCH('Plant wise prices'!F$2,'Steelmint prices for last 36m'!$A$29:$A$80,0),MATCH('Plant wise prices'!$D22,'Steelmint prices for last 36m'!$A$29:$N$29,0)) -> 46368 | G22: =INDEX('Steelmint prices for last 36m'!$A$29:$N$80,MATCH('Plant wise prices'!G$2,'Steelmint prices for last 36m'!$A$29:$A$80,0),MATCH('Plant wise prices'!$D22,'Steelmint prices for last 36m'!$A$29:$N$29,0)) -> 44909 | H22: =INDEX('Steelmint prices for last 36m'!$A$29:$N$80,MATCH('Plant wise prices'!H$2,'Steelmint prices for last 36m'!$A$29:$A$80,0),MATCH('Plant wise prices'!$D22,'Steelmint prices for last 36m'!$A$29:$N$29,0)) -> 42005.667 | I22: =INDEX('Steelmint prices for last 36m'!$A$29:$N$80,MATCH('Plant wise prices'!I$2,'Steelmint prices for last 36m'!$A$29:$A$80,0),MATCH('Plant wise prices'!$D22,'Steelmint prices for last 36m'!$A$29:$N$29,0)) -> 42310 | J22: =INDEX('Steelmint prices for last 36m'!$A$29:$N$80,MATCH('Plant wise prices'!J$2,'Steelmint prices for last 36m'!$A$29:$A$80,0),MATCH('Plant wise prices'!$D22,'Steelmint prices for last 36m'!$A$29:$N$29,0)) -> 42985.667 | K22: =INDEX('Steelmint prices for last 36m'!$A$29:$N$80,MATCH('Plant wise prices'!K$2,'Steelmint prices for last 36m'!$A$29:$A$80,0),MATCH('Plant wise prices'!$D22,'Steelmint prices for last 36m'!$A$29:$N$29,0)) -> 42769.333 | L22: =INDEX('Steelmint prices for last 36m'!$A$29:$N$80,MATCH('Plant wise prices'!L$2,'Steelmint prices for last 36m'!$A$29:$A$80,0),MATCH('Plant wise prices'!$D22,'Steelmint prices for last 36m'!$A$29:$N$29,0)) -> 41708 | ... P22: =INDEX('Steelmint prices for last 36m'!$A$29:$N$80,MATCH('Plant wise prices'!P$2,'Steelmint prices for last 36m'!$A$29:$A$80,0),MATCH('Plant wise prices'!$D22,'Steelmint prices for last 36m'!$A$29:$N$29,0)) -> 44542.222
A23: 550D | B23: =B11 -> Rashmi Steel | C23: 3665 | D23: =D11 -> Durgapur | E23: =INDEX('Steelmint prices for last 36m'!$A$29:$N$80,MATCH('Plant wise prices'!E$2,'Steelmint prices for last 36m'!$A$29:$A$80,0),MATCH('Plant wise prices'!$D23,'Steelmint prices for last 36m'!$A$29:$N$29,0)) -> 47844.333 | F23: =INDEX('Steelmint prices for last 36m'!$A$29:$N$80,MATCH('Plant wise prices'!F$2,'Steelmint prices for last 36m'!$A$29:$A$80,0),MATCH('Plant wise prices'!$D23,'Steelmint prices for last 36m'!$A$29:$N$29,0)) -> 46166.667 | G23: =INDEX('Steelmint prices for last 36m'!$A$29:$N$80,MATCH('Plant wise prices'!G$2,'Steelmint prices for last 36m'!$A$29:$A$80,0),MATCH('Plant wise prices'!$D23,'Steelmint prices for last 36m'!$A$29:$N$29,0)) -> 44392 | H23: =INDEX('Steelmint prices for last 36m'!$A$29:$N$80,MATCH('Plant wise prices'!H$2,'Steelmint prices for last 36m'!$A$29:$A$80,0),MATCH('Plant wise prices'!$D23,'Steelmint prices for last 36m'!$A$29:$N$29,0)) -> 42156 | I23: =INDEX('Steelmint prices for last 36m'!$A$29:$N$80,MATCH('Plant wise prices'!I$2,'Steelmint prices for last 36m'!$A$29:$A$80,0),MATCH('Plant wise prices'!$D23,'Steelmint prices for last 36m'!$A$29:$N$29,0)) -> 42114.333 | J23: =INDEX('Steelmint prices for last 36m'!$A$29:$N$80,MATCH('Plant wise prices'!J$2,'Steelmint prices for last 36m'!$A$29:$A$80,0),MATCH('Plant wise prices'!$D23,'Steelmint prices for last 36m'!$A$29:$N$29,0)) -> 42390 | K23: =INDEX('Steelmint prices for last 36m'!$A$29:$N$80,MATCH('Plant wise prices'!K$2,'Steelmint prices for last 36m'!$A$29:$A$80,0),MATCH('Plant wise prices'!$D23,'Steelmint prices for last 36m'!$A$29:$N$29,0)) -> 42379 | L23: =INDEX('Steelmint prices for last 36m'!$A$29:$N$80,MATCH('Plant wise prices'!L$2,'Steelmint prices for last 36m'!$A$29:$A$80,0),MATCH('Plant wise prices'!$D23,'Steelmint prices for last 36m'!$A$29:$N$29,0)) -> 41367.667 | ... P23: =INDEX('Steelmint prices for last 36m'!$A$29:$N$80,MATCH('Plant wise prices'!P$2,'Steelmint prices for last 36m'!$A$29:$A$80,0),MATCH('Plant wise prices'!$D23,'Steelmint prices for last 36m'!$A$29:$N$29,0)) -> 44539.778
A24: 550D | B24: =B12 -> Telangana - New Plant | C24: 3665 | D24: Hyderabad | E24: =INDEX('Steelmint prices for last 36m'!$A$29:$N$80,MATCH('Plant wise prices'!E$2,'Steelmint prices for last 36m'!$A$29:$A$80,0),MATCH('Plant wise prices'!$D24,'Steelmint prices for last 36m'!$A$29:$N$29,0)) -> 49673.667 | F24: =INDEX('Steelmint prices for last 36m'!$A$29:$N$80,MATCH('Plant wise prices'!F$2,'Steelmint prices for last 36m'!$A$29:$A$80,0),MATCH('Plant wise prices'!$D24,'Steelmint prices for last 36m'!$A$29:$N$29,0)) -> 48756 | G24: =INDEX('Steelmint prices for last 36m'!$A$29:$N$80,MATCH('Plant wise prices'!G$2,'Steelmint prices for last 36m'!$A$29:$A$80,0),MATCH('Plant wise prices'!$D24,'Steelmint prices for last 36m'!$A$29:$N$29,0)) -> 46797.667 | H24: =INDEX('Steelmint prices for last 36m'!$A$29:$N$80,MATCH('Plant wise prices'!H$2,'Steelmint prices for last 36m'!$A$29:$A$80,0),MATCH('Plant wise prices'!$D24,'Steelmint prices for last 36m'!$A$29:$N$29,0)) -> 45036 | I24: =INDEX('Steelmint prices for last 36m'!$A$29:$N$80,MATCH('Plant wise prices'!I$2,'Steelmint prices for last 36m'!$A$29:$A$80,0),MATCH('Plant wise prices'!$D24,'Steelmint prices for last 36m'!$A$29:$N$29,0)) -> 44642.333 | J24: =INDEX('Steelmint prices for last 36m'!$A$29:$N$80,MATCH('Plant wise prices'!J$2,'Steelmint prices for last 36m'!$A$29:$A$80,0),MATCH('Plant wise prices'!$D24,'Steelmint prices for last 36m'!$A$29:$N$29,0)) -> 45460.667 | K24: =INDEX('Steelmint prices for last 36m'!$A$29:$N$80,MATCH('Plant wise prices'!K$2,'Steelmint prices for last 36m'!$A$29:$A$80,0),MATCH('Plant wise prices'!$D24,'Steelmint prices for last 36m'!$A$29:$N$29,0)) -> 45104 | L24: =INDEX('Steelmint prices for last 36m'!$A$29:$N$80,MATCH('Plant wise prices'!L$2,'Steelmint prices for last 36m'!$A$29:$A$80,0),MATCH('Plant wise prices'!$D24,'Steelmint prices for last 36m'!$A$29:$N$29,0)) -> 44154 | ... P24: =INDEX('Steelmint prices for last 36m'!$A$29:$N$80,MATCH('Plant wise prices'!P$2,'Steelmint prices for last 36m'!$A$29:$A$80,0),MATCH('Plant wise prices'!$D24,'Steelmint prices for last 36m'!$A$29:$N$29,0)) -> 47053.778
A25: 550D | B25: =B13 -> Maharashtra - New Plant | C25: 3665 | D25: Mumbai | E25: =INDEX('Steelmint prices for last 36m'!$A$29:$N$80,MATCH('Plant wise prices'!E$2,'Steelmint prices for last 36m'!$A$29:$A$80,0),MATCH('Plant wise prices'!$D25,'Steelmint prices for last 36m'!$A$29:$N$29,0)) -> 51608.667 | F25: =INDEX('Steelmint prices for last 36m'!$A$29:$N$80,MATCH('Plant wise prices'!F$2,'Steelmint prices for last 36m'!$A$29:$A$80,0),MATCH('Plant wise prices'!$D25,'Steelmint prices for last 36m'!$A$29:$N$29,0)) -> 51348 | G25: =INDEX('Steelmint prices for last 36m'!$A$29:$N$80,MATCH('Plant wise prices'!G$2,'Steelmint prices for last 36m'!$A$29:$A$80,0),MATCH('Plant wise prices'!$D25,'Steelmint prices for last 36m'!$A$29:$N$29,0)) -> 48694.667 | H25: =INDEX('Steelmint prices for last 36m'!$A$29:$N$80,MATCH('Plant wise prices'!H$2,'Steelmint prices for last 36m'!$A$29:$A$80,0),MATCH('Plant wise prices'!$D25,'Steelmint prices for last 36m'!$A$29:$N$29,0)) -> 45745.333 | I25: =INDEX('Steelmint prices for last 36m'!$A$29:$N$80,MATCH('Plant wise prices'!I$2,'Steelmint prices for last 36m'!$A$29:$A$80,0),MATCH('Plant wise prices'!$D25,'Steelmint prices for last 36m'!$A$29:$N$29,0)) -> 46515.333 | J25: =INDEX('Steelmint prices for last 36m'!$A$29:$N$80,MATCH('Plant wise prices'!J$2,'Steelmint prices for last 36m'!$A$29:$A$80,0),MATCH('Plant wise prices'!$D25,'Steelmint prices for last 36m'!$A$29:$N$29,0)) -> 47287.333 | K25: =INDEX('Steelmint prices for last 36m'!$A$29:$N$80,MATCH('Plant wise prices'!K$2,'Steelmint prices for last 36m'!$A$29:$A$80,0),MATCH('Plant wise prices'!$D25,'Steelmint prices for last 36m'!$A$29:$N$29,0)) -> 47096.333 | L25: =INDEX('Steelmint prices for last 36m'!$A$29:$N$80,MATCH('Plant wise prices'!L$2,'Steelmint prices for last 36m'!$A$29:$A$80,0),MATCH('Plant wise prices'!$D25,'Steelmint prices for last 36m'!$A$29:$N$29,0)) -> 46410.333 | ... P25: =INDEX('Steelmint prices for last 36m'!$A$29:$N$80,MATCH('Plant wise prices'!P$2,'Steelmint prices for last 36m'!$A$29:$A$80,0),MATCH('Plant wise prices'!$D25,'Steelmint prices for last 36m'!$A$29:$N$29,0)) -> 50040.556
A28: Purchase prices
A29: Grade | B29: CM | C29: Loading+BIS | D29: City for Steelmint pricing | E29: 46113 | F29: 46143 | G29: 46174 | H29: 46204 | I29: 46235 | J29: 46266 | K29: 46296 | L29: 46327 | M29: 46357 | N29: 46388 | O29: 46419 | P29: 46447
A30: 550 | B30: AIC IRON INDUSTRIES PRIVATE LIMITED | C30: 2970 | D30: Durgapur | E30: =E3+$C3 -> 50814.333 | F30: =F3+$C3 -> 49136.667 | G30: =G3+$C3 -> 47362 | H30: =H3+$C3 -> 45126 | I30: =I3+$C3 -> 45084.333 | J30: =J3+$C3 -> 45360 | K30: =K3+$C3 -> 45349 | L30: =L3+$C3 -> 44337.667 | ... P30: =P3+$C3 -> 47509.778
A31: 550 | B31: Aditya Industries | C31: 650 | D31: Mandi Gobindgarh | E31: =E4+$C4 -> 51574.333 | F31: =F4+$C4 -> 51184.667 | G31: =G4+$C4 -> 50362.333 | H31: =H4+$C4 -> 48448 | I31: =I4+$C4 -> 48145.667 | J31: =J4+$C4 -> 48009.667 | K31: =K4+$C4 -> 47746.333 | L31: =L4+$C4 -> 46976 | ... P31: =P4+$C4 -> 48745.556
A32: 550 | B32: Ambashakti Industries Limited | C32: 1400 | D32: Delhi/NCR | E32: =E5+$C5 -> 51840.333 | F32: =F5+$C5 -> 51197.667 | G32: =G5+$C5 -> 50037 | H32: =H5+$C5 -> 47897.333 | I32: =I5+$C5 -> 47373 | J32: =J5+$C5 -> 47328.667 | K32: =K5+$C5 -> 47153 | L32: =L5+$C5 -> 46274 | ... P32: =P5+$C5 -> 48892.889 | Q32: =SUMPRODUCT(E32:P32,E161:P161)/Q161 -> 48537.663
A33: 550 | B33: AMBASHAKTI UDYOG LIMITED- GWALIOR | C33: 1400 | E33: =E6+$C6 -> 51040.333 | F33: =F6+$C6 -> 50397.667 | G33: =G6+$C6 -> 49237 | H33: =H6+$C6 -> 47097.333 | I33: =I6+$C6 -> 46573 | J33: =J6+$C6 -> 46528.667 | K33: =K6+$C6 -> 46353 | L33: =L6+$C6 -> 45474 | ... P33: =P6+$C6 -> 48092.889
A34: 550 | B34: API Ispat And Powertech Private Limited | C34: 2415 | D34: Raipur | E34: =E7+$C7 -> 49773.333 | F34: =F7+$C7 -> 48783 | G34: =G7+$C7 -> 47324 | H34: =H7+$C7 -> 44420.667 | I34: =I7+$C7 -> 44725 | J34: =J7+$C7 -> 45400.667 | K34: =K7+$C7 -> 45184.333 | L34: =L7+$C7 -> 44123 | ... P34: =P7+$C7 -> 46957.222
A35: 550 | B35: GERMAN GREEN STEEL AND POWER LIMITED | C35: 200 | D35: Ahmedabad | E35: =E8+$C8 -> 50522.333 | F35: =F8+$C8 -> 50113.667 | G35: =G8+$C8 -> 48720.667 | H35: =H8+$C8 -> 46167 | I35: =I8+$C8 -> 46457.333 | J35: =J8+$C8 -> 46815.333 | K35: =K8+$C8 -> 46481.333 | L35: =L8+$C8 -> 45782.667 | ... P35: =P8+$C8 -> 48595.111
A36: 550 | B36: SKA Ispat Private Limited | C36: 2075 | D36: Raipur | E36: =E9+$C9 -> 49433.333 | F36: =F9+$C9 -> 48443 | G36: =G9+$C9 -> 46984 | H36: =H9+$C9 -> 44080.667 | I36: =I9+$C9 -> 44385 | J36: =J9+$C9 -> 45060.667 | K36: =K9+$C9 -> 44844.333 | L36: =L9+$C9 -> 43783 | ... P36: =P9+$C9 -> 46617.222
A37: 550 | B37: Real Ispat | C37: 0 | D37: Raipur | E37: =E10+$C10 -> 47358.333 | F37: =F10+$C10 -> 46368 | G37: =G10+$C10 -> 44909 | H37: =H10+$C10 -> 42005.667 | I37: =I10+$C10 -> 42310 | J37: =J10+$C10 -> 42985.667 | K37: =K10+$C10 -> 42769.333 | L37: =L10+$C10 -> 41708 | ... P37: =P10+$C10 -> 44542.222
A38: 550 | B38: Rashmi Steel | C38: 2415 | D38: Durgapur | E38: =E11+$C11 -> 50259.333 | F38: =F11+$C11 -> 48581.667 | G38: =G11+$C11 -> 46807 | H38: =H11+$C11 -> 44571 | I38: =I11+$C11 -> 44529.333 | J38: =J11+$C11 -> 44805 | K38: =K11+$C11 -> 44794 | L38: =L11+$C11 -> 43782.667 | ... P38: =P11+$C11 -> 46954.778
A39: 550 | B39: Telangana - New Plant | C39: 2415 | D39: Hyderabad | E39: =E12+$C12 -> 52088.667 | F39: =F12+$C12 -> 51171 | G39: =G12+$C12 -> 49212.667 | H39: =H12+$C12 -> 47451 | I39: =I12+$C12 -> 47057.333 | J39: =J12+$C12 -> 47875.667 | K39: =K12+$C12 -> 47519 | L39: =L12+$C12 -> 46569 | ... P39: =P12+$C12 -> 49468.778
A40: 550 | B40: Maharashtra - New Plant | C40: 2415 | D40: Mumbai | E40: =E13+$C13 -> 54023.667 | F40: =F13+$C13 -> 53763 | G40: =G13+$C13 -> 51109.667 | H40: =H13+$C13 -> 48160.333 | I40: =I13+$C13 -> 48930.333 | J40: =J13+$C13 -> 49702.333 | K40: =K13+$C13 -> 49511.333 | L40: =L13+$C13 -> 48825.333 | ... P40: =P13+$C13 -> 52455.556
A42: 550D | B42: AIC IRON INDUSTRIES PRIVATE LIMITED | C42: 3770 | D42: Durgapur | E42: =E15+$C15 -> 51614.333 | F42: =F15+$C15 -> 49936.667 | G42: =G15+$C15 -> 48162 | H42: =H15+$C15 -> 45926 | I42: =I15+$C15 -> 45884.333 | J42: =J15+$C15 -> 46160 | K42: =K15+$C15 -> 46149 | L42: =L15+$C15 -> 45137.667 | ... P42: =P15+$C15 -> 48309.778
A43: 550D | B43: Aditya Industries | C43: 1450 | D43: Mandi Gobindgarh | E43: =E16+$C16 -> 52374.333 | F43: =F16+$C16 -> 51984.667 | G43: =G16+$C16 -> 51162.333 | H43: =H16+$C16 -> 49248 | I43: =I16+$C16 -> 48945.667 | J43: =J16+$C16 -> 48809.667 | K43: =K16+$C16 -> 48546.333 | L43: =L16+$C16 -> 47776 | ... P43: =P16+$C16 -> 49545.556
A44: 550D | B44: Ambashakti Industries Limited | C44: 2400 | D44: Delhi/NCR | E44: =E17+$C17 -> 52840.333 | F44: =F17+$C17 -> 52197.667 | G44: =G17+$C17 -> 51037 | H44: =H17+$C17 -> 48897.333 | I44: =I17+$C17 -> 48373 | J44: =J17+$C17 -> 48328.667 | K44: =K17+$C17 -> 48153 | L44: =L17+$C17 -> 47274 | ... P44: =P17+$C17 -> 49892.889
A45: 550D | B45: AMBASHAKTI UDYOG LIMITED- GWALIOR | C45: 3400 | E45: =E18+$C18 -> 53040.333 | F45: =F18+$C18 -> 52397.667 | G45: =G18+$C18 -> 51237 | H45: =H18+$C18 -> 49097.333 | I45: =I18+$C18 -> 48573 | J45: =J18+$C18 -> 48528.667 | K45: =K18+$C18 -> 48353 | L45: =L18+$C18 -> 47474 | ... P45: =P18+$C18 -> 50092.889
A46: 550D | B46: API Ispat And Powertech Private Limited | C46: 3665 | D46: Raipur | E46: =E19+$C19 -> 51023.333 | F46: =F19+$C19 -> 50033 | G46: =G19+$C19 -> 48574 | H46: =H19+$C19 -> 45670.667 | I46: =I19+$C19 -> 45975 | J46: =J19+$C19 -> 46650.667 | K46: =K19+$C19 -> 46434.333 | L46: =L19+$C19 -> 45373 | ... P46: =P19+$C19 -> 48207.222
A47: 550D | B47: GERMAN GREEN STEEL AND POWER LIMITED | C47: 1200 | D47: Ahmedabad | E47: =E20+$C20 -> 51522.333 | F47: =F20+$C20 -> 51113.667 | G47: =G20+$C20 -> 49720.667 | H47: =H20+$C20 -> 47167 | I47: =I20+$C20 -> 47457.333 | J47: =J20+$C20 -> 47815.333 | K47: =K20+$C20 -> 47481.333 | L47: =L20+$C20 -> 46782.667 | ... P47: =P20+$C20 -> 49595.111
A48: 550D | B48: SKA Ispat Private Limited | C48: 3075 | D48: Raipur | E48: =E21+$C21 -> 50433.333 | F48: =F21+$C21 -> 49443 | G48: =G21+$C21 -> 47984 | H48: =H21+$C21 -> 45080.667 | I48: =I21+$C21 -> 45385 | J48: =J21+$C21 -> 46060.667 | K48: =K21+$C21 -> 45844.333 | L48: =L21+$C21 -> 44783 | ... P48: =P21+$C21 -> 47617.222
A49: 550D | B49: Real Ispat | C49: 4500 | D49: Raipur | E49: =E22+$C22 -> 51858.333 | F49: =F22+$C22 -> 50868 | G49: =G22+$C22 -> 49409 | H49: =H22+$C22 -> 46505.667 | I49: =I22+$C22 -> 46810 | J49: =J22+$C22 -> 47485.667 | K49: =K22+$C22 -> 47269.333 | L49: =L22+$C22 -> 46208 | ... P49: =P22+$C22 -> 49042.222
A50: 550D | B50: Rashmi Steel | C50: 3665 | D50: Durgapur | E50: =E23+$C23 -> 51509.333 | F50: =F23+$C23 -> 49831.667 | G50: =G23+$C23 -> 48057 | H50: =H23+$C23 -> 45821 | I50: =I23+$C23 -> 45779.333 | J50: =J23+$C23 -> 46055 | K50: =K23+$C23 -> 46044 | L50: =L23+$C23 -> 45032.667 | ... P50: =P23+$C23 -> 48204.778
A51: 550D | B51: Telangana - New Plant | C51: 3665 | D51: Hyderabad | E51: =E24+$C24 -> 53338.667 | F51: =F24+$C24 -> 52421 | G51: =G24+$C24 -> 50462.667 | H51: =H24+$C24 -> 48701 | I51: =I24+$C24 -> 48307.333 | J51: =J24+$C24 -> 49125.667 | K51: =K24+$C24 -> 48769 | L51: =L24+$C24 -> 47819 | ... P51: =P24+$C24 -> 50718.778
A52: 550D | B52: Maharashtra - New Plant | C52: 3665 | D52: Mumbai | E52: =E25+$C25 -> 55273.667 | F52: =F25+$C25 -> 55013 | G52: =G25+$C25 -> 52359.667 | H52: =H25+$C25 -> 49410.333 | I52: =I25+$C25 -> 50180.333 | J52: =J25+$C25 -> 50952.333 | K52: =K25+$C25 -> 50761.333 | L52: =L25+$C25 -> 50075.333 | ... P52: =P25+$C25 -> 53705.556
A53: One helix
A54: Grade | B54: CM | C54: Loading+BIS | D54: City for Steelmint pricing
A55: 550 | B55: AIC IRON INDUSTRIES PRIVATE LIMITED | C55: 2970 | D55: Durgapur | E55: =E30 -> 50814.333 | F55: =F30 -> 49136.667 | G55: =G30 -> 47362 | H55: =H30 -> 45126 | I55: =I30 -> 45084.333 | J55: =J30 -> 45360 | K55: =K30 -> 45349 | L55: =L30 -> 44337.667 | ... P55: =P30 -> 47509.778
A56: 550 | B56: Aditya Industries | C56: 650 | D56: Mandi Gobindgarh | E56: =E31 -> 51574.333 | F56: =F31 -> 51184.667 | G56: =G31 -> 50362.333 | H56: =H31 -> 48448 | I56: =I31 -> 48145.667 | J56: =J31 -> 48009.667 | K56: =K31 -> 47746.333 | L56: =L31 -> 46976 | ... P56: =P31 -> 48745.556
A57: 550 | B57: Ambashakti Industries Limited | C57: 1400 | D57: Delhi/NCR | E57: =E32 -> 51840.333 | F57: =F32 -> 51197.667 | G57: =G32 -> 50037 | H57: =H32 -> 47897.333 | I57: =I32 -> 47373 | J57: =J32 -> 47328.667 | K57: =K32 -> 47153 | L57: =L32 -> 46274 | ... P57: =P32 -> 48892.889
A58: 550 | B58: AMBASHAKTI UDYOG LIMITED- GWALIOR | C58: 1400 | E58: =E33 -> 51040.333 | F58: =F33 -> 50397.667 | G58: =G33 -> 49237 | H58: =H33 -> 47097.333 | I58: =I33 -> 46573 | J58: =J33 -> 46528.667 | K58: =K33 -> 46353 | L58: =L33 -> 45474 | ... P58: =P33 -> 48092.889
A59: 550 | B59: API Ispat And Powertech Private Limited | C59: 2415 | D59: Raipur | E59: =E34 -> 49773.333 | F59: =F34 -> 48783 | G59: =G34 -> 47324 | H59: =H34 -> 44420.667 | I59: =I34 -> 44725 | J59: =J34 -> 45400.667 | K59: =K34 -> 45184.333 | L59: =L34 -> 44123 | ... P59: =P34 -> 46957.222
A60: 550 | B60: GERMAN GREEN STEEL AND POWER LIMITED | C60: 200 | D60: Ahmedabad | E60: =E35 -> 50522.333 | F60: =F35 -> 50113.667 | G60: =G35 -> 48720.667 | H60: =H35 -> 46167 | I60: =I35 -> 46457.333 | J60: =J35 -> 46815.333 | K60: =K35 -> 46481.333 | L60: =L35 -> 45782.667 | ... P60: =P35 -> 48595.111
A61: 550 | B61: SKA Ispat Private Limited | C61: 2075 | D61: Raipur | E61: =E36 -> 49433.333 | F61: =F36 -> 48443 | G61: =G36 -> 46984 | H61: =H36 -> 44080.667 | I61: =I36 -> 44385 | J61: =J36 -> 45060.667 | K61: =K36 -> 44844.333 | L61: =L36 -> 43783 | ... P61: =P36 -> 46617.222
A62: 550 | B62: Real Ispat | C62: 0 | D62: Raipur | E62: =E37 -> 47358.333 | F62: =F37 -> 46368 | G62: =G37 -> 44909 | H62: =H37 -> 42005.667 | I62: =I37 -> 42310 | J62: =J37 -> 42985.667 | K62: =K37 -> 42769.333 | L62: =L37 -> 41708 | ... P62: =P37 -> 44542.222
A63: 550 | B63: Rashmi Steel | C63: 2415 | D63: Durgapur | E63: =E38 -> 50259.333 | F63: =F38 -> 48581.667 | G63: =G38 -> 46807 | H63: =H38 -> 44571 | I63: =I38 -> 44529.333 | J63: =J38 -> 44805 | K63: =K38 -> 44794 | L63: =L38 -> 43782.667 | ... P63: =P38 -> 46954.778
A64: 550 | B64: Telangana - New Plant | C64: 2415 | D64: Hyderabad | E64: =E39 -> 52088.667 | F64: =F39 -> 51171 | G64: =G39 -> 49212.667 | H64: =H39 -> 47451 | I64: =I39 -> 47057.333 | J64: =J39 -> 47875.667 | K64: =K39 -> 47519 | L64: =L39 -> 46569 | ... P64: =P39 -> 49468.778
A65: 550 | B65: Maharashtra - New Plant | C65: 2415 | D65: Mumbai | E65: =E40 -> 54023.667 | F65: =F40 -> 53763 | G65: =G40 -> 51109.667 | H65: =H40 -> 48160.333 | I65: =I40 -> 48930.333 | J65: =J40 -> 49702.333 | K65: =K40 -> 49511.333 | L65: =L40 -> 48825.333 | ... P65: =P40 -> 52455.556
A69: Sales price
A70: Grade | B70: CM | E70: 46113 | F70: 46143 | G70: 46174 | H70: 46204 | I70: 46235 | J70: 46266 | K70: 46296 | L70: 46327 | M70: 46357 | N70: 46388 | O70: 46419 | P70: 46447
A71: 550 | B71: AIC IRON INDUSTRIES PRIVATE LIMITED | E71: =INDEX('Sales price'!$P$1:$AA$19,MATCH('Plant wise prices'!E$70,'Sales price'!$P$1:$P$19,0),MATCH('Plant wise prices'!$B71,'Sales price'!$P$1:$AA$1,0)) -> 53750 | F71: =INDEX('Sales price'!$P$1:$AA$19,MATCH('Plant wise prices'!F$70,'Sales price'!$P$1:$P$19,0),MATCH('Plant wise prices'!$B71,'Sales price'!$P$1:$AA$1,0)) -> 52750 | G71: =INDEX('Sales price'!$P$1:$AA$19,MATCH('Plant wise prices'!G$70,'Sales price'!$P$1:$P$19,0),MATCH('Plant wise prices'!$B71,'Sales price'!$P$1:$AA$1,0)) -> 50750 | H71: =INDEX('Sales price'!$P$1:$AA$19,MATCH('Plant wise prices'!H$70,'Sales price'!$P$1:$P$19,0),MATCH('Plant wise prices'!$B71,'Sales price'!$P$1:$AA$1,0)) -> 47750 | I71: =INDEX('Sales price'!$P$1:$AA$19,MATCH('Plant wise prices'!I$70,'Sales price'!$P$1:$P$19,0),MATCH('Plant wise prices'!$B71,'Sales price'!$P$1:$AA$1,0)) -> 46750 | J71: =INDEX('Sales price'!$P$1:$AA$19,MATCH('Plant wise prices'!J$70,'Sales price'!$P$1:$P$19,0),MATCH('Plant wise prices'!$B71,'Sales price'!$P$1:$AA$1,0)) -> 47750 | K71: =INDEX('Sales price'!$P$1:$AA$19,MATCH('Plant wise prices'!K$70,'Sales price'!$P$1:$P$19,0),MATCH('Plant wise prices'!$B71,'Sales price'!$P$1:$AA$1,0)) -> 49750 | L71: =INDEX('Sales price'!$P$1:$AA$19,MATCH('Plant wise prices'!L$70,'Sales price'!$P$1:$P$19,0),MATCH('Plant wise prices'!$B71,'Sales price'!$P$1:$AA$1,0)) -> 48750 | ... P71: =INDEX('Sales price'!$P$1:$AA$19,MATCH('Plant wise prices'!P$70,'Sales price'!$P$1:$P$19,0),MATCH('Plant wise prices'!$B71,'Sales price'!$P$1:$AA$1,0)) -> 50750
A72: 550 | B72: Aditya Industries | E72: =INDEX('Sales price'!$P$1:$AA$19,MATCH('Plant wise prices'!E$70,'Sales price'!$P$1:$P$19,0),MATCH('Plant wise prices'!$B72,'Sales price'!$P$1:$AA$1,0)) -> 54000 | F72: =INDEX('Sales price'!$P$1:$AA$19,MATCH('Plant wise prices'!F$70,'Sales price'!$P$1:$P$19,0),MATCH('Plant wise prices'!$B72,'Sales price'!$P$1:$AA$1,0)) -> 53000 | G72: =INDEX('Sales price'!$P$1:$AA$19,MATCH('Plant wise prices'!G$70,'Sales price'!$P$1:$P$19,0),MATCH('Plant wise prices'!$B72,'Sales price'!$P$1:$AA$1,0)) -> 51000 | H72: =INDEX('Sales price'!$P$1:$AA$19,MATCH('Plant wise prices'!H$70,'Sales price'!$P$1:$P$19,0),MATCH('Plant wise prices'!$B72,'Sales price'!$P$1:$AA$1,0)) -> 48000 | I72: =INDEX('Sales price'!$P$1:$AA$19,MATCH('Plant wise prices'!I$70,'Sales price'!$P$1:$P$19,0),MATCH('Plant wise prices'!$B72,'Sales price'!$P$1:$AA$1,0)) -> 47000 | J72: =INDEX('Sales price'!$P$1:$AA$19,MATCH('Plant wise prices'!J$70,'Sales price'!$P$1:$P$19,0),MATCH('Plant wise prices'!$B72,'Sales price'!$P$1:$AA$1,0)) -> 48000 | K72: =INDEX('Sales price'!$P$1:$AA$19,MATCH('Plant wise prices'!K$70,'Sales price'!$P$1:$P$19,0),MATCH('Plant wise prices'!$B72,'Sales price'!$P$1:$AA$1,0)) -> 50000 | L72: =INDEX('Sales price'!$P$1:$AA$19,MATCH('Plant wise prices'!L$70,'Sales price'!$P$1:$P$19,0),MATCH('Plant wise prices'!$B72,'Sales price'!$P$1:$AA$1,0)) -> 49000 | ... P72: =INDEX('Sales price'!$P$1:$AA$19,MATCH('Plant wise prices'!P$70,'Sales price'!$P$1:$P$19,0),MATCH('Plant wise prices'!$B72,'Sales price'!$P$1:$AA$1,0)) -> 51000
A73: 550 | B73: Ambashakti Industries Limited | E73: =INDEX('Sales price'!$P$1:$AA$19,MATCH('Plant wise prices'!E$70,'Sales price'!$P$1:$P$19,0),MATCH('Plant wise prices'!$B73,'Sales price'!$P$1:$AA$1,0)) -> 55000 | F73: =INDEX('Sales price'!$P$1:$AA$19,MATCH('Plant wise prices'!F$70,'Sales price'!$P$1:$P$19,0),MATCH('Plant wise prices'!$B73,'Sales price'!$P$1:$AA$1,0)) -> 54000 | G73: =INDEX('Sales price'!$P$1:$AA$19,MATCH('Plant wise prices'!G$70,'Sales price'!$P$1:$P$19,0),MATCH('Plant wise prices'!$B73,'Sales price'!$P$1:$AA$1,0)) -> 52000 | H73: =INDEX('Sales price'!$P$1:$AA$19,MATCH('Plant wise prices'!H$70,'Sales price'!$P$1:$P$19,0),MATCH('Plant wise prices'!$B73,'Sales price'!$P$1:$AA$1,0)) -> 49000 | I73: =INDEX('Sales price'!$P$1:$AA$19,MATCH('Plant wise prices'!I$70,'Sales price'!$P$1:$P$19,0),MATCH('Plant wise prices'!$B73,'Sales price'!$P$1:$AA$1,0)) -> 48000 | J73: =INDEX('Sales price'!$P$1:$AA$19,MATCH('Plant wise prices'!J$70,'Sales price'!$P$1:$P$19,0),MATCH('Plant wise prices'!$B73,'Sales price'!$P$1:$AA$1,0)) -> 49000 | K73: =INDEX('Sales price'!$P$1:$AA$19,MATCH('Plant wise prices'!K$70,'Sales price'!$P$1:$P$19,0),MATCH('Plant wise prices'!$B73,'Sales price'!$P$1:$AA$1,0)) -> 51000 | L73: =INDEX('Sales price'!$P$1:$AA$19,MATCH('Plant wise prices'!L$70,'Sales price'!$P$1:$P$19,0),MATCH('Plant wise prices'!$B73,'Sales price'!$P$1:$AA$1,0)) -> 50000 | ... P73: =INDEX('Sales price'!$P$1:$AA$19,MATCH('Plant wise prices'!P$70,'Sales price'!$P$1:$P$19,0),MATCH('Plant wise prices'!$B73,'Sales price'!$P$1:$AA$1,0)) -> 52000 | Q73: =SUMPRODUCT(E73:P73,E161:P161)/Q161 -> 51003.567
A74: 550 | B74: AMBASHAKTI UDYOG LIMITED- GWALIOR | E74: =INDEX('Sales price'!$P$1:$AA$19,MATCH('Plant wise prices'!E$70,'Sales price'!$P$1:$P$19,0),MATCH('Plant wise prices'!$B74,'Sales price'!$P$1:$AA$1,0)) -> 54200 | F74: =INDEX('Sales price'!$P$1:$AA$19,MATCH('Plant wise prices'!F$70,'Sales price'!$P$1:$P$19,0),MATCH('Plant wise prices'!$B74,'Sales price'!$P$1:$AA$1,0)) -> 53200 | G74: =INDEX('Sales price'!$P$1:$AA$19,MATCH('Plant wise prices'!G$70,'Sales price'!$P$1:$P$19,0),MATCH('Plant wise prices'!$B74,'Sales price'!$P$1:$AA$1,0)) -> 51200 | H74: =INDEX('Sales price'!$P$1:$AA$19,MATCH('Plant wise prices'!H$70,'Sales price'!$P$1:$P$19,0),MATCH('Plant wise prices'!$B74,'Sales price'!$P$1:$AA$1,0)) -> 48200 | I74: =INDEX('Sales price'!$P$1:$AA$19,MATCH('Plant wise prices'!I$70,'Sales price'!$P$1:$P$19,0),MATCH('Plant wise prices'!$B74,'Sales price'!$P$1:$AA$1,0)) -> 47200 | J74: =INDEX('Sales price'!$P$1:$AA$19,MATCH('Plant wise prices'!J$70,'Sales price'!$P$1:$P$19,0),MATCH('Plant wise prices'!$B74,'Sales price'!$P$1:$AA$1,0)) -> 48200 | K74: =INDEX('Sales price'!$P$1:$AA$19,MATCH('Plant wise prices'!K$70,'Sales price'!$P$1:$P$19,0),MATCH('Plant wise prices'!$B74,'Sales price'!$P$1:$AA$1,0)) -> 50200 | L74: =INDEX('Sales price'!$P$1:$AA$19,MATCH('Plant wise prices'!L$70,'Sales price'!$P$1:$P$19,0),MATCH('Plant wise prices'!$B74,'Sales price'!$P$1:$AA$1,0)) -> 49200 | ... P74: =INDEX('Sales price'!$P$1:$AA$19,MATCH('Plant wise prices'!P$70,'Sales price'!$P$1:$P$19,0),MATCH('Plant wise prices'!$B74,'Sales price'!$P$1:$AA$1,0)) -> 51200
A75: 550 | B75: API Ispat And Powertech Private Limited | E75: =INDEX('Sales price'!$P$1:$AA$19,MATCH('Plant wise prices'!E$70,'Sales price'!$P$1:$P$19,0),MATCH('Plant wise prices'!$B75,'Sales price'!$P$1:$AA$1,0)) -> 53500 | F75: =INDEX('Sales price'!$P$1:$AA$19,MATCH('Plant wise prices'!F$70,'Sales price'!$P$1:$P$19,0),MATCH('Plant wise prices'!$B75,'Sales price'!$P$1:$AA$1,0)) -> 52500 | G75: =INDEX('Sales price'!$P$1:$AA$19,MATCH('Plant wise prices'!G$70,'Sales price'!$P$1:$P$19,0),MATCH('Plant wise prices'!$B75,'Sales price'!$P$1:$AA$1,0)) -> 50500 | H75: =INDEX('Sales price'!$P$1:$AA$19,MATCH('Plant wise prices'!H$70,'Sales price'!$P$1:$P$19,0),MATCH('Plant wise prices'!$B75,'Sales price'!$P$1:$AA$1,0)) -> 47500 | I75: =INDEX('Sales price'!$P$1:$AA$19,MATCH('Plant wise prices'!I$70,'Sales price'!$P$1:$P$19,0),MATCH('Plant wise prices'!$B75,'Sales price'!$P$1:$AA$1,0)) -> 46500 | J75: =INDEX('Sales price'!$P$1:$AA$19,MATCH('Plant wise prices'!J$70,'Sales price'!$P$1:$P$19,0),MATCH('Plant wise prices'!$B75,'Sales price'!$P$1:$AA$1,0)) -> 47500 | K75: =INDEX('Sales price'!$P$1:$AA$19,MATCH('Plant wise prices'!K$70,'Sales price'!$P$1:$P$19,0),MATCH('Plant wise prices'!$B75,'Sales price'!$P$1:$AA$1,0)) -> 49500 | L75: =INDEX('Sales price'!$P$1:$AA$19,MATCH('Plant wise prices'!L$70,'Sales price'!$P$1:$P$19,0),MATCH('Plant wise prices'!$B75,'Sales price'!$P$1:$AA$1,0)) -> 48500 | ... P75: =INDEX('Sales price'!$P$1:$AA$19,MATCH('Plant wise prices'!P$70,'Sales price'!$P$1:$P$19,0),MATCH('Plant wise prices'!$B75,'Sales price'!$P$1:$AA$1,0)) -> 50500
A76: 550 | B76: GERMAN GREEN STEEL AND POWER LIMITED | E76: =INDEX('Sales price'!$P$1:$AA$19,MATCH('Plant wise prices'!E$70,'Sales price'!$P$1:$P$19,0),MATCH('Plant wise prices'!$B76,'Sales price'!$P$1:$AA$1,0)) -> 53750 | F76: =INDEX('Sales price'!$P$1:$AA$19,MATCH('Plant wise prices'!F$70,'Sales price'!$P$1:$P$19,0),MATCH('Plant wise prices'!$B76,'Sales price'!$P$1:$AA$1,0)) -> 52750 | G76: =INDEX('Sales price'!$P$1:$AA$19,MATCH('Plant wise prices'!G$70,'Sales price'!$P$1:$P$19,0),MATCH('Plant wise prices'!$B76,'Sales price'!$P$1:$AA$1,0)) -> 50750 | H76: =INDEX('Sales price'!$P$1:$AA$19,MATCH('Plant wise prices'!H$70,'Sales price'!$P$1:$P$19,0),MATCH('Plant wise prices'!$B76,'Sales price'!$P$1:$AA$1,0)) -> 47750 | I76: =INDEX('Sales price'!$P$1:$AA$19,MATCH('Plant wise prices'!I$70,'Sales price'!$P$1:$P$19,0),MATCH('Plant wise prices'!$B76,'Sales price'!$P$1:$AA$1,0)) -> 46750 | J76: =INDEX('Sales price'!$P$1:$AA$19,MATCH('Plant wise prices'!J$70,'Sales price'!$P$1:$P$19,0),MATCH('Plant wise prices'!$B76,'Sales price'!$P$1:$AA$1,0)) -> 47750 | K76: =INDEX('Sales price'!$P$1:$AA$19,MATCH('Plant wise prices'!K$70,'Sales price'!$P$1:$P$19,0),MATCH('Plant wise prices'!$B76,'Sales price'!$P$1:$AA$1,0)) -> 49750 | L76: =INDEX('Sales price'!$P$1:$AA$19,MATCH('Plant wise prices'!L$70,'Sales price'!$P$1:$P$19,0),MATCH('Plant wise prices'!$B76,'Sales price'!$P$1:$AA$1,0)) -> 48750 | ... P76: =INDEX('Sales price'!$P$1:$AA$19,MATCH('Plant wise prices'!P$70,'Sales price'!$P$1:$P$19,0),MATCH('Plant wise prices'!$B76,'Sales price'!$P$1:$AA$1,0)) -> 50750
A77: 550 | B77: SKA Ispat Private Limited | E77: =INDEX('Sales price'!$P$1:$AA$19,MATCH('Plant wise prices'!E$70,'Sales price'!$P$1:$P$19,0),MATCH('Plant wise prices'!$B77,'Sales price'!$P$1:$AA$1,0)) -> 53500 | F77: =INDEX('Sales price'!$P$1:$AA$19,MATCH('Plant wise prices'!F$70,'Sales price'!$P$1:$P$19,0),MATCH('Plant wise prices'!$B77,'Sales price'!$P$1:$AA$1,0)) -> 52500 | G77: =INDEX('Sales price'!$P$1:$AA$19,MATCH('Plant wise prices'!G$70,'Sales price'!$P$1:$P$19,0),MATCH('Plant wise prices'!$B77,'Sales price'!$P$1:$AA$1,0)) -> 50500 | H77: =INDEX('Sales price'!$P$1:$AA$19,MATCH('Plant wise prices'!H$70,'Sales price'!$P$1:$P$19,0),MATCH('Plant wise prices'!$B77,'Sales price'!$P$1:$AA$1,0)) -> 47500 | I77: =INDEX('Sales price'!$P$1:$AA$19,MATCH('Plant wise prices'!I$70,'Sales price'!$P$1:$P$19,0),MATCH('Plant wise prices'!$B77,'Sales price'!$P$1:$AA$1,0)) -> 46500 | J77: =INDEX('Sales price'!$P$1:$AA$19,MATCH('Plant wise prices'!J$70,'Sales price'!$P$1:$P$19,0),MATCH('Plant wise prices'!$B77,'Sales price'!$P$1:$AA$1,0)) -> 47500 | K77: =INDEX('Sales price'!$P$1:$AA$19,MATCH('Plant wise prices'!K$70,'Sales price'!$P$1:$P$19,0),MATCH('Plant wise prices'!$B77,'Sales price'!$P$1:$AA$1,0)) -> 49500 | L77: =INDEX('Sales price'!$P$1:$AA$19,MATCH('Plant wise prices'!L$70,'Sales price'!$P$1:$P$19,0),MATCH('Plant wise prices'!$B77,'Sales price'!$P$1:$AA$1,0)) -> 48500 | ... P77: =INDEX('Sales price'!$P$1:$AA$19,MATCH('Plant wise prices'!P$70,'Sales price'!$P$1:$P$19,0),MATCH('Plant wise prices'!$B77,'Sales price'!$P$1:$AA$1,0)) -> 50500
A78: 550 | B78: Real Ispat
A79: 550 | B79: Rashmi Steel | E79: =INDEX('Sales price'!$P$1:$AA$19,MATCH('Plant wise prices'!E$70,'Sales price'!$P$1:$P$19,0),MATCH('Plant wise prices'!$B79,'Sales price'!$P$1:$AA$1,0)) -> 53750 | F79: =INDEX('Sales price'!$P$1:$AA$19,MATCH('Plant wise prices'!F$70,'Sales price'!$P$1:$P$19,0),MATCH('Plant wise prices'!$B79,'Sales price'!$P$1:$AA$1,0)) -> 52750 | G79: =INDEX('Sales price'!$P$1:$AA$19,MATCH('Plant wise prices'!G$70,'Sales price'!$P$1:$P$19,0),MATCH('Plant wise prices'!$B79,'Sales price'!$P$1:$AA$1,0)) -> 50750 | H79: =INDEX('Sales price'!$P$1:$AA$19,MATCH('Plant wise prices'!H$70,'Sales price'!$P$1:$P$19,0),MATCH('Plant wise prices'!$B79,'Sales price'!$P$1:$AA$1,0)) -> 47750 | I79: =INDEX('Sales price'!$P$1:$AA$19,MATCH('Plant wise prices'!I$70,'Sales price'!$P$1:$P$19,0),MATCH('Plant wise prices'!$B79,'Sales price'!$P$1:$AA$1,0)) -> 46750 | J79: =INDEX('Sales price'!$P$1:$AA$19,MATCH('Plant wise prices'!J$70,'Sales price'!$P$1:$P$19,0),MATCH('Plant wise prices'!$B79,'Sales price'!$P$1:$AA$1,0)) -> 47750 | K79: =INDEX('Sales price'!$P$1:$AA$19,MATCH('Plant wise prices'!K$70,'Sales price'!$P$1:$P$19,0),MATCH('Plant wise prices'!$B79,'Sales price'!$P$1:$AA$1,0)) -> 49750 | L79: =INDEX('Sales price'!$P$1:$AA$19,MATCH('Plant wise prices'!L$70,'Sales price'!$P$1:$P$19,0),MATCH('Plant wise prices'!$B79,'Sales price'!$P$1:$AA$1,0)) -> 48750 | ... P79: =INDEX('Sales price'!$P$1:$AA$19,MATCH('Plant wise prices'!P$70,'Sales price'!$P$1:$P$19,0),MATCH('Plant wise prices'!$B79,'Sales price'!$P$1:$AA$1,0)) -> 50750
A80: 550 | B80: Telangana - New Plant | E80: =INDEX('Sales price'!$P$1:$AA$19,MATCH('Plant wise prices'!E$70,'Sales price'!$P$1:$P$19,0),MATCH('Plant wise prices'!$B80,'Sales price'!$P$1:$AA$1,0)) -> 54500 | F80: =INDEX('Sales price'!$P$1:$AA$19,MATCH('Plant wise prices'!F$70,'Sales price'!$P$1:$P$19,0),MATCH('Plant wise prices'!$B80,'Sales price'!$P$1:$AA$1,0)) -> 53500 | G80: =INDEX('Sales price'!$P$1:$AA$19,MATCH('Plant wise prices'!G$70,'Sales price'!$P$1:$P$19,0),MATCH('Plant wise prices'!$B80,'Sales price'!$P$1:$AA$1,0)) -> 51500 | H80: =INDEX('Sales price'!$P$1:$AA$19,MATCH('Plant wise prices'!H$70,'Sales price'!$P$1:$P$19,0),MATCH('Plant wise prices'!$B80,'Sales price'!$P$1:$AA$1,0)) -> 48500 | I80: =INDEX('Sales price'!$P$1:$AA$19,MATCH('Plant wise prices'!I$70,'Sales price'!$P$1:$P$19,0),MATCH('Plant wise prices'!$B80,'Sales price'!$P$1:$AA$1,0)) -> 47500 | J80: =INDEX('Sales price'!$P$1:$AA$19,MATCH('Plant wise prices'!J$70,'Sales price'!$P$1:$P$19,0),MATCH('Plant wise prices'!$B80,'Sales price'!$P$1:$AA$1,0)) -> 48500 | K80: =INDEX('Sales price'!$P$1:$AA$19,MATCH('Plant wise prices'!K$70,'Sales price'!$P$1:$P$19,0),MATCH('Plant wise prices'!$B80,'Sales price'!$P$1:$AA$1,0)) -> 50500 | L80: =INDEX('Sales price'!$P$1:$AA$19,MATCH('Plant wise prices'!L$70,'Sales price'!$P$1:$P$19,0),MATCH('Plant wise prices'!$B80,'Sales price'!$P$1:$AA$1,0)) -> 49500 | ... P80: =INDEX('Sales price'!$P$1:$AA$19,MATCH('Plant wise prices'!P$70,'Sales price'!$P$1:$P$19,0),MATCH('Plant wise prices'!$B80,'Sales price'!$P$1:$AA$1,0)) -> 51500
A81: 550 | B81: Maharashtra - New Plant | E81: =INDEX('Sales price'!$P$1:$AA$19,MATCH('Plant wise prices'!E$70,'Sales price'!$P$1:$P$19,0),MATCH('Plant wise prices'!$B81,'Sales price'!$P$1:$AA$1,0)) -> 54500 | F81: =INDEX('Sales price'!$P$1:$AA$19,MATCH('Plant wise prices'!F$70,'Sales price'!$P$1:$P$19,0),MATCH('Plant wise prices'!$B81,'Sales price'!$P$1:$AA$1,0)) -> 53500 | G81: =INDEX('Sales price'!$P$1:$AA$19,MATCH('Plant wise prices'!G$70,'Sales price'!$P$1:$P$19,0),MATCH('Plant wise prices'!$B81,'Sales price'!$P$1:$AA$1,0)) -> 51500 | H81: =INDEX('Sales price'!$P$1:$AA$19,MATCH('Plant wise prices'!H$70,'Sales price'!$P$1:$P$19,0),MATCH('Plant wise prices'!$B81,'Sales price'!$P$1:$AA$1,0)) -> 48500 | I81: =INDEX('Sales price'!$P$1:$AA$19,MATCH('Plant wise prices'!I$70,'Sales price'!$P$1:$P$19,0),MATCH('Plant wise prices'!$B81,'Sales price'!$P$1:$AA$1,0)) -> 47500 | J81: =INDEX('Sales price'!$P$1:$AA$19,MATCH('Plant wise prices'!J$70,'Sales price'!$P$1:$P$19,0),MATCH('Plant wise prices'!$B81,'Sales price'!$P$1:$AA$1,0)) -> 48500 | K81: =INDEX('Sales price'!$P$1:$AA$19,MATCH('Plant wise prices'!K$70,'Sales price'!$P$1:$P$19,0),MATCH('Plant wise prices'!$B81,'Sales price'!$P$1:$AA$1,0)) -> 50500 | L81: =INDEX('Sales price'!$P$1:$AA$19,MATCH('Plant wise prices'!L$70,'Sales price'!$P$1:$P$19,0),MATCH('Plant wise prices'!$B81,'Sales price'!$P$1:$AA$1,0)) -> 49500 | ... P81: =INDEX('Sales price'!$P$1:$AA$19,MATCH('Plant wise prices'!P$70,'Sales price'!$P$1:$P$19,0),MATCH('Plant wise prices'!$B81,'Sales price'!$P$1:$AA$1,0)) -> 51500
A83: 550D | B83: AIC IRON INDUSTRIES PRIVATE LIMITED | E83: =INDEX('Sales price'!$D$1:$N$19,MATCH('Plant wise prices'!E$70,'Sales price'!$D$1:$D$19,0),MATCH('Plant wise prices'!$B83,'Sales price'!$D$1:$N$1,0)) -> 54750 | F83: =INDEX('Sales price'!$D$1:$N$19,MATCH('Plant wise prices'!F$70,'Sales price'!$D$1:$D$19,0),MATCH('Plant wise prices'!$B83,'Sales price'!$D$1:$N$1,0)) -> 53750 | G83: =INDEX('Sales price'!$D$1:$N$19,MATCH('Plant wise prices'!G$70,'Sales price'!$D$1:$D$19,0),MATCH('Plant wise prices'!$B83,'Sales price'!$D$1:$N$1,0)) -> 51750 | H83: =INDEX('Sales price'!$D$1:$N$19,MATCH('Plant wise prices'!H$70,'Sales price'!$D$1:$D$19,0),MATCH('Plant wise prices'!$B83,'Sales price'!$D$1:$N$1,0)) -> 48750 | I83: =INDEX('Sales price'!$D$1:$N$19,MATCH('Plant wise prices'!I$70,'Sales price'!$D$1:$D$19,0),MATCH('Plant wise prices'!$B83,'Sales price'!$D$1:$N$1,0)) -> 47750 | J83: =INDEX('Sales price'!$D$1:$N$19,MATCH('Plant wise prices'!J$70,'Sales price'!$D$1:$D$19,0),MATCH('Plant wise prices'!$B83,'Sales price'!$D$1:$N$1,0)) -> 48750 | K83: =INDEX('Sales price'!$D$1:$N$19,MATCH('Plant wise prices'!K$70,'Sales price'!$D$1:$D$19,0),MATCH('Plant wise prices'!$B83,'Sales price'!$D$1:$N$1,0)) -> 50750 | L83: =INDEX('Sales price'!$D$1:$N$19,MATCH('Plant wise prices'!L$70,'Sales price'!$D$1:$D$19,0),MATCH('Plant wise prices'!$B83,'Sales price'!$D$1:$N$1,0)) -> 49750 | ... P83: =INDEX('Sales price'!$D$1:$N$19,MATCH('Plant wise prices'!P$70,'Sales price'!$D$1:$D$19,0),MATCH('Plant wise prices'!$B83,'Sales price'!$D$1:$N$1,0)) -> 51750
A84: 550D | B84: Aditya Industries | E84: =INDEX('Sales price'!$D$1:$N$19,MATCH('Plant wise prices'!E$70,'Sales price'!$D$1:$D$19,0),MATCH('Plant wise prices'!$B84,'Sales price'!$D$1:$N$1,0)) -> 55000 | F84: =INDEX('Sales price'!$D$1:$N$19,MATCH('Plant wise prices'!F$70,'Sales price'!$D$1:$D$19,0),MATCH('Plant wise prices'!$B84,'Sales price'!$D$1:$N$1,0)) -> 54000 | G84: =INDEX('Sales price'!$D$1:$N$19,MATCH('Plant wise prices'!G$70,'Sales price'!$D$1:$D$19,0),MATCH('Plant wise prices'!$B84,'Sales price'!$D$1:$N$1,0)) -> 52000 | H84: =INDEX('Sales price'!$D$1:$N$19,MATCH('Plant wise prices'!H$70,'Sales price'!$D$1:$D$19,0),MATCH('Plant wise prices'!$B84,'Sales price'!$D$1:$N$1,0)) -> 49000 | I84: =INDEX('Sales price'!$D$1:$N$19,MATCH('Plant wise prices'!I$70,'Sales price'!$D$1:$D$19,0),MATCH('Plant wise prices'!$B84,'Sales price'!$D$1:$N$1,0)) -> 48000 | J84: =INDEX('Sales price'!$D$1:$N$19,MATCH('Plant wise prices'!J$70,'Sales price'!$D$1:$D$19,0),MATCH('Plant wise prices'!$B84,'Sales price'!$D$1:$N$1,0)) -> 49000 | K84: =INDEX('Sales price'!$D$1:$N$19,MATCH('Plant wise prices'!K$70,'Sales price'!$D$1:$D$19,0),MATCH('Plant wise prices'!$B84,'Sales price'!$D$1:$N$1,0)) -> 51000 | L84: =INDEX('Sales price'!$D$1:$N$19,MATCH('Plant wise prices'!L$70,'Sales price'!$D$1:$D$19,0),MATCH('Plant wise prices'!$B84,'Sales price'!$D$1:$N$1,0)) -> 50000 | ... P84: =INDEX('Sales price'!$D$1:$N$19,MATCH('Plant wise prices'!P$70,'Sales price'!$D$1:$D$19,0),MATCH('Plant wise prices'!$B84,'Sales price'!$D$1:$N$1,0)) -> 52000
A85: 550D | B85: Ambashakti Industries Limited | E85: =INDEX('Sales price'!$D$1:$N$19,MATCH('Plant wise prices'!E$70,'Sales price'!$D$1:$D$19,0),MATCH('Plant wise prices'!$B85,'Sales price'!$D$1:$N$1,0)) -> 56000 | F85: =INDEX('Sales price'!$D$1:$N$19,MATCH('Plant wise prices'!F$70,'Sales price'!$D$1:$D$19,0),MATCH('Plant wise prices'!$B85,'Sales price'!$D$1:$N$1,0)) -> 55000 | G85: =INDEX('Sales price'!$D$1:$N$19,MATCH('Plant wise prices'!G$70,'Sales price'!$D$1:$D$19,0),MATCH('Plant wise prices'!$B85,'Sales price'!$D$1:$N$1,0)) -> 53000 | H85: =INDEX('Sales price'!$D$1:$N$19,MATCH('Plant wise prices'!H$70,'Sales price'!$D$1:$D$19,0),MATCH('Plant wise prices'!$B85,'Sales price'!$D$1:$N$1,0)) -> 50000 | I85: =INDEX('Sales price'!$D$1:$N$19,MATCH('Plant wise prices'!I$70,'Sales price'!$D$1:$D$19,0),MATCH('Plant wise prices'!$B85,'Sales price'!$D$1:$N$1,0)) -> 49000 | J85: =INDEX('Sales price'!$D$1:$N$19,MATCH('Plant wise prices'!J$70,'Sales price'!$D$1:$D$19,0),MATCH('Plant wise prices'!$B85,'Sales price'!$D$1:$N$1,0)) -> 50000 | K85: =INDEX('Sales price'!$D$1:$N$19,MATCH('Plant wise prices'!K$70,'Sales price'!$D$1:$D$19,0),MATCH('Plant wise prices'!$B85,'Sales price'!$D$1:$N$1,0)) -> 52000 | L85: =INDEX('Sales price'!$D$1:$N$19,MATCH('Plant wise prices'!L$70,'Sales price'!$D$1:$D$19,0),MATCH('Plant wise prices'!$B85,'Sales price'!$D$1:$N$1,0)) -> 51000 | ... P85: =INDEX('Sales price'!$D$1:$N$19,MATCH('Plant wise prices'!P$70,'Sales price'!$D$1:$D$19,0),MATCH('Plant wise prices'!$B85,'Sales price'!$D$1:$N$1,0)) -> 53000
A86: 550D | B86: AMBASHAKTI UDYOG LIMITED- GWALIOR | E86: =INDEX('Sales price'!$D$1:$N$19,MATCH('Plant wise prices'!E$70,'Sales price'!$D$1:$D$19,0),MATCH('Plant wise prices'!$B86,'Sales price'!$D$1:$N$1,0)) -> 55200 | F86: =INDEX('Sales price'!$D$1:$N$19,MATCH('Plant wise prices'!F$70,'Sales price'!$D$1:$D$19,0),MATCH('Plant wise prices'!$B86,'Sales price'!$D$1:$N$1,0)) -> 54200 | G86: =INDEX('Sales price'!$D$1:$N$19,MATCH('Plant wise prices'!G$70,'Sales price'!$D$1:$D$19,0),MATCH('Plant wise prices'!$B86,'Sales price'!$D$1:$N$1,0)) -> 52200 | H86: =INDEX('Sales price'!$D$1:$N$19,MATCH('Plant wise prices'!H$70,'Sales price'!$D$1:$D$19,0),MATCH('Plant wise prices'!$B86,'Sales price'!$D$1:$N$1,0)) -> 49200 | I86: =INDEX('Sales price'!$D$1:$N$19,MATCH('Plant wise prices'!I$70,'Sales price'!$D$1:$D$19,0),MATCH('Plant wise prices'!$B86,'Sales price'!$D$1:$N$1,0)) -> 48200 | J86: =INDEX('Sales price'!$D$1:$N$19,MATCH('Plant wise prices'!J$70,'Sales price'!$D$1:$D$19,0),MATCH('Plant wise prices'!$B86,'Sales price'!$D$1:$N$1,0)) -> 49200 | K86: =INDEX('Sales price'!$D$1:$N$19,MATCH('Plant wise prices'!K$70,'Sales price'!$D$1:$D$19,0),MATCH('Plant wise prices'!$B86,'Sales price'!$D$1:$N$1,0)) -> 51200 | L86: =INDEX('Sales price'!$D$1:$N$19,MATCH('Plant wise prices'!L$70,'Sales price'!$D$1:$D$19,0),MATCH('Plant wise prices'!$B86,'Sales price'!$D$1:$N$1,0)) -> 50200 | ... P86: =INDEX('Sales price'!$D$1:$N$19,MATCH('Plant wise prices'!P$70,'Sales price'!$D$1:$D$19,0),MATCH('Plant wise prices'!$B86,'Sales price'!$D$1:$N$1,0)) -> 52200
A87: 550D | B87: API Ispat And Powertech Private Limited | E87: =INDEX('Sales price'!$D$1:$N$19,MATCH('Plant wise prices'!E$70,'Sales price'!$D$1:$D$19,0),MATCH('Plant wise prices'!$B87,'Sales price'!$D$1:$N$1,0)) -> 54500 | F87: =INDEX('Sales price'!$D$1:$N$19,MATCH('Plant wise prices'!F$70,'Sales price'!$D$1:$D$19,0),MATCH('Plant wise prices'!$B87,'Sales price'!$D$1:$N$1,0)) -> 53500 | G87: =INDEX('Sales price'!$D$1:$N$19,MATCH('Plant wise prices'!G$70,'Sales price'!$D$1:$D$19,0),MATCH('Plant wise prices'!$B87,'Sales price'!$D$1:$N$1,0)) -> 51500 | H87: =INDEX('Sales price'!$D$1:$N$19,MATCH('Plant wise prices'!H$70,'Sales price'!$D$1:$D$19,0),MATCH('Plant wise prices'!$B87,'Sales price'!$D$1:$N$1,0)) -> 48500 | I87: =INDEX('Sales price'!$D$1:$N$19,MATCH('Plant wise prices'!I$70,'Sales price'!$D$1:$D$19,0),MATCH('Plant wise prices'!$B87,'Sales price'!$D$1:$N$1,0)) -> 47500 | J87: =INDEX('Sales price'!$D$1:$N$19,MATCH('Plant wise prices'!J$70,'Sales price'!$D$1:$D$19,0),MATCH('Plant wise prices'!$B87,'Sales price'!$D$1:$N$1,0)) -> 48500 | K87: =INDEX('Sales price'!$D$1:$N$19,MATCH('Plant wise prices'!K$70,'Sales price'!$D$1:$D$19,0),MATCH('Plant wise prices'!$B87,'Sales price'!$D$1:$N$1,0)) -> 50500 | L87: =INDEX('Sales price'!$D$1:$N$19,MATCH('Plant wise prices'!L$70,'Sales price'!$D$1:$D$19,0),MATCH('Plant wise prices'!$B87,'Sales price'!$D$1:$N$1,0)) -> 49500 | ... P87: =INDEX('Sales price'!$D$1:$N$19,MATCH('Plant wise prices'!P$70,'Sales price'!$D$1:$D$19,0),MATCH('Plant wise prices'!$B87,'Sales price'!$D$1:$N$1,0)) -> 51500
A88: 550D | B88: GERMAN GREEN STEEL AND POWER LIMITED | E88: =INDEX('Sales price'!$D$1:$N$19,MATCH('Plant wise prices'!E$70,'Sales price'!$D$1:$D$19,0),MATCH('Plant wise prices'!$B88,'Sales price'!$D$1:$N$1,0)) -> 54750 | F88: =INDEX('Sales price'!$D$1:$N$19,MATCH('Plant wise prices'!F$70,'Sales price'!$D$1:$D$19,0),MATCH('Plant wise prices'!$B88,'Sales price'!$D$1:$N$1,0)) -> 53750 | G88: =INDEX('Sales price'!$D$1:$N$19,MATCH('Plant wise prices'!G$70,'Sales price'!$D$1:$D$19,0),MATCH('Plant wise prices'!$B88,'Sales price'!$D$1:$N$1,0)) -> 51750 | H88: =INDEX('Sales price'!$D$1:$N$19,MATCH('Plant wise prices'!H$70,'Sales price'!$D$1:$D$19,0),MATCH('Plant wise prices'!$B88,'Sales price'!$D$1:$N$1,0)) -> 48750 | I88: =INDEX('Sales price'!$D$1:$N$19,MATCH('Plant wise prices'!I$70,'Sales price'!$D$1:$D$19,0),MATCH('Plant wise prices'!$B88,'Sales price'!$D$1:$N$1,0)) -> 47750 | J88: =INDEX('Sales price'!$D$1:$N$19,MATCH('Plant wise prices'!J$70,'Sales price'!$D$1:$D$19,0),MATCH('Plant wise prices'!$B88,'Sales price'!$D$1:$N$1,0)) -> 48750 | K88: =INDEX('Sales price'!$D$1:$N$19,MATCH('Plant wise prices'!K$70,'Sales price'!$D$1:$D$19,0),MATCH('Plant wise prices'!$B88,'Sales price'!$D$1:$N$1,0)) -> 50750 | L88: =INDEX('Sales price'!$D$1:$N$19,MATCH('Plant wise prices'!L$70,'Sales price'!$D$1:$D$19,0),MATCH('Plant wise prices'!$B88,'Sales price'!$D$1:$N$1,0)) -> 49750 | ... P88: =INDEX('Sales price'!$D$1:$N$19,MATCH('Plant wise prices'!P$70,'Sales price'!$D$1:$D$19,0),MATCH('Plant wise prices'!$B88,'Sales price'!$D$1:$N$1,0)) -> 51750
A89: 550D | B89: SKA Ispat Private Limited | E89: =INDEX('Sales price'!$D$1:$N$19,MATCH('Plant wise prices'!E$70,'Sales price'!$D$1:$D$19,0),MATCH('Plant wise prices'!$B89,'Sales price'!$D$1:$N$1,0)) -> 54500 | F89: =INDEX('Sales price'!$D$1:$N$19,MATCH('Plant wise prices'!F$70,'Sales price'!$D$1:$D$19,0),MATCH('Plant wise prices'!$B89,'Sales price'!$D$1:$N$1,0)) -> 53500 | G89: =INDEX('Sales price'!$D$1:$N$19,MATCH('Plant wise prices'!G$70,'Sales price'!$D$1:$D$19,0),MATCH('Plant wise prices'!$B89,'Sales price'!$D$1:$N$1,0)) -> 51500 | H89: =INDEX('Sales price'!$D$1:$N$19,MATCH('Plant wise prices'!H$70,'Sales price'!$D$1:$D$19,0),MATCH('Plant wise prices'!$B89,'Sales price'!$D$1:$N$1,0)) -> 48500 | I89: =INDEX('Sales price'!$D$1:$N$19,MATCH('Plant wise prices'!I$70,'Sales price'!$D$1:$D$19,0),MATCH('Plant wise prices'!$B89,'Sales price'!$D$1:$N$1,0)) -> 47500 | J89: =INDEX('Sales price'!$D$1:$N$19,MATCH('Plant wise prices'!J$70,'Sales price'!$D$1:$D$19,0),MATCH('Plant wise prices'!$B89,'Sales price'!$D$1:$N$1,0)) -> 48500 | K89: =INDEX('Sales price'!$D$1:$N$19,MATCH('Plant wise prices'!K$70,'Sales price'!$D$1:$D$19,0),MATCH('Plant wise prices'!$B89,'Sales price'!$D$1:$N$1,0)) -> 50500 | L89: =INDEX('Sales price'!$D$1:$N$19,MATCH('Plant wise prices'!L$70,'Sales price'!$D$1:$D$19,0),MATCH('Plant wise prices'!$B89,'Sales price'!$D$1:$N$1,0)) -> 49500 | ... P89: =INDEX('Sales price'!$D$1:$N$19,MATCH('Plant wise prices'!P$70,'Sales price'!$D$1:$D$19,0),MATCH('Plant wise prices'!$B89,'Sales price'!$D$1:$N$1,0)) -> 51500
A90: 550D | B90: Real Ispat | E90: =INDEX('Sales price'!$D$1:$N$19,MATCH('Plant wise prices'!E$70,'Sales price'!$D$1:$D$19,0),MATCH('Plant wise prices'!$B90,'Sales price'!$D$1:$N$1,0)) -> 54500 | F90: =INDEX('Sales price'!$D$1:$N$19,MATCH('Plant wise prices'!F$70,'Sales price'!$D$1:$D$19,0),MATCH('Plant wise prices'!$B90,'Sales price'!$D$1:$N$1,0)) -> 53500 | G90: =INDEX('Sales price'!$D$1:$N$19,MATCH('Plant wise prices'!G$70,'Sales price'!$D$1:$D$19,0),MATCH('Plant wise prices'!$B90,'Sales price'!$D$1:$N$1,0)) -> 51500 | H90: =INDEX('Sales price'!$D$1:$N$19,MATCH('Plant wise prices'!H$70,'Sales price'!$D$1:$D$19,0),MATCH('Plant wise prices'!$B90,'Sales price'!$D$1:$N$1,0)) -> 48500 | I90: =INDEX('Sales price'!$D$1:$N$19,MATCH('Plant wise prices'!I$70,'Sales price'!$D$1:$D$19,0),MATCH('Plant wise prices'!$B90,'Sales price'!$D$1:$N$1,0)) -> 47500 | J90: =INDEX('Sales price'!$D$1:$N$19,MATCH('Plant wise prices'!J$70,'Sales price'!$D$1:$D$19,0),MATCH('Plant wise prices'!$B90,'Sales price'!$D$1:$N$1,0)) -> 48500 | K90: =INDEX('Sales price'!$D$1:$N$19,MATCH('Plant wise prices'!K$70,'Sales price'!$D$1:$D$19,0),MATCH('Plant wise prices'!$B90,'Sales price'!$D$1:$N$1,0)) -> 50500 | L90: =INDEX('Sales price'!$D$1:$N$19,MATCH('Plant wise prices'!L$70,'Sales price'!$D$1:$D$19,0),MATCH('Plant wise prices'!$B90,'Sales price'!$D$1:$N$1,0)) -> 49500 | ... P90: =INDEX('Sales price'!$D$1:$N$19,MATCH('Plant wise prices'!P$70,'Sales price'!$D$1:$D$19,0),MATCH('Plant wise prices'!$B90,'Sales price'!$D$1:$N$1,0)) -> 51500
A91: 550D | B91: Rashmi Steel | E91: =INDEX('Sales price'!$D$1:$N$19,MATCH('Plant wise prices'!E$70,'Sales price'!$D$1:$D$19,0),MATCH('Plant wise prices'!$B91,'Sales price'!$D$1:$N$1,0)) -> 54750 | F91: =INDEX('Sales price'!$D$1:$N$19,MATCH('Plant wise prices'!F$70,'Sales price'!$D$1:$D$19,0),MATCH('Plant wise prices'!$B91,'Sales price'!$D$1:$N$1,0)) -> 53750 | G91: =INDEX('Sales price'!$D$1:$N$19,MATCH('Plant wise prices'!G$70,'Sales price'!$D$1:$D$19,0),MATCH('Plant wise prices'!$B91,'Sales price'!$D$1:$N$1,0)) -> 51750 | H91: =INDEX('Sales price'!$D$1:$N$19,MATCH('Plant wise prices'!H$70,'Sales price'!$D$1:$D$19,0),MATCH('Plant wise prices'!$B91,'Sales price'!$D$1:$N$1,0)) -> 48750 | I91: =INDEX('Sales price'!$D$1:$N$19,MATCH('Plant wise prices'!I$70,'Sales price'!$D$1:$D$19,0),MATCH('Plant wise prices'!$B91,'Sales price'!$D$1:$N$1,0)) -> 47750 | J91: =INDEX('Sales price'!$D$1:$N$19,MATCH('Plant wise prices'!J$70,'Sales price'!$D$1:$D$19,0),MATCH('Plant wise prices'!$B91,'Sales price'!$D$1:$N$1,0)) -> 48750 | K91: =INDEX('Sales price'!$D$1:$N$19,MATCH('Plant wise prices'!K$70,'Sales price'!$D$1:$D$19,0),MATCH('Plant wise prices'!$B91,'Sales price'!$D$1:$N$1,0)) -> 50750 | L91: =INDEX('Sales price'!$D$1:$N$19,MATCH('Plant wise prices'!L$70,'Sales price'!$D$1:$D$19,0),MATCH('Plant wise prices'!$B91,'Sales price'!$D$1:$N$1,0)) -> 49750 | ... P91: =INDEX('Sales price'!$D$1:$N$19,MATCH('Plant wise prices'!P$70,'Sales price'!$D$1:$D$19,0),MATCH('Plant wise prices'!$B91,'Sales price'!$D$1:$N$1,0)) -> 51750
A92: 550D | B92: Telangana - New Plant
A93: 550D | B93: Maharashtra - New Plant
A95: One Helix
A96: Grade | B96: CM
A97: 550 | B97: AIC IRON INDUSTRIES PRIVATE LIMITED | E97: =INDEX('Sales price'!$AC$1:$AN$19,MATCH('Plant wise prices'!E$70,'Sales price'!$AC$1:$AC$19,0),MATCH('Plant wise prices'!$B97,'Sales price'!$AC$1:$AN$1,0)) -> 52750 | F97: =INDEX('Sales price'!$AC$1:$AN$19,MATCH('Plant wise prices'!F$70,'Sales price'!$AC$1:$AC$19,0),MATCH('Plant wise prices'!$B97,'Sales price'!$AC$1:$AN$1,0)) -> 51750 | G97: =INDEX('Sales price'!$AC$1:$AN$19,MATCH('Plant wise prices'!G$70,'Sales price'!$AC$1:$AC$19,0),MATCH('Plant wise prices'!$B97,'Sales price'!$AC$1:$AN$1,0)) -> 49750 | H97: =INDEX('Sales price'!$AC$1:$AN$19,MATCH('Plant wise prices'!H$70,'Sales price'!$AC$1:$AC$19,0),MATCH('Plant wise prices'!$B97,'Sales price'!$AC$1:$AN$1,0)) -> 46750 | I97: =INDEX('Sales price'!$AC$1:$AN$19,MATCH('Plant wise prices'!I$70,'Sales price'!$AC$1:$AC$19,0),MATCH('Plant wise prices'!$B97,'Sales price'!$AC$1:$AN$1,0)) -> 45750 | J97: =INDEX('Sales price'!$AC$1:$AN$19,MATCH('Plant wise prices'!J$70,'Sales price'!$AC$1:$AC$19,0),MATCH('Plant wise prices'!$B97,'Sales price'!$AC$1:$AN$1,0)) -> 46750 | K97: =INDEX('Sales price'!$AC$1:$AN$19,MATCH('Plant wise prices'!K$70,'Sales price'!$AC$1:$AC$19,0),MATCH('Plant wise prices'!$B97,'Sales price'!$AC$1:$AN$1,0)) -> 48750 | L97: =INDEX('Sales price'!$AC$1:$AN$19,MATCH('Plant wise prices'!L$70,'Sales price'!$AC$1:$AC$19,0),MATCH('Plant wise prices'!$B97,'Sales price'!$AC$1:$AN$1,0)) -> 47750 | ... P97: =INDEX('Sales price'!$AC$1:$AN$19,MATCH('Plant wise prices'!P$70,'Sales price'!$AC$1:$AC$19,0),MATCH('Plant wise prices'!$B97,'Sales price'!$AC$1:$AN$1,0)) -> 49750
A98: 550 | B98: Aditya Industries | E98: =INDEX('Sales price'!$AC$1:$AN$19,MATCH('Plant wise prices'!E$70,'Sales price'!$AC$1:$AC$19,0),MATCH('Plant wise prices'!$B98,'Sales price'!$AC$1:$AN$1,0)) -> 53000 | F98: =INDEX('Sales price'!$AC$1:$AN$19,MATCH('Plant wise prices'!F$70,'Sales price'!$AC$1:$AC$19,0),MATCH('Plant wise prices'!$B98,'Sales price'!$AC$1:$AN$1,0)) -> 52000 | G98: =INDEX('Sales price'!$AC$1:$AN$19,MATCH('Plant wise prices'!G$70,'Sales price'!$AC$1:$AC$19,0),MATCH('Plant wise prices'!$B98,'Sales price'!$AC$1:$AN$1,0)) -> 50000 | H98: =INDEX('Sales price'!$AC$1:$AN$19,MATCH('Plant wise prices'!H$70,'Sales price'!$AC$1:$AC$19,0),MATCH('Plant wise prices'!$B98,'Sales price'!$AC$1:$AN$1,0)) -> 47000 | I98: =INDEX('Sales price'!$AC$1:$AN$19,MATCH('Plant wise prices'!I$70,'Sales price'!$AC$1:$AC$19,0),MATCH('Plant wise prices'!$B98,'Sales price'!$AC$1:$AN$1,0)) -> 46000 | J98: =INDEX('Sales price'!$AC$1:$AN$19,MATCH('Plant wise prices'!J$70,'Sales price'!$AC$1:$AC$19,0),MATCH('Plant wise prices'!$B98,'Sales price'!$AC$1:$AN$1,0)) -> 47000 | K98: =INDEX('Sales price'!$AC$1:$AN$19,MATCH('Plant wise prices'!K$70,'Sales price'!$AC$1:$AC$19,0),MATCH('Plant wise prices'!$B98,'Sales price'!$AC$1:$AN$1,0)) -> 49000 | L98: =INDEX('Sales price'!$AC$1:$AN$19,MATCH('Plant wise prices'!L$70,'Sales price'!$AC$1:$AC$19,0),MATCH('Plant wise prices'!$B98,'Sales price'!$AC$1:$AN$1,0)) -> 48000 | ... P98: =INDEX('Sales price'!$AC$1:$AN$19,MATCH('Plant wise prices'!P$70,'Sales price'!$AC$1:$AC$19,0),MATCH('Plant wise prices'!$B98,'Sales price'!$AC$1:$AN$1,0)) -> 50000
A99: 550 | B99: Ambashakti Industries Limited | E99: =INDEX('Sales price'!$AC$1:$AN$19,MATCH('Plant wise prices'!E$70,'Sales price'!$AC$1:$AC$19,0),MATCH('Plant wise prices'!$B99,'Sales price'!$AC$1:$AN$1,0)) -> 54000 | F99: =INDEX('Sales price'!$AC$1:$AN$19,MATCH('Plant wise prices'!F$70,'Sales price'!$AC$1:$AC$19,0),MATCH('Plant wise prices'!$B99,'Sales price'!$AC$1:$AN$1,0)) -> 53000 | G99: =INDEX('Sales price'!$AC$1:$AN$19,MATCH('Plant wise prices'!G$70,'Sales price'!$AC$1:$AC$19,0),MATCH('Plant wise prices'!$B99,'Sales price'!$AC$1:$AN$1,0)) -> 51000 | H99: =INDEX('Sales price'!$AC$1:$AN$19,MATCH('Plant wise prices'!H$70,'Sales price'!$AC$1:$AC$19,0),MATCH('Plant wise prices'!$B99,'Sales price'!$AC$1:$AN$1,0)) -> 48000 | I99: =INDEX('Sales price'!$AC$1:$AN$19,MATCH('Plant wise prices'!I$70,'Sales price'!$AC$1:$AC$19,0),MATCH('Plant wise prices'!$B99,'Sales price'!$AC$1:$AN$1,0)) -> 47000 | J99: =INDEX('Sales price'!$AC$1:$AN$19,MATCH('Plant wise prices'!J$70,'Sales price'!$AC$1:$AC$19,0),MATCH('Plant wise prices'!$B99,'Sales price'!$AC$1:$AN$1,0)) -> 48000 | K99: =INDEX('Sales price'!$AC$1:$AN$19,MATCH('Plant wise prices'!K$70,'Sales price'!$AC$1:$AC$19,0),MATCH('Plant wise prices'!$B99,'Sales price'!$AC$1:$AN$1,0)) -> 50000 | L99: =INDEX('Sales price'!$AC$1:$AN$19,MATCH('Plant wise prices'!L$70,'Sales price'!$AC$1:$AC$19,0),MATCH('Plant wise prices'!$B99,'Sales price'!$AC$1:$AN$1,0)) -> 49000 | ... P99: =INDEX('Sales price'!$AC$1:$AN$19,MATCH('Plant wise prices'!P$70,'Sales price'!$AC$1:$AC$19,0),MATCH('Plant wise prices'!$B99,'Sales price'!$AC$1:$AN$1,0)) -> 51000
A100: 550 | B100: AMBASHAKTI UDYOG LIMITED- GWALIOR | E100: =INDEX('Sales price'!$AC$1:$AN$19,MATCH('Plant wise prices'!E$70,'Sales price'!$AC$1:$AC$19,0),MATCH('Plant wise prices'!$B100,'Sales price'!$AC$1:$AN$1,0)) -> 53200 | F100: =INDEX('Sales price'!$AC$1:$AN$19,MATCH('Plant wise prices'!F$70,'Sales price'!$AC$1:$AC$19,0),MATCH('Plant wise prices'!$B100,'Sales price'!$AC$1:$AN$1,0)) -> 52200 | G100: =INDEX('Sales price'!$AC$1:$AN$19,MATCH('Plant wise prices'!G$70,'Sales price'!$AC$1:$AC$19,0),MATCH('Plant wise prices'!$B100,'Sales price'!$AC$1:$AN$1,0)) -> 50200 | H100: =INDEX('Sales price'!$AC$1:$AN$19,MATCH('Plant wise prices'!H$70,'Sales price'!$AC$1:$AC$19,0),MATCH('Plant wise prices'!$B100,'Sales price'!$AC$1:$AN$1,0)) -> 47200 | I100: =INDEX('Sales price'!$AC$1:$AN$19,MATCH('Plant wise prices'!I$70,'Sales price'!$AC$1:$AC$19,0),MATCH('Plant wise prices'!$B100,'Sales price'!$AC$1:$AN$1,0)) -> 46200 | J100: =INDEX('Sales price'!$AC$1:$AN$19,MATCH('Plant wise prices'!J$70,'Sales price'!$AC$1:$AC$19,0),MATCH('Plant wise prices'!$B100,'Sales price'!$AC$1:$AN$1,0)) -> 47200 | K100: =INDEX('Sales price'!$AC$1:$AN$19,MATCH('Plant wise prices'!K$70,'Sales price'!$AC$1:$AC$19,0),MATCH('Plant wise prices'!$B100,'Sales price'!$AC$1:$AN$1,0)) -> 49200 | L100: =INDEX('Sales price'!$AC$1:$AN$19,MATCH('Plant wise prices'!L$70,'Sales price'!$AC$1:$AC$19,0),MATCH('Plant wise prices'!$B100,'Sales price'!$AC$1:$AN$1,0)) -> 48200 | ... P100: =INDEX('Sales price'!$AC$1:$AN$19,MATCH('Plant wise prices'!P$70,'Sales price'!$AC$1:$AC$19,0),MATCH('Plant wise prices'!$B100,'Sales price'!$AC$1:$AN$1,0)) -> 50200
A101: 550 | B101: API Ispat And Powertech Private Limited | E101: =INDEX('Sales price'!$AC$1:$AN$19,MATCH('Plant wise prices'!E$70,'Sales price'!$AC$1:$AC$19,0),MATCH('Plant wise prices'!$B101,'Sales price'!$AC$1:$AN$1,0)) -> 52500 | F101: =INDEX('Sales price'!$AC$1:$AN$19,MATCH('Plant wise prices'!F$70,'Sales price'!$AC$1:$AC$19,0),MATCH('Plant wise prices'!$B101,'Sales price'!$AC$1:$AN$1,0)) -> 51500 | G101: =INDEX('Sales price'!$AC$1:$AN$19,MATCH('Plant wise prices'!G$70,'Sales price'!$AC$1:$AC$19,0),MATCH('Plant wise prices'!$B101,'Sales price'!$AC$1:$AN$1,0)) -> 49500 | H101: =INDEX('Sales price'!$AC$1:$AN$19,MATCH('Plant wise prices'!H$70,'Sales price'!$AC$1:$AC$19,0),MATCH('Plant wise prices'!$B101,'Sales price'!$AC$1:$AN$1,0)) -> 46500 | I101: =INDEX('Sales price'!$AC$1:$AN$19,MATCH('Plant wise prices'!I$70,'Sales price'!$AC$1:$AC$19,0),MATCH('Plant wise prices'!$B101,'Sales price'!$AC$1:$AN$1,0)) -> 45500 | J101: =INDEX('Sales price'!$AC$1:$AN$19,MATCH('Plant wise prices'!J$70,'Sales price'!$AC$1:$AC$19,0),MATCH('Plant wise prices'!$B101,'Sales price'!$AC$1:$AN$1,0)) -> 46500 | K101: =INDEX('Sales price'!$AC$1:$AN$19,MATCH('Plant wise prices'!K$70,'Sales price'!$AC$1:$AC$19,0),MATCH('Plant wise prices'!$B101,'Sales price'!$AC$1:$AN$1,0)) -> 48500 | L101: =INDEX('Sales price'!$AC$1:$AN$19,MATCH('Plant wise prices'!L$70,'Sales price'!$AC$1:$AC$19,0),MATCH('Plant wise prices'!$B101,'Sales price'!$AC$1:$AN$1,0)) -> 47500 | ... P101: =INDEX('Sales price'!$AC$1:$AN$19,MATCH('Plant wise prices'!P$70,'Sales price'!$AC$1:$AC$19,0),MATCH('Plant wise prices'!$B101,'Sales price'!$AC$1:$AN$1,0)) -> 49500
A102: 550 | B102: GERMAN GREEN STEEL AND POWER LIMITED | E102: =INDEX('Sales price'!$AC$1:$AN$19,MATCH('Plant wise prices'!E$70,'Sales price'!$AC$1:$AC$19,0),MATCH('Plant wise prices'!$B102,'Sales price'!$AC$1:$AN$1,0)) -> 52750 | F102: =INDEX('Sales price'!$AC$1:$AN$19,MATCH('Plant wise prices'!F$70,'Sales price'!$AC$1:$AC$19,0),MATCH('Plant wise prices'!$B102,'Sales price'!$AC$1:$AN$1,0)) -> 51750 | G102: =INDEX('Sales price'!$AC$1:$AN$19,MATCH('Plant wise prices'!G$70,'Sales price'!$AC$1:$AC$19,0),MATCH('Plant wise prices'!$B102,'Sales price'!$AC$1:$AN$1,0)) -> 49750 | H102: =INDEX('Sales price'!$AC$1:$AN$19,MATCH('Plant wise prices'!H$70,'Sales price'!$AC$1:$AC$19,0),MATCH('Plant wise prices'!$B102,'Sales price'!$AC$1:$AN$1,0)) -> 46750 | I102: =INDEX('Sales price'!$AC$1:$AN$19,MATCH('Plant wise prices'!I$70,'Sales price'!$AC$1:$AC$19,0),MATCH('Plant wise prices'!$B102,'Sales price'!$AC$1:$AN$1,0)) -> 45750 | J102: =INDEX('Sales price'!$AC$1:$AN$19,MATCH('Plant wise prices'!J$70,'Sales price'!$AC$1:$AC$19,0),MATCH('Plant wise prices'!$B102,'Sales price'!$AC$1:$AN$1,0)) -> 46750 | K102: =INDEX('Sales price'!$AC$1:$AN$19,MATCH('Plant wise prices'!K$70,'Sales price'!$AC$1:$AC$19,0),MATCH('Plant wise prices'!$B102,'Sales price'!$AC$1:$AN$1,0)) -> 48750 | L102: =INDEX('Sales price'!$AC$1:$AN$19,MATCH('Plant wise prices'!L$70,'Sales price'!$AC$1:$AC$19,0),MATCH('Plant wise prices'!$B102,'Sales price'!$AC$1:$AN$1,0)) -> 47750 | ... P102: =INDEX('Sales price'!$AC$1:$AN$19,MATCH('Plant wise prices'!P$70,'Sales price'!$AC$1:$AC$19,0),MATCH('Plant wise prices'!$B102,'Sales price'!$AC$1:$AN$1,0)) -> 49750
A103: 550 | B103: SKA Ispat Private Limited | E103: =INDEX('Sales price'!$AC$1:$AN$19,MATCH('Plant wise prices'!E$70,'Sales price'!$AC$1:$AC$19,0),MATCH('Plant wise prices'!$B103,'Sales price'!$AC$1:$AN$1,0)) -> 52500 | F103: =INDEX('Sales price'!$AC$1:$AN$19,MATCH('Plant wise prices'!F$70,'Sales price'!$AC$1:$AC$19,0),MATCH('Plant wise prices'!$B103,'Sales price'!$AC$1:$AN$1,0)) -> 51500 | G103: =INDEX('Sales price'!$AC$1:$AN$19,MATCH('Plant wise prices'!G$70,'Sales price'!$AC$1:$AC$19,0),MATCH('Plant wise prices'!$B103,'Sales price'!$AC$1:$AN$1,0)) -> 49500 | H103: =INDEX('Sales price'!$AC$1:$AN$19,MATCH('Plant wise prices'!H$70,'Sales price'!$AC$1:$AC$19,0),MATCH('Plant wise prices'!$B103,'Sales price'!$AC$1:$AN$1,0)) -> 46500 | I103: =INDEX('Sales price'!$AC$1:$AN$19,MATCH('Plant wise prices'!I$70,'Sales price'!$AC$1:$AC$19,0),MATCH('Plant wise prices'!$B103,'Sales price'!$AC$1:$AN$1,0)) -> 45500 | J103: =INDEX('Sales price'!$AC$1:$AN$19,MATCH('Plant wise prices'!J$70,'Sales price'!$AC$1:$AC$19,0),MATCH('Plant wise prices'!$B103,'Sales price'!$AC$1:$AN$1,0)) -> 46500 | K103: =INDEX('Sales price'!$AC$1:$AN$19,MATCH('Plant wise prices'!K$70,'Sales price'!$AC$1:$AC$19,0),MATCH('Plant wise prices'!$B103,'Sales price'!$AC$1:$AN$1,0)) -> 48500 | L103: =INDEX('Sales price'!$AC$1:$AN$19,MATCH('Plant wise prices'!L$70,'Sales price'!$AC$1:$AC$19,0),MATCH('Plant wise prices'!$B103,'Sales price'!$AC$1:$AN$1,0)) -> 47500 | ... P103: =INDEX('Sales price'!$AC$1:$AN$19,MATCH('Plant wise prices'!P$70,'Sales price'!$AC$1:$AC$19,0),MATCH('Plant wise prices'!$B103,'Sales price'!$AC$1:$AN$1,0)) -> 49500
A104: 550 | B104: Real Ispat
A105: 550 | B105: Rashmi Steel | E105: =INDEX('Sales price'!$AC$1:$AN$19,MATCH('Plant wise prices'!E$70,'Sales price'!$AC$1:$AC$19,0),MATCH('Plant wise prices'!$B105,'Sales price'!$AC$1:$AN$1,0)) -> 52750 | F105: =INDEX('Sales price'!$AC$1:$AN$19,MATCH('Plant wise prices'!F$70,'Sales price'!$AC$1:$AC$19,0),MATCH('Plant wise prices'!$B105,'Sales price'!$AC$1:$AN$1,0)) -> 51750 | G105: =INDEX('Sales price'!$AC$1:$AN$19,MATCH('Plant wise prices'!G$70,'Sales price'!$AC$1:$AC$19,0),MATCH('Plant wise prices'!$B105,'Sales price'!$AC$1:$AN$1,0)) -> 49750 | H105: =INDEX('Sales price'!$AC$1:$AN$19,MATCH('Plant wise prices'!H$70,'Sales price'!$AC$1:$AC$19,0),MATCH('Plant wise prices'!$B105,'Sales price'!$AC$1:$AN$1,0)) -> 46750 | I105: =INDEX('Sales price'!$AC$1:$AN$19,MATCH('Plant wise prices'!I$70,'Sales price'!$AC$1:$AC$19,0),MATCH('Plant wise prices'!$B105,'Sales price'!$AC$1:$AN$1,0)) -> 45750 | J105: =INDEX('Sales price'!$AC$1:$AN$19,MATCH('Plant wise prices'!J$70,'Sales price'!$AC$1:$AC$19,0),MATCH('Plant wise prices'!$B105,'Sales price'!$AC$1:$AN$1,0)) -> 46750 | K105: =INDEX('Sales price'!$AC$1:$AN$19,MATCH('Plant wise prices'!K$70,'Sales price'!$AC$1:$AC$19,0),MATCH('Plant wise prices'!$B105,'Sales price'!$AC$1:$AN$1,0)) -> 48750 | L105: =INDEX('Sales price'!$AC$1:$AN$19,MATCH('Plant wise prices'!L$70,'Sales price'!$AC$1:$AC$19,0),MATCH('Plant wise prices'!$B105,'Sales price'!$AC$1:$AN$1,0)) -> 47750 | ... P105: =INDEX('Sales price'!$AC$1:$AN$19,MATCH('Plant wise prices'!P$70,'Sales price'!$AC$1:$AC$19,0),MATCH('Plant wise prices'!$B105,'Sales price'!$AC$1:$AN$1,0)) -> 49750
A106: 550 | B106: Telangana - New Plant | E106: =INDEX('Sales price'!$AC$1:$AN$19,MATCH('Plant wise prices'!E$70,'Sales price'!$AC$1:$AC$19,0),MATCH('Plant wise prices'!$B106,'Sales price'!$AC$1:$AN$1,0)) -> 53500 | F106: =INDEX('Sales price'!$AC$1:$AN$19,MATCH('Plant wise prices'!F$70,'Sales price'!$AC$1:$AC$19,0),MATCH('Plant wise prices'!$B106,'Sales price'!$AC$1:$AN$1,0)) -> 52500 | G106: =INDEX('Sales price'!$AC$1:$AN$19,MATCH('Plant wise prices'!G$70,'Sales price'!$AC$1:$AC$19,0),MATCH('Plant wise prices'!$B106,'Sales price'!$AC$1:$AN$1,0)) -> 50500 | H106: =INDEX('Sales price'!$AC$1:$AN$19,MATCH('Plant wise prices'!H$70,'Sales price'!$AC$1:$AC$19,0),MATCH('Plant wise prices'!$B106,'Sales price'!$AC$1:$AN$1,0)) -> 47500 | I106: =INDEX('Sales price'!$AC$1:$AN$19,MATCH('Plant wise prices'!I$70,'Sales price'!$AC$1:$AC$19,0),MATCH('Plant wise prices'!$B106,'Sales price'!$AC$1:$AN$1,0)) -> 46500 | J106: =INDEX('Sales price'!$AC$1:$AN$19,MATCH('Plant wise prices'!J$70,'Sales price'!$AC$1:$AC$19,0),MATCH('Plant wise prices'!$B106,'Sales price'!$AC$1:$AN$1,0)) -> 47500 | K106: =INDEX('Sales price'!$AC$1:$AN$19,MATCH('Plant wise prices'!K$70,'Sales price'!$AC$1:$AC$19,0),MATCH('Plant wise prices'!$B106,'Sales price'!$AC$1:$AN$1,0)) -> 49500 | L106: =INDEX('Sales price'!$AC$1:$AN$19,MATCH('Plant wise prices'!L$70,'Sales price'!$AC$1:$AC$19,0),MATCH('Plant wise prices'!$B106,'Sales price'!$AC$1:$AN$1,0)) -> 48500 | ... P106: =INDEX('Sales price'!$AC$1:$AN$19,MATCH('Plant wise prices'!P$70,'Sales price'!$AC$1:$AC$19,0),MATCH('Plant wise prices'!$B106,'Sales price'!$AC$1:$AN$1,0)) -> 50500
A107: 550 | B107: Maharashtra - New Plant | E107: =INDEX('Sales price'!$AC$1:$AN$19,MATCH('Plant wise prices'!E$70,'Sales price'!$AC$1:$AC$19,0),MATCH('Plant wise prices'!$B107,'Sales price'!$AC$1:$AN$1,0)) -> 53500 | F107: =INDEX('Sales price'!$AC$1:$AN$19,MATCH('Plant wise prices'!F$70,'Sales price'!$AC$1:$AC$19,0),MATCH('Plant wise prices'!$B107,'Sales price'!$AC$1:$AN$1,0)) -> 52500 | G107: =INDEX('Sales price'!$AC$1:$AN$19,MATCH('Plant wise prices'!G$70,'Sales price'!$AC$1:$AC$19,0),MATCH('Plant wise prices'!$B107,'Sales price'!$AC$1:$AN$1,0)) -> 50500 | H107: =INDEX('Sales price'!$AC$1:$AN$19,MATCH('Plant wise prices'!H$70,'Sales price'!$AC$1:$AC$19,0),MATCH('Plant wise prices'!$B107,'Sales price'!$AC$1:$AN$1,0)) -> 47500 | I107: =INDEX('Sales price'!$AC$1:$AN$19,MATCH('Plant wise prices'!I$70,'Sales price'!$AC$1:$AC$19,0),MATCH('Plant wise prices'!$B107,'Sales price'!$AC$1:$AN$1,0)) -> 46500 | J107: =INDEX('Sales price'!$AC$1:$AN$19,MATCH('Plant wise prices'!J$70,'Sales price'!$AC$1:$AC$19,0),MATCH('Plant wise prices'!$B107,'Sales price'!$AC$1:$AN$1,0)) -> 47500 | K107: =INDEX('Sales price'!$AC$1:$AN$19,MATCH('Plant wise prices'!K$70,'Sales price'!$AC$1:$AC$19,0),MATCH('Plant wise prices'!$B107,'Sales price'!$AC$1:$AN$1,0)) -> 49500 | L107: =INDEX('Sales price'!$AC$1:$AN$19,MATCH('Plant wise prices'!L$70,'Sales price'!$AC$1:$AC$19,0),MATCH('Plant wise prices'!$B107,'Sales price'!$AC$1:$AN$1,0)) -> 48500 | ... P107: =INDEX('Sales price'!$AC$1:$AN$19,MATCH('Plant wise prices'!P$70,'Sales price'!$AC$1:$AC$19,0),MATCH('Plant wise prices'!$B107,'Sales price'!$AC$1:$AN$1,0)) -> 50500
A109: Qty-Retail
B111: Name of Plants | C111: JSW One brands being manufactured | E111: Overall-550 JSW One TMT
...

Sheet Wt average prices
E2: 46113 | F2: 46143 | G2: 46174 | H2: 46204 | I2: 46235 | J2: 46266 | K2: 46296 | L2: 46327 | M2: 46357 | N2: 46388 | O2: 46419 | P2: 46447 | Q2: Total
A3: Sales price
A4: Retail
A5: 550 | E5: =SUMPRODUCT('Plant wise prices'!E71:E81,'Plant wise prices'!E159:E169)/SUM('Plant wise prices'!E159:E169) -> 54609.623 | F5: =SUMPRODUCT('Plant wise prices'!F71:F81,'Plant wise prices'!F159:F169)/SUM('Plant wise prices'!F159:F169) -> 53611.564 | G5: =SUMPRODUCT('Plant wise prices'!G71:G81,'Plant wise prices'!G159:G169)/SUM('Plant wise prices'!G159:G169) -> 51623.705 | H5: =SUMPRODUCT('Plant wise prices'!H71:H81,'Plant wise prices'!H159:H169)/SUM('Plant wise prices'!H159:H169) -> 48629.558 | I5: =SUMPRODUCT('Plant wise prices'!I71:I81,'Plant wise prices'!I159:I169)/SUM('Plant wise prices'!I159:I169) -> 47685.571 | J5: =SUMPRODUCT('Plant wise prices'!J71:J81,'Plant wise prices'!J159:J169)/SUM('Plant wise prices'!J159:J169) -> 48707.024 | K5: =SUMPRODUCT('Plant wise prices'!K71:K81,'Plant wise prices'!K159:K169)/SUM('Plant wise prices'!K159:K169) -> 50731.404 | L5: =SUMPRODUCT('Plant wise prices'!L71:L81,'Plant wise prices'!L159:L169)/SUM('Plant wise prices'!L159:L169) -> 49801.247 | ... P5: =SUMPRODUCT('Plant wise prices'!P71:P81,'Plant wise prices'!P159:P169)/SUM('Plant wise prices'!P159:P169) -> 52000 | Q5: =SUMPRODUCT(E5:P5,E22:P22)/Q22 -> 50799.804 | T5: =50000*268000 -> 13400000000
A6: 550D | E6: =SUMPRODUCT('Plant wise prices'!E83:E93,'Plant wise prices'!E189:E199)/SUM('Plant wise prices'!E189:E199) -> 53464.73 | F6: =SUMPRODUCT('Plant wise prices'!F83:F93,'Plant wise prices'!F189:F199)/SUM('Plant wise prices'!F189:F199) -> 52455.761 | G6: =SUMPRODUCT('Plant wise prices'!G83:G93,'Plant wise prices'!G189:G199)/SUM('Plant wise prices'!G189:G199) -> 50530.225 | H6: =SUMPRODUCT('Plant wise prices'!H83:H93,'Plant wise prices'!H189:H199)/SUM('Plant wise prices'!H189:H199) -> 47618.972 | I6: =SUMPRODUCT('Plant wise prices'!I83:I93,'Plant wise prices'!I189:I199)/SUM('Plant wise prices'!I189:I199) -> 46549.846 | J6: =SUMPRODUCT('Plant wise prices'!J83:J93,'Plant wise prices'!J189:J199)/SUM('Plant wise prices'!J189:J199) -> 47663.581 | K6: =SUMPRODUCT('Plant wise prices'!K83:K93,'Plant wise prices'!K189:K199)/SUM('Plant wise prices'!K189:K199) -> 49556.131 | L6: =SUMPRODUCT('Plant wise prices'!L83:L93,'Plant wise prices'!L189:L199)/SUM('Plant wise prices'!L189:L199) -> 48641.075 | ... P6: =SUMPRODUCT('Plant wise prices'!P83:P93,'Plant wise prices'!P189:P199)/SUM('Plant wise prices'!P189:P199) -> 50555.906 | Q6: =SUMPRODUCT(E6:P6,E23:P23)/Q23 -> 49489.043 | T6: 3.0957256e+08
A7: One Helix 550 | E7: =SUMPRODUCT('Plant wise prices'!E97:E107,'Plant wise prices'!E174:E184)/SUM('Plant wise prices'!E174:E184) -> 52737.105 | F7: =SUMPRODUCT('Plant wise prices'!F97:F107,'Plant wise prices'!F174:F184)/SUM('Plant wise prices'!F174:F184) -> 51737.589 | G7: =SUMPRODUCT('Plant wise prices'!G97:G107,'Plant wise prices'!G174:G184)/SUM('Plant wise prices'!G174:G184) -> 49729.615 | H7: =SUMPRODUCT('Plant wise prices'!H97:H107,'Plant wise prices'!H174:H184)/SUM('Plant wise prices'!H174:H184) -> 46726.55 | I7: =SUMPRODUCT('Plant wise prices'!I97:I107,'Plant wise prices'!I174:I184)/SUM('Plant wise prices'!I174:I184) -> 45748.045 | J7: =SUMPRODUCT('Plant wise prices'!J97:J107,'Plant wise prices'!J174:J184)/SUM('Plant wise prices'!J174:J184) -> 46770.718 | K7: =SUMPRODUCT('Plant wise prices'!K97:K107,'Plant wise prices'!K174:K184)/SUM('Plant wise prices'!K174:K184) -> 48942.212 | L7: =SUMPRODUCT('Plant wise prices'!L97:L107,'Plant wise prices'!L174:L184)/SUM('Plant wise prices'!L174:L184) -> 48009.03 | ... P7: =SUMPRODUCT('Plant wise prices'!P97:P107,'Plant wise prices'!P174:P184)/SUM('Plant wise prices'!P174:P184) -> 50231.075 | Q7: =SUMPRODUCT(E7:P7,E24:P24)/Q24 -> 48868.048 | T7: =T6/T5 -> 0.02310243
A9: Project | T9: =Q7*121000 -> 5.9130338e+09
A10: 550 | E10: =E5-1000 -> 53609.623 | F10: =F5-1000 -> 52611.564 | G10: =G5-1000 -> 50623.705 | H10: =H5-1000 -> 47629.558 | I10: =I5-1000 -> 46685.571 | J10: =J5-1000 -> 47707.024 | K10: =K5-1000 -> 49731.404 | L10: =L5-1000 -> 48801.247 | ... P10: =P5-1000 -> 51000 | Q10: =SUMPRODUCT(E10:P10,E27:P27)/Q27 -> 49515.676 | T10: 329632115
A11: 550D | E11: =E6-1000 -> 52464.73 | F11: =F6-1000 -> 51455.761 | G11: =G6-1000 -> 49530.225 | H11: =H6-1000 -> 46618.972 | I11: =I6-1000 -> 45549.846 | J11: =J6-1000 -> 46663.581 | K11: =K6-1000 -> 48556.131 | L11: =L6-1000 -> 47641.075 | ... P11: =P6-1000 -> 49555.906 | Q11: =SUMPRODUCT(E11:P11,E28:P28)/Q28 -> 48479.885 | T11: =T10/T9 -> 0.055746699
A14: Purchase price
A15: Retail/project
A16: 550 | E16: =SUMPRODUCT('Plant wise prices'!E30:E40,'Plant wise prices'!E159:E169)/SUM('Plant wise prices'!E159:E169) -> 51284.328 | F16: =SUMPRODUCT('Plant wise prices'!F30:F40,'Plant wise prices'!F159:F169)/SUM('Plant wise prices'!F159:F169) -> 50550.631 | G16: =SUMPRODUCT('Plant wise prices'!G30:G40,'Plant wise prices'!G159:G169)/SUM('Plant wise prices'!G159:G169) -> 49315.494 | H16: =SUMPRODUCT('Plant wise prices'!H30:H40,'Plant wise prices'!H159:H169)/SUM('Plant wise prices'!H159:H169) -> 47014.332 | I16: =SUMPRODUCT('Plant wise prices'!I30:I40,'Plant wise prices'!I159:I169)/SUM('Plant wise prices'!I159:I169) -> 46791.178 | J16: =SUMPRODUCT('Plant wise prices'!J30:J40,'Plant wise prices'!J159:J169)/SUM('Plant wise prices'!J159:J169) -> 46930.057 | K16: =SUMPRODUCT('Plant wise prices'!K30:K40,'Plant wise prices'!K159:K169)/SUM('Plant wise prices'!K159:K169) -> 46770.826 | L16: =SUMPRODUCT('Plant wise prices'!L30:L40,'Plant wise prices'!L159:L169)/SUM('Plant wise prices'!L159:L169) -> 45959.71 | ... P16: =SUMPRODUCT('Plant wise prices'!P30:P40,'Plant wise prices'!P159:P169)/SUM('Plant wise prices'!P159:P169) -> 48892.889 | Q16: =SUMPRODUCT(E16:P16,E22:P22)/Q22 -> 48148.791
A17: 550D | E17: =SUMPRODUCT('Plant wise prices'!E42:E52,'Plant wise prices'!E189:E199)/SUM('Plant wise prices'!E189:E199) -> 52126.245 | F17: =SUMPRODUCT('Plant wise prices'!F42:F52,'Plant wise prices'!F189:F199)/SUM('Plant wise prices'!F189:F199) -> 50910.957 | G17: =SUMPRODUCT('Plant wise prices'!G42:G52,'Plant wise prices'!G189:G199)/SUM('Plant wise prices'!G189:G199) -> 49368.216 | H17: =SUMPRODUCT('Plant wise prices'!H42:H52,'Plant wise prices'!H189:H199)/SUM('Plant wise prices'!H189:H199) -> 47106.594 | I17: =SUMPRODUCT('Plant wise prices'!I42:I52,'Plant wise prices'!I189:I199)/SUM('Plant wise prices'!I189:I199) -> 46932.455 | J17: =SUMPRODUCT('Plant wise prices'!J42:J52,'Plant wise prices'!J189:J199)/SUM('Plant wise prices'!J189:J199) -> 47147.821 | K17: =SUMPRODUCT('Plant wise prices'!K42:K52,'Plant wise prices'!K189:K199)/SUM('Plant wise prices'!K189:K199) -> 47052.242 | L17: =SUMPRODUCT('Plant wise prices'!L42:L52,'Plant wise prices'!L189:L199)/SUM('Plant wise prices'!L189:L199) -> 46086.944 | ... P17: =SUMPRODUCT('Plant wise prices'!P42:P52,'Plant wise prices'!P189:P199)/SUM('Plant wise prices'!P189:P199) -> 49016.251 | Q17: =SUMPRODUCT(E17:P17,E23:P23)/Q23 -> 48155.854
A18: One Helix 550 | E18: =SUMPRODUCT('Plant wise prices'!E55:E65,'Plant wise prices'!E174:E184)/SUM('Plant wise prices'!E174:E184) -> 50576.969 | F18: =SUMPRODUCT('Plant wise prices'!F55:F65,'Plant wise prices'!F174:F184)/SUM('Plant wise prices'!F174:F184) -> 49966.311 | G18: =SUMPRODUCT('Plant wise prices'!G55:G65,'Plant wise prices'!G174:G184)/SUM('Plant wise prices'!G174:G184) -> 48680.874 | H18: =SUMPRODUCT('Plant wise prices'!H55:H65,'Plant wise prices'!H174:H184)/SUM('Plant wise prices'!H174:H184) -> 46160.449 | I18: =SUMPRODUCT('Plant wise prices'!I55:I65,'Plant wise prices'!I174:I184)/SUM('Plant wise prices'!I174:I184) -> 46159.839 | J18: =SUMPRODUCT('Plant wise prices'!J55:J65,'Plant wise prices'!J174:J184)/SUM('Plant wise prices'!J174:J184) -> 46532.946 | K18: =SUMPRODUCT('Plant wise prices'!K55:K65,'Plant wise prices'!K174:K184)/SUM('Plant wise prices'!K174:K184) -> 46330.628 | L18: =SUMPRODUCT('Plant wise prices'!L55:L65,'Plant wise prices'!L174:L184)/SUM('Plant wise prices'!L174:L184) -> 45411.093 | ... P18: =SUMPRODUCT('Plant wise prices'!P55:P65,'Plant wise prices'!P174:P184)/SUM('Plant wise prices'!P174:P184) -> 48164.807 | Q18: =SUMPRODUCT(E18:P18,E24:P24)/Q24 -> 47275.514
A20: Qty
A21: Retail
A22: 550 | E22: =SUM('Plant wise prices'!E159:E169) -> 9.519 | F22: =SUM('Plant wise prices'!F159:F169) -> 12.885 | G22: =SUM('Plant wise prices'!G159:G169) -> 11.006 | H22: =SUM('Plant wise prices'!H159:H169) -> 9.351 | I22: =SUM('Plant wise prices'!I159:I169) -> 7.256 | J22: =SUM('Plant wise prices'!J159:J169) -> 7.731 | K22: =SUM('Plant wise prices'!K159:K169) -> 8.3015 | L22: =SUM('Plant wise prices'!L159:L169) -> 8.6225 | ... P22: =SUM('Plant wise prices'!P159:P169) -> 5.651 | Q22: =SUM(E22:P22) -> 101.4495
A23: 550D | E23: =SUM('Plant wise prices'!E189:E199) -> 9.725 | F23: =SUM('Plant wise prices'!F189:F199) -> 13.28 | G23: =SUM('Plant wise prices'!G189:G199) -> 11.58 | H23: =SUM('Plant wise prices'!H189:H199) -> 9.725 | I23: =SUM('Plant wise prices'!I189:I199) -> 8.135 | J23: =SUM('Plant wise prices'!J189:J199) -> 9.075 | K23: =SUM('Plant wise prices'!K189:K199) -> 11.58 | L23: =SUM('Plant wise prices'!L189:L199) -> 14.145 | ... P23: =SUM('Plant wise prices'!P189:P199) -> 24.595 | Q23: =SUM(E23:P23) -> 166.695
A24: One Helix 550 | E24: =SUM('Plant wise prices'!E174:E184) -> 3.606 | F24: =SUM('Plant wise prices'!F174:F184) -> 4.935 | G24: =SUM('Plant wise prices'!G174:G184) -> 4.464 | H24: =SUM('Plant wise prices'!H174:H184) -> 3.774 | I24: =SUM('Plant wise prices'!I174:I184) -> 3.709 | J24: =SUM('Plant wise prices'!J174:J184) -> 4.344 | K24: =SUM('Plant wise prices'!K174:K184) -> 7.1685 | L24: =SUM('Plant wise prices'!L174:L184) -> 10.3825 | ... P24: =SUM('Plant wise prices'!P174:P184) -> 27.054 | Q24: =SUM(E24:P24) -> 121.4055
A26: Project
A27: 550 | E27: =SUM('Plant wise prices'!Y159:Y169) -> 4.475 | F27: =SUM('Plant wise prices'!Z159:Z169) -> 4.91 | G27: =SUM('Plant wise prices'!AA159:AA169) -> 5.225 | H27: =SUM('Plant wise prices'!AB159:AB169) -> 5.055 | I27: =SUM('Plant wise prices'!AC159:AC169) -> 5.185 | J27: =SUM('Plant wise prices'!AD159:AD169) -> 5.855 | K27: =SUM('Plant wise prices'!AE159:AE169) -> 7.25 | L27: =SUM('Plant wise prices'!AF159:AF169) -> 8.095 | ... P27: =SUM('Plant wise prices'!AJ159:AJ169) -> 13.075 | Q27: =SUM(E27:P27) -> 89.79
A28: 550D | E28: =SUM('Plant wise prices'!Y189:Y199) -> 11.025 | F28: =SUM('Plant wise prices'!Z189:Z199) -> 12.94 | G28: =SUM('Plant wise prices'!AA189:AA199) -> 12.675 | H28: =SUM('Plant wise prices'!AB189:AB199) -> 10.195 | I28: =SUM('Plant wise prices'!AC189:AC199) -> 9.915 | J28: =SUM('Plant wise prices'!AD189:AD199) -> 10.045 | K28: =SUM('Plant wise prices'!AE189:AE199) -> 11.225 | L28: =SUM('Plant wise prices'!AF189:AF199) -> 12.755 | ... P28: =SUM('Plant wise prices'!AJ189:AJ199) -> 25.325 | Q28: =SUM(E28:P28) -> 171.385
A30: Total qty | E30: =SUM(E22:E28) -> 38.35 | F30: =SUM(F22:F28) -> 48.95 | G30: =SUM(G22:G28) -> 44.95 | H30: =SUM(H22:H28) -> 38.1 | I30: =SUM(I22:I28) -> 34.2 | J30: =SUM(J22:J28) -> 37.05 | K30: =SUM(K22:K28) -> 45.525 | L30: =SUM(L22:L28) -> 54 | ... Q30: =SUM(Q22:Q28) -> 650.725
A31: Total qty-One TMT | E31: =SUM(E27:E28,E22:E23) -> 34.744 | F31: =SUM(F27:F28,F22:F23) -> 44.015 | G31: =SUM(G27:G28,G22:G23) -> 40.486 | H31: =SUM(H27:H28,H22:H23) -> 34.326 | I31: =SUM(I27:I28,I22:I23) -> 30.491 | J31: =SUM(J27:J28,J22:J23) -> 32.706 | K31: =SUM(K27:K28,K22:K23) -> 38.3565 | L31: =SUM(L27:L28,L22:L23) -> 43.6175 | ... Q31: =SUM(Q27:Q28,Q22:Q23) -> 529.3195
A34: Gross margin | D34: 550 | E34: 1500 | F34: 1500 | G34: 1500 | H34: 1000 | I34: 1000 | J34: 1000 | K34: 1500 | L34: 1500 | M34: 1750 | N34: 2000 | O34: 2250 | P34: 2500 | Q34: =SUMPRODUCT(E34:P34,E22:P22)/SUM(E22:P22) -> 1540.0532 | R34: Net CM | S34: =Q36-Q34 -> 1110.9601 | V34: Can increase by 200-250
A35: Retail | D35: 550D | Q35: To taper it down proportionately as in 550
A36: 550 | E36: =E5-E16 -> 3325.2948 | F36: =F5-F16 -> 3060.9333 | G36: =G5-G16 -> 2308.2111 | H36: =H5-H16 -> 1615.2261 | I36: =I5-I16 -> 894.39292 | J36: =J5-J16 -> 1776.9665 | K36: =K5-K16 -> 3960.5782 | L36: =L5-L16 -> 3841.537 | ... Q36: =Q5-Q16 -> 2651.0133 | S36: =AVERAGE(E36:P36)-AVERAGE(E34:P34) -> 1038.898
A37: 550D | E37: =E6-E17 -> 1338.4848 | F37: =F6-F17 -> 1544.804 | G37: =G6-G17 -> 1162.0086 | H37: =H6-H17 -> 512.37738 | I37: =I6-I17 -> -382.60828 | J37: =J6-J17 -> 515.75978 | K37: =K6-K17 -> 2503.8896 | L37: =L6-L17 -> 2554.131 | ... Q37: =Q6-Q17 -> 1333.1891 | T37: 500
A38: One Helix 550 | E38: =E7-E18 -> 2160.1359 | F38: =F7-F18 -> 1771.2773 | G38: =G7-G18 -> 1048.7412 | H38: =H7-H18 -> 566.10069 | I38: =I7-I18 -> -411.79339 | J38: =J7-J18 -> 237.77248 | K38: =K7-K18 -> 2611.584 | L38: =L7-L18 -> 2597.9368 | ... Q38: =Q7-Q18 -> 1592.534 | T38: 1000
A40: Project
A41: 550 | E41: =E10-E16 -> 2325.2948 | F41: =F10-F16 -> 2060.9333 | G41: =G10-G16 -> 1308.2111 | H41: =H10-H16 -> 615.22611 | I41: =I10-I16 -> -105.60708 | J41: =J10-J16 -> 776.9665 | K41: =K10-K16 -> 2960.5782 | L41: =L10-L16 -> 2841.537 | ... Q41: =Q10-Q16 -> 1366.8851 | S41: =AVERAGE(E41:P41)-AVERAGE(E36:P36) -> -1000
A42: 550D | E42: =E11-E17 -> 338.48483 | F42: =F11-F17 -> 544.80397 | G42: =G11-G17 -> 162.00864 | H42: =H11-H17 -> -487.62262 | I42: =I11-I17 -> -1382.6083 | J42: =J11-J17 -> -484.24022 | K42: =K11-K17 -> 1503.8896 | L42: =L11-L17 -> 1554.131 | ... Q42: =Q11-Q17 -> 324.03161 | S42: =AVERAGE(E42:P42)-AVERAGE(E36:P36) -> -2369.8367
A44: Overall Average margin | E44: =SUMPRODUCT(E22:E28,E36:E42)/SUM(E22:E28) -> 1736.5629 | F44: =SUMPRODUCT(F22:F28,F36:F42)/SUM(F22:F28) -> 1754.1434 | G44: =SUMPRODUCT(G22:G28,G36:G42)/SUM(G22:G28) -> 1166.4221 | H44: =SUMPRODUCT(H22:H28,H36:H42)/SUM(H22:H28) -> 534.43487 | I44: =SUMPRODUCT(I22:I28,I36:I42)/SUM(I22:I28) -> -362.75669 | J44: =SUMPRODUCT(J22:J28,J36:J42)/SUM(J22:J28) -> 516.49332 | K44: =SUMPRODUCT(K22:K28,K36:K42)/SUM(K22:K28) -> 2612.6365 | L44: =SUMPRODUCT(L22:L28,L36:L42)/SUM(L22:L28) -> 2575.0018 | ... P44: =SUMPRODUCT(P22:P28,P36:P42)/SUM(P22:P28) -> 1593.9826 | Q44: =SUMPRODUCT(E44:P44,E30:P30)/SUM(E30:P30) -> 1361.931
A46: Average margin- One TMT | E46: =(SUMPRODUCT(E36:E37,E22:E23)+SUMPRODUCT(E41:E42,E27:E28))/SUM(E22:E23,E27:E28) -> 1692.6012 | F46: =(SUMPRODUCT(F36:F37,F22:F23)+SUMPRODUCT(F41:F42,F27:F28))/SUM(F22:F23,F27:F28) -> 1752.2224 | G46: =(SUMPRODUCT(G36:G37,G22:G23)+SUMPRODUCT(G41:G42,G27:G28))/SUM(G22:G23,G27:G28) -> 1179.3977 | H46: =(SUMPRODUCT(H36:H37,H22:H23)+SUMPRODUCT(H41:H42,H27:H28))/SUM(H22:H23,H27:H28) -> 530.95335 | I46: =(SUMPRODUCT(I36:I37,I22:I23)+SUMPRODUCT(I41:I42,I27:I28))/SUM(I22:I23,I27:I28) -> -356.79175 | J46: =(SUMPRODUCT(J36:J37,J22:J23)+SUMPRODUCT(J41:J42,J27:J28))/SUM(J22:J23,J27:J28) -> 553.51293 | K46: =(SUMPRODUCT(K36:K37,K22:K23)+SUMPRODUCT(K41:K42,K27:K28))/SUM(K22:K23,K27:K28) -> 2612.8332 | L46: =(SUMPRODUCT(L36:L37,L22:L23)+SUMPRODUCT(L41:L42,L27:L28))/SUM(L22:L23,L27:L28) -> 2569.5425 | ... P46: =(SUMPRODUCT(P36:P37,P22:P23)+SUMPRODUCT(P41:P42,P27:P28))/SUM(P22:P23,P27:P28) -> 1407.8509 | Q46: =SUMPRODUCT(E46:P46,E31:P31)/SUM(E31:P31) -> 1309.0396

Sheet Sales price
A1: Month | B1: Neo | F1: Real Ispat | G1: API Ispat And Powertech Private Limited | H1: SKA Ispat Private Limited | I1: GERMAN GREEN STEEL AND POWER LIMITED | J1: Ambashakti Industries Limited | K1: AMBASHAKTI UDYOG LIMITED- GWALIOR | L1: Rashmi Steel | M1: AIC IRON INDUSTRIES PRIVATE LIMITED | N1: Aditya Industries | R1: API Ispat And Powertech Private Limited | S1: SKA Ispat Private Limited | T1: GERMAN GREEN STEEL AND POWER LIMITED | U1: Ambashakti Industries Limited | V1: AMBASHAKTI UDYOG LIMITED- GWALIOR | W1: Rashmi Steel | X1: AIC IRON INDUSTRIES PRIVATE LIMITED | Y1: Aditya Industries | Z1: Maharashtra - New Plant | AA1: Telangana - New Plant | AE1: API Ispat And Powertech Private Limited | AF1: SKA Ispat Private Limited | AG1: GERMAN GREEN STEEL AND POWER LIMITED | AH1: Ambashakti Industries Limited | AI1: AMBASHAKTI UDYOG LIMITED- GWALIOR | AJ1: Rashmi Steel | AK1: AIC IRON INDUSTRIES PRIVATE LIMITED | AL1: Aditya Industries | AM1: Maharashtra - New Plant | AN1: Telangana - New Plant
A2: Grade | F2: JSW One 550D | G2: =F2 -> JSW One 550D | H2: =F2 -> JSW One 550D | I2: JSW One 550D | J2: JSW One 550D | K2: JSW One 550D | L2: JSW One 550D | M2: =L2 -> JSW One 550D | N2: JSW One 550D | R2: JSW One 550 | S2: =R2 -> JSW One 550 | T2: JSW One 550 | U2: JSW One 550 | V2: JSW One 550 | W2: JSW One 550 | X2: =W2 -> JSW One 550 | Y2: JSW One 550 | Z2: JSW One 550 | AA2: JSW One 550 | AE2: One Helix | AF2: =AE2 -> One Helix | AG2: One Helix | AH2: One Helix | AI2: One Helix | AJ2: One Helix | AK2: =AJ2 -> One Helix | AL2: One Helix | AM2: One Helix | AN2: One Helix
A3: Type | F3: Retail | G3: =F3 -> Retail | H3: =F3 -> Retail | I3: Retail | J3: Retail | K3: Retail | L3: Retail | M3: =L3 -> Retail | N3: Retail | R3: Retail | S3: =R3 -> Retail | T3: Retail | U3: Retail | V3: Retail | W3: Retail | X3: =W3 -> Retail | Y3: Retail | Z3: Retail | AA3: Retail | AE3: Retail | AF3: =AE3 -> Retail | AG3: Retail | AH3: Retail | AI3: Retail | AJ3: Retail | AK3: =AJ3 -> Retail | AL3: Retail | AM3: Retail | AN3: Retail
A4: Frt | F4: 2500 | G4: =F4 -> 2500 | H4: =F4 -> 2500 | I4: =750+1500 -> 2250 | J4: 1000 | K4: 1800 | L4: =750+1500 -> 2250 | M4: =L4 -> 2250 | N4: 2000 | Z4: =500+2000 -> 2500 | AA4: =500+2000 -> 2500 | AF4: =AE4 -> 0 | AM4: =500+2000 -> 2500 | AN4: =500+2000 -> 2500
A5: 44927 | B5: 60888 | C5: =ROUND(AVERAGE(B5,B17,B30),-3) -> 55000 | F5: =$C5-F$4 -> 52500 | G5: =F5 -> 52500 | H5: =F5 -> 52500 | I5: =$C5-I$4 -> 52750 | J5: =$C5-J$4 -> 54000 | K5: =$C5-K$4 -> 53200 | L5: =$C5-L$4 -> 52750 | M5: =L5 -> 52750 | N5: =$C5-N$4 -> 53000 | R5: =F5-1000 -> 51500 | S5: =R5 -> 51500 | T5: =I5-1000 -> 51750 | U5: =J5-1000 -> 53000 | V5: =K5-1000 -> 52200 | W5: =L5-1000 -> 51750 | X5: =W5 -> 51750 | Y5: =N5-1000 -> 52000 | Z5: =$C5-Z$4 -> 52500 | AA5: =$C5-AA$4 -> 52500 | AE5: =R5-1000 -> 50500 | AF5: =AE5 -> 50500 | AG5: =T5-1000 -> 50750 | AH5: =U5-1000 -> 52000 | AI5: =V5-1000 -> 51200 | AJ5: =W5-1000 -> 50750 | AK5: =AJ5 -> 50750 | AL5: =Y5-1000 -> 51000 | AM5: =Z5-1000 -> 51500 | AN5: =AA5-1000 -> 51500
A6: 44958 | B6: 62783 | C6: =ROUND(AVERAGE(B6,B18,B31),-3) -> 55000 | F6: =$C6-F$4 -> 52500 | G6: =F6 -> 52500 | H6: =F6 -> 52500 | I6: =$C6-I$4 -> 52750 | J6: =$C6-J$4 -> 54000 | K6: =$C6-K$4 -> 53200 | L6: =$C6-L$4 -> 52750 | M6: =L6 -> 52750 | N6: =$C6-N$4 -> 53000 | R6: =F6-1000 -> 51500 | S6: =R6 -> 51500 | T6: =I6-1000 -> 51750 | U6: =J6-1000 -> 53000 | V6: =K6-1000 -> 52200 | W6: =L6-1000 -> 51750 | X6: =W6 -> 51750 | Y6: =N6-1000 -> 52000 | Z6: =$C6-Z$4 -> 52500 | AA6: =$C6-AA$4 -> 52500 | AE6: =R6-1000 -> 50500 | AF6: =AE6 -> 50500 | AG6: =T6-1000 -> 50750 | AH6: =U6-1000 -> 52000 | AI6: =V6-1000 -> 51200 | AJ6: =W6-1000 -> 50750 | AK6: =AJ6 -> 50750 | AL6: =Y6-1000 -> 51000 | AM6: =Z6-1000 -> 51500 | AN6: =AA6-1000 -> 51500
A7: 44986 | B7: 60450 | C7: =ROUND(AVERAGE(B7,B19,B32),-3) -> 56000 | D7: Month | E7: Average price | F7: =$C7-F$4 -> 53500 | G7: =F7 -> 53500 | H7: =F7 -> 53500 | I7: =$C7-I$4 -> 53750 | J7: =$C7-J$4 -> 55000 | K7: =$C7-K$4 -> 54200 | L7: =$C7-L$4 -> 53750 | M7: =L7 -> 53750 | N7: =$C7-N$4 -> 54000 | P7: Month | Q7: Average price | R7: =F7-1000 -> 52500 | S7: =R7 -> 52500 | T7: =I7-1000 -> 52750 | U7: =J7-1000 -> 54000 | V7: =K7-1000 -> 53200 | W7: =L7-1000 -> 52750 | X7: =W7 -> 52750 | Y7: =N7-1000 -> 53000 | Z7: =$C7-Z$4 -> 53500 | AA7: =$C7-AA$4 -> 53500 | AC7: Month | AD7: Average price | AE7: =R7-1000 -> 51500 | AF7: =AE7 -> 51500 | AG7: =T7-1000 -> 51750 | AH7: =U7-1000 -> 53000 | AI7: =V7-1000 -> 52200 | AJ7: =W7-1000 -> 51750 | AK7: =AJ7 -> 51750 | AL7: =Y7-1000 -> 52000 | AM7: =Z7-1000 -> 52500 | AN7: =AA7-1000 -> 52500
A8: 45017 | B8: 58867 | C8: =ROUND(AVERAGE(B8,B20,B33),-3) -> 57000 | D8: 46113 | E8: =AVERAGE(F8:N8) -> 54883.333 | F8: =$C8-F$4 -> 54500 | G8: =F8 -> 54500 | H8: =F8 -> 54500 | I8: =$C8-I$4 -> 54750 | J8: =$C8-J$4 -> 56000 | K8: =$C8-K$4 -> 55200 | L8: =$C8-L$4 -> 54750 | M8: =L8 -> 54750 | N8: =$C8-N$4 -> 55000 | P8: 46113 | Q8: =AVERAGE(R8:AA8) -> 54045 | R8: =F8-1000 -> 53500 | S8: =R8 -> 53500 | T8: =I8-1000 -> 53750 | U8: =J8-1000 -> 55000 | V8: =K8-1000 -> 54200 | W8: =L8-1000 -> 53750 | X8: =W8 -> 53750 | Y8: =N8-1000 -> 54000 | Z8: =$C8-Z$4 -> 54500 | AA8: =$C8-AA$4 -> 54500 | AC8: 46113 | AD8: =AVERAGE(AE8:AN8) -> 53045 | AE8: =R8-1000 -> 52500 | AF8: =AE8 -> 52500 | AG8: =T8-1000 -> 52750 | AH8: =U8-1000 -> 54000 | AI8: =V8-1000 -> 53200 | AJ8: =W8-1000 -> 52750 | AK8: =AJ8 -> 52750 | AL8: =Y8-1000 -> 53000 | AM8: =Z8-1000 -> 53500 | AN8: =AA8-1000 -> 53500
A9: 45047 | B9: 55300 | C9: =ROUND(AVERAGE(B9,B21,B34),-3) -> 56000 | D9: 46143 | E9: =AVERAGE(F9:N9) -> 53883.333 | F9: =$C9-F$4 -> 53500 | G9: =F9 -> 53500 | H9: =F9 -> 53500 | I9: =$C9-I$4 -> 53750 | J9: =$C9-J$4 -> 55000 | K9: =$C9-K$4 -> 54200 | L9: =$C9-L$4 -> 53750 | M9: =L9 -> 53750 | N9: =$C9-N$4 -> 54000 | P9: 46143 | Q9: =AVERAGE(R9:AA9) -> 53045 | R9: =F9-1000 -> 52500 | S9: =R9 -> 52500 | T9: =I9-1000 -> 52750 | U9: =J9-1000 -> 54000 | V9: =K9-1000 -> 53200 | W9: =L9-1000 -> 52750 | X9: =W9 -> 52750 | Y9: =N9-1000 -> 53000 | Z9: =$C9-Z$4 -> 53500 | AA9: =$C9-AA$4 -> 53500 | AC9: 46143 | AD9: =AVERAGE(AE9:AN9) -> 52045 | AE9: =R9-1000 -> 51500 | AF9: =AE9 -> 51500 | AG9: =T9-1000 -> 51750 | AH9: =U9-1000 -> 53000 | AI9: =V9-1000 -> 52200 | AJ9: =W9-1000 -> 51750 | AK9: =AJ9 -> 51750 | AL9: =Y9-1000 -> 52000 | AM9: =Z9-1000 -> 52500 | AN9: =AA9-1000 -> 52500
A10: 45078 | B10: 52700 | C10: =ROUND(AVERAGE(B10,B22,B35),-3) -> 54000 | D10: 46174 | E10: =AVERAGE(F10:N10) -> 51883.333 | F10: =$C10-F$4 -> 51500 | G10: =F10 -> 51500 | H10: =F10 -> 51500 | I10: =$C10-I$4 -> 51750 | J10: =$C10-J$4 -> 53000 | K10: =$C10-K$4 -> 52200 | L10: =$C10-L$4 -> 51750 | M10: =L10 -> 51750 | N10: =$C10-N$4 -> 52000 | P10: 46174 | Q10: =AVERAGE(R10:AA10) -> 51045 | R10: =F10-1000 -> 50500 | S10: =R10 -> 50500 | T10: =I10-1000 -> 50750 | U10: =J10-1000 -> 52000 | V10: =K10-1000 -> 51200 | W10: =L10-1000 -> 50750 | X10: =W10 -> 50750 | Y10: =N10-1000 -> 51000 | Z10: =$C10-Z$4 -> 51500 | AA10: =$C10-AA$4 -> 51500 | AC10: 46174 | AD10: =AVERAGE(AE10:AN10) -> 50045 | AE10: =R10-1000 -> 49500 | AF10: =AE10 -> 49500 | AG10: =T10-1000 -> 49750 | AH10: =U10-1000 -> 51000 | AI10: =V10-1000 -> 50200 | AJ10: =W10-1000 -> 49750 | AK10: =AJ10 -> 49750 | AL10: =Y10-1000 -> 50000 | AM10: =Z10-1000 -> 50500 | AN10: =AA10-1000 -> 50500
A11: 45108 | B11: 51450 | C11: =ROUND(AVERAGE(B11,B23,B36),-3) -> 51000 | D11: 46204 | E11: =AVERAGE(F11:N11) -> 48883.333 | F11: =$C11-F$4 -> 48500 | G11: =F11 -> 48500 | H11: =F11 -> 48500 | I11: =$C11-I$4 -> 48750 | J11: =$C11-J$4 -> 50000 | K11: =$C11-K$4 -> 49200 | L11: =$C11-L$4 -> 48750 | M11: =L11 -> 48750 | N11: =$C11-N$4 -> 49000 | P11: 46204 | Q11: =AVERAGE(R11:AA11) -> 48045 | R11: =F11-1000 -> 47500 | S11: =R11 -> 47500 | T11: =I11-1000 -> 47750 | U11: =J11-1000 -> 49000 | V11: =K11-1000 -> 48200 | W11: =L11-1000 -> 47750 | X11: =W11 -> 47750 | Y11: =N11-1000 -> 48000 | Z11: =$C11-Z$4 -> 48500 | AA11: =$C11-AA$4 -> 48500 | AC11: 46204 | AD11: =AVERAGE(AE11:AN11) -> 47045 | AE11: =R11-1000 -> 46500 | AF11: =AE11 -> 46500 | AG11: =T11-1000 -> 46750 | AH11: =U11-1000 -> 48000 | AI11: =V11-1000 -> 47200 | AJ11: =W11-1000 -> 46750 | AK11: =AJ11 -> 46750 | AL11: =Y11-1000 -> 47000 | AM11: =Z11-1000 -> 47500 | AN11: =AA11-1000 -> 47500
A12: 45139 | B12: 52400 | C12: =ROUND(AVERAGE(B12,B24,B37),-3) -> 50000 | D12: 46235 | E12: =AVERAGE(F12:N12) -> 47883.333 | F12: =$C12-F$4 -> 47500 | G12: =F12 -> 47500 | H12: =F12 -> 47500 | I12: =$C12-I$4 -> 47750 | J12: =$C12-J$4 -> 49000 | K12: =$C12-K$4 -> 48200 | L12: =$C12-L$4 -> 47750 | M12: =L12 -> 47750 | N12: =$C12-N$4 -> 48000 | P12: 46235 | Q12: =AVERAGE(R12:AA12) -> 47045 | R12: =F12-1000 -> 46500 | S12: =R12 -> 46500 | T12: =I12-1000 -> 46750 | U12: =J12-1000 -> 48000 | V12: =K12-1000 -> 47200 | W12: =L12-1000 -> 46750 | X12: =W12 -> 46750 | Y12: =N12-1000 -> 47000 | Z12: =$C12-Z$4 -> 47500 | AA12: =$C12-AA$4 -> 47500 | AC12: 46235 | AD12: =AVERAGE(AE12:AN12) -> 46045 | AE12: =R12-1000 -> 45500 | AF12: =AE12 -> 45500 | AG12: =T12-1000 -> 45750 | AH12: =U12-1000 -> 47000 | AI12: =V12-1000 -> 46200 | AJ12: =W12-1000 -> 45750 | AK12: =AJ12 -> 45750 | AL12: =Y12-1000 -> 46000 | AM12: =Z12-1000 -> 46500 | AN12: =AA12-1000 -> 46500
A13: 45170 | B13: 57763 | C13: =ROUND(AVERAGE(B13,B25,B38),-3) -> 51000 | D13: 46266 | E13: =AVERAGE(F13:N13) -> 48883.333 | F13: =$C13-F$4 -> 48500 | G13: =F13 -> 48500 | H13: =F13 -> 48500 | I13: =$C13-I$4 -> 48750 | J13: =$C13-J$4 -> 50000 | K13: =$C13-K$4 -> 49200 | L13: =$C13-L$4 -> 48750 | M13: =L13 -> 48750 | N13: =$C13-N$4 -> 49000 | P13: 46266 | Q13: =AVERAGE(R13:AA13) -> 48045 | R13: =F13-1000 -> 47500 | S13: =R13 -> 47500 | T13: =I13-1000 -> 47750 | U13: =J13-1000 -> 49000 | V13: =K13-1000 -> 48200 | W13: =L13-1000 -> 47750 | X13: =W13 -> 47750 | Y13: =N13-1000 -> 48000 | Z13: =$C13-Z$4 -> 48500 | AA13: =$C13-AA$4 -> 48500 | AC13: 46266 | AD13: =AVERAGE(AE13:AN13) -> 47045 | AE13: =R13-1000 -> 46500 | AF13: =AE13 -> 46500 | AG13: =T13-1000 -> 46750 | AH13: =U13-1000 -> 48000 | AI13: =V13-1000 -> 47200 | AJ13: =W13-1000 -> 46750 | AK13: =AJ13 -> 46750 | AL13: =Y13-1000 -> 47000 | AM13: =Z13-1000 -> 47500 | AN13: =AA13-1000 -> 47500
A14: 45200 | B14: 57325 | C14: =ROUND(AVERAGE(B14,B26,B39),-3) -> 53000 | D14: 46296 | E14: =AVERAGE(F14:N14) -> 50883.333 | F14: =$C14-F$4 -> 50500 | G14: =F14 -> 50500 | H14: =F14 -> 50500 | I14: =$C14-I$4 -> 50750 | J14: =$C14-J$4 -> 52000 | K14: =$C14-K$4 -> 51200 | L14: =$C14-L$4 -> 50750 | M14: =L14 -> 50750 | N14: =$C14-N$4 -> 51000 | P14: 46296 | Q14: =AVERAGE(R14:AA14) -> 50045 | R14: =F14-1000 -> 49500 | S14: =R14 -> 49500 | T14: =I14-1000 -> 49750 | U14: =J14-1000 -> 51000 | V14: =K14-1000 -> 50200 | W14: =L14-1000 -> 49750 | X14: =W14 -> 49750 | Y14: =N14-1000 -> 50000 | Z14: =$C14-Z$4 -> 50500 | AA14: =$C14-AA$4 -> 50500 | AC14: 46296 | AD14: =AVERAGE(AE14:AN14) -> 49045 | AE14: =R14-1000 -> 48500 | AF14: =AE14 -> 48500 | AG14: =T14-1000 -> 48750 | AH14: =U14-1000 -> 50000 | AI14: =V14-1000 -> 49200 | AJ14: =W14-1000 -> 48750 | AK14: =AJ14 -> 48750 | AL14: =Y14-1000 -> 49000 | AM14: =Z14-1000 -> 49500 | AN14: =AA14-1000 -> 49500
A15: 45231 | B15: 55700 | C15: =ROUND(AVERAGE(B15,B27,B40),-3) -> 52000 | D15: 46327 | E15: =AVERAGE(F15:N15) -> 49883.333 | F15: =$C15-F$4 -> 49500 | G15: =F15 -> 49500 | H15: =F15 -> 49500 | I15: =$C15-I$4 -> 49750 | J15: =$C15-J$4 -> 51000 | K15: =$C15-K$4 -> 50200 | L15: =$C15-L$4 -> 49750 | M15: =L15 -> 49750 | N15: =$C15-N$4 -> 50000 | P15: 46327 | Q15: =AVERAGE(R15:AA15) -> 49045 | R15: =F15-1000 -> 48500 | S15: =R15 -> 48500 | T15: =I15-1000 -> 48750 | U15: =J15-1000 -> 50000 | V15: =K15-1000 -> 49200 | W15: =L15-1000 -> 48750 | X15: =W15 -> 48750 | Y15: =N15-1000 -> 49000 | Z15: =$C15-Z$4 -> 49500 | AA15: =$C15-AA$4 -> 49500 | AC15: 46327 | AD15: =AVERAGE(AE15:AN15) -> 48045 | AE15: =R15-1000 -> 47500 | AF15: =AE15 -> 47500 | AG15: =T15-1000 -> 47750 | AH15: =U15-1000 -> 49000 | AI15: =V15-1000 -> 48200 | AJ15: =W15-1000 -> 47750 | AK15: =AJ15 -> 47750 | AL15: =Y15-1000 -> 48000 | AM15: =Z15-1000 -> 48500 | AN15: =AA15-1000 -> 48500
A16: 45261 | B16: 53200 | C16: =ROUND(AVERAGE(B16,B29,B41),-3) -> 51000 | D16: 46357 | E16: =AVERAGE(F16:N16) -> 48883.333 | F16: =$C16-F$4 -> 48500 | G16: =F16 -> 48500 | H16: =F16 -> 48500 | I16: =$C16-I$4 -> 48750 | J16: =$C16-J$4 -> 50000 | K16: =$C16-K$4 -> 49200 | L16: =$C16-L$4 -> 48750 | M16: =L16 -> 48750 | N16: =$C16-N$4 -> 49000 | P16: 46357 | Q16: =AVERAGE(R16:AA16) -> 48045 | R16: =F16-1000 -> 47500 | S16: =R16 -> 47500 | T16: =I16-1000 -> 47750 | U16: =J16-1000 -> 49000 | V16: =K16-1000 -> 48200 | W16: =L16-1000 -> 47750 | X16: =W16 -> 47750 | Y16: =N16-1000 -> 48000 | Z16: =$C16-Z$4 -> 48500 | AA16: =$C16-AA$4 -> 48500 | AC16: 46357 | AD16: =AVERAGE(AE16:AN16) -> 47045 | AE16: =R16-1000 -> 46500 | AF16: =AE16 -> 46500 | AG16: =T16-1000 -> 46750 | AH16: =U16-1000 -> 48000 | AI16: =V16-1000 -> 47200 | AJ16: =W16-1000 -> 46750 | AK16: =AJ16 -> 46750 | AL16: =Y16-1000 -> 47000 | AM16: =Z16-1000 -> 47500 | AN16: =AA16-1000 -> 47500
A17: 45292 | B17: 51950 | C17: =ROUND(AVERAGE(B17,B30,B42),-3) -> 53000 | D17: 46388 | E17: =AVERAGE(F17:N17) -> 50883.333 | F17: =$C17-F$4 -> 50500 | G17: =F17 -> 50500 | H17: =F17 -> 50500 | I17: =$C17-I$4 -> 50750 | J17: =$C17-J$4 -> 52000 | K17: =$C17-K$4 -> 51200 | L17: =$C17-L$4 -> 50750 | M17: =L17 -> 50750 | N17: =$C17-N$4 -> 51000 | P17: 46388 | Q17: =AVERAGE(R17:AA17) -> 50045 | R17: =F17-1000 -> 49500 | S17: =R17 -> 49500 | T17: =I17-1000 -> 49750 | U17: =J17-1000 -> 51000 | V17: =K17-1000 -> 50200 | W17: =L17-1000 -> 49750 | X17: =W17 -> 49750 | Y17: =N17-1000 -> 50000 | Z17: =$C17-Z$4 -> 50500 | AA17: =$C17-AA$4 -> 50500 | AC17: 46388 | AD17: =AVERAGE(AE17:AN17) -> 49045 | AE17: =R17-1000 -> 48500 | AF17: =AE17 -> 48500 | AG17: =T17-1000 -> 48750 | AH17: =U17-1000 -> 50000 | AI17: =V17-1000 -> 49200 | AJ17: =W17-1000 -> 48750 | AK17: =AJ17 -> 48750 | AL17: =Y17-1000 -> 49000 | AM17: =Z17-1000 -> 49500 | AN17: =AA17-1000 -> 49500
A18: 45323 | B18: 51867 | C18: =ROUND(AVERAGE(B18,B31,B43),-3) -> 52000 | D18: 46419 | E18: =AVERAGE(F18:N18) -> 49883.333 | F18: =$C18-F$4 -> 49500 | G18: =F18 -> 49500 | H18: =F18 -> 49500 | I18: =$C18-I$4 -> 49750 | J18: =$C18-J$4 -> 51000 | K18: =$C18-K$4 -> 50200 | L18: =$C18-L$4 -> 49750 | M18: =L18 -> 49750 | N18: =$C18-N$4 -> 50000 | P18: 46419 | Q18: =AVERAGE(R18:AA18) -> 49045 | R18: =F18-1000 -> 48500 | S18: =R18 -> 48500 | T18: =I18-1000 -> 48750 | U18: =J18-1000 -> 50000 | V18: =K18-1000 -> 49200 | W18: =L18-1000 -> 48750 | X18: =W18 -> 48750 | Y18: =N18-1000 -> 49000 | Z18: =$C18-Z$4 -> 49500 | AA18: =$C18-AA$4 -> 49500 | AC18: 46419 | AD18: =AVERAGE(AE18:AN18) -> 48045 | AE18: =R18-1000 -> 47500 | AF18: =AE18 -> 47500 | AG18: =T18-1000 -> 47750 | AH18: =U18-1000 -> 49000 | AI18: =V18-1000 -> 48200 | AJ18: =W18-1000 -> 47750 | AK18: =AJ18 -> 47750 | AL18: =Y18-1000 -> 48000 | AM18: =Z18-1000 -> 48500 | AN18: =AA18-1000 -> 48500
A19: 45352 | B19: 52700 | C19: =ROUND(AVERAGE(B19,B32,B44),-3) -> 54000 | D19: 46447 | E19: =AVERAGE(F19:N19) -> 51883.333 | F19: =$C19-F$4 -> 51500 | G19: =F19 -> 51500 | H19: =F19 -> 51500 | I19: =$C19-I$4 -> 51750 | J19: =$C19-J$4 -> 53000 | K19: =$C19-K$4 -> 52200 | L19: =$C19-L$4 -> 51750 | M19: =L19 -> 51750 | N19: =$C19-N$4 -> 52000 | P19: 46447 | Q19: =AVERAGE(R19:AA19) -> 51045 | R19: =F19-1000 -> 50500 | S19: =R19 -> 50500 | T19: =I19-1000 -> 50750 | U19: =J19-1000 -> 52000 | V19: =K19-1000 -> 51200 | W19: =L19-1000 -> 50750 | X19: =W19 -> 50750 | Y19: =N19-1000 -> 51000 | Z19: =$C19-Z$4 -> 51500 | AA19: =$C19-AA$4 -> 51500 | AC19: 46447 | AD19: =AVERAGE(AE19:AN19) -> 50045 | AE19: =R19-1000 -> 49500 | AF19: =AE19 -> 49500 | AG19: =T19-1000 -> 49750 | AH19: =U19-1000 -> 51000 | AI19: =V19-1000 -> 50200 | AJ19: =W19-1000 -> 49750 | AK19: =AJ19 -> 49750 | AL19: =Y19-1000 -> 50000 | AM19: =Z19-1000 -> 50500 | AN19: =AA19-1000 -> 50500
A20: 45383 | B20: 55325
A21: 45413 | B21: 58300
A22: 45444 | B22: 57075
A23: 45474 | B23: 52950
A24: 45505 | B24: 49762.5
A25: 45536 | B25: 50283
A26: 45566 | B26: 54000
A27: 45597 | B27: 54000
A29: 45627 | B29: 51750
A30: 45658 | B30: 51250
A31: 45689 | B31: 51275
A32: 45717 | B32: 54317
... A40: 45986 | B40: 46750
A41: Dec'25 | B41: 49000
A42: Jan'26 | B42: 54850
A43: Average | B43: =AVERAGE(B5:B42) -> 53438.662

Sheet QD from CM
A1: Quantity Discount
A2: Particulars | B2: Qty-Monthly | C2: Rate
A3: ='Plant wise prices'!B3 -> AIC IRON INDUSTRIES PRIVATE LIMITED | B3: =_xlfn.XLOOKUP(A3,'Supply plan'!$BU$2:$BU$14,'Supply plan'!$CL$2:$CL$14,"Not found",0)*1000 -> 0 | C3: =IF(B3>6000,500,IF(AND(B3>4000,B3<6000),300,IF(AND(B3>3000,B3<4000),200,IF(AND(B3>2000,B3<3000),100,0)))) -> 0
A4: ='Plant wise prices'!B4 -> Aditya Industries | B4: =_xlfn.XLOOKUP(A4,'Supply plan'!$BU$2:$BU$14,'Supply plan'!$CL$2:$CL$14,"Not found",0)*1000 -> 42150.92 | C4: =IF(B4>6000,500,IF(AND(B4>5000,B4<=6000),400,IF(AND(B4>3500,B4<=5000),300,IF(AND(B4>2000,B4<=3500),200,0)))) -> 500
A5: ='Plant wise prices'!B5 -> Ambashakti Industries Limited | B5: =_xlfn.XLOOKUP(A5,'Supply plan'!$BU$2:$BU$14,'Supply plan'!$CL$2:$CL$14,"Not found",0)*1000 -> 113929.12 | C5: =IF(B5>4000,350,IF(AND(B5>=3001,B5<4000),250,IF(AND(B5>=2501,B5<3000),100))) -> 350
A6: ='Plant wise prices'!B6 -> AMBASHAKTI UDYOG LIMITED- GWALIOR | B6: =_xlfn.XLOOKUP(A6,'Supply plan'!$BU$2:$BU$14,'Supply plan'!$CL$2:$CL$14,"Not found",0)*1000 -> 94810.865 | C6: =IF(B6>4000,350,IF(AND(B6>=3001,B6<4000),250,IF(AND(B6>=2501,B6<3000),100))) -> 350
A7: ='Plant wise prices'!B7 -> API Ispat And Powertech Private Limited | B7: =_xlfn.XLOOKUP(A7,'Supply plan'!$BU$2:$BU$14,'Supply plan'!$CL$2:$CL$14,"Not found",0)*1000 -> 11420.48 | C7: 0
A8: ='Plant wise prices'!B8 -> GERMAN GREEN STEEL AND POWER LIMITED | B8: =_xlfn.XLOOKUP(A8,'Supply plan'!$BU$2:$BU$14,'Supply plan'!$CL$2:$CL$14,"Not found",0)*1000 -> 11028.32 | C8: {=_xlfn.IFS( B8<2000,0, B8<=3000,200, B8<=4000,300, B8<=6000,400, B8>6000,600 )} -> 600
A9: ='Plant wise prices'!B9 -> SKA Ispat Private Limited | B9: =_xlfn.XLOOKUP(A9,'Supply plan'!$BU$2:$BU$14,'Supply plan'!$CL$2:$CL$14,"Not found",0)*1000 -> 66634.57 | C9: 0
A10: ='Plant wise prices'!B10 -> Real Ispat | B10: =_xlfn.XLOOKUP(A10,'Supply plan'!$BU$2:$BU$14,'Supply plan'!$CL$2:$CL$14,"Not found",0)*1000 -> 48500.12 | C10: 0 | D10: No QD provision in agreement
A11: ='Plant wise prices'!B11 -> Rashmi Steel | B11: =_xlfn.XLOOKUP(A11,'Supply plan'!$BU$2:$BU$14,'Supply plan'!$CL$2:$CL$14,"Not found",0)*1000 -> 116161.56 | C11: 0 | D11: No QD provision in agreement
A12: ='Plant wise prices'!B12 -> Telangana - New Plant | B12: =_xlfn.XLOOKUP(A12,'Supply plan'!$BU$2:$BU$14,'Supply plan'!$CL$2:$CL$14,"Not found",0)*1000 -> 5283.6 | C12: 0 | D12: New CM
A13: ='Plant wise prices'!B13 -> Maharashtra - New Plant | B13: =_xlfn.XLOOKUP(A13,'Supply plan'!$BU$2:$BU$14,'Supply plan'!$CL$2:$CL$14,"Not found",0)*1000 -> 7957.95 | C13: 0 | D13: New CM
A15: Total | B15: =SUM(B3:B13) -> 517877.5
A19: ='Supply plan'!AO1 -> Name of Plants | B19: ='Supply plan'!AP1 -> JSW One brands being manufactured | C19: ='Supply plan'!AQ1 -> Plant Capacity | F19: ='Supply plan'!AT1 -> Overall
C20: ='Supply plan'!BW2 -> FE 550 | D20: ='Supply plan'!BX2 -> FE 550D | E20: ='Supply plan'!BY2 -> Total | F20: ='Supply plan'!BZ2 -> 46113 | G20: ='Supply plan'!CA2 -> 46143 | H20: ='Supply plan'!CB2 -> 46174 | I20: ='Supply plan'!CC2 -> 46204 | J20: ='Supply plan'!CD2 -> 46235 | ... R20: ='Supply plan'!CL2 -> Total
A21: ='Supply plan'!AO3 -> AIC IRON INDUSTRIES PRIVATE LIMITED | F21: ='Supply plan'!AT3*1000 -> 0 | G21: ='Supply plan'!AU3*1000 -> 0 | H21: ='Supply plan'!AV3*1000 -> 0 | I21: ='Supply plan'!AW3*1000 -> 0 | J21: ='Supply plan'!AX3*1000 -> 0 | K21: ='Supply plan'!AY3*1000 -> 0 | L21: ='Supply plan'!AZ3*1000 -> 0 | M21: ='Supply plan'!BA3*1000 -> 0 | ... R21: ='Supply plan'!BF3*1000 -> 0
A22: ='Supply plan'!BU4 -> Aditya Industries | F22: ='Supply plan'!AT4*1000 -> 4082.58 | G22: ='Supply plan'!AU4*1000 -> 4332.28 | H22: ='Supply plan'!AV4*1000 -> 4522.72 | I22: ='Supply plan'!AW4*1000 -> 3852.3 | J22: ='Supply plan'!AX4*1000 -> 3422.02 | K22: ='Supply plan'!AY4*1000 -> 3501.9 | L22: ='Supply plan'!AZ4*1000 -> 3946.92 | M22: ='Supply plan'!BA4*1000 -> 4522.12 | ... R22: ='Supply plan'!BF4*1000 -> 58775.92
A23: ='Supply plan'!AO5 -> Ambashakti Industries Limited | F23: ='Supply plan'!AT5*1000 -> 9120.71 | G23: ='Supply plan'!AU5*1000 -> 11930.67 | H23: ='Supply plan'!AV5*1000 -> 10855.71 | I23: ='Supply plan'!AW5*1000 -> 9435.4 | J23: ='Supply plan'!AX5*1000 -> 8455.4 | K23: ='Supply plan'!AY5*1000 -> 9235.395 | L23: ='Supply plan'!AZ5*1000 -> 11515.395 | M23: ='Supply plan'!BA5*1000 -> 13715.48 | ... R23: ='Supply plan'!BF5*1000 -> 159617.12
A24: ='Supply plan'!BU6 -> AMBASHAKTI UDYOG LIMITED- GWALIOR | F24: ='Supply plan'!AT6*1000 -> 6272.21 | G24: ='Supply plan'!AU6*1000 -> 7402.05 | H24: ='Supply plan'!AV6*1000 -> 6886.97 | I24: ='Supply plan'!AW6*1000 -> 5486.1 | J24: ='Supply plan'!AX6*1000 -> 5156.18 | K24: ='Supply plan'!AY6*1000 -> 5486.105 | L24: ='Supply plan'!AZ6*1000 -> 6676.185 | M24: ='Supply plan'!BA6*1000 -> 7926.5 | ... R24: ='Supply plan'!BF6*1000 -> 94810.865
A25: ='Supply plan'!AO7 -> API Ispat And Powertech Private Limited | F25: ='Supply plan'!AT7*1000 -> 2380.1 | G25: ='Supply plan'!AU7*1000 -> 3340.16 | H25: ='Supply plan'!AV7*1000 -> 3013.14 | I25: ='Supply plan'!AW7*1000 -> 2642.1 | J25: ='Supply plan'!AX7*1000 -> 2308.08 | K25: ='Supply plan'!AY7*1000 -> 2520.08 | L25: ='Supply plan'!AZ7*1000 -> 3254.08 | M25: ='Supply plan'!BA7*1000 -> 4032.1 | ... R25: ='Supply plan'!BF7*1000 -> 45750.48
A26: ='Supply plan'!BU8 -> GERMAN GREEN STEEL AND POWER LIMITED | F26: ='Supply plan'!AT8*1000 -> 1520.32 | G26: ='Supply plan'!AU8*1000 -> 2520.72 | H26: ='Supply plan'!AV8*1000 -> 2140.64 | I26: ='Supply plan'!AW8*1000 -> 1780.48 | J26: ='Supply plan'!AX8*1000 -> 1580.48 | K26: ='Supply plan'!AY8*1000 -> 1760.56 | L26: ='Supply plan'!AZ8*1000 -> 2260.56 | M26: ='Supply plan'!BA8*1000 -> 2640.64 | ... R26: ='Supply plan'!BF8*1000 -> 31028.32
A27: ='Supply plan'!AO9 -> SKA Ispat Private Limited | F27: ='Supply plan'!AT9*1000 -> 2816.01 | G27: ='Supply plan'!AU9*1000 -> 6519.42 | H27: ='Supply plan'!AV9*1000 -> 5850.94 | I27: ='Supply plan'!AW9*1000 -> 5205.98 | J27: ='Supply plan'!AX9*1000 -> 4729.84 | K27: ='Supply plan'!AY9*1000 -> 4572.34 | L27: ='Supply plan'!AZ9*1000 -> 4868.26 | M27: ='Supply plan'!BA9*1000 -> 5770.92 | ... R27: ='Supply plan'!BF9*1000 -> 76114.57
A28: ='Supply plan'!BU10 -> Real Ispat | F28: ='Supply plan'!AT10*1000 -> 7859.27 | G28: ='Supply plan'!AU10*1000 -> 7307.4 | H28: ='Supply plan'!AV10*1000 -> 6246.98 | I28: ='Supply plan'!AW10*1000 -> 1465.66 | J28: ='Supply plan'!AX10*1000 -> 1290.58 | K28: ='Supply plan'!AY10*1000 -> 1530.7 | L28: ='Supply plan'!AZ10*1000 -> 2651.65 | M28: ='Supply plan'!BA10*1000 -> 3011.84 | ... R28: ='Supply plan'!BF10*1000 -> 48500.12
A29: ='Supply plan'!AO11 -> Rashmi Steel | F29: ='Supply plan'!AT11*1000 -> 3985.7 | G29: ='Supply plan'!AU11*1000 -> 5235.9 | H29: ='Supply plan'!AV11*1000 -> 5096.1 | I29: ='Supply plan'!AW11*1000 -> 7677.04 | J29: ='Supply plan'!AX11*1000 -> 6651.58 | K29: ='Supply plan'!AY11*1000 -> 7416.6 | L29: ='Supply plan'!AZ11*1000 -> 8501.38 | M29: ='Supply plan'!BA11*1000 -> 9991.54 | ... R29: ='Supply plan'!BF11*1000 -> 116161.56
A30: ='Supply plan'!BU12 -> Telangana - New Plant | F30: ='Supply plan'!AT12*1000 -> 425 | G30: ='Supply plan'!AU12*1000 -> 575 | H30: ='Supply plan'!AV12*1000 -> 500 | I30: ='Supply plan'!AW12*1000 -> 665.24 | J30: ='Supply plan'!AX12*1000 -> 615.24 | K30: ='Supply plan'!AY12*1000 -> 935.32 | L30: ='Supply plan'!AZ12*1000 -> 1060.32 | M30: ='Supply plan'!BA12*1000 -> 1200.36 | ... R30: ='Supply plan'!BF12*1000 -> 12483.6
A31: ='Supply plan'!AO13 -> Maharashtra - New Plant | F31: ='Supply plan'!AT13*1000 -> 0 | G31: ='Supply plan'!AU13*1000 -> 0 | H31: ='Supply plan'!AV13*1000 -> 0 | I31: ='Supply plan'!AW13*1000 -> 0 | J31: ='Supply plan'!AX13*1000 -> 0 | K31: ='Supply plan'!AY13*1000 -> 0 | L31: ='Supply plan'!AZ13*1000 -> 950.95 | M31: ='Supply plan'!BA13*1000 -> 1001 | ... R31: ='Supply plan'!BF13*1000 -> 7957.95
A32: ='Supply plan'!BU14 -> TOTAL | F32: ='Supply plan'!AT14*1000 -> 38461.9 | G32: ='Supply plan'!AU14*1000 -> 49163.6 | H32: ='Supply plan'!AV14*1000 -> 45113.2 | I32: ='Supply plan'!AW14*1000 -> 38210.3 | J32: ='Supply plan'!AX14*1000 -> 34209.4 | K32: ='Supply plan'!AY14*1000 -> 36959 | L32: ='Supply plan'!AZ14*1000 -> 45685.7 | M32: ='Supply plan'!BA14*1000 -> 53812.5 | ... R32: ='Supply plan'!BF14*1000 -> 651200.5
A35: =A19 -> Name of Plants | F35: =F20 -> 46113 | G35: =G20 -> 46143 | H35: =H20 -> 46174 | I35: =I20 -> 46204 | J35: =J20 -> 46235 | K35: =K20 -> 46266 | L35: =L20 -> 46296 | M35: =M20 -> 46327 | ... R35: =R20 -> Total
A36: QD PMT
A37: =A21 -> AIC IRON INDUSTRIES PRIVATE LIMITED | F37: =IF(F21>6000,500, IF(AND(F21>4000,F21<6000),300, IF(AND(F21>3000,F21<4000),200, IF(AND(F21>2000,F21<3000),100,0)))) -> 0 | G37: =IF(G21>6000,500, IF(AND(G21>4000,G21<6000),300, IF(AND(G21>3000,G21<4000),200, IF(AND(G21>2000,G21<3000),100,0)))) -> 0 | H37: =IF(H21>6000,500, IF(AND(H21>4000,H21<6000),300, IF(AND(H21>3000,H21<4000),200, IF(AND(H21>2000,H21<3000),100,0)))) -> 0 | I37: =IF(I21>6000,500, IF(AND(I21>4000,I21<6000),300, IF(AND(I21>3000,I21<4000),200, IF(AND(I21>2000,I21<3000),100,0)))) -> 0 | J37: =IF(J21>6000,500, IF(AND(J21>4000,J21<6000),300, IF(AND(J21>3000,J21<4000),200, IF(AND(J21>2000,J21<3000),100,0)))) -> 0 | K37: =IF(K21>6000,500, IF(AND(K21>4000,K21<6000),300, IF(AND(K21>3000,K21<4000),200, IF(AND(K21>2000,K21<3000),100,0)))) -> 0 | L37: =IF(L21>6000,500, IF(AND(L21>4000,L21<6000),300, IF(AND(L21>3000,L21<4000),200, IF(AND(L21>2000,L21<3000),100,0)))) -> 0 | M37: =IF(M21>6000,500, IF(AND(M21>4000,M21<6000),300, IF(AND(M21>3000,M21<4000),200, IF(AND(M21>2000,M21<3000),100,0)))) -> 0 | ... Q37: =IF(Q21>6000,500, IF(AND(Q21>4000,Q21<6000),300, IF(AND(Q21>3000,Q21<4000),200, IF(AND(Q21>2000,Q21<3000),100,0)))) -> 0
A38: =A22 -> Aditya Industries | F38: =IF(F22>6000,500, IF(AND(F22>5000,F22<=6000),400, IF(AND(F22>3500,F22<=5000),300, IF(AND(F22>2000,F22<=3500),200,0)))) -> 300 | G38: =IF(G22>6000,500, IF(AND(G22>5000,G22<=6000),400, IF(AND(G22>3500,G22<=5000),300, IF(AND(G22>2000,G22<=3500),200,0)))) -> 300 | H38: =IF(H22>6000,500, IF(AND(H22>5000,H22<=6000),400, IF(AND(H22>3500,H22<=5000),300, IF(AND(H22>2000,H22<=3500),200,0)))) -> 300 | I38: =IF(I22>6000,500, IF(AND(I22>5000,I22<=6000),400, IF(AND(I22>3500,I22<=5000),300, IF(AND(I22>2000,I22<=3500),200,0)))) -> 300 | J38: =IF(J22>6000,500, IF(AND(J22>5000,J22<=6000),400, IF(AND(J22>3500,J22<=5000),300, IF(AND(J22>2000,J22<=3500),200,0)))) -> 200 | K38: =IF(K22>6000,500, IF(AND(K22>5000,K22<=6000),400, IF(AND(K22>3500,K22<=5000),300, IF(AND(K22>2000,K22<=3500),200,0)))) -> 300 | L38: =IF(L22>6000,500, IF(AND(L22>5000,L22<=6000),400, IF(AND(L22>3500,L22<=5000),300, IF(AND(L22>2000,L22<=3500),200,0)))) -> 300 | M38: =IF(M22>6000,500, IF(AND(M22>5000,M22<=6000),400, IF(AND(M22>3500,M22<=5000),300, IF(AND(M22>2000,M22<=3500),200,0)))) -> 300 | ... Q38: =IF(Q22>6000,500, IF(AND(Q22>5000,Q22<=6000),400, IF(AND(Q22>3500,Q22<=5000),300, IF(AND(Q22>2000,Q22<=3500),200,0)))) -> 500
A39: =A23 -> Ambashakti Industries Limited | F39: =IF(F23>4000,350, IF(AND(F23>=3001,F23<4000),250, IF(AND(F23>=2501,F23<3000),100))) -> 350 | G39: =IF(G23>4000,350, IF(AND(G23>=3001,G23<4000),250, IF(AND(G23>=2501,G23<3000),100))) -> 350 | H39: =IF(H23>4000,350, IF(AND(H23>=3001,H23<4000),250, IF(AND(H23>=2501,H23<3000),100))) -> 350 | I39: =IF(I23>4000,350, IF(AND(I23>=3001,I23<4000),250, IF(AND(I23>=2501,I23<3000),100))) -> 350 | J39: =IF(J23>4000,350, IF(AND(J23>=3001,J23<4000),250, IF(AND(J23>=2501,J23<3000),100))) -> 350 | K39: =IF(K23>4000,350, IF(AND(K23>=3001,K23<4000),250, IF(AND(K23>=2501,K23<3000),100))) -> 350 | L39: =IF(L23>4000,350, IF(AND(L23>=3001,L23<4000),250, IF(AND(L23>=2501,L23<3000),100))) -> 350 | M39: =IF(M23>4000,350, IF(AND(M23>=3001,M23<4000),250, IF(AND(M23>=2501,M23<3000),100))) -> 350 | ... Q39: =IF(Q23>4000,350, IF(AND(Q23>=3001,Q23<4000),250, IF(AND(Q23>=2501,Q23<3000),100))) -> 350
A40: =A24 -> AMBASHAKTI UDYOG LIMITED- GWALIOR | F40: =IF(F24>4000,350, IF(AND(F24>=3001,F24<4000),250, IF(AND(F24>=2501,F24<3000),100))) -> 350 | G40: =IF(G24>4000,350, IF(AND(G24>=3001,G24<4000),250, IF(AND(G24>=2501,G24<3000),100))) -> 350 | H40: =IF(H24>4000,350, IF(AND(H24>=3001,H24<4000),250, IF(AND(H24>=2501,H24<3000),100))) -> 350 | I40: =IF(I24>4000,350, IF(AND(I24>=3001,I24<4000),250, IF(AND(I24>=2501,I24<3000),100))) -> 350 | J40: =IF(J24>4000,350, IF(AND(J24>=3001,J24<4000),250, IF(AND(J24>=2501,J24<3000),100))) -> 350 | K40: =IF(K24>4000,350, IF(AND(K24>=3001,K24<4000),250, IF(AND(K24>=2501,K24<3000),100))) -> 350 | L40: =IF(L24>4000,350, IF(AND(L24>=3001,L24<4000),250, IF(AND(L24>=2501,L24<3000),100))) -> 350 | M40: =IF(M24>4000,350, IF(AND(M24>=3001,M24<4000),250, IF(AND(M24>=2501,M24<3000),100))) -> 350 | ... Q40: =IF(Q24>4000,350, IF(AND(Q24>=3001,Q24<4000),250, IF(AND(Q24>=2501,Q24<3000),100))) -> 350
A41: =A25 -> API Ispat And Powertech Private Limited | F41: 0 | G41: 0 | H41: 0 | I41: 0 | J41: 0 | K41: 0 | L41: 0 | M41: 0 | N41: 0 | O41: 0 | P41: 0 | Q41: 0
A42: =A26 -> GERMAN GREEN STEEL AND POWER LIMITED | F42: {=_xlfn.IFS( F26<2000,0, F26<=3000,200, F26<=4000,300, F26<=6000,400, F26>6000,600 )} -> 0 | G42: {=_xlfn.IFS( G26<2000,0, G26<=3000,200, G26<=4000,300, G26<=6000,400, G26>6000,600 )} -> 200 | H42: {=_xlfn.IFS( H26<2000,0, H26<=3000,200, H26<=4000,300, H26<=6000,400, H26>6000,600 )} -> 200 | I42: {=_xlfn.IFS( I26<2000,0, I26<=3000,200, I26<=4000,300, I26<=6000,400, I26>6000,600 )} -> 0 | J42: {=_xlfn.IFS( J26<2000,0, J26<=3000,200, J26<=4000,300, J26<=6000,400, J26>6000,600 )} -> 0 | K42: {=_xlfn.IFS( K26<2000,0, K26<=3000,200, K26<=4000,300, K26<=6000,400, K26>6000,600 )} -> 0 | L42: {=_xlfn.IFS( L26<2000,0, L26<=3000,200, L26<=4000,300, L26<=6000,400, L26>6000,600 )} -> 200 | M42: {=_xlfn.IFS( M26<2000,0, M26<=3000,200, M26<=4000,300, M26<=6000,400, M26>6000,600 )} -> 200 | ... Q42: {=_xlfn.IFS( Q26<2000,0, Q26<=3000,200, Q26<=4000,300, Q26<=6000,400, Q26>6000,600 )} -> 400
A43: =A27 -> SKA Ispat Private Limited | F43: 0 | G43: 0 | H43: 0 | I43: 0 | J43: 0 | K43: 0 | L43: 0 | M43: 0 | N43: 0 | O43: 0 | P43: 0 | Q43: 0
A44: =A28 -> Real Ispat
A45: =A29 -> Rashmi Steel
A46: =A30 -> Telangana - New Plant
A47: =A31 -> Maharashtra - New Plant
A48: =A32 -> TOTAL
A50: =A35 -> Name of Plants | F50: =F35 -> 46113 | G50: =G35 -> 46143 | H50: =H35 -> 46174 | I50: =I35 -> 46204 | J50: =J35 -> 46235 | K50: =K35 -> 46266 | L50: =L35 -> 46296 | M50: =M35 -> 46327 | ... Q50: =Q35 -> 46447 | R50: Total
A51: QD Total
A52: =A37 -> AIC IRON INDUSTRIES PRIVATE LIMITED | F52: =F37*F21 -> 0 | G52: =G37*G21 -> 0 | H52: =H37*H21 -> 0 | I52: =I37*I21 -> 0 | J52: =J37*J21 -> 0 | K52: =K37*K21 -> 0 | L52: =L37*L21 -> 0 | M52: =M37*M21 -> 0 | ... Q52: =Q37*Q21 -> 0
A53: =A38 -> Aditya Industries | F53: =F38*F22 -> 1224774 | G53: =G38*G22 -> 1299684 | H53: =H38*H22 -> 1356816 | I53: =I38*I22 -> 1155690 | J53: =J38*J22 -> 684404 | K53: =K38*K22 -> 1050570 | L53: =L38*L22 -> 1184076 | M53: =M38*M22 -> 1356636 | ... Q53: =Q38*Q22 -> 4267190 | R53: =SUM(F53:Q53) -> 21051458
A54: =A39 -> Ambashakti Industries Limited | F54: =F39*F23 -> 3192248.5 | G54: =G39*G23 -> 4175734.5 | H54: =H39*H23 -> 3799498.5 | I54: =I39*I23 -> 3302390 | J54: =J39*J23 -> 2959390 | K54: =K39*K23 -> 3232388.2 | L54: =L39*L23 -> 4030388.2 | M54: =M39*M23 -> 4800418 | ... Q54: =Q39*Q23 -> 8024089.5 | R54: =SUM(F54:Q54) -> 55865990
A55: =A40 -> AMBASHAKTI UDYOG LIMITED- GWALIOR | F55: =F40*F24 -> 2195273.5 | G55: =G40*G24 -> 2590717.5 | H55: =H40*H24 -> 2410439.5 | I55: =I40*I24 -> 1920135 | J55: =J40*J24 -> 1804663 | K55: =K40*K24 -> 1920136.7 | L55: =L40*L24 -> 2336664.8 | M55: =M40*M24 -> 2774275 | ... Q55: =Q40*Q24 -> 4643712.5 | R55: =SUM(F55:Q55) -> 33183803
A56: =A41 -> API Ispat And Powertech Private Limited | F56: =F41*F25 -> 0 | G56: =G41*G25 -> 0 | H56: =H41*H25 -> 0 | I56: =I41*I25 -> 0 | J56: =J41*J25 -> 0 | K56: =K41*K25 -> 0 | L56: =L41*L25 -> 0 | M56: =M41*M25 -> 0 | ... Q56: =Q41*Q25 -> 0 | R56: =SUM(F56:Q56) -> 0
A57: =A42 -> GERMAN GREEN STEEL AND POWER LIMITED | F57: =F42*F26 -> 0 | G57: =G42*G26 -> 504144 | H57: =H42*H26 -> 428128 | I57: =I42*I26 -> 0 | J57: =J42*J26 -> 0 | K57: =K42*K26 -> 0 | L57: =L42*L26 -> 452112 | M57: =M42*M26 -> 528128 | ... Q57: =Q42*Q26 -> 1832512 | R57: =SUM(F57:Q57) -> 6937856
A58: =A43 -> SKA Ispat Private Limited | F58: =F43*F27 -> 0 | G58: =G43*G27 -> 0 | H58: =H43*H27 -> 0 | I58: =I43*I27 -> 0 | J58: =J43*J27 -> 0 | K58: =K43*K27 -> 0 | L58: =L43*L27 -> 0 | M58: =M43*M27 -> 0 | ... Q58: =Q43*Q27 -> 0 | R58: =SUM(F58:Q58) -> 0
A59: =A44 -> Real Ispat | F59: =F44*F28 -> 0 | G59: =G44*G28 -> 0 | H59: =H44*H28 -> 0 | I59: =I44*I28 -> 0 | J59: =J44*J28 -> 0 | K59: =K44*K28 -> 0 | L59: =L44*L28 -> 0 | M59: =M44*M28 -> 0 | ... Q59: =Q44*Q28 -> 0 | R59: =SUM(F59:Q59) -> 0
A60: =A45 -> Rashmi Steel | F60: =F45*F29 -> 0 | G60: =G45*G29 -> 0 | H60: =H45*H29 -> 0 | I60: =I45*I29 -> 0 | J60: =J45*J29 -> 0 | K60: =K45*K29 -> 0 | L60: =L45*L29 -> 0 | M60: =M45*M29 -> 0 | ... Q60: =Q45*Q29 -> 0 | R60: =SUM(F60:Q60) -> 0
A61: =A46 -> Telangana - New Plant | F61: =F46*F30 -> 0 | G61: =G46*G30 -> 0 | H61: =H46*H30 -> 0 | I61: =I46*I30 -> 0 | J61: =J46*J30 -> 0 | K61: =K46*K30 -> 0 | L61: =L46*L30 -> 0 | M61: =M46*M30 -> 0 | ... Q61: =Q46*Q30 -> 0 | R61: =SUM(F61:Q61) -> 0
A62: =A47 -> Maharashtra - New Plant | F62: =F47*F31 -> 0 | G62: =G47*G31 -> 0 | H62: =H47*H31 -> 0 | I62: =I47*I31 -> 0 | J62: =J47*J31 -> 0 | K62: =K47*K31 -> 0 | L62: =L47*L31 -> 0 | M62: =M47*M31 -> 0 | ... Q62: =Q47*Q31 -> 0 | R62: =SUM(F62:Q62) -> 0
A63: =A48 -> TOTAL | F63: =SUM(F52:F62) -> 6612296 | G63: =SUM(G52:G62) -> 8570280 | H63: =SUM(H52:H62) -> 7994882 | I63: =SUM(I52:I62) -> 6378215 | J63: =SUM(J52:J62) -> 5448457 | K63: =SUM(K52:K62) -> 6203095 | L63: =SUM(L52:L62) -> 8003241 | M63: =SUM(M52:M62) -> 9459457 | ... Q63: =SUM(Q52:Q62) -> 18767504 | R63: =SUM(F63:Q63) -> 117039107
A64: Average QD PMT | F64: =F63/F32 -> 171.91808 | G64: =G63/G32 -> 174.32165 | H64: =H63/H32 -> 177.21824 | I64: =I63/I32 -> 166.92397 | J64: =J63/J32 -> 159.26783 | K64: =K63/K32 -> 167.8372 | L64: =L63/L32 -> 175.18044 | M64: =M63/M32 -> 175.7855 | ... R64: =R63/R32 -> 179.72822

Sheet Sheet5
A2: Ship to- Zoho location | B2: City as per Pricing team | C2: Project/Retail | D2: Grade (550/550D) | E2: Plant | F2: FOR/MT | G2: BE Quantity (Retail+Project at Special prices) | H2: BE Quantity-2 (PB projects) | I2: Total BE | J2: Actuals | K2: Purchase price | L2: Invoice Date | M2: Invoice Number | N2: Sales order number | O2: Order ID | P2: CF.Purchase Bill Reference No | Q2: Customer Name | R2: ROY Quantity | S2: Sales (incl. freight for retail) | T2: Taxable Value excl freight | U2: Freight | V2: CGST | W2: SGST | X2: IGST | Y2: Remarks | Z2: Grade | AA2: LRF | AB2: CM's Name | AC2: CM Name 2 | AD2: CM State | AE2: Ship to | AF2: Delivery Method | AG2: Purchase quantity | AH2: Purchase price ex-works | AI2: Price Difference-Purchase | AJ2: 3PL Cost /MT | AK2: 3PL cost (actual/estimated as per JOTS team) | AL2: 3PL cost (estimated as per Pricing team) | AM2: Gross Margin | AN2: MOU | AO2: SFDC | AP2: Price support | AQ2: Price difference-Sales | AR2: Service charges | AS2: QD from CM | AT2: Contribution margin
